// 
// Decompiled by Procyon v0.5.30
// 

package com.whatsapp.messaging;

import java.net.InetAddress;
import java.net.Socket;
import java.security.KeyManagementException;
import com.whatsapp.util.Log;
import java.security.SecureRandom;
import javax.net.ssl.KeyManager;
import javax.net.ssl.SSLSocketFactory;
import javax.net.ssl.SSLContext;
import javax.net.ssl.TrustManager;
import java.security.cert.X509Certificate;

public final class a6 extends aq
{
    private static a6 c;
    private static final X509Certificate[] d;
    private static final TrustManager[] e;
    private static final String[] z;
    
    static {
        // 
        // This method could not be decompiled.
        // 
        // Original Bytecode:
        // 
        //     0: iconst_2       
        //     1: anewarray       Ljava/lang/String;
        //     4: astore_0       
        //     5: ldc             "\u001c`E^ls\b/:\u000f\u0011\u000e-!\u0015x\u000b!0\u0000e\bE^l\u001c`b>\bx\u000e]\t\u0002r\f\u00042\u0002p\u001c-\u0004\u0005`\u0014\"8.k\u0004\u0000\u0005\"\u007f\f96\u0007s\u001c)\u0004&S>\u00109\u0005p$*\u0014\u000fg\u000f)\u0010\u0015v|2\u001b#v!,)\u0019{}b:\u0007k%\n4-Z\u00140!1S\u007f\\\u0014\u0015\\\u001bX\u0017s\b4\t\t\u0004i\u0000*&\u0006p|=6\u0002Y\u0000'%,w>\t&\u000f].\u0006\"2x\b\u0004\u0006\u0018Hy\u0010=\u0015p7b1&\u007f\u001b*22e\u0001.))S\n\u00047\u001bi\u0007X:\u0004\u007f>1+\u000fK\u0004,:&d\nQ\u0000 f\u0003]:\u0007k%\n4-Z\u00140!1S\u007f\\\u0014\u0010i\u001bX\u0012\u0006\b4b\u0012\u0019cx% \u0004F\u0005\u001f*\u0005g\u001c97\u0004I%\u0007\u0017\tc:'\u001ayG)[\u0017r}#2\u001b#v!\u0002)\u0019{}$\u001e\u000fG/;K9x\t)\u0016\u0003V&\u0019\u001b*X\nbJ6\u0001\u000f+\"\u0004f\b?\u001f4k Q2%\\\u000b\u001b\u0012\u0016\u007f!\u000b\u001d\u0010D\u0014ZJ5|\u000f\\+\u0005e&]>\u0005h4&\u0019\u0000F\u0000<\u0018p\u007f\u000b\u0007+\u0005e\b]>\u0005h4b=+p:%'*\u0000\u0003.\u001c6V/\u001b\u000b\u000bu\f\u00011&\u007f\u001b*2\"e\nY))S\n\u00047\u001bi\u0007X:\u0007k%\n4-Z\u00140!1S\u007f\\\u0014\u0015\\\u001bX\u0017s\b4b\u0012;t\u0015%1\u0014v\fY&\u0004r%%<\u0017\\\u000b\u001b\u0012\u0014\u007f!\u000b\u001d\u0010B\u0004-\u001f4h4\\\u000b\u000fe\f\u00121&\u007f\u001b*22e\u0001.))S\n\u00047\u001bi\u0007X:\u0004\u007f>b*\u0019\u007f7!7\bV\u0018/J2P\u001a&F\bw\u0017\u0000\u0011\u0006]&1+\u0013A/ZG&`\u0015>C vt\u0011\u0012\u0019cx% \u0004F\u0005\u001f*\u0005g\u001c97\u0004I%\u0007\u0017\tc:b<(\t;\f@%\u0002\u0001\u0006))S\n\u0004\u0019\u001bi\u0007X?,\u007f;\n yI\u0004,2$s*\u0003\u0002)Z$/J6\u0001\u000f+\"\u0004f\b?\u001f4k Q2%\\\u000b\u001b\u0012\u0016\u007f!b\u0010/`81AxE\u0000!4'|\fX4\u0002b</ \bS~,\"\u0004s\f9&\u0000py/=\u0000u\u000e*\u001a\u0010z\u000f\u000f\"\u0005~\u0002\u0006;\n\u0004,\u001e:\u0016k\u0007>BwG\u0014b\u0017\u0000\u0006x_\u0007/\u0003\u001b=\u0017\u001bk\u0018\u000b<\u0003g\u0015\u000bEtV\u007f859e\u0015\f>6K7\u0002\u00007d\n\"D\u0012g\u000e+ \u0013C\u000e\u0004E;W\u0003Y \rd7\u0005B\u000fktb$-\\=2\u0017\u0013{\b\u0011C*e\u001f\u0010\"#\u0006\u0015*\u001b\u0017`zG\u001d\tZ}Y\u000b\u0002\u001a\u0014,\u0014*c\"#$;Z\u007f2\\\f\u001e\u001b0\u0004#az:\u0015\u001by\u0000XGv`\u001eb\u0005uU&C=.bb\u0012\u0010/F/&74\u001at_\u0011(\u0004=Q\u0004\bu\f92\u0003|\fX4\u0002b</ \bS~,\"\u0004s\u000f9&\u0000py/1\u0000u9G&\u0006\b;b&\u000bb\u0017;$\b\u0005\u0002*J\r\u001a\u00060:\u0011@(+\u0014'h?\u0010X+w7\u001d\u0014wt\u0004$?\u0006p\u000e''#\u0003\"?;jY(90pDf\u0005=3\u0001\u000527;e8b:\u0018t\u0017\u00077\u000b{\u00068'\u0004[!\n%\u0014[\u001dQ&\u000fgf\u0005$6ux%\u001f\f\u001e\u0000\u001c\u00000\u0003,\u0012 (v\u0000]\u0011\u0014|\u0000\u0002G\u0010B>\u0010\u0000.U4\t\u001e\u0004F\u000eb$na\u0002\u001d)w].\u000fF\nE7PKtY\u0017\u0007X\r\u00069\f68\t\u001aQ%(y}8\u0017K\u001c`E^lt\u0003,S\u0002t\u001f<:\u0007x\u000e)'\u0004\u001c`E^l;`E^l\u001c\u000f-4\b\u007fm+6\u0013e\u0004.:\u0002p\u0019-^l\u001c`Ey\fx\u0004,\u0001;r\u000e)\u0003$V\f\u001f:\u0003p*!\"\u0002u;\u000f%1s\u000e:\u0001\u0006Y)?\u0001\u000bf\u0017 ;\u0012[\f&1&Z<\u0000\u0018(vt\u001fC\u0003p\u001c=5\u0000u\u000f\u0000y\f`>\u001f0\u0010h\t>\"\u0010v\b\u001f9\u0017d7-%\fs\u0000/2pd\b+\u001b\f|\u001f/\u001f/P\u0018&\u001f\"_\u001c\u000f \u0016\u0004'%!*F\u000b\u001f*\u0005g\u001c9?\u0004I\u000f[y%\u0002.\u001d)\u0006]#\t$\u000f].\u0006\"4h\u007fQ\u0007\fb\f\u001f;&h\t>\"\u0010u\b\u0010\u0017\u0004P\u001a\f\u0003\u0010\u0003\u001b\u0011\u0017\u0002s\u0005\n4xX\u0014?\u0004&d Q\u0005%r\u000f,y\u0010e\f\r56\u0001:&\u0019\u0004I\u0000<26|\t)\u0004\fu\u000f\t56\u00017%'\u0004I\u0000<26|\t)\u0004\fu\u000f\t>\u0006t5+\t\u0000{\u000f\u000f=\u0017s\f1'\u0000]\u001b<y\fc\u0018\u001f66h\t>\"\u0010z\b\u001f\u000b\u0004P\u001a\f\u0003\u0010\u0003\u001b\u0011\u0017\u0002s\u0007\n\u001e\fI\n<2\u0019s*&%\u0003p><6\tU~\f\ntZ,?\u00171h\u007f>\n%rx\u0002y#\u0003}\u0010:\u0005p(*\u0014\u000fg\u000f)>\u0015w}:\u0003\u001b\u0003!,)\u0019{}!6%B/Z9)S\u000e* #\u0003tX:\u0004\u007f\u000f%:\bs\u0004\u00022\u000fs*\u0003\u0002)Z$/yxF}*2\u0010t\u000b)2\u000er\f9K\u0000|\u0004!1\u0002V\u0006+2\u0010t\f\\\u00197Y\b0?$@\u0006<'.\u0000(\u0019&\nz\u001d+@$`4\t8-\u0006%$<-]>*y\u0002b\t%2\u001b~#<\u0019\u0002\u0002\u0018G\u0017\u0005I\n\u00032\u0017\u0004~\u0001\u0019\u0012})\u0000\u0004\u001bp\f!6\u000bK>\\\u0011&\u0006b\u000e\t\u0015E5:\u0006\rf\u0017\u001b\u0010\u0007B~1\u001d\u0007^t_y/Y{>\u0015$\u0007~;8\fx\u007f\u001c\u00127T*\u001fF\u0003\\\u001bG -\u0001+\u001e1'\u0005<_D4z\u0003\fC'\u0002=\\\u001e\u0017\\\u000b\t4tR\u0004\u00129\rG}_2ww=\u001cyu\u0002\u000eG\u00179rbG2\t\u0003%\f\u001e.c\u000f**\f@!Y4\u000fi\u001f\u0007\u0001tyy\u0001\u00170\b\u0007\u0007\tjt&!*\bG\u00180D\u0010\u0007%$X)@&\u0018>'ez8y\u0015\u0000t\u001b\u0017-\u0007*;\t$c#\u001c\u0004(\u0004 [<\u0007s<'\u00122Gf\u0012\u0011\fd\u0017*\u0015\tf4\u0005\u0016\fCb\u0011D7C\u0019+C\rd<_\u0017\u0003|9\u0007>p~b\\y&U\u001a_\u0019\u0017Vb\u001c!7^\u001e;\u001a(R\u0003\u0007\u000b\u0003\u007f~[\u0000)S4<21~\u000f^\u00195b'Y\u00165if\u0002\u0018\f~;\"\u0004\bu\f92\u0003^\u007f%\u0004\u0018e\f'y\u0003V\u0003>;\u0010\t\u000f)\u0015yt\u000f)>\u0002p\u00141\u0004\u0005F\u0014,%\u0013\u0001\u0019)\"\t\u001e\u000f)&6p:-1nK\f\f1&\u007f\u001b \"ut\u000b\u000f\"\u0014pt]\"\u000fg/:y\u0015}9\u0005K\na$/\u000b7u!_:x\u0001\u001b=\u0004\tF\u0014,%\u0013\u0001'*1&F\u000b\u00072\u0014pt]\"\u000fg/:'\rE P8\u0011X\n\u0010\u0005\u0005]z!Jqg\u0018\u001fy\u0005`\u0014\"8.k\u0004\u0000\u0005\"\u007f\f96\u0007s\u001c)7&V\b*2\fD.&E1x\b\u0010:\n\u001a9Y6/tt;\u0000\u0011e+\u001a\u0014\u0015\u0000(0\u0018\b^49*nt>\u001ay)|\f\u001c\u0006%i\u0005G\u0005\u0015s\u0005Y\u0019\rD\nZ\u0010$_\u0019\u0006\u001e\u0002\\?-\u0011\u0019[.#0)K\u0018\u0011:,k\u0002%\u0018\u0019u$\u0019\u0004yR;\u0018<1\u001e\u007f8%tp)\u000fyq\u0007\u0002G\u001d\u0017B\u0007P\u0017\u0016~yY#q[ 8E\u0011\u0007+\n\u0007\u0006S+1\u001e#f}?F\u0003[+!\u00075T=[ 1\u001a)?<\bC\u001a\u000b1\u0000xfX\u0007\nx\u0007.y\u0011_!=\u0018(P\u0014\\:\u0003x<,\u00157\t\u00032F\u0018s/\r\u0001\u000eV\u0002\u0012$wB\u001f*\u0010u}}\u0006\u0012ud\u0018C83Z\u007f=Ky\u0007\u0018)\u0011r}8\u00026\u0017\u0001!\u001by\u0018b\b1B\u0010b9\r76B\u0002\u000713Af\u001d\u0005\u0007c\u0019\u0018A\b_\u000f\u001d')By\u001852X;Q\u00184i.\u0004%;u\f/\n\u0012[y\f\t1\u0002}\fK5S\u001c\u0003y\u0002p\u0018\u001fD\u0002\u0003t+Dxw;Y0t@+8\u0001,p\b;\u0001\"X\u0004\u0010\u0003&\u0001\u0015\\C\na\u0000\n\u0003pk\u001a>\u0011%\u0005pb^l\u001c`E6\u000fum+6\u0013e\u0004.:\u0002p\u0019-^l\u001c`Eyl\u001c`E^\u0003t\n!=ar\b:'\bw\u0004+2\u0015t`E^l\u001cG%:\bt\f,0\u0002p8\u0001\u0014\u0000F\u0004*2&x\u000f)7\u0000\u007f\u000f\u000f\u00180Y&\u00014xF}*2\u0010d\u000b)7\u0003[\u00009\u00006r\u001c17\u0017`\u001c/66{\u001b=\t\u0004YG%1yv\fY&\u0004r%%*\u0017v%\u0004:\u0004U;!6\u0013Y\u0017/!tx\b\f\n#\u0002\u001b\u001f?\u0002s\u0007\n\u001e\fD\u0000<66}:17\u0017`\u001c$68Y\u0005\n\n\u0003tG1$\u0013Z(;1\u0005S\n.\t\"H\f\u0011:\u0004\u007f!\u000b\u001d\u0013A\u0017\u0005\u001f+h\u0015:\u0003#\u0003y\u000f\"\u0019g}\t4xH,0!t|\u000f\\+\u0005e\fX>\u0005h4''\u0004\u0002G%7\u0018H\u0000.\u001c\u0019u\u0019%C\fu\u0014\u0011<\u0015t~%7\u0018H\u0000.\u001c6h7-?\fp&/2pd\b*\u001b\fr\u001b>>9x\u0019)\u0015\u0003V\u0003>1\u0000^\u0019/5\u0013^G2 \u0003y/\u00111\u0004h\u001a:\u0018$b\u000f \u0010,\b|\u000b06V\u001e?F+}'-\u000b\fru/2pd\b+\u000b\f^\u001fZK&c\n.\u0018\u001by&\u000f\"sI%\u000b@\fVG%\u001a\u0003u\u001709qP\u001a2\u0003\u0018\u0003\u000bX\u0012\u0016\b8!6\u0007\u0000)/\u001b7R \u0004C$e\u000e+2\u0012p:,\"\u0018{\u0006\u0007)\bY;\u000b=\u0000`\b*1\u0010p\t\u000f\u0014\u0004\u007fG)7\u0002r\f9\u0014\u0002V*-1\u0000\u007f{\fBjA\u0015/6,Y\u001aC\u0005\u0019i}\u00014wCz\f\\je;2\u000b;\u0001\u0017?\u001a;g~/\u0014\u0019_(_D\u001bE\u0007^+\u0002pG8%\u0018h\u0014\u001f\u001b7\u0003;$>qutG2-`$>1\u0005h>\u0007;\u0014F\u0005=J\u0012\u0002b \u0017y|f\r82P\f_&&P4Q\u0002\n\u0006\u0005.\u001a\t\u0006\b\u001d\u000bwFG\u001f\u0017)w\u0007ZX0\u007f|\u0002@)H/0A\u0002\u0002\u007f\u0019!$\u0002\u0005[:se<1+\u0011\u0003\u001a1\u00185B<\n\u001fsXb\u0007\u0019&rt]\\th}>G$G\u0001'\u0007\u0019XG-\u0002\be\u0001\f\u001a\u000eC|P \u0011P\f!1\u0010X\u007f08\u0017]\u0002)!\u0007\\\u001f^\u0019\u0018v\u000fX\u000b\u0014v!\u000b\u001e\bS\u0014\u001b&'S|P\u0012\u0010Cy+&\u0016f\"\u001a\u001a\fhG\t\u00059\u0005\f^\u001f\u000fWy,7j@9\t\\\nw\f\u0018>.k\u000b\u001eE8H\u0002Q\u0016\"F~\u001d\u0017v\u0003,Q\u001d,h;$6\tk{!%\u0005U\u007f\u000f$\fk\b\r\u0004.\u001aG1\u001a)W8\u00036\td|\u0002#\u0004iy\\\u0017\fiyGD\u0017A&!X\u0004U\u0002\u0019+\u0006\u0007u+2\u0010~'\u000f\u0010\u0000F*\nC6y\u001c17\u0017c}'1\u0003h\b.=\rtG\u001b=\nc|-\u0004\u0013R/&\u001b8K\u007f\u0000\\5\u0003\"\t\u0007\u0015[\u0000!4\u000fs*&%\tb\u0000-\u0014\u0018d:\u000f*\np\u000b&?\u0004B\u0003#!pt::\u0010#\u007f%\u0011\tsYGG\u0007s^,\u001c'+^\u001a\r\u0018\u001be\u000f\u0002>\u0010B:+\"\u0018u\u001b9\"\u0006t:\"%\u0014K\b\u0000>\u0003\t\n)B\u0014t\u000e\u0000>\u0018g\n\u0000\u001f\bt)\u001e:\u0004c%24\u0013\u0004G!6%H/[%6}\u000e*9#\\\u0000\u001d>\u0015t:$\u0004\u0018u\u001b9\"\rt4\u0000;#H\u000f-*\u0016c&\r \u0003u//5;R4)\n\bt\u0003\u0004\u0010/c=2\u001e-[G1+\u0013A/ZG&`\u0015>C vt\u0011\u0012\u0019cx\u000f\u0014\u0004p\u0000)\u0004\u0006p|=\u0017\u0004F\u001c.>\u0000|\u000f)\u0015yF\t9*\u000bz\"2:)G.&2\u0010t\u000b*\"\u0000uG\u000f\u0014\u0004s\f,9\r\tz$8\u0011A\u0005P62P%*G8~)^2;s%:\u0010*sy1J6X 8\".kf1\u0016\u0000t\u001a]\u0003t{\u00140>\u0011\t}\u0003$\u000fHG'<v|\u0005)4+y\u00179\u001c1u\u0005Z\u00162c\u0018Y\\#]\u0000>\u0014\u0005^>\u0012<\u0018E8=!\u0019~|\u001eC\u0019{\u0007$+\u0017V*#\u0007\b\u0002!\u0018\u0019#X\u007f<\u0010vaG<>.K\u0004C\u0014\"X\u0006\u0019\u0017(\u0001\u000b\u001d52Z*]*,T7<\u0005 R\u001d\fX,b\u0014\u000f5\u0007`!\u0019AtK%\r\u0012#x\u0017X8#x\u0004'\u0002\u0011[\u000e,#.`G \u001e8fz\\\u0010\u000fI\fQ\u001b(\u0007~\u001d\u00148D\u001bC:wb% :t\u00074,\u0002&\u001a\u007f,\t\u001bU8+?;C\u0019\u0001\u0012sR4\u001e\u0018q\u001e\u0017%\\(k5\\\u001e\u0004cG\f63\u001e\u001b\u0010\u0002\tu~>:\rBt:\u0012\u0013T*)\u001b\u000bY!\f+\u0013`\u0001!\"\u0015~z-\u0001\u0003s\t\u0018\u0002\u0016T\u000e\u001c$\u0017h=\u0007=;\u0005$+\u000b\u0015x\u0000]04WG:\u0016\u0018\u007f#\u0011\u001a\"B/\u0003\u0002\u0016](\u001c=6\u001a; +nS;2K|;`E^l\u001c\b&7ar\b:'\bw\u0004+2\u0015t`E^l\u001cGE^l\u001c`*6\u0006x\u0003H0\u0004c\u0019!5\br\f<6l\u001c`E^K|\u0004!7%K\u000e+2-\u001a*)\u0004\bs\f\u000f:\u0004p*)24e\f&1&Z<\u0000\u0018(vt\u001fC\u0003p\u001c=5\u0000u\u000f\t>\u0010B:+\"\u0018u\u001b9\"\u0006t:\"9Kc\u0019- \fs\f/2pd\b+\u001b\f{\u001c\u000552U\n\u0004\u0007#\u0002\u0007\u0004>\u0013|:-\"\u0018u\u001b9\"\rt:\u00187$f\u0007\u0004\u0010-c4\f+\u000f\u0001\u0000;:6x\f17Kg\u001c97\u0004I!+*\u0016I}\t$pG.\u0005&&`~\u0004\u001a\u001bi\u0007=\u0010/g7\f0\u0003b/ZJq|\u000f\\+\u0005e\f\u001f>\u0005d5%\u0019\u0004\u0005\u0003,*6|\u000b\u0007+Ku\u0019!B\fu\u0018\u0010>+x7&'*F\u0000.\u001c6f'-?\fp&/2pd\b*\u001b\fr\u001e=&9t')\"\u0003V\u0003>1\u0000^\u0019+&\u000bY/ !1S\u001aQ\nKk\u0019-'\fs\b/2pd\b+\u000b\fz\u001c[\u001f(k\u0015\"&\"_\u001b\u0012\u0017\u0005t$%0\u0000v\fY&\u0004p5%)\u0010\\\u000b\u001b\u0017\u0006]9\n@\u000b]\u0004-=th >\nKg\u0005\"B\"\u0002\u001c\u000f&,\b;\f7\u0002r\f;:6u\u001c19\n^\u0017!\u001b7R\u0003)\"\u0004s\u000f92\u0005V*-#\u0000u\u000e+2\u0010^\u000e\u000f\u0014\u0004s\f#>\u0004D4#\u0001K\\\tY+wr\u0017\u0011\u001e3gxY0/Xy\r\u001a\u0017V\u0001/\u0004u\u00008'88\\,2=jY\u0015\rA6r\u001c>\u0007sH*\u001d\t,z$1\u0005w\u0001$&\u001c\u0012\u00077\u0002\u0001Kx\u0017[2\u0010b>*&/D\u0004\fJ\fR'P\u0016wD\u0014\u0001B V#\u0006\u0010jV\u001f98'c7%\u0003([\u001e[\u001f+F8\u0005&\u000fz\"=>\f^{\u001e$3{\u0014\r8K\\=1\u00100f(\\#6K\u001bQ\\-b\b\u0011\\\u0002vt>\u0004\"a\u000e8\u0004\u0003}\u0006*\u00004Py\f\u001d\n|~\u0018@pG'\u001b\u0006'w\":6\u000bx\bQ?\u0000F<;\u0006Ki ,X5@\u0014.\\\re)*B*r|.\u0018\u0018\\\n8B1f\u001d\u000f\u0018\u0000It0\u0011\bv(\u001e<\u0007\u00078\u001e&\u0000\u0007x\r\u001b\u0005\u0004+G\u000b\u0019E,\n\tt~\u00192\nKU.Q@\u0014Z~\u0012\n\u001bp>\u001d'r]4;=\u0015a5P\u0018,r\u000b\u000b1tZ=\u001e\u0010\u0018\u0007z'\u00174Y'\u0018\u0001-\u0002\u001f\u0002>v\u0000\"/7\tF(!BsGb\u0011\u0016K[!X\u0002)@)&\u0018\u000fF#/\u0019*r\f\u001f6\u0000p,&5\ft\u0000\u001f;\u0010h\t>!q~\u000f**\u0004w\u0002?\u0017\u0016e\u000e+!p[\u0000\u001a#.x\u001b,\u0012\u0006T7\u0019BKs\b[\u0004\fs\u0004/2pd)-\u0004\u0004sb\u001f\"\b|\f11\u0000Wu+2\u0010|:,\u0014\u0018u\u001b:C\u0011p\u001c \\\u0003p\u001c,2&t\n%2qv\u000e;\u0002\u0006b\u0004\n@Ku\u001c-1\u0003`\u0018)2ux\u000f)\"\u0002w\t.A\u000e\u0004\nQ! t\u0004.\u001c\u000f\u0003z<\n\"]%)<x\b\u007f<J\rU.\u001fGw`\u001c.X7P\u0006;\u001esT\u0019QAK\b%\u0003'\b\u0006*907]\u0014\u0018=\u0013Y.$C\u0004h\u001a\u0007 (Y+>03\u0002\u000b\u001e7\u0003\t|\u001d\u0018\f{\u0014Z4\u0010tb\u001b\t\n\u007ff'>\u0018\u0002\b=\\5\u0002\u001a\u000f\u000bK[&\u0012 2F\u000bXD3\u0004|0\u0014%x\n\u0006J6\u001e52\u0010)|\u000f]\u001b#V\u000bG+j\u001a\u0017:4+uu)05a%;=;Z\bY\u0012*I(\u0000\u001an^\u000e\u001aCKt=\u0006@.\u0001\u001a+G;I(Q)sT9\u000b\u001a$W\u000e_:1{x'0\u0003c\u0001\n\u0015pF/?\u0000 hzY\u0018tYf[\t7u4\u0006\nw\u0006\n_\u00158d\u0004\u0000\tKZ>$\u001auI,&\u001e+x\u000e\u0019Guh~\r\u0018\u0010t(]X\u000fP89\u0001;\u0005:\u0004;3`\u0000\u0012A/k\u001cGBnx{\r*2\b\u0005:06s\u0015\n\u0000%E\u0019$ Kct!G\rE\tC\u0014%F4\t\u001bw\u0000z\u0002\t\u0017\u001e\u0002\r1\tc#,9\u0004}<1\t,AGE^l\u001c`-=\u0005\u0011\u000e-!\u0015x\u000b!0\u0000e\bE^l\u001c`b^l\u001c`E1\u0004v\u0004&S\u0002t\u001f<:\u0007x\u000e)'\u0004\u001c`E^l;\u0000!:\u0005I\u0019+0\u0000@\u007f\u000f26x\u000f)\u0014\b`\f\u0019\u000b\"{ \u0007?\u0010{880r_4\u001a\u0018\u0018])\u00122\u000fs*\u0003\u0002)Z$/J6\u0001\u000f)\"\u0014w\f,12;\u00009\u00006r\u001c17\u0017`\u001c/66{\u001b=\t\u0004g\u0000*>\u0006p|=6\u0002Y\u0000%!\u0006]#\t&\u000f].\u0006\"&b\u001a]\u0019\fc&\u001f56h\t>\"\u0010}\b\u00101r;)[\u00104k\n\u0004\u001d f\u0003\u0004\u0010/`81AxE\u0000;\u00006z\u001c17\u0017`\u001c,68{\b\t$%A\u001cZ%8U\u000e*: f)\u0007:\u0004w7\u000b@\u0017H\u0014?F+;\u0017;1\u0007g$* #\u0003tX:\u0004\u007f\u000f%1ui\t<2s|\u0019-\u000b\fu\f\u001f>\u0005p:%5.i\t<>9|\u0019-\u000b\fu\f\u001f>\u0005p:%5.F/,6\r;\u0000)\u0018\u0006p|=6\u0003Y\u0000+%\u0017|5.'\u0000e\u000f\u000f=\u0017s\f\u0007'\u0005t\u001f\u0018)s]\t2+\u000b\u0001\u0004-\u001f4h7-)\fs./2pd\b+\u000b\f`)[\u0017r;\u0001\u0005!1k\u007f\u0004\u0019\u001bi\u0007X?,\u007f;\n'\u0004C\u0000+\u0018\u0006p|=6\u0000I\u0000\u0001!\u0006]#\t&\u000f].\u0006\"&b\n\u0004\u001d r\u000f*\u0010r\u007f|\u000b\u001e\u0007D\u0014Z&&;\u001f>*&d Q\u0005%r\u000f,\"\u0015r\u000e) \bF\t9*\u000bz\"2:)G.&2\u0010t\u000f*\"\u0000u*\u000f6\u0011p\t+0\u0000`\"+\u0014&t\u000f)>#|x0#,;fQ v\u0004\u001eX\u0007\f@/\u000eF\u0018tb\u0011\u0010q]\u001e\n)9z>8%-u\u001f\u0006\u001c&^.\u001b5xA=\u000309I\u0001\r\n+\b\u000e1\u0003\n]\u000f?'3e~\"'\u0016;\u001d&\u0007q~\u0006:8;t}\u0004\u00147U\u0006\u0018%\fb\u0002'D;b\u001aY\u000b*ix\u0002\u00070D 0K\u000eZ%8\u001b\u0011h!/Xj|\u0015\u001bA;X\u001e\\\u0004#]\u000e\"6\f;5+\u001b\u0003g+\u001e?\u0016^&>\u0015/y\"&\u0011x\u007f.\u000f\u0018xG'\u0007G\u0014w9[>\u0013D\u0003\u001bK\"Z\u001f2\u0002/C\nX2\u0007w\"-\u0007v^\u0019^B\u0004z -5\u0003;\u0004\u0003F-h\u0014\r1\u0010g\u000e\u0005\u0016\u0017H\u0007[\u001b-z\u001bQ&4\u0004!X\u0010\u0014H5C\u001e\f\u0001,*\u001b Z, #\u0010\u007f\f9'\u0019z\u000b\u0010CpAu>\u00175T\u0017'6r;%\u00121\u0016s\u0002=!5r )67wx'*(X\f\u00005y{\u007f\t@(})\\K2^\u0006\u00197(C\u000e\u0005'\u0002G\u007f2\u0017-h\u0019*\u001c\u0012d(\u0000BqP\u0018)\u0000&;\b\u001b\u000b\u0003D\u007f\\?\u0014e$\\ yB\u000e)\u0004\u0004p\f\t=+|\n-\u0004\u0005V\u0014,%\u0013\u0001\u001d)\"\t\u001e\u000f)\"\u0005p*/4\fpu/2pd)-\u0004\u0004sb\u001f\"\u0007;\u0000)>\u0003p+P\u0004\t`\u0014,%\u0013\u0001\u0002*1\u0018t\u000b$6jF\u007f\u00037j}t 2%b\u0014\"\u001b.x\f\u001dJ+k\u000e\u001e7\fsu/2pd)!\u0004\u0010h\u0000*\u0012\u0000;\u000b$6jF\u007f\u00037j}t 2%b\u0014\"\u001b.x\f\u001dJ+k\u000e\u001e7\fp}/0\u0012@\n;:#\u0002\t96\u0003s\u001c=2\u0000\u0005\u0004*2\u0010p./\u0014 i~&\u0016\";#\u0012\n\bk*1:\u0017H\u0005\n:\u0014Wy#\u001e$@;\u0010\u00148U&)\"\u0017\t\n#KrC\u0017-$\u0016~\u0003\u000e\u0002$\u001e\b?B/E!%>\u0014Dy\u0003\u0016)u\u0001!E;;(%D#\u0005|&F\"U/\u0004:\u001b`\u000fZ\u001f\u0016y \u0001!*\b\"\u0018\u001e;\u007f{\u000b=y\u0003\"&?\u0007A \u0011#\b_#\u000f\u001a\n\u0002\u000f,Gpg\u0005%$\u0004kzY\u0019\u0007;%;J\u000e|\u001d\t\u0014\fc\u0014\u0002\n\u000eW$2!\u0018K4_K v{)Jj|=\r\u001a;v\u000112({\u00019\u0004\u0006i\u000b#@9a&#\u001e\u000ft\u001b0Fyb;\u0006\u0004s;\u0014\u0012\u001axc\u0006:\\tr\u0014\u001a02b\u0015\t\"rA''?\u0000t\u000b\rG8y\u0014;\u0018\u0017i4;4/h;+\u001c\u0002f:Q6pr\f\u0010Anb{\u000b0\u001bU&/0$;;-\u0000\u0019r\u001eCC8Ix,\u0012\fZ\u0005\"K\tb\u00158\u00150x/\u0004\u001c\u0004A:P\u001d\r\u001a(G:\u0003R Z#\u000f\u0006\b\r\u0002\u000bb)\u0006\u001c\u0005W7):\u000b\b\u001b&\u00161;f'\u00184t{&@wst#yl\u001c`E^\u0004\u007f\tH0\u0004c\u0019!5\br\f<6l\u001c`E^K"
        //     7: astore_1       
        //     8: iconst_m1      
        //     9: istore_2       
        //    10: aload_0        
        //    11: astore_3       
        //    12: iconst_0       
        //    13: istore          4
        //    15: aload_1        
        //    16: invokevirtual   java/lang/String.toCharArray:()[C
        //    19: astore          5
        //    21: aload           5
        //    23: arraylength    
        //    24: istore          6
        //    26: iconst_0       
        //    27: istore          7
        //    29: iload           6
        //    31: iload           7
        //    33: if_icmpgt       223
        //    36: new             Ljava/lang/String;
        //    39: dup            
        //    40: aload           5
        //    42: invokespecial   java/lang/String.<init>:([C)V
        //    45: invokevirtual   java/lang/String.intern:()Ljava/lang/String;
        //    48: astore          10
        //    50: iload_2        
        //    51: tableswitch {
        //                0: 87
        //          default: 68
        //        }
        //    68: aload_3        
        //    69: iload           4
        //    71: aload           10
        //    73: aastore        
        //    74: ldc             "d\u0019.^y"
        //    76: astore_1       
        //    77: iconst_1       
        //    78: istore          4
        //    80: aload_0        
        //    81: astore_3       
        //    82: iconst_0       
        //    83: istore_2       
        //    84: goto            15
        //    87: aload_3        
        //    88: iload           4
        //    90: aload           10
        //    92: aastore        
        //    93: aload_0        
        //    94: putstatic       com/whatsapp/messaging/a6.z:[Ljava/lang/String;
        //    97: ldc             "ic]Cx"
        //    99: invokevirtual   java/lang/String.toCharArray:()[C
        //   102: astore          11
        //   104: aload           11
        //   106: arraylength    
        //   107: istore          12
        //   109: iconst_0       
        //   110: istore          13
        //   112: iload           12
        //   114: iload           13
        //   116: if_icmpgt       313
        //   119: new             Ljava/lang/String;
        //   122: dup            
        //   123: aload           11
        //   125: invokespecial   java/lang/String.<init>:([C)V
        //   128: invokevirtual   java/lang/String.intern:()Ljava/lang/String;
        //   131: astore          16
        //   133: aload           16
        //   135: invokestatic    java/security/cert/CertificateFactory.getInstance:(Ljava/lang/String;)Ljava/security/cert/CertificateFactory;
        //   138: astore          18
        //   140: aload           18
        //   142: new             Ljava/io/ByteArrayInputStream;
        //   145: dup            
        //   146: getstatic       com/whatsapp/messaging/a6.z:[Ljava/lang/String;
        //   149: iconst_0       
        //   150: aaload         
        //   151: getstatic       com/whatsapp/messaging/a6.z:[Ljava/lang/String;
        //   154: iconst_1       
        //   155: aaload         
        //   156: invokevirtual   java/lang/String.getBytes:(Ljava/lang/String;)[B
        //   159: invokespecial   java/io/ByteArrayInputStream.<init>:([B)V
        //   162: invokevirtual   java/security/cert/CertificateFactory.generateCertificates:(Ljava/io/InputStream;)Ljava/util/Collection;
        //   165: astore          21
        //   167: aload           21
        //   169: aload           21
        //   171: invokeinterface java/util/Collection.size:()I
        //   176: anewarray       Ljava/security/cert/X509Certificate;
        //   179: invokeinterface java/util/Collection.toArray:([Ljava/lang/Object;)[Ljava/lang/Object;
        //   184: checkcast       [Ljava/security/cert/X509Certificate;
        //   187: putstatic       com/whatsapp/messaging/a6.d:[Ljava/security/cert/X509Certificate;
        //   190: iconst_1       
        //   191: anewarray       Ljavax/net/ssl/TrustManager;
        //   194: astore          22
        //   196: aload           22
        //   198: iconst_0       
        //   199: new             Lcom/whatsapp/messaging/q;
        //   202: dup            
        //   203: invokespecial   com/whatsapp/messaging/q.<init>:()V
        //   206: aastore        
        //   207: aload           22
        //   209: putstatic       com/whatsapp/messaging/a6.e:[Ljavax/net/ssl/TrustManager;
        //   212: new             Lcom/whatsapp/messaging/a6;
        //   215: dup            
        //   216: invokespecial   com/whatsapp/messaging/a6.<init>:()V
        //   219: putstatic       com/whatsapp/messaging/a6.c:Lcom/whatsapp/messaging/a6;
        //   222: return         
        //   223: aload           5
        //   225: iload           7
        //   227: caload         
        //   228: istore          8
        //   230: iload           7
        //   232: iconst_5       
        //   233: irem           
        //   234: tableswitch {
        //                0: 285
        //                1: 292
        //                2: 299
        //                3: 306
        //          default: 264
        //        }
        //   264: bipush          65
        //   266: istore          9
        //   268: aload           5
        //   270: iload           7
        //   272: iload           9
        //   274: iload           8
        //   276: ixor           
        //   277: i2c            
        //   278: castore        
        //   279: iinc            7, 1
        //   282: goto            29
        //   285: bipush          49
        //   287: istore          9
        //   289: goto            268
        //   292: bipush          77
        //   294: istore          9
        //   296: goto            268
        //   299: bipush          104
        //   301: istore          9
        //   303: goto            268
        //   306: bipush          115
        //   308: istore          9
        //   310: goto            268
        //   313: aload           11
        //   315: iload           13
        //   317: caload         
        //   318: istore          14
        //   320: iload           13
        //   322: iconst_5       
        //   323: irem           
        //   324: tableswitch {
        //                0: 377
        //                1: 384
        //                2: 391
        //                3: 398
        //          default: 356
        //        }
        //   356: bipush          65
        //   358: istore          15
        //   360: aload           11
        //   362: iload           13
        //   364: iload           15
        //   366: iload           14
        //   368: ixor           
        //   369: i2c            
        //   370: castore        
        //   371: iinc            13, 1
        //   374: goto            112
        //   377: bipush          49
        //   379: istore          15
        //   381: goto            360
        //   384: bipush          77
        //   386: istore          15
        //   388: goto            360
        //   391: bipush          104
        //   393: istore          15
        //   395: goto            360
        //   398: bipush          115
        //   400: istore          15
        //   402: goto            360
        //   405: astore          17
        //   407: new             Ljava/lang/RuntimeException;
        //   410: dup            
        //   411: aload           17
        //   413: invokespecial   java/lang/RuntimeException.<init>:(Ljava/lang/Throwable;)V
        //   416: athrow         
        //   417: astore          20
        //   419: new             Ljava/lang/RuntimeException;
        //   422: dup            
        //   423: aload           20
        //   425: invokespecial   java/lang/RuntimeException.<init>:(Ljava/lang/Throwable;)V
        //   428: athrow         
        //   429: astore          19
        //   431: new             Ljava/lang/Error;
        //   434: dup            
        //   435: aload           19
        //   437: invokespecial   java/lang/Error.<init>:(Ljava/lang/Throwable;)V
        //   440: athrow         
        //    Exceptions:
        //  Try           Handler
        //  Start  End    Start  End    Type                                     
        //  -----  -----  -----  -----  -----------------------------------------
        //  133    140    405    417    Ljava/security/cert/CertificateException;
        //  140    190    417    429    Ljava/security/cert/CertificateException;
        //  140    190    429    441    Ljava/io/UnsupportedEncodingException;
        // 
        // The error that occurred was:
        // 
        // java.lang.IllegalStateException: Expression is linked from several locations: Label_0223:
        //     at com.strobel.decompiler.ast.Error.expressionLinkedFromMultipleLocations(Error.java:27)
        //     at com.strobel.decompiler.ast.AstOptimizer.mergeDisparateObjectInitializations(AstOptimizer.java:2592)
        //     at com.strobel.decompiler.ast.AstOptimizer.optimize(AstOptimizer.java:235)
        //     at com.strobel.decompiler.ast.AstOptimizer.optimize(AstOptimizer.java:42)
        //     at com.strobel.decompiler.languages.java.ast.AstMethodBodyBuilder.createMethodBody(AstMethodBodyBuilder.java:214)
        //     at com.strobel.decompiler.languages.java.ast.AstMethodBodyBuilder.createMethodBody(AstMethodBodyBuilder.java:99)
        //     at com.strobel.decompiler.languages.java.ast.AstBuilder.createMethodBody(AstBuilder.java:757)
        //     at com.strobel.decompiler.languages.java.ast.AstBuilder.createMethod(AstBuilder.java:655)
        //     at com.strobel.decompiler.languages.java.ast.AstBuilder.addTypeMembers(AstBuilder.java:532)
        //     at com.strobel.decompiler.languages.java.ast.AstBuilder.createTypeCore(AstBuilder.java:499)
        //     at com.strobel.decompiler.languages.java.ast.AstBuilder.createTypeNoCache(AstBuilder.java:141)
        //     at com.strobel.decompiler.languages.java.ast.AstBuilder.createType(AstBuilder.java:130)
        //     at com.strobel.decompiler.languages.java.ast.AstBuilder.addType(AstBuilder.java:105)
        //     at com.strobel.decompiler.languages.java.JavaLanguage.buildAst(JavaLanguage.java:71)
        //     at com.strobel.decompiler.languages.java.JavaLanguage.decompileType(JavaLanguage.java:59)
        //     at com.strobel.decompiler.DecompilerDriver.decompileType(DecompilerDriver.java:317)
        //     at com.strobel.decompiler.DecompilerDriver.decompileJar(DecompilerDriver.java:238)
        //     at com.strobel.decompiler.DecompilerDriver.main(DecompilerDriver.java:123)
        // 
        throw new IllegalStateException("An error occurred while decompiling this method.");
    }
    
    static X509Certificate[] a() {
        return a6.d;
    }
    
    public static a6 b() {
        return a6.c;
    }
    
    @Override
    protected SSLSocketFactory a(final SSLContext sslContext) {
        try {
            sslContext.init(null, a6.e, null);
            return sslContext.getSocketFactory();
        }
        catch (KeyManagementException ex) {
            Log.b(ex);
            throw new RuntimeException(ex);
        }
    }
    
    @Override
    public Socket createSocket() {
        return super.createSocket();
    }
    
    @Override
    public Socket createSocket(final String s, final int n) {
        return super.createSocket(s, n);
    }
    
    @Override
    public Socket createSocket(final String s, final int n, final InetAddress inetAddress, final int n2) {
        return super.createSocket(s, n, inetAddress, n2);
    }
    
    @Override
    public Socket createSocket(final InetAddress inetAddress, final int n) {
        return super.createSocket(inetAddress, n);
    }
    
    @Override
    public Socket createSocket(final InetAddress inetAddress, final int n, final InetAddress inetAddress2, final int n2) {
        return super.createSocket(inetAddress, n, inetAddress2, n2);
    }
    
    @Override
    public Socket createSocket(final Socket socket, final String s, final int n, final boolean b) {
        return super.createSocket(socket, s, n, b);
    }
    
    @Override
    public String[] getDefaultCipherSuites() {
        return super.getDefaultCipherSuites();
    }
    
    @Override
    public String[] getSupportedCipherSuites() {
        return super.getSupportedCipherSuites();
    }
}
