// 
// Decompiled by Procyon v0.5.30
// 

package com.google;

import java.util.Map;

public final class bv implements hV
{
    @Override
    public aU a(final c1 p0, final Map p1) {
        // 
        // This method could not be decompiled.
        // 
        // Original Bytecode:
        // 
        //     0: aconst_null    
        //     1: astore_3       
        //     2: getstatic       com/google/fi.d:Z
        //     5: istore          4
        //     7: new             Lcom/google/i;
        //    10: dup            
        //    11: aload_1        
        //    12: invokevirtual   com/google/c1.c:()Lcom/google/L;
        //    15: invokespecial   com/google/i.<init>:(Lcom/google/L;)V
        //    18: astore          5
        //    20: aload           5
        //    22: iconst_0       
        //    23: invokevirtual   com/google/i.a:(Z)Lcom/google/fi;
        //    26: astore          27
        //    28: aload           27
        //    30: invokevirtual   com/google/fi.a:()[Lcom/google/cs;
        //    33: astore          28
        //    35: aload           28
        //    37: astore          7
        //    39: new             Lcom/google/bP;
        //    42: dup            
        //    43: invokespecial   com/google/bP.<init>:()V
        //    46: aload           27
        //    48: invokevirtual   com/google/bP.a:(Lcom/google/fi;)Lcom/google/aS;
        //    51: astore          29
        //    53: aload           29
        //    55: astore          8
        //    57: aconst_null    
        //    58: astore          9
        //    60: aload           8
        //    62: ifnonnull       327
        //    65: aload           5
        //    67: iconst_1       
        //    68: invokevirtual   com/google/i.a:(Z)Lcom/google/fi;
        //    71: astore          23
        //    73: aload           23
        //    75: invokevirtual   com/google/fi.a:()[Lcom/google/cs;
        //    78: astore          24
        //    80: new             Lcom/google/bP;
        //    83: dup            
        //    84: invokespecial   com/google/bP.<init>:()V
        //    87: aload           23
        //    89: invokevirtual   com/google/bP.a:(Lcom/google/fi;)Lcom/google/aS;
        //    92: astore          25
        //    94: aload           25
        //    96: astore          10
        //    98: aload           24
        //   100: astore          11
        //   102: aload_2        
        //   103: ifnull          168
        //   106: aload_2        
        //   107: getstatic       com/google/bj.NEED_RESULT_POINT_CALLBACK:Lcom/google/bj;
        //   110: invokeinterface java/util/Map.get:(Ljava/lang/Object;)Ljava/lang/Object;
        //   115: checkcast       Lcom/google/fs;
        //   118: astore          17
        //   120: aload           17
        //   122: ifnull          168
        //   125: aload           11
        //   127: arraylength    
        //   128: istore          18
        //   130: iconst_0       
        //   131: istore          19
        //   133: iload           19
        //   135: iload           18
        //   137: if_icmpge       168
        //   140: aload           17
        //   142: aload           11
        //   144: iload           19
        //   146: aaload         
        //   147: invokeinterface com/google/fs.a:(Lcom/google/cs;)V
        //   152: iinc            19, 1
        //   155: iload           4
        //   157: ifeq            133
        //   160: iconst_1       
        //   161: getstatic       com/google/fN.a:I
        //   164: iadd           
        //   165: putstatic       com/google/fN.a:I
        //   168: new             Lcom/google/aU;
        //   171: dup            
        //   172: aload           10
        //   174: invokevirtual   com/google/aS.a:()Ljava/lang/String;
        //   177: aload           10
        //   179: invokevirtual   com/google/aS.e:()[B
        //   182: aload           11
        //   184: getstatic       com/google/d3.AZTEC:Lcom/google/d3;
        //   187: invokespecial   com/google/aU.<init>:(Ljava/lang/String;[B[Lcom/google/cs;Lcom/google/d3;)V
        //   190: astore          12
        //   192: aload           10
        //   194: invokevirtual   com/google/aS.f:()Ljava/util/List;
        //   197: astore          13
        //   199: aload           13
        //   201: ifnull          214
        //   204: aload           12
        //   206: getstatic       com/google/A.BYTE_SEGMENTS:Lcom/google/A;
        //   209: aload           13
        //   211: invokevirtual   com/google/aU.a:(Lcom/google/A;Ljava/lang/Object;)V
        //   214: aload           10
        //   216: invokevirtual   com/google/aS.c:()Ljava/lang/String;
        //   219: astore          14
        //   221: aload           14
        //   223: ifnull          236
        //   226: aload           12
        //   228: getstatic       com/google/A.ERROR_CORRECTION_LEVEL:Lcom/google/A;
        //   231: aload           14
        //   233: invokevirtual   com/google/aU.a:(Lcom/google/A;Ljava/lang/Object;)V
        //   236: aload           12
        //   238: areturn        
        //   239: astore          26
        //   241: aconst_null    
        //   242: astore          7
        //   244: aload           26
        //   246: astore          9
        //   248: aconst_null    
        //   249: astore          8
        //   251: aconst_null    
        //   252: astore_3       
        //   253: goto            60
        //   256: astore          6
        //   258: aconst_null    
        //   259: astore          7
        //   261: aload           6
        //   263: astore_3       
        //   264: aconst_null    
        //   265: astore          8
        //   267: aconst_null    
        //   268: astore          9
        //   270: goto            60
        //   273: astore          20
        //   275: aload           9
        //   277: ifnull          288
        //   280: aload           9
        //   282: athrow         
        //   283: astore          22
        //   285: aload           22
        //   287: athrow         
        //   288: aload_3        
        //   289: ifnull          299
        //   292: aload_3        
        //   293: athrow         
        //   294: astore          21
        //   296: aload           21
        //   298: athrow         
        //   299: aload           20
        //   301: athrow         
        //   302: astore          16
        //   304: aload           16
        //   306: athrow         
        //   307: astore          15
        //   309: aload           15
        //   311: athrow         
        //   312: astore          20
        //   314: goto            275
        //   317: astore          6
        //   319: goto            261
        //   322: astore          26
        //   324: goto            244
        //   327: aload           8
        //   329: astore          10
        //   331: aload           7
        //   333: astore          11
        //   335: goto            102
        //    Exceptions:
        //  Try           Handler
        //  Start  End    Start  End    Type           
        //  -----  -----  -----  -----  ---------------
        //  20     35     239    244    Lcom/google/fv;
        //  20     35     256    261    Lcom/google/fD;
        //  39     53     322    327    Lcom/google/fv;
        //  39     53     317    322    Lcom/google/fD;
        //  65     94     273    275    Lcom/google/fv;
        //  65     94     312    317    Lcom/google/fD;
        //  204    214    302    307    Lcom/google/fv;
        //  226    236    307    312    Lcom/google/fv;
        //  280    283    283    288    Lcom/google/fv;
        //  292    294    294    299    Lcom/google/fv;
        // 
        // The error that occurred was:
        // 
        // java.lang.IndexOutOfBoundsException: Index: 161, Size: 161
        //     at java.util.ArrayList.rangeCheck(ArrayList.java:653)
        //     at java.util.ArrayList.get(ArrayList.java:429)
        //     at com.strobel.decompiler.ast.AstBuilder.convertToAst(AstBuilder.java:3303)
        //     at com.strobel.decompiler.ast.AstBuilder.convertToAst(AstBuilder.java:3417)
        //     at com.strobel.decompiler.ast.AstBuilder.build(AstBuilder.java:113)
        //     at com.strobel.decompiler.languages.java.ast.AstMethodBodyBuilder.createMethodBody(AstMethodBodyBuilder.java:210)
        //     at com.strobel.decompiler.languages.java.ast.AstMethodBodyBuilder.createMethodBody(AstMethodBodyBuilder.java:99)
        //     at com.strobel.decompiler.languages.java.ast.AstBuilder.createMethodBody(AstBuilder.java:757)
        //     at com.strobel.decompiler.languages.java.ast.AstBuilder.createMethod(AstBuilder.java:655)
        //     at com.strobel.decompiler.languages.java.ast.AstBuilder.addTypeMembers(AstBuilder.java:532)
        //     at com.strobel.decompiler.languages.java.ast.AstBuilder.createTypeCore(AstBuilder.java:499)
        //     at com.strobel.decompiler.languages.java.ast.AstBuilder.createTypeNoCache(AstBuilder.java:141)
        //     at com.strobel.decompiler.languages.java.ast.AstBuilder.createType(AstBuilder.java:130)
        //     at com.strobel.decompiler.languages.java.ast.AstBuilder.addType(AstBuilder.java:105)
        //     at com.strobel.decompiler.languages.java.JavaLanguage.buildAst(JavaLanguage.java:71)
        //     at com.strobel.decompiler.languages.java.JavaLanguage.decompileType(JavaLanguage.java:59)
        //     at com.strobel.decompiler.DecompilerDriver.decompileType(DecompilerDriver.java:317)
        //     at com.strobel.decompiler.DecompilerDriver.decompileJar(DecompilerDriver.java:238)
        //     at com.strobel.decompiler.DecompilerDriver.main(DecompilerDriver.java:123)
        // 
        throw new IllegalStateException("An error occurred while decompiling this method.");
    }
    
    @Override
    public void a() {
    }
}
