// 
// Decompiled by Procyon v0.5.30
// 

package com.google;

final class eK extends e_
{
    private static final String z;
    
    static {
        final char[] charArray = "$mLCs\t%M\u000f`\u0015kMJ7".toCharArray();
        for (int i = charArray.length, n = 0; i > n; ++n) {
            final char c = charArray[n];
            char c2 = '\0';
            switch (n % 5) {
                default: {
                    c2 = '\u0017';
                    break;
                }
                case 0: {
                    c2 = 'g';
                    break;
                }
                case 1: {
                    c2 = '\u0002';
                    break;
                }
                case 2: {
                    c2 = '9';
                    break;
                }
                case 3: {
                    c2 = '/';
                    break;
                }
            }
            charArray[n] = (char)(c2 ^ c);
        }
        z = new String(charArray).intern();
    }
    
    public void a(final c3 p0, final fL p1) {
        // 
        // This method could not be decompiled.
        // 
        // Original Bytecode:
        // 
        //     0: getstatic       com/google/cK.l:Z
        //     3: istore_3       
        //     4: aload_2        
        //     5: ifnull          19
        //     8: aload_2        
        //     9: invokevirtual   com/google/fL.b:()Z
        //    12: istore          31
        //    14: iload           31
        //    16: ifeq            28
        //    19: aload_1        
        //    20: invokevirtual   com/google/c3.i:()Lcom/google/c3;
        //    23: pop            
        //    24: iload_3        
        //    25: ifeq            345
        //    28: aload_2        
        //    29: invokevirtual   com/google/fL.g:()Z
        //    32: istore          6
        //    34: iload           6
        //    36: ifeq            111
        //    39: aload_2        
        //    40: invokevirtual   com/google/fL.f:()Lcom/google/f5;
        //    43: astore          20
        //    45: aload           20
        //    47: invokevirtual   com/google/f5.f:()Z
        //    50: istore          25
        //    52: iload           25
        //    54: ifeq            71
        //    57: aload_1        
        //    58: aload           20
        //    60: invokevirtual   com/google/f5.h:()Ljava/lang/Number;
        //    63: invokevirtual   com/google/c3.a:(Ljava/lang/Number;)Lcom/google/c3;
        //    66: pop            
        //    67: iload_3        
        //    68: ifeq            107
        //    71: aload           20
        //    73: invokevirtual   com/google/f5.d:()Z
        //    76: istore          26
        //    78: iload           26
        //    80: ifeq            97
        //    83: aload_1        
        //    84: aload           20
        //    86: invokevirtual   com/google/f5.c:()Z
        //    89: invokevirtual   com/google/c3.b:(Z)Lcom/google/c3;
        //    92: pop            
        //    93: iload_3        
        //    94: ifeq            107
        //    97: aload_1        
        //    98: aload           20
        //   100: invokevirtual   com/google/f5.g:()Ljava/lang/String;
        //   103: invokevirtual   com/google/c3.a:(Ljava/lang/String;)Lcom/google/c3;
        //   106: pop            
        //   107: iload_3        
        //   108: ifeq            345
        //   111: aload_2        
        //   112: invokevirtual   com/google/fL.a:()Z
        //   115: istore          8
        //   117: iload           8
        //   119: ifeq            174
        //   122: aload_1        
        //   123: invokevirtual   com/google/c3.e:()Lcom/google/c3;
        //   126: pop            
        //   127: aload_2        
        //   128: invokevirtual   com/google/fL.d:()Lcom/google/fb;
        //   131: invokevirtual   com/google/fb.iterator:()Ljava/util/Iterator;
        //   134: astore          18
        //   136: aload           18
        //   138: invokeinterface java/util/Iterator.hasNext:()Z
        //   143: ifeq            165
        //   146: aload_0        
        //   147: aload_1        
        //   148: aload           18
        //   150: invokeinterface java/util/Iterator.next:()Ljava/lang/Object;
        //   155: checkcast       Lcom/google/fL;
        //   158: invokevirtual   com/google/eK.a:(Lcom/google/c3;Lcom/google/fL;)V
        //   161: iload_3        
        //   162: ifeq            136
        //   165: aload_1        
        //   166: invokevirtual   com/google/c3.c:()Lcom/google/c3;
        //   169: pop            
        //   170: iload_3        
        //   171: ifeq            345
        //   174: aload_2        
        //   175: invokevirtual   com/google/fL.e:()Z
        //   178: istore          10
        //   180: iload           10
        //   182: ifeq            269
        //   185: aload_1        
        //   186: invokevirtual   com/google/c3.b:()Lcom/google/c3;
        //   189: pop            
        //   190: aload_2        
        //   191: invokevirtual   com/google/fL.c:()Lcom/google/fk;
        //   194: invokevirtual   com/google/fk.a:()Ljava/util/Set;
        //   197: invokeinterface java/util/Set.iterator:()Ljava/util/Iterator;
        //   202: astore          13
        //   204: aload           13
        //   206: invokeinterface java/util/Iterator.hasNext:()Z
        //   211: ifeq            260
        //   214: aload           13
        //   216: invokeinterface java/util/Iterator.next:()Ljava/lang/Object;
        //   221: checkcast       Ljava/util/Map$Entry;
        //   224: astore          15
        //   226: aload_1        
        //   227: aload           15
        //   229: invokeinterface java/util/Map$Entry.getKey:()Ljava/lang/Object;
        //   234: checkcast       Ljava/lang/String;
        //   237: invokevirtual   com/google/c3.b:(Ljava/lang/String;)Lcom/google/c3;
        //   240: pop            
        //   241: aload_0        
        //   242: aload_1        
        //   243: aload           15
        //   245: invokeinterface java/util/Map$Entry.getValue:()Ljava/lang/Object;
        //   250: checkcast       Lcom/google/fL;
        //   253: invokevirtual   com/google/eK.a:(Lcom/google/c3;Lcom/google/fL;)V
        //   256: iload_3        
        //   257: ifeq            204
        //   260: aload_1        
        //   261: invokevirtual   com/google/c3.g:()Lcom/google/c3;
        //   264: pop            
        //   265: iload_3        
        //   266: ifeq            345
        //   269: new             Ljava/lang/IllegalArgumentException;
        //   272: dup            
        //   273: new             Ljava/lang/StringBuilder;
        //   276: dup            
        //   277: invokespecial   java/lang/StringBuilder.<init>:()V
        //   280: getstatic       com/google/eK.z:Ljava/lang/String;
        //   283: invokevirtual   java/lang/StringBuilder.append:(Ljava/lang/String;)Ljava/lang/StringBuilder;
        //   286: aload_2        
        //   287: invokevirtual   java/lang/Object.getClass:()Ljava/lang/Class;
        //   290: invokevirtual   java/lang/StringBuilder.append:(Ljava/lang/Object;)Ljava/lang/StringBuilder;
        //   293: invokevirtual   java/lang/StringBuilder.toString:()Ljava/lang/String;
        //   296: invokespecial   java/lang/IllegalArgumentException.<init>:(Ljava/lang/String;)V
        //   299: athrow         
        //   300: astore          11
        //   302: aload           11
        //   304: athrow         
        //   305: astore          30
        //   307: aload           30
        //   309: athrow         
        //   310: astore          4
        //   312: aload           4
        //   314: athrow         
        //   315: astore          21
        //   317: aload           21
        //   319: athrow         
        //   320: astore          22
        //   322: aload           22
        //   324: athrow         
        //   325: astore          23
        //   327: aload           23
        //   329: athrow         
        //   330: astore          24
        //   332: aload           24
        //   334: athrow         
        //   335: astore          7
        //   337: aload           7
        //   339: athrow         
        //   340: astore          9
        //   342: aload           9
        //   344: athrow         
        //   345: return         
        //    Exceptions:
        //  Try           Handler
        //  Start  End    Start  End    Type                                
        //  -----  -----  -----  -----  ------------------------------------
        //  8      14     305    310    Ljava/lang/IllegalArgumentException;
        //  19     24     310    315    Ljava/lang/IllegalArgumentException;
        //  28     34     310    315    Ljava/lang/IllegalArgumentException;
        //  45     52     315    320    Ljava/lang/IllegalArgumentException;
        //  57     67     320    325    Ljava/lang/IllegalArgumentException;
        //  71     78     325    330    Ljava/lang/IllegalArgumentException;
        //  83     93     330    335    Ljava/lang/IllegalArgumentException;
        //  97     107    330    335    Ljava/lang/IllegalArgumentException;
        //  111    117    335    340    Ljava/lang/IllegalArgumentException;
        //  165    170    340    345    Ljava/lang/IllegalArgumentException;
        //  174    180    340    345    Ljava/lang/IllegalArgumentException;
        //  260    265    300    305    Ljava/lang/IllegalArgumentException;
        //  269    300    300    305    Ljava/lang/IllegalArgumentException;
        //  307    310    310    315    Ljava/lang/IllegalArgumentException;
        //  317    320    320    325    Ljava/lang/IllegalArgumentException;
        //  322    325    325    330    Ljava/lang/IllegalArgumentException;
        //  327    330    330    335    Ljava/lang/IllegalArgumentException;
        // 
        // The error that occurred was:
        // 
        // java.lang.IndexOutOfBoundsException: Index: 161, Size: 161
        //     at java.util.ArrayList.rangeCheck(ArrayList.java:653)
        //     at java.util.ArrayList.get(ArrayList.java:429)
        //     at com.strobel.decompiler.ast.AstBuilder.convertToAst(AstBuilder.java:3303)
        //     at com.strobel.decompiler.ast.AstBuilder.build(AstBuilder.java:113)
        //     at com.strobel.decompiler.languages.java.ast.AstMethodBodyBuilder.createMethodBody(AstMethodBodyBuilder.java:210)
        //     at com.strobel.decompiler.languages.java.ast.AstMethodBodyBuilder.createMethodBody(AstMethodBodyBuilder.java:99)
        //     at com.strobel.decompiler.languages.java.ast.AstBuilder.createMethodBody(AstBuilder.java:757)
        //     at com.strobel.decompiler.languages.java.ast.AstBuilder.createMethod(AstBuilder.java:655)
        //     at com.strobel.decompiler.languages.java.ast.AstBuilder.addTypeMembers(AstBuilder.java:532)
        //     at com.strobel.decompiler.languages.java.ast.AstBuilder.createTypeCore(AstBuilder.java:499)
        //     at com.strobel.decompiler.languages.java.ast.AstBuilder.createTypeNoCache(AstBuilder.java:141)
        //     at com.strobel.decompiler.languages.java.ast.AstBuilder.createType(AstBuilder.java:130)
        //     at com.strobel.decompiler.languages.java.ast.AstBuilder.addType(AstBuilder.java:105)
        //     at com.strobel.decompiler.languages.java.JavaLanguage.buildAst(JavaLanguage.java:71)
        //     at com.strobel.decompiler.languages.java.JavaLanguage.decompileType(JavaLanguage.java:59)
        //     at com.strobel.decompiler.DecompilerDriver.decompileType(DecompilerDriver.java:317)
        //     at com.strobel.decompiler.DecompilerDriver.decompileJar(DecompilerDriver.java:238)
        //     at com.strobel.decompiler.DecompilerDriver.main(DecompilerDriver.java:123)
        // 
        throw new IllegalStateException("An error occurred while decompiling this method.");
    }
    
    @Override
    public void a(final c3 c3, final Object o) {
        this.a(c3, (fL)o);
    }
}
