// 
// Decompiled by Procyon v0.5.30
// 

package com.whatsapp;

import android.os.AsyncTask;

public class a6s extends AsyncTask
{
    private static final String[] z;
    private byte[] a;
    private String b;
    final EnterPhoneNumber c;
    private int d;
    private int e;
    private Runnable f;
    private long g;
    private Runnable h;
    private byte[] i;
    private String j;
    private byte[] k;
    private String l;
    private boolean m;
    
    static {
        final String[] z2 = new String[21];
        String s = "vT>}!%C?";
        int n = -1;
        String[] array = z2;
        int n2 = 0;
        String intern = null;
    Label_0557:
        while (true) {
            final char[] charArray = s.toCharArray();
            for (int i = charArray.length, n3 = 0; i > n3; ++n3) {
                final char c = charArray[n3];
                char c2 = '\0';
                switch (n3 % 5) {
                    default: {
                        c2 = 'T';
                        break;
                    }
                    case 0: {
                        c2 = 'V';
                        break;
                    }
                    case 1: {
                        c2 = '&';
                        break;
                    }
                    case 2: {
                        c2 = '[';
                        break;
                    }
                    case 3: {
                        c2 = '\u001b';
                        break;
                    }
                }
                charArray[n3] = (char)(c2 ^ c);
            }
            intern = new String(charArray).intern();
            switch (n) {
                default: {
                    array[n2] = intern;
                    s = "3H/~&&N4u1yE3~7=T>r:%R:w83Btr;3T)t&v";
                    n2 = 1;
                    array = z2;
                    n = 0;
                    continue;
                }
                case 0: {
                    array[n2] = intern;
                    s = "3H/~&&N4u1yE3~7=T>r:%R:w83Bt~&$I)";
                    n2 = 2;
                    array = z2;
                    n = 1;
                    continue;
                }
                case 1: {
                    array[n2] = intern;
                    s = "3H/~&&N4u1yV3t:3\u000b5n94C)6 9Ivh<9T/";
                    n2 = 3;
                    array = z2;
                    n = 2;
                    continue;
                }
                case 2: {
                    array[n2] = intern;
                    s = "3H/~&&N4u1yC#k=$C?";
                    n2 = 4;
                    array = z2;
                    n = 3;
                    continue;
                }
                case 3: {
                    array[n2] = intern;
                    n2 = 5;
                    array = z2;
                    s = "3H/~&&N4u1yH>ly?H(o5:J:o=9H";
                    n = 4;
                    continue;
                }
                case 4: {
                    array[n2] = intern;
                    n2 = 6;
                    s = "3H/~&&N4u1yR>v$9T:i=:_vn:7P:r87D7~";
                    n = 5;
                    array = z2;
                    continue;
                }
                case 5: {
                    array[n2] = intern;
                    n2 = 7;
                    s = "3H/~&&N4u1yC)i;$\u000b.u'&C8r2?C?";
                    n = 6;
                    array = z2;
                    continue;
                }
                case 6: {
                    array[n2] = intern;
                    n2 = 8;
                    s = "3H/~&&N4u1yV3t:3\u000b5n94C)667Bv};$K:o";
                    n = 7;
                    array = z2;
                    continue;
                }
                case 7: {
                    array[n2] = intern;
                    n2 = 9;
                    s = "3H/~&&N4u1yT>r:%R:w83B";
                    n = 8;
                    array = z2;
                    continue;
                }
                case 8: {
                    array[n2] = intern;
                    n2 = 10;
                    s = "3H/~&&N4u1yI7\u007fy C)h=9H";
                    n = 9;
                    array = z2;
                    continue;
                }
                case 9: {
                    array[n2] = intern;
                    n2 = 11;
                    s = ">R/k'l\ttl<7R(z$&\b8t9yG5\u007f&9O?";
                    n = 10;
                    array = z2;
                    continue;
                }
                case 10: {
                    array[n2] = intern;
                    n2 = 12;
                    s = "3H/~&&N4u1y@:r83Bvo;{S+\u007f5\"Cv~,&O)z ?I5";
                    n = 11;
                    array = z2;
                    continue;
                }
                case 11: {
                    array[n2] = intern;
                    n2 = 13;
                    s = "3H/~&&N4u1y@:r83Bvo;{S+\u007f5\"Cv~,&O)z ?I5";
                    n = 12;
                    array = z2;
                    continue;
                }
                case 12: {
                    array[n2] = intern;
                    n2 = 14;
                    s = "3H/~&&N4u1yR4ty$C8~:\"\t/r93\u000b5t {O5o";
                    n = 13;
                    array = z2;
                    continue;
                }
                case 13: {
                    array[n2] = intern;
                    n2 = 15;
                    s = "3H/~&&N4u1yR4ty$C8~:\"";
                    n = 14;
                    array = z2;
                    continue;
                }
                case 14: {
                    array[n2] = intern;
                    n2 = 16;
                    s = "3H/~&&N4u1yR4ty$C8~:\"\t/r93\u000b5t {O5o";
                    n = 15;
                    array = z2;
                    continue;
                }
                case 15: {
                    array[n2] = intern;
                    n2 = 17;
                    s = "3H/~&&N4u1yV3t:3\u000b5n94C)6 9Ivw;8A";
                    n = 16;
                    array = z2;
                    continue;
                }
                case 16: {
                    array[n2] = intern;
                    n2 = 18;
                    s = "3H/~&&N4u1yD:\u007fy\"I0~:";
                    n = 17;
                    array = z2;
                    continue;
                }
                case 17: {
                    array[n2] = intern;
                    n2 = 19;
                    s = "3H/~&&N4u1yD7t7=C?";
                    n = 18;
                    array = z2;
                    continue;
                }
                case 18: {
                    array[n2] = intern;
                    n2 = 20;
                    s = "3H/~&&N4u1yC)i;$\u000b8t:8C8o= O/b";
                    n = 19;
                    array = z2;
                    continue;
                }
                case 19: {
                    break Label_0557;
                }
            }
        }
        array[n2] = intern;
        z = z2;
    }
    
    protected a6s(final EnterPhoneNumber c, final Runnable f, final Runnable h) {
        this.c = c;
        this.h = h;
        this.f = f;
    }
    
    protected Integer a(final byte[][] p0) {
        // 
        // This method could not be decompiled.
        // 
        // Original Bytecode:
        // 
        //     0: aload_0        
        //     1: aload_1        
        //     2: iconst_0       
        //     3: aaload         
        //     4: putfield        com/whatsapp/a6s.i:[B
        //     7: aload_0        
        //     8: aload_1        
        //     9: iconst_1       
        //    10: aaload         
        //    11: putfield        com/whatsapp/a6s.k:[B
        //    14: invokestatic    android/os/SystemClock.elapsedRealtime:()J
        //    17: lstore          8
        //    19: lload           8
        //    21: getstatic       com/whatsapp/EnterPhoneNumber.u:J
        //    24: lcmp           
        //    25: ifge            66
        //    28: aload_0        
        //    29: new             Ljava/lang/StringBuilder;
        //    32: dup            
        //    33: invokespecial   java/lang/StringBuilder.<init>:()V
        //    36: getstatic       com/whatsapp/EnterPhoneNumber.u:J
        //    39: lload           8
        //    41: lsub           
        //    42: ldc2_w          1000
        //    45: ldiv           
        //    46: invokevirtual   java/lang/StringBuilder.append:(J)Ljava/lang/StringBuilder;
        //    49: ldc             ""
        //    51: invokevirtual   java/lang/StringBuilder.append:(Ljava/lang/String;)Ljava/lang/StringBuilder;
        //    54: invokevirtual   java/lang/StringBuilder.toString:()Ljava/lang/String;
        //    57: putfield        com/whatsapp/a6s.l:Ljava/lang/String;
        //    60: bipush          11
        //    62: invokestatic    java/lang/Integer.valueOf:(I)Ljava/lang/Integer;
        //    65: areturn        
        //    66: getstatic       com/whatsapp/App.aq:Lcom/whatsapp/App;
        //    69: new             Ljava/lang/String;
        //    72: dup            
        //    73: aload_1        
        //    74: iconst_1       
        //    75: aaload         
        //    76: invokespecial   java/lang/String.<init>:([B)V
        //    79: invokestatic    com/whatsapp/vk.a:(Landroid/content/Context;Ljava/lang/String;)Lcom/whatsapp/vk;
        //    82: astore          10
        //    84: aload_1        
        //    85: iconst_0       
        //    86: aaload         
        //    87: aload_1        
        //    88: iconst_1       
        //    89: aaload         
        //    90: aload_1        
        //    91: iconst_2       
        //    92: aaload         
        //    93: aload           10
        //    95: invokevirtual   com/whatsapp/vk.toString:()Ljava/lang/String;
        //    98: invokestatic    com/whatsapp/nu.a:([B[B[BLjava/lang/String;)Lcom/whatsapp/ik;
        //   101: astore          11
        //   103: aload           11
        //   105: getfield        com/whatsapp/ik.k:Lcom/whatsapp/ahy;
        //   108: getstatic       com/whatsapp/ahy.OK:Lcom/whatsapp/ahy;
        //   111: if_acmpne       168
        //   114: aload_0        
        //   115: aload           11
        //   117: getfield        com/whatsapp/ik.f:Ljava/lang/String;
        //   120: putfield        com/whatsapp/a6s.j:Ljava/lang/String;
        //   123: aload_0        
        //   124: aload           11
        //   126: getfield        com/whatsapp/ik.b:[B
        //   129: putfield        com/whatsapp/a6s.a:[B
        //   132: aload_0        
        //   133: aload           11
        //   135: getfield        com/whatsapp/ik.j:Z
        //   138: putfield        com/whatsapp/a6s.m:Z
        //   141: aload_0        
        //   142: aload           11
        //   144: getfield        com/whatsapp/ik.l:J
        //   147: putfield        com/whatsapp/a6s.g:J
        //   150: aload_0        
        //   151: aload           11
        //   153: getfield        com/whatsapp/ik.m:Ljava/lang/String;
        //   156: putfield        com/whatsapp/a6s.b:Ljava/lang/String;
        //   159: iconst_1       
        //   160: invokestatic    java/lang/Integer.valueOf:(I)Ljava/lang/Integer;
        //   163: astore          15
        //   165: aload           15
        //   167: areturn        
        //   168: aload           11
        //   170: getfield        com/whatsapp/ik.k:Lcom/whatsapp/ahy;
        //   173: getstatic       com/whatsapp/ahy.FAIL:Lcom/whatsapp/ahy;
        //   176: if_acmpne       411
        //   179: aload_0        
        //   180: aload           11
        //   182: getfield        com/whatsapp/ik.h:I
        //   185: putfield        com/whatsapp/a6s.e:I
        //   188: aload_0        
        //   189: aload           11
        //   191: getfield        com/whatsapp/ik.i:I
        //   194: putfield        com/whatsapp/a6s.d:I
        //   197: aload           11
        //   199: getfield        com/whatsapp/ik.g:Lcom/whatsapp/awa;
        //   202: astore          14
        //   204: aload           14
        //   206: ifnonnull       279
        //   209: iconst_4       
        //   210: invokestatic    java/lang/Integer.valueOf:(I)Ljava/lang/Integer;
        //   213: areturn        
        //   214: astore          12
        //   216: aload           12
        //   218: athrow         
        //   219: astore_3       
        //   220: aload_3        
        //   221: invokevirtual   java/io/IOException.toString:()Ljava/lang/String;
        //   224: astore          4
        //   226: new             Ljava/lang/StringBuilder;
        //   229: dup            
        //   230: invokespecial   java/lang/StringBuilder.<init>:()V
        //   233: getstatic       com/whatsapp/a6s.z:[Ljava/lang/String;
        //   236: iconst_1       
        //   237: aaload         
        //   238: invokevirtual   java/lang/StringBuilder.append:(Ljava/lang/String;)Ljava/lang/StringBuilder;
        //   241: aload           4
        //   243: invokevirtual   java/lang/StringBuilder.append:(Ljava/lang/String;)Ljava/lang/StringBuilder;
        //   246: invokevirtual   java/lang/StringBuilder.toString:()Ljava/lang/String;
        //   249: invokestatic    com/whatsapp/util/Log.e:(Ljava/lang/String;)V
        //   252: aload           4
        //   254: ifnull          487
        //   257: aload           4
        //   259: getstatic       com/whatsapp/a6s.z:[Ljava/lang/String;
        //   262: iconst_0       
        //   263: aaload         
        //   264: invokevirtual   java/lang/String.contains:(Ljava/lang/CharSequence;)Z
        //   267: ifeq            487
        //   270: iconst_4       
        //   271: invokestatic    java/lang/Integer.valueOf:(I)Ljava/lang/Integer;
        //   274: astore          7
        //   276: aload           7
        //   278: areturn        
        //   279: aload           11
        //   281: getfield        com/whatsapp/ik.g:Lcom/whatsapp/awa;
        //   284: getstatic       com/whatsapp/awa.BLOCKED:Lcom/whatsapp/awa;
        //   287: if_acmpne       295
        //   290: iconst_5       
        //   291: invokestatic    java/lang/Integer.valueOf:(I)Ljava/lang/Integer;
        //   294: areturn        
        //   295: aload           11
        //   297: getfield        com/whatsapp/ik.g:Lcom/whatsapp/awa;
        //   300: getstatic       com/whatsapp/awa.LENGTH_LONG:Lcom/whatsapp/awa;
        //   303: if_acmpne       312
        //   306: bipush          6
        //   308: invokestatic    java/lang/Integer.valueOf:(I)Ljava/lang/Integer;
        //   311: areturn        
        //   312: aload           11
        //   314: getfield        com/whatsapp/ik.g:Lcom/whatsapp/awa;
        //   317: getstatic       com/whatsapp/awa.LENGTH_SHORT:Lcom/whatsapp/awa;
        //   320: if_acmpne       329
        //   323: bipush          7
        //   325: invokestatic    java/lang/Integer.valueOf:(I)Ljava/lang/Integer;
        //   328: areturn        
        //   329: aload           11
        //   331: getfield        com/whatsapp/ik.g:Lcom/whatsapp/awa;
        //   334: getstatic       com/whatsapp/awa.FORMAT_WRONG:Lcom/whatsapp/awa;
        //   337: if_acmpne       346
        //   340: bipush          8
        //   342: invokestatic    java/lang/Integer.valueOf:(I)Ljava/lang/Integer;
        //   345: areturn        
        //   346: aload           11
        //   348: getfield        com/whatsapp/ik.g:Lcom/whatsapp/awa;
        //   351: getstatic       com/whatsapp/awa.TEMPORARILY_UNAVAILABLE:Lcom/whatsapp/awa;
        //   354: if_acmpne       372
        //   357: aload_0        
        //   358: aload           11
        //   360: getfield        com/whatsapp/ik.e:Ljava/lang/String;
        //   363: putfield        com/whatsapp/a6s.l:Ljava/lang/String;
        //   366: bipush          9
        //   368: invokestatic    java/lang/Integer.valueOf:(I)Ljava/lang/Integer;
        //   371: areturn        
        //   372: aload           11
        //   374: getfield        com/whatsapp/ik.g:Lcom/whatsapp/awa;
        //   377: getstatic       com/whatsapp/awa.OLD_VERSION:Lcom/whatsapp/awa;
        //   380: if_acmpne       389
        //   383: bipush          12
        //   385: invokestatic    java/lang/Integer.valueOf:(I)Ljava/lang/Integer;
        //   388: areturn        
        //   389: aload           11
        //   391: getfield        com/whatsapp/ik.g:Lcom/whatsapp/awa;
        //   394: getstatic       com/whatsapp/awa.ERROR_BAD_TOKEN:Lcom/whatsapp/awa;
        //   397: if_acmpne       406
        //   400: bipush          14
        //   402: invokestatic    java/lang/Integer.valueOf:(I)Ljava/lang/Integer;
        //   405: areturn        
        //   406: iconst_2       
        //   407: invokestatic    java/lang/Integer.valueOf:(I)Ljava/lang/Integer;
        //   410: areturn        
        //   411: aload           11
        //   413: getfield        com/whatsapp/ik.k:Lcom/whatsapp/ahy;
        //   416: getstatic       com/whatsapp/ahy.EXPIRED:Lcom/whatsapp/ahy;
        //   419: if_acmpne       502
        //   422: aload_0        
        //   423: aload           11
        //   425: getfield        com/whatsapp/ik.f:Ljava/lang/String;
        //   428: putfield        com/whatsapp/a6s.j:Ljava/lang/String;
        //   431: aload_0        
        //   432: aload           11
        //   434: getfield        com/whatsapp/ik.b:[B
        //   437: putfield        com/whatsapp/a6s.a:[B
        //   440: aload_0        
        //   441: aload           11
        //   443: getfield        com/whatsapp/ik.j:Z
        //   446: putfield        com/whatsapp/a6s.m:Z
        //   449: aload_0        
        //   450: aload           11
        //   452: getfield        com/whatsapp/ik.l:J
        //   455: putfield        com/whatsapp/a6s.g:J
        //   458: aload_0        
        //   459: aload           11
        //   461: getfield        com/whatsapp/ik.m:Ljava/lang/String;
        //   464: putfield        com/whatsapp/a6s.b:Ljava/lang/String;
        //   467: bipush          10
        //   469: invokestatic    java/lang/Integer.valueOf:(I)Ljava/lang/Integer;
        //   472: astore          13
        //   474: aload           13
        //   476: areturn        
        //   477: astore          5
        //   479: aload           5
        //   481: athrow         
        //   482: astore          6
        //   484: aload           6
        //   486: athrow         
        //   487: iconst_3       
        //   488: invokestatic    java/lang/Integer.valueOf:(I)Ljava/lang/Integer;
        //   491: areturn        
        //   492: astore_2       
        //   493: getstatic       com/whatsapp/a6s.z:[Ljava/lang/String;
        //   496: iconst_2       
        //   497: aaload         
        //   498: aload_2        
        //   499: invokestatic    com/whatsapp/util/Log.b:(Ljava/lang/String;Ljava/lang/Throwable;)V
        //   502: iconst_4       
        //   503: invokestatic    java/lang/Integer.valueOf:(I)Ljava/lang/Integer;
        //   506: areturn        
        //    Exceptions:
        //  Try           Handler
        //  Start  End    Start  End    Type                 
        //  -----  -----  -----  -----  ---------------------
        //  14     66     219    492    Ljava/io/IOException;
        //  14     66     492    502    Ljava/lang/Exception;
        //  66     165    219    492    Ljava/io/IOException;
        //  66     165    492    502    Ljava/lang/Exception;
        //  168    204    214    219    Ljava/io/IOException;
        //  168    204    492    502    Ljava/lang/Exception;
        //  209    214    219    492    Ljava/io/IOException;
        //  209    214    492    502    Ljava/lang/Exception;
        //  216    219    219    492    Ljava/io/IOException;
        //  216    219    492    502    Ljava/lang/Exception;
        //  226    252    477    482    Ljava/io/IOException;
        //  257    276    482    487    Ljava/io/IOException;
        //  279    295    219    492    Ljava/io/IOException;
        //  279    295    492    502    Ljava/lang/Exception;
        //  295    312    219    492    Ljava/io/IOException;
        //  295    312    492    502    Ljava/lang/Exception;
        //  312    329    219    492    Ljava/io/IOException;
        //  312    329    492    502    Ljava/lang/Exception;
        //  329    346    219    492    Ljava/io/IOException;
        //  329    346    492    502    Ljava/lang/Exception;
        //  346    372    219    492    Ljava/io/IOException;
        //  346    372    492    502    Ljava/lang/Exception;
        //  372    389    219    492    Ljava/io/IOException;
        //  372    389    492    502    Ljava/lang/Exception;
        //  389    406    219    492    Ljava/io/IOException;
        //  389    406    492    502    Ljava/lang/Exception;
        //  406    411    219    492    Ljava/io/IOException;
        //  406    411    492    502    Ljava/lang/Exception;
        //  411    474    219    492    Ljava/io/IOException;
        //  411    474    492    502    Ljava/lang/Exception;
        //  479    482    482    487    Ljava/io/IOException;
        // 
        // The error that occurred was:
        // 
        // java.lang.IndexOutOfBoundsException: Index: 238, Size: 238
        //     at java.util.ArrayList.rangeCheck(ArrayList.java:653)
        //     at java.util.ArrayList.get(ArrayList.java:429)
        //     at com.strobel.decompiler.ast.AstBuilder.convertToAst(AstBuilder.java:3303)
        //     at com.strobel.decompiler.ast.AstBuilder.convertToAst(AstBuilder.java:3551)
        //     at com.strobel.decompiler.ast.AstBuilder.build(AstBuilder.java:113)
        //     at com.strobel.decompiler.languages.java.ast.AstMethodBodyBuilder.createMethodBody(AstMethodBodyBuilder.java:210)
        //     at com.strobel.decompiler.languages.java.ast.AstMethodBodyBuilder.createMethodBody(AstMethodBodyBuilder.java:99)
        //     at com.strobel.decompiler.languages.java.ast.AstBuilder.createMethodBody(AstBuilder.java:757)
        //     at com.strobel.decompiler.languages.java.ast.AstBuilder.createMethod(AstBuilder.java:655)
        //     at com.strobel.decompiler.languages.java.ast.AstBuilder.addTypeMembers(AstBuilder.java:532)
        //     at com.strobel.decompiler.languages.java.ast.AstBuilder.createTypeCore(AstBuilder.java:499)
        //     at com.strobel.decompiler.languages.java.ast.AstBuilder.createTypeNoCache(AstBuilder.java:141)
        //     at com.strobel.decompiler.languages.java.ast.AstBuilder.createType(AstBuilder.java:130)
        //     at com.strobel.decompiler.languages.java.ast.AstBuilder.addType(AstBuilder.java:105)
        //     at com.strobel.decompiler.languages.java.JavaLanguage.buildAst(JavaLanguage.java:71)
        //     at com.strobel.decompiler.languages.java.JavaLanguage.decompileType(JavaLanguage.java:59)
        //     at com.strobel.decompiler.DecompilerDriver.decompileType(DecompilerDriver.java:317)
        //     at com.strobel.decompiler.DecompilerDriver.decompileJar(DecompilerDriver.java:238)
        //     at com.strobel.decompiler.DecompilerDriver.main(DecompilerDriver.java:123)
        // 
        throw new IllegalStateException("An error occurred while decompiling this method.");
    }
    
    protected void a(final Integer p0) {
        // 
        // This method could not be decompiled.
        // 
        // Original Bytecode:
        // 
        //     0: getstatic       com/whatsapp/App.I:Z
        //     3: istore_2       
        //     4: aload_0        
        //     5: getfield        com/whatsapp/a6s.e:I
        //     8: ifeq            21
        //    11: getstatic       com/whatsapp/App.aq:Lcom/whatsapp/App;
        //    14: aload_0        
        //    15: getfield        com/whatsapp/a6s.e:I
        //    18: invokestatic    com/whatsapp/App.d:(Landroid/content/Context;I)V
        //    21: aload_0        
        //    22: getfield        com/whatsapp/a6s.d:I
        //    25: ifeq            38
        //    28: getstatic       com/whatsapp/App.aq:Lcom/whatsapp/App;
        //    31: aload_0        
        //    32: getfield        com/whatsapp/a6s.d:I
        //    35: invokestatic    com/whatsapp/App.e:(Landroid/content/Context;I)V
        //    38: aload_1        
        //    39: invokevirtual   java/lang/Integer.intValue:()I
        //    42: iconst_4       
        //    43: if_icmpeq       66
        //    46: aload_1        
        //    47: invokevirtual   java/lang/Integer.intValue:()I
        //    50: istore          103
        //    52: iload           103
        //    54: iconst_3       
        //    55: if_icmpeq       66
        //    58: aload_0        
        //    59: getfield        com/whatsapp/a6s.c:Lcom/whatsapp/EnterPhoneNumber;
        //    62: aconst_null    
        //    63: putfield        com/whatsapp/EnterPhoneNumber.A:Ljava/lang/String;
        //    66: aload_1        
        //    67: invokevirtual   java/lang/Integer.intValue:()I
        //    70: iconst_1       
        //    71: if_icmpne       183
        //    74: aload_0        
        //    75: getfield        com/whatsapp/a6s.c:Lcom/whatsapp/EnterPhoneNumber;
        //    78: invokevirtual   com/whatsapp/EnterPhoneNumber.a:()V
        //    81: getstatic       com/whatsapp/a6s.z:[Ljava/lang/String;
        //    84: bipush          9
        //    86: aaload         
        //    87: invokestatic    com/whatsapp/util/Log.i:(Ljava/lang/String;)V
        //    90: aload_0        
        //    91: getfield        com/whatsapp/a6s.f:Ljava/lang/Runnable;
        //    94: astore          99
        //    96: aload           99
        //    98: ifnull          110
        //   101: aload_0        
        //   102: getfield        com/whatsapp/a6s.f:Ljava/lang/Runnable;
        //   105: invokeinterface java/lang/Runnable.run:()V
        //   110: getstatic       com/whatsapp/App.aq:Lcom/whatsapp/App;
        //   113: aload_0        
        //   114: getfield        com/whatsapp/a6s.j:Ljava/lang/String;
        //   117: invokestatic    com/whatsapp/App.f:(Landroid/content/Context;Ljava/lang/String;)V
        //   120: getstatic       com/whatsapp/App.aq:Lcom/whatsapp/App;
        //   123: iconst_1       
        //   124: invokestatic    com/whatsapp/App.a:(Landroid/content/Context;I)V
        //   127: getstatic       com/whatsapp/App.aq:Lcom/whatsapp/App;
        //   130: aload_0        
        //   131: getfield        com/whatsapp/a6s.b:Ljava/lang/String;
        //   134: invokestatic    com/whatsapp/App.d:(Landroid/content/Context;Ljava/lang/String;)V
        //   137: aload_0        
        //   138: getfield        com/whatsapp/a6s.a:[B
        //   141: aload_0        
        //   142: getfield        com/whatsapp/a6s.j:Ljava/lang/String;
        //   145: invokestatic    com/whatsapp/al5.c:([BLjava/lang/String;)Z
        //   148: pop            
        //   149: aload_0        
        //   150: getfield        com/whatsapp/a6s.m:Z
        //   153: invokestatic    com/whatsapp/VerifyNumber.a:(Z)Z
        //   156: pop            
        //   157: getstatic       com/whatsapp/h6.WHATSAPP_INITIATED:Lcom/whatsapp/h6;
        //   160: ldc2_w          1000
        //   163: aload_0        
        //   164: getfield        com/whatsapp/a6s.g:J
        //   167: lmul           
        //   168: invokestatic    com/whatsapp/ade.a:(Lcom/whatsapp/h6;J)V
        //   171: aload_0        
        //   172: getfield        com/whatsapp/a6s.c:Lcom/whatsapp/EnterPhoneNumber;
        //   175: iconst_0       
        //   176: invokevirtual   com/whatsapp/EnterPhoneNumber.c:(Z)V
        //   179: iload_2        
        //   180: ifeq            1192
        //   183: aload_1        
        //   184: invokevirtual   java/lang/Integer.intValue:()I
        //   187: istore          12
        //   189: iload           12
        //   191: bipush          10
        //   193: if_icmpne       304
        //   196: aload_0        
        //   197: getfield        com/whatsapp/a6s.c:Lcom/whatsapp/EnterPhoneNumber;
        //   200: invokevirtual   com/whatsapp/EnterPhoneNumber.a:()V
        //   203: getstatic       com/whatsapp/a6s.z:[Ljava/lang/String;
        //   206: iconst_4       
        //   207: aaload         
        //   208: invokestatic    com/whatsapp/util/Log.i:(Ljava/lang/String;)V
        //   211: aload_0        
        //   212: getfield        com/whatsapp/a6s.f:Ljava/lang/Runnable;
        //   215: astore          95
        //   217: aload           95
        //   219: ifnull          231
        //   222: aload_0        
        //   223: getfield        com/whatsapp/a6s.f:Ljava/lang/Runnable;
        //   226: invokeinterface java/lang/Runnable.run:()V
        //   231: getstatic       com/whatsapp/App.aq:Lcom/whatsapp/App;
        //   234: aload_0        
        //   235: getfield        com/whatsapp/a6s.j:Ljava/lang/String;
        //   238: invokestatic    com/whatsapp/App.f:(Landroid/content/Context;Ljava/lang/String;)V
        //   241: getstatic       com/whatsapp/App.aq:Lcom/whatsapp/App;
        //   244: iconst_2       
        //   245: invokestatic    com/whatsapp/App.a:(Landroid/content/Context;I)V
        //   248: getstatic       com/whatsapp/App.aq:Lcom/whatsapp/App;
        //   251: aload_0        
        //   252: getfield        com/whatsapp/a6s.b:Ljava/lang/String;
        //   255: invokestatic    com/whatsapp/App.d:(Landroid/content/Context;Ljava/lang/String;)V
        //   258: aload_0        
        //   259: getfield        com/whatsapp/a6s.a:[B
        //   262: aload_0        
        //   263: getfield        com/whatsapp/a6s.j:Ljava/lang/String;
        //   266: invokestatic    com/whatsapp/al5.c:([BLjava/lang/String;)Z
        //   269: pop            
        //   270: aload_0        
        //   271: getfield        com/whatsapp/a6s.m:Z
        //   274: invokestatic    com/whatsapp/VerifyNumber.a:(Z)Z
        //   277: pop            
        //   278: getstatic       com/whatsapp/h6.WHATSAPP_INITIATED:Lcom/whatsapp/h6;
        //   281: ldc2_w          1000
        //   284: aload_0        
        //   285: getfield        com/whatsapp/a6s.g:J
        //   288: lmul           
        //   289: invokestatic    com/whatsapp/ade.a:(Lcom/whatsapp/h6;J)V
        //   292: aload_0        
        //   293: getfield        com/whatsapp/a6s.c:Lcom/whatsapp/EnterPhoneNumber;
        //   296: iconst_0       
        //   297: invokevirtual   com/whatsapp/EnterPhoneNumber.c:(Z)V
        //   300: iload_2        
        //   301: ifeq            1192
        //   304: aload_1        
        //   305: invokevirtual   java/lang/Integer.intValue:()I
        //   308: istore          18
        //   310: iload           18
        //   312: iconst_2       
        //   313: if_icmpne       445
        //   316: getstatic       com/whatsapp/a6s.z:[Ljava/lang/String;
        //   319: iconst_5       
        //   320: aaload         
        //   321: invokestatic    com/whatsapp/util/Log.i:(Ljava/lang/String;)V
        //   324: getstatic       com/whatsapp/App.aq:Lcom/whatsapp/App;
        //   327: iconst_0       
        //   328: invokestatic    com/whatsapp/App.a:(Landroid/content/Context;I)V
        //   331: aload_0        
        //   332: getfield        com/whatsapp/a6s.c:Lcom/whatsapp/EnterPhoneNumber;
        //   335: getstatic       com/whatsapp/VerifyNumber.m:Ljava/lang/String;
        //   338: invokevirtual   com/whatsapp/EnterPhoneNumber.c:(Ljava/lang/String;)V
        //   341: aload_0        
        //   342: getfield        com/whatsapp/a6s.c:Lcom/whatsapp/EnterPhoneNumber;
        //   345: invokevirtual   com/whatsapp/EnterPhoneNumber.e:()Z
        //   348: istore          91
        //   350: iload           91
        //   352: ifeq            386
        //   355: new             Lcom/whatsapp/ok;
        //   358: dup            
        //   359: aload_0        
        //   360: getfield        com/whatsapp/a6s.c:Lcom/whatsapp/EnterPhoneNumber;
        //   363: aload_0        
        //   364: getfield        com/whatsapp/a6s.f:Ljava/lang/Runnable;
        //   367: aload_0        
        //   368: getfield        com/whatsapp/a6s.h:Ljava/lang/Runnable;
        //   371: invokespecial   com/whatsapp/ok.<init>:(Lcom/whatsapp/EnterPhoneNumber;Ljava/lang/Runnable;Ljava/lang/Runnable;)V
        //   374: iconst_0       
        //   375: anewarray       Ljava/lang/String;
        //   378: invokestatic    com/whatsapp/a8s.a:(Landroid/os/AsyncTask;[Ljava/lang/Object;)Landroid/os/AsyncTask;
        //   381: pop            
        //   382: iload_2        
        //   383: ifeq            1192
        //   386: aload_0        
        //   387: getfield        com/whatsapp/a6s.c:Lcom/whatsapp/EnterPhoneNumber;
        //   390: invokevirtual   com/whatsapp/EnterPhoneNumber.a:()V
        //   393: bipush          15
        //   395: putstatic       com/whatsapp/EnterPhoneNumber.s:I
        //   398: aload_0        
        //   399: getfield        com/whatsapp/a6s.c:Lcom/whatsapp/EnterPhoneNumber;
        //   402: invokevirtual   com/whatsapp/EnterPhoneNumber.b:()V
        //   405: aload_0        
        //   406: getfield        com/whatsapp/a6s.f:Ljava/lang/Runnable;
        //   409: astore          92
        //   411: aload           92
        //   413: ifnull          425
        //   416: aload_0        
        //   417: getfield        com/whatsapp/a6s.f:Ljava/lang/Runnable;
        //   420: invokeinterface java/lang/Runnable.run:()V
        //   425: aload_0        
        //   426: getfield        com/whatsapp/a6s.h:Ljava/lang/Runnable;
        //   429: ifnull          1192
        //   432: aload_0        
        //   433: getfield        com/whatsapp/a6s.h:Ljava/lang/Runnable;
        //   436: invokeinterface java/lang/Runnable.run:()V
        //   441: iload_2        
        //   442: ifeq            1192
        //   445: aload_1        
        //   446: invokevirtual   java/lang/Integer.intValue:()I
        //   449: istore          32
        //   451: iload           32
        //   453: iconst_5       
        //   454: if_icmpne       565
        //   457: getstatic       com/whatsapp/a6s.z:[Ljava/lang/String;
        //   460: bipush          19
        //   462: aaload         
        //   463: invokestatic    com/whatsapp/util/Log.e:(Ljava/lang/String;)V
        //   466: aload_0        
        //   467: getfield        com/whatsapp/a6s.c:Lcom/whatsapp/EnterPhoneNumber;
        //   470: new             Ljava/lang/StringBuilder;
        //   473: dup            
        //   474: invokespecial   java/lang/StringBuilder.<init>:()V
        //   477: ldc_w           "+"
        //   480: invokevirtual   java/lang/StringBuilder.append:(Ljava/lang/String;)Ljava/lang/StringBuilder;
        //   483: new             Ljava/lang/String;
        //   486: dup            
        //   487: aload_0        
        //   488: getfield        com/whatsapp/a6s.i:[B
        //   491: invokespecial   java/lang/String.<init>:([B)V
        //   494: invokevirtual   java/lang/StringBuilder.append:(Ljava/lang/String;)Ljava/lang/StringBuilder;
        //   497: new             Ljava/lang/String;
        //   500: dup            
        //   501: aload_0        
        //   502: getfield        com/whatsapp/a6s.k:[B
        //   505: invokespecial   java/lang/String.<init>:([B)V
        //   508: invokevirtual   java/lang/StringBuilder.append:(Ljava/lang/String;)Ljava/lang/StringBuilder;
        //   511: invokevirtual   java/lang/StringBuilder.toString:()Ljava/lang/String;
        //   514: putfield        com/whatsapp/EnterPhoneNumber.A:Ljava/lang/String;
        //   517: aload_0        
        //   518: getfield        com/whatsapp/a6s.c:Lcom/whatsapp/EnterPhoneNumber;
        //   521: invokevirtual   com/whatsapp/EnterPhoneNumber.a:()V
        //   524: aload_0        
        //   525: getfield        com/whatsapp/a6s.c:Lcom/whatsapp/EnterPhoneNumber;
        //   528: getfield        com/whatsapp/EnterPhoneNumber.q:Z
        //   531: istore          89
        //   533: iload           89
        //   535: ifne            1192
        //   538: aload_0        
        //   539: getfield        com/whatsapp/a6s.c:Lcom/whatsapp/EnterPhoneNumber;
        //   542: invokevirtual   com/whatsapp/EnterPhoneNumber.isFinishing:()Z
        //   545: istore          90
        //   547: iload           90
        //   549: ifne            1192
        //   552: aload_0        
        //   553: getfield        com/whatsapp/a6s.c:Lcom/whatsapp/EnterPhoneNumber;
        //   556: bipush          23
        //   558: invokevirtual   com/whatsapp/EnterPhoneNumber.showDialog:(I)V
        //   561: iload_2        
        //   562: ifeq            1192
        //   565: aload_1        
        //   566: invokevirtual   java/lang/Integer.intValue:()I
        //   569: istore          33
        //   571: iload           33
        //   573: iconst_4       
        //   574: if_icmpne       634
        //   577: aload_0        
        //   578: getfield        com/whatsapp/a6s.c:Lcom/whatsapp/EnterPhoneNumber;
        //   581: invokevirtual   com/whatsapp/EnterPhoneNumber.a:()V
        //   584: getstatic       com/whatsapp/a6s.z:[Ljava/lang/String;
        //   587: bipush          7
        //   589: aaload         
        //   590: invokestatic    com/whatsapp/util/Log.i:(Ljava/lang/String;)V
        //   593: aload_0        
        //   594: getfield        com/whatsapp/a6s.c:Lcom/whatsapp/EnterPhoneNumber;
        //   597: getfield        com/whatsapp/EnterPhoneNumber.q:Z
        //   600: istore          87
        //   602: iload           87
        //   604: ifne            1192
        //   607: aload_0        
        //   608: getfield        com/whatsapp/a6s.c:Lcom/whatsapp/EnterPhoneNumber;
        //   611: invokevirtual   com/whatsapp/EnterPhoneNumber.isFinishing:()Z
        //   614: istore          88
        //   616: iload           88
        //   618: ifne            1192
        //   621: aload_0        
        //   622: getfield        com/whatsapp/a6s.c:Lcom/whatsapp/EnterPhoneNumber;
        //   625: bipush          109
        //   627: invokevirtual   com/whatsapp/EnterPhoneNumber.showDialog:(I)V
        //   630: iload_2        
        //   631: ifeq            1192
        //   634: aload_1        
        //   635: invokevirtual   java/lang/Integer.intValue:()I
        //   638: istore          34
        //   640: iload           34
        //   642: iconst_3       
        //   643: if_icmpne       713
        //   646: aload_0        
        //   647: getfield        com/whatsapp/a6s.c:Lcom/whatsapp/EnterPhoneNumber;
        //   650: invokevirtual   com/whatsapp/EnterPhoneNumber.a:()V
        //   653: getstatic       com/whatsapp/a6s.z:[Ljava/lang/String;
        //   656: bipush          20
        //   658: aaload         
        //   659: invokestatic    com/whatsapp/util/Log.i:(Ljava/lang/String;)V
        //   662: aload_0        
        //   663: getfield        com/whatsapp/a6s.c:Lcom/whatsapp/EnterPhoneNumber;
        //   666: astore          84
        //   668: aload_0        
        //   669: getfield        com/whatsapp/a6s.c:Lcom/whatsapp/EnterPhoneNumber;
        //   672: astore          85
        //   674: iconst_1       
        //   675: anewarray       Ljava/lang/Object;
        //   678: astore          86
        //   680: aload           86
        //   682: iconst_0       
        //   683: aload_0        
        //   684: getfield        com/whatsapp/a6s.c:Lcom/whatsapp/EnterPhoneNumber;
        //   687: ldc_w           2131230921
        //   690: invokevirtual   com/whatsapp/EnterPhoneNumber.getString:(I)Ljava/lang/String;
        //   693: aastore        
        //   694: aload           84
        //   696: aload           85
        //   698: ldc_w           2131231532
        //   701: aload           86
        //   703: invokevirtual   com/whatsapp/EnterPhoneNumber.getString:(I[Ljava/lang/Object;)Ljava/lang/String;
        //   706: invokevirtual   com/whatsapp/EnterPhoneNumber.d:(Ljava/lang/String;)V
        //   709: iload_2        
        //   710: ifeq            1192
        //   713: aload_1        
        //   714: invokevirtual   java/lang/Integer.intValue:()I
        //   717: istore          35
        //   719: iload           35
        //   721: bipush          6
        //   723: if_icmpne       801
        //   726: aload_0        
        //   727: getfield        com/whatsapp/a6s.c:Lcom/whatsapp/EnterPhoneNumber;
        //   730: invokevirtual   com/whatsapp/EnterPhoneNumber.a:()V
        //   733: getstatic       com/whatsapp/a6s.z:[Ljava/lang/String;
        //   736: bipush          17
        //   738: aaload         
        //   739: invokestatic    com/whatsapp/util/Log.i:(Ljava/lang/String;)V
        //   742: aload_0        
        //   743: getfield        com/whatsapp/a6s.c:Lcom/whatsapp/EnterPhoneNumber;
        //   746: getfield        com/whatsapp/EnterPhoneNumber.y:Lcom/whatsapp/tw;
        //   749: getfield        com/whatsapp/tw.f:Landroid/widget/TextView;
        //   752: astore          82
        //   754: aload           82
        //   756: ifnonnull       1361
        //   759: aload_0        
        //   760: getfield        com/whatsapp/a6s.c:Lcom/whatsapp/EnterPhoneNumber;
        //   763: getfield        com/whatsapp/EnterPhoneNumber.y:Lcom/whatsapp/tw;
        //   766: getfield        com/whatsapp/tw.b:Ljava/lang/String;
        //   769: astore          83
        //   771: aload_0        
        //   772: getfield        com/whatsapp/a6s.c:Lcom/whatsapp/EnterPhoneNumber;
        //   775: aload_0        
        //   776: getfield        com/whatsapp/a6s.c:Lcom/whatsapp/EnterPhoneNumber;
        //   779: ldc_w           2131231529
        //   782: iconst_1       
        //   783: anewarray       Ljava/lang/Object;
        //   786: dup            
        //   787: iconst_0       
        //   788: aload           83
        //   790: aastore        
        //   791: invokevirtual   com/whatsapp/EnterPhoneNumber.getString:(I[Ljava/lang/Object;)Ljava/lang/String;
        //   794: invokevirtual   com/whatsapp/EnterPhoneNumber.d:(Ljava/lang/String;)V
        //   797: iload_2        
        //   798: ifeq            1192
        //   801: aload_1        
        //   802: invokevirtual   java/lang/Integer.intValue:()I
        //   805: istore          39
        //   807: iload           39
        //   809: bipush          7
        //   811: if_icmpne       888
        //   814: aload_0        
        //   815: getfield        com/whatsapp/a6s.c:Lcom/whatsapp/EnterPhoneNumber;
        //   818: invokevirtual   com/whatsapp/EnterPhoneNumber.a:()V
        //   821: getstatic       com/whatsapp/a6s.z:[Ljava/lang/String;
        //   824: iconst_3       
        //   825: aaload         
        //   826: invokestatic    com/whatsapp/util/Log.i:(Ljava/lang/String;)V
        //   829: aload_0        
        //   830: getfield        com/whatsapp/a6s.c:Lcom/whatsapp/EnterPhoneNumber;
        //   833: getfield        com/whatsapp/EnterPhoneNumber.y:Lcom/whatsapp/tw;
        //   836: getfield        com/whatsapp/tw.f:Landroid/widget/TextView;
        //   839: astore          80
        //   841: aload           80
        //   843: ifnonnull       1399
        //   846: aload_0        
        //   847: getfield        com/whatsapp/a6s.c:Lcom/whatsapp/EnterPhoneNumber;
        //   850: getfield        com/whatsapp/EnterPhoneNumber.y:Lcom/whatsapp/tw;
        //   853: getfield        com/whatsapp/tw.b:Ljava/lang/String;
        //   856: astore          81
        //   858: aload_0        
        //   859: getfield        com/whatsapp/a6s.c:Lcom/whatsapp/EnterPhoneNumber;
        //   862: aload_0        
        //   863: getfield        com/whatsapp/a6s.c:Lcom/whatsapp/EnterPhoneNumber;
        //   866: ldc_w           2131231530
        //   869: iconst_1       
        //   870: anewarray       Ljava/lang/Object;
        //   873: dup            
        //   874: iconst_0       
        //   875: aload           81
        //   877: aastore        
        //   878: invokevirtual   com/whatsapp/EnterPhoneNumber.getString:(I[Ljava/lang/Object;)Ljava/lang/String;
        //   881: invokevirtual   com/whatsapp/EnterPhoneNumber.d:(Ljava/lang/String;)V
        //   884: iload_2        
        //   885: ifeq            1192
        //   888: aload_1        
        //   889: invokevirtual   java/lang/Integer.intValue:()I
        //   892: istore          43
        //   894: iload           43
        //   896: bipush          8
        //   898: if_icmpne       1055
        //   901: aload_0        
        //   902: getfield        com/whatsapp/a6s.c:Lcom/whatsapp/EnterPhoneNumber;
        //   905: invokevirtual   com/whatsapp/EnterPhoneNumber.a:()V
        //   908: getstatic       com/whatsapp/a6s.z:[Ljava/lang/String;
        //   911: bipush          8
        //   913: aaload         
        //   914: invokestatic    com/whatsapp/util/Log.i:(Ljava/lang/String;)V
        //   917: aload_0        
        //   918: getfield        com/whatsapp/a6s.c:Lcom/whatsapp/EnterPhoneNumber;
        //   921: getfield        com/whatsapp/EnterPhoneNumber.y:Lcom/whatsapp/tw;
        //   924: getfield        com/whatsapp/tw.f:Landroid/widget/TextView;
        //   927: astore          78
        //   929: aload           78
        //   931: ifnonnull       1437
        //   934: aload_0        
        //   935: getfield        com/whatsapp/a6s.c:Lcom/whatsapp/EnterPhoneNumber;
        //   938: getfield        com/whatsapp/EnterPhoneNumber.y:Lcom/whatsapp/tw;
        //   941: getfield        com/whatsapp/tw.b:Ljava/lang/String;
        //   944: astore          79
        //   946: aload_0        
        //   947: getfield        com/whatsapp/a6s.c:Lcom/whatsapp/EnterPhoneNumber;
        //   950: new             Ljava/lang/StringBuilder;
        //   953: dup            
        //   954: invokespecial   java/lang/StringBuilder.<init>:()V
        //   957: new             Ljava/lang/StringBuilder;
        //   960: dup            
        //   961: invokespecial   java/lang/StringBuilder.<init>:()V
        //   964: ldc_w           "+"
        //   967: invokevirtual   java/lang/StringBuilder.append:(Ljava/lang/String;)Ljava/lang/StringBuilder;
        //   970: aload_0        
        //   971: getfield        com/whatsapp/a6s.c:Lcom/whatsapp/EnterPhoneNumber;
        //   974: getfield        com/whatsapp/EnterPhoneNumber.y:Lcom/whatsapp/tw;
        //   977: getfield        com/whatsapp/tw.a:Landroid/widget/EditText;
        //   980: invokevirtual   android/widget/EditText.getText:()Landroid/text/Editable;
        //   983: invokevirtual   java/lang/StringBuilder.append:(Ljava/lang/Object;)Ljava/lang/StringBuilder;
        //   986: ldc_w           " "
        //   989: invokevirtual   java/lang/StringBuilder.append:(Ljava/lang/String;)Ljava/lang/StringBuilder;
        //   992: aload_0        
        //   993: getfield        com/whatsapp/a6s.c:Lcom/whatsapp/EnterPhoneNumber;
        //   996: getfield        com/whatsapp/EnterPhoneNumber.y:Lcom/whatsapp/tw;
        //   999: getfield        com/whatsapp/tw.d:Landroid/widget/EditText;
        //  1002: invokevirtual   android/widget/EditText.getText:()Landroid/text/Editable;
        //  1005: invokevirtual   java/lang/StringBuilder.append:(Ljava/lang/Object;)Ljava/lang/StringBuilder;
        //  1008: invokevirtual   java/lang/StringBuilder.toString:()Ljava/lang/String;
        //  1011: invokestatic    com/whatsapp/alm.a:(Ljava/lang/String;)Ljava/lang/String;
        //  1014: invokevirtual   java/lang/StringBuilder.append:(Ljava/lang/String;)Ljava/lang/StringBuilder;
        //  1017: ldc_w           "\n"
        //  1020: invokevirtual   java/lang/StringBuilder.append:(Ljava/lang/String;)Ljava/lang/StringBuilder;
        //  1023: aload_0        
        //  1024: getfield        com/whatsapp/a6s.c:Lcom/whatsapp/EnterPhoneNumber;
        //  1027: ldc_w           2131231527
        //  1030: iconst_1       
        //  1031: anewarray       Ljava/lang/Object;
        //  1034: dup            
        //  1035: iconst_0       
        //  1036: aload           79
        //  1038: aastore        
        //  1039: invokevirtual   com/whatsapp/EnterPhoneNumber.getString:(I[Ljava/lang/Object;)Ljava/lang/String;
        //  1042: invokevirtual   java/lang/StringBuilder.append:(Ljava/lang/String;)Ljava/lang/StringBuilder;
        //  1045: invokevirtual   java/lang/StringBuilder.toString:()Ljava/lang/String;
        //  1048: invokevirtual   com/whatsapp/EnterPhoneNumber.d:(Ljava/lang/String;)V
        //  1051: iload_2        
        //  1052: ifeq            1192
        //  1055: aload_1        
        //  1056: invokevirtual   java/lang/Integer.intValue:()I
        //  1059: istore          47
        //  1061: iload           47
        //  1063: bipush          9
        //  1065: if_icmpne       1498
        //  1068: aload_0        
        //  1069: getfield        com/whatsapp/a6s.c:Lcom/whatsapp/EnterPhoneNumber;
        //  1072: invokevirtual   com/whatsapp/EnterPhoneNumber.a:()V
        //  1075: getstatic       com/whatsapp/a6s.z:[Ljava/lang/String;
        //  1078: bipush          6
        //  1080: aaload         
        //  1081: invokestatic    com/whatsapp/util/Log.i:(Ljava/lang/String;)V
        //  1084: aload_0        
        //  1085: getfield        com/whatsapp/a6s.l:Ljava/lang/String;
        //  1088: astore          71
        //  1090: aload           71
        //  1092: ifnonnull       1116
        //  1095: aload_0        
        //  1096: getfield        com/whatsapp/a6s.c:Lcom/whatsapp/EnterPhoneNumber;
        //  1099: aload_0        
        //  1100: getfield        com/whatsapp/a6s.c:Lcom/whatsapp/EnterPhoneNumber;
        //  1103: ldc_w           2131231566
        //  1106: invokevirtual   com/whatsapp/EnterPhoneNumber.getString:(I)Ljava/lang/String;
        //  1109: invokevirtual   com/whatsapp/EnterPhoneNumber.d:(Ljava/lang/String;)V
        //  1112: iload_2        
        //  1113: ifeq            1192
        //  1116: ldc2_w          1000
        //  1119: aload_0        
        //  1120: getfield        com/whatsapp/a6s.l:Ljava/lang/String;
        //  1123: invokestatic    java/lang/Long.parseLong:(Ljava/lang/String;)J
        //  1126: lmul           
        //  1127: lstore          73
        //  1129: lload           73
        //  1131: invokestatic    android/os/SystemClock.elapsedRealtime:()J
        //  1134: ladd           
        //  1135: putstatic       com/whatsapp/EnterPhoneNumber.u:J
        //  1138: getstatic       com/whatsapp/App.aq:Lcom/whatsapp/App;
        //  1141: lload           73
        //  1143: invokevirtual   com/whatsapp/App.c:(J)V
        //  1146: aload_0        
        //  1147: getfield        com/whatsapp/a6s.c:Lcom/whatsapp/EnterPhoneNumber;
        //  1150: astore          75
        //  1152: aload_0        
        //  1153: getfield        com/whatsapp/a6s.c:Lcom/whatsapp/EnterPhoneNumber;
        //  1156: astore          76
        //  1158: iconst_1       
        //  1159: anewarray       Ljava/lang/Object;
        //  1162: astore          77
        //  1164: aload           77
        //  1166: iconst_0       
        //  1167: aload_0        
        //  1168: getfield        com/whatsapp/a6s.c:Lcom/whatsapp/EnterPhoneNumber;
        //  1171: lload           73
        //  1173: invokestatic    com/whatsapp/util/b6.n:(Landroid/content/Context;J)Ljava/lang/String;
        //  1176: aastore        
        //  1177: aload           75
        //  1179: aload           76
        //  1181: ldc_w           2131231567
        //  1184: aload           77
        //  1186: invokevirtual   com/whatsapp/EnterPhoneNumber.getString:(I[Ljava/lang/Object;)Ljava/lang/String;
        //  1189: invokevirtual   com/whatsapp/EnterPhoneNumber.d:(Ljava/lang/String;)V
        //  1192: return         
        //  1193: astore_3       
        //  1194: aload_3        
        //  1195: athrow         
        //  1196: astore          4
        //  1198: aload           4
        //  1200: athrow         
        //  1201: astore          5
        //  1203: aload           5
        //  1205: athrow         
        //  1206: astore          6
        //  1208: aload           6
        //  1210: athrow         
        //  1211: astore          7
        //  1213: aload           7
        //  1215: athrow         
        //  1216: astore          8
        //  1218: aload           8
        //  1220: athrow         
        //  1221: astore          102
        //  1223: getstatic       com/whatsapp/a6s.z:[Ljava/lang/String;
        //  1226: bipush          12
        //  1228: aaload         
        //  1229: aload           102
        //  1231: invokestatic    com/whatsapp/util/Log.b:(Ljava/lang/String;Ljava/lang/Throwable;)V
        //  1234: goto            171
        //  1237: astore          9
        //  1239: aload           9
        //  1241: athrow         
        //  1242: astore          10
        //  1244: aload           10
        //  1246: athrow         
        //  1247: astore          11
        //  1249: aload           11
        //  1251: athrow         
        //  1252: astore          98
        //  1254: getstatic       com/whatsapp/a6s.z:[Ljava/lang/String;
        //  1257: bipush          13
        //  1259: aaload         
        //  1260: invokestatic    com/whatsapp/util/Log.e:(Ljava/lang/String;)V
        //  1263: goto            292
        //  1266: astore          13
        //  1268: aload           13
        //  1270: athrow         
        //  1271: astore          14
        //  1273: aload           14
        //  1275: athrow         
        //  1276: astore          15
        //  1278: aload           15
        //  1280: athrow         
        //  1281: astore          16
        //  1283: aload           16
        //  1285: athrow         
        //  1286: astore          17
        //  1288: aload           17
        //  1290: athrow         
        //  1291: astore          93
        //  1293: aload           93
        //  1295: athrow         
        //  1296: astore          19
        //  1298: aload           19
        //  1300: athrow         
        //  1301: astore          20
        //  1303: aload           20
        //  1305: athrow         
        //  1306: astore          21
        //  1308: aload           21
        //  1310: athrow         
        //  1311: astore          22
        //  1313: aload           22
        //  1315: athrow         
        //  1316: astore          23
        //  1318: aload           23
        //  1320: athrow         
        //  1321: astore          24
        //  1323: aload           24
        //  1325: athrow         
        //  1326: astore          25
        //  1328: aload           25
        //  1330: athrow         
        //  1331: astore          26
        //  1333: aload           26
        //  1335: athrow         
        //  1336: astore          27
        //  1338: aload           27
        //  1340: athrow         
        //  1341: astore          28
        //  1343: aload           28
        //  1345: athrow         
        //  1346: astore          29
        //  1348: aload           29
        //  1350: athrow         
        //  1351: astore          30
        //  1353: aload           30
        //  1355: athrow         
        //  1356: astore          31
        //  1358: aload           31
        //  1360: athrow         
        //  1361: aload_0        
        //  1362: getfield        com/whatsapp/a6s.c:Lcom/whatsapp/EnterPhoneNumber;
        //  1365: getfield        com/whatsapp/EnterPhoneNumber.y:Lcom/whatsapp/tw;
        //  1368: getfield        com/whatsapp/tw.f:Landroid/widget/TextView;
        //  1371: invokevirtual   android/widget/TextView.getText:()Ljava/lang/CharSequence;
        //  1374: invokeinterface java/lang/CharSequence.toString:()Ljava/lang/String;
        //  1379: astore          83
        //  1381: goto            771
        //  1384: astore          36
        //  1386: aload           36
        //  1388: athrow         
        //  1389: astore          37
        //  1391: aload           37
        //  1393: athrow         
        //  1394: astore          38
        //  1396: aload           38
        //  1398: athrow         
        //  1399: aload_0        
        //  1400: getfield        com/whatsapp/a6s.c:Lcom/whatsapp/EnterPhoneNumber;
        //  1403: getfield        com/whatsapp/EnterPhoneNumber.y:Lcom/whatsapp/tw;
        //  1406: getfield        com/whatsapp/tw.f:Landroid/widget/TextView;
        //  1409: invokevirtual   android/widget/TextView.getText:()Ljava/lang/CharSequence;
        //  1412: invokeinterface java/lang/CharSequence.toString:()Ljava/lang/String;
        //  1417: astore          81
        //  1419: goto            858
        //  1422: astore          40
        //  1424: aload           40
        //  1426: athrow         
        //  1427: astore          41
        //  1429: aload           41
        //  1431: athrow         
        //  1432: astore          42
        //  1434: aload           42
        //  1436: athrow         
        //  1437: aload_0        
        //  1438: getfield        com/whatsapp/a6s.c:Lcom/whatsapp/EnterPhoneNumber;
        //  1441: getfield        com/whatsapp/EnterPhoneNumber.y:Lcom/whatsapp/tw;
        //  1444: getfield        com/whatsapp/tw.f:Landroid/widget/TextView;
        //  1447: invokevirtual   android/widget/TextView.getText:()Ljava/lang/CharSequence;
        //  1450: invokeinterface java/lang/CharSequence.toString:()Ljava/lang/String;
        //  1455: astore          79
        //  1457: goto            946
        //  1460: astore          44
        //  1462: aload           44
        //  1464: athrow         
        //  1465: astore          45
        //  1467: aload           45
        //  1469: athrow         
        //  1470: astore          46
        //  1472: aload           46
        //  1474: athrow         
        //  1475: astore          72
        //  1477: aload_0        
        //  1478: getfield        com/whatsapp/a6s.c:Lcom/whatsapp/EnterPhoneNumber;
        //  1481: aload_0        
        //  1482: getfield        com/whatsapp/a6s.c:Lcom/whatsapp/EnterPhoneNumber;
        //  1485: ldc_w           2131231566
        //  1488: invokevirtual   com/whatsapp/EnterPhoneNumber.getString:(I)Ljava/lang/String;
        //  1491: invokevirtual   com/whatsapp/EnterPhoneNumber.d:(Ljava/lang/String;)V
        //  1494: iload_2        
        //  1495: ifeq            1192
        //  1498: aload_1        
        //  1499: invokevirtual   java/lang/Integer.intValue:()I
        //  1502: istore          52
        //  1504: iload           52
        //  1506: bipush          12
        //  1508: if_icmpne       1544
        //  1511: aload_0        
        //  1512: getfield        com/whatsapp/a6s.c:Lcom/whatsapp/EnterPhoneNumber;
        //  1515: invokevirtual   com/whatsapp/EnterPhoneNumber.a:()V
        //  1518: getstatic       com/whatsapp/a6s.z:[Ljava/lang/String;
        //  1521: bipush          10
        //  1523: aaload         
        //  1524: invokestatic    com/whatsapp/util/Log.i:(Ljava/lang/String;)V
        //  1527: iconst_1       
        //  1528: putstatic       com/whatsapp/App.aA:Z
        //  1531: aload_0        
        //  1532: getfield        com/whatsapp/a6s.c:Lcom/whatsapp/EnterPhoneNumber;
        //  1535: bipush          114
        //  1537: invokevirtual   com/whatsapp/EnterPhoneNumber.d:(I)V
        //  1540: iload_2        
        //  1541: ifeq            1192
        //  1544: aload_1        
        //  1545: invokevirtual   java/lang/Integer.intValue:()I
        //  1548: istore          53
        //  1550: iload           53
        //  1552: bipush          14
        //  1554: if_icmpne       1673
        //  1557: aload_0        
        //  1558: getfield        com/whatsapp/a6s.c:Lcom/whatsapp/EnterPhoneNumber;
        //  1561: invokevirtual   com/whatsapp/EnterPhoneNumber.a:()V
        //  1564: getstatic       com/whatsapp/a6s.z:[Ljava/lang/String;
        //  1567: bipush          18
        //  1569: aaload         
        //  1570: invokestatic    com/whatsapp/util/Log.i:(Ljava/lang/String;)V
        //  1573: getstatic       com/whatsapp/App.aS:I
        //  1576: istore          65
        //  1578: iload           65
        //  1580: iconst_2       
        //  1581: if_icmpne       1600
        //  1584: aload_0        
        //  1585: getfield        com/whatsapp/a6s.c:Lcom/whatsapp/EnterPhoneNumber;
        //  1588: ldc_w           2131231555
        //  1591: invokevirtual   com/whatsapp/EnterPhoneNumber.getString:(I)Ljava/lang/String;
        //  1594: astore          70
        //  1596: iload_2        
        //  1597: ifeq            1660
        //  1600: getstatic       com/whatsapp/App.aS:I
        //  1603: istore          67
        //  1605: iload           67
        //  1607: ifne            1626
        //  1610: aload_0        
        //  1611: getfield        com/whatsapp/a6s.c:Lcom/whatsapp/EnterPhoneNumber;
        //  1614: ldc_w           2131231556
        //  1617: invokevirtual   com/whatsapp/EnterPhoneNumber.getString:(I)Ljava/lang/String;
        //  1620: astore          70
        //  1622: iload_2        
        //  1623: ifeq            1660
        //  1626: aload_0        
        //  1627: getfield        com/whatsapp/a6s.c:Lcom/whatsapp/EnterPhoneNumber;
        //  1630: astore          68
        //  1632: iconst_1       
        //  1633: anewarray       Ljava/lang/Object;
        //  1636: astore          69
        //  1638: aload           69
        //  1640: iconst_0       
        //  1641: getstatic       com/whatsapp/a6s.z:[Ljava/lang/String;
        //  1644: bipush          11
        //  1646: aaload         
        //  1647: aastore        
        //  1648: aload           68
        //  1650: ldc_w           2131231557
        //  1653: aload           69
        //  1655: invokevirtual   com/whatsapp/EnterPhoneNumber.getString:(I[Ljava/lang/Object;)Ljava/lang/String;
        //  1658: astore          70
        //  1660: aload_0        
        //  1661: getfield        com/whatsapp/a6s.c:Lcom/whatsapp/EnterPhoneNumber;
        //  1664: aload           70
        //  1666: invokevirtual   com/whatsapp/EnterPhoneNumber.d:(Ljava/lang/String;)V
        //  1669: iload_2        
        //  1670: ifeq            1192
        //  1673: aload_1        
        //  1674: invokevirtual   java/lang/Integer.intValue:()I
        //  1677: istore          56
        //  1679: iload           56
        //  1681: bipush          11
        //  1683: if_icmpne       1192
        //  1686: aload_0        
        //  1687: getfield        com/whatsapp/a6s.c:Lcom/whatsapp/EnterPhoneNumber;
        //  1690: invokevirtual   com/whatsapp/EnterPhoneNumber.a:()V
        //  1693: getstatic       com/whatsapp/a6s.z:[Ljava/lang/String;
        //  1696: bipush          15
        //  1698: aaload         
        //  1699: invokestatic    com/whatsapp/util/Log.w:(Ljava/lang/String;)V
        //  1702: aload_0        
        //  1703: getfield        com/whatsapp/a6s.l:Ljava/lang/String;
        //  1706: astore          57
        //  1708: aload           57
        //  1710: ifnull          1822
        //  1713: ldc2_w          1000
        //  1716: aload_0        
        //  1717: getfield        com/whatsapp/a6s.l:Ljava/lang/String;
        //  1720: invokestatic    java/lang/Long.parseLong:(Ljava/lang/String;)J
        //  1723: lmul           
        //  1724: lstore          60
        //  1726: lload           60
        //  1728: invokestatic    android/os/SystemClock.elapsedRealtime:()J
        //  1731: ladd           
        //  1732: putstatic       com/whatsapp/EnterPhoneNumber.u:J
        //  1735: getstatic       com/whatsapp/App.aq:Lcom/whatsapp/App;
        //  1738: lload           60
        //  1740: invokevirtual   com/whatsapp/App.c:(J)V
        //  1743: aload_0        
        //  1744: getfield        com/whatsapp/a6s.c:Lcom/whatsapp/EnterPhoneNumber;
        //  1747: astore          62
        //  1749: aload_0        
        //  1750: getfield        com/whatsapp/a6s.c:Lcom/whatsapp/EnterPhoneNumber;
        //  1753: astore          63
        //  1755: iconst_1       
        //  1756: anewarray       Ljava/lang/Object;
        //  1759: astore          64
        //  1761: aload           64
        //  1763: iconst_0       
        //  1764: aload_0        
        //  1765: getfield        com/whatsapp/a6s.c:Lcom/whatsapp/EnterPhoneNumber;
        //  1768: lload           60
        //  1770: invokestatic    com/whatsapp/util/b6.n:(Landroid/content/Context;J)Ljava/lang/String;
        //  1773: aastore        
        //  1774: aload           62
        //  1776: aload           63
        //  1778: ldc_w           2131231570
        //  1781: aload           64
        //  1783: invokevirtual   com/whatsapp/EnterPhoneNumber.getString:(I[Ljava/lang/Object;)Ljava/lang/String;
        //  1786: invokevirtual   com/whatsapp/EnterPhoneNumber.d:(Ljava/lang/String;)V
        //  1789: return         
        //  1790: astore          59
        //  1792: getstatic       com/whatsapp/a6s.z:[Ljava/lang/String;
        //  1795: bipush          16
        //  1797: aaload         
        //  1798: invokestatic    com/whatsapp/util/Log.w:(Ljava/lang/String;)V
        //  1801: aload_0        
        //  1802: getfield        com/whatsapp/a6s.c:Lcom/whatsapp/EnterPhoneNumber;
        //  1805: aload_0        
        //  1806: getfield        com/whatsapp/a6s.c:Lcom/whatsapp/EnterPhoneNumber;
        //  1809: ldc_w           2131231571
        //  1812: invokevirtual   com/whatsapp/EnterPhoneNumber.getString:(I)Ljava/lang/String;
        //  1815: invokevirtual   com/whatsapp/EnterPhoneNumber.d:(Ljava/lang/String;)V
        //  1818: iload_2        
        //  1819: ifeq            1192
        //  1822: getstatic       com/whatsapp/a6s.z:[Ljava/lang/String;
        //  1825: bipush          14
        //  1827: aaload         
        //  1828: invokestatic    com/whatsapp/util/Log.w:(Ljava/lang/String;)V
        //  1831: aload_0        
        //  1832: getfield        com/whatsapp/a6s.c:Lcom/whatsapp/EnterPhoneNumber;
        //  1835: aload_0        
        //  1836: getfield        com/whatsapp/a6s.c:Lcom/whatsapp/EnterPhoneNumber;
        //  1839: ldc_w           2131231571
        //  1842: invokevirtual   com/whatsapp/EnterPhoneNumber.getString:(I)Ljava/lang/String;
        //  1845: invokevirtual   com/whatsapp/EnterPhoneNumber.d:(Ljava/lang/String;)V
        //  1848: return         
        //  1849: astore          58
        //  1851: aload           58
        //  1853: athrow         
        //  1854: astore          48
        //  1856: aload           48
        //  1858: athrow         
        //  1859: astore          49
        //  1861: aload           49
        //  1863: athrow         
        //  1864: astore          50
        //  1866: aload           50
        //  1868: athrow         
        //  1869: astore          51
        //  1871: aload           51
        //  1873: athrow         
        //  1874: astore          66
        //  1876: aload           66
        //  1878: athrow         
        //  1879: astore          54
        //  1881: aload           54
        //  1883: athrow         
        //  1884: astore          55
        //  1886: aload           55
        //  1888: athrow         
        //    Exceptions:
        //  Try           Handler
        //  Start  End    Start  End    Type                             
        //  -----  -----  -----  -----  ---------------------------------
        //  4      21     1193   1196   Ljava/lang/NumberFormatException;
        //  21     38     1196   1201   Ljava/lang/NumberFormatException;
        //  38     52     1201   1206   Ljava/lang/NumberFormatException;
        //  58     66     1206   1211   Ljava/lang/NumberFormatException;
        //  66     96     1211   1216   Ljava/lang/NumberFormatException;
        //  101    110    1216   1221   Ljava/lang/NumberFormatException;
        //  157    171    1221   1237   Ljava/lang/NumberFormatException;
        //  171    179    1237   1242   Ljava/lang/NumberFormatException;
        //  183    189    1237   1242   Ljava/lang/NumberFormatException;
        //  196    217    1242   1247   Ljava/lang/NumberFormatException;
        //  222    231    1247   1252   Ljava/lang/NumberFormatException;
        //  278    292    1252   1266   Ljava/lang/NumberFormatException;
        //  292    300    1266   1271   Ljava/lang/NumberFormatException;
        //  304    310    1266   1271   Ljava/lang/NumberFormatException;
        //  316    350    1271   1276   Ljava/lang/NumberFormatException;
        //  355    382    1276   1281   Ljava/lang/NumberFormatException;
        //  386    411    1281   1286   Ljava/lang/NumberFormatException;
        //  416    425    1286   1291   Ljava/lang/NumberFormatException;
        //  425    441    1291   1296   Ljava/lang/NumberFormatException;
        //  445    451    1296   1301   Ljava/lang/NumberFormatException;
        //  457    533    1301   1306   Ljava/lang/NumberFormatException;
        //  538    547    1306   1311   Ljava/lang/NumberFormatException;
        //  552    561    1311   1316   Ljava/lang/NumberFormatException;
        //  565    571    1316   1321   Ljava/lang/NumberFormatException;
        //  577    602    1321   1326   Ljava/lang/NumberFormatException;
        //  607    616    1326   1331   Ljava/lang/NumberFormatException;
        //  621    630    1331   1336   Ljava/lang/NumberFormatException;
        //  634    640    1336   1341   Ljava/lang/NumberFormatException;
        //  646    709    1341   1346   Ljava/lang/NumberFormatException;
        //  713    719    1346   1351   Ljava/lang/NumberFormatException;
        //  726    754    1351   1356   Ljava/lang/NumberFormatException;
        //  759    771    1356   1361   Ljava/lang/NumberFormatException;
        //  771    797    1384   1389   Ljava/lang/NumberFormatException;
        //  801    807    1384   1389   Ljava/lang/NumberFormatException;
        //  814    841    1389   1394   Ljava/lang/NumberFormatException;
        //  846    858    1394   1399   Ljava/lang/NumberFormatException;
        //  858    884    1422   1427   Ljava/lang/NumberFormatException;
        //  888    894    1422   1427   Ljava/lang/NumberFormatException;
        //  901    929    1427   1432   Ljava/lang/NumberFormatException;
        //  934    946    1432   1437   Ljava/lang/NumberFormatException;
        //  946    1051   1460   1465   Ljava/lang/NumberFormatException;
        //  1055   1061   1460   1465   Ljava/lang/NumberFormatException;
        //  1068   1090   1465   1470   Ljava/lang/NumberFormatException;
        //  1095   1112   1470   1475   Ljava/lang/NumberFormatException;
        //  1116   1192   1475   1498   Ljava/lang/NumberFormatException;
        //  1203   1206   1206   1211   Ljava/lang/NumberFormatException;
        //  1213   1216   1216   1221   Ljava/lang/NumberFormatException;
        //  1239   1242   1242   1247   Ljava/lang/NumberFormatException;
        //  1244   1247   1247   1252   Ljava/lang/NumberFormatException;
        //  1268   1271   1271   1276   Ljava/lang/NumberFormatException;
        //  1273   1276   1276   1281   Ljava/lang/NumberFormatException;
        //  1278   1281   1281   1286   Ljava/lang/NumberFormatException;
        //  1283   1286   1286   1291   Ljava/lang/NumberFormatException;
        //  1293   1296   1296   1301   Ljava/lang/NumberFormatException;
        //  1298   1301   1301   1306   Ljava/lang/NumberFormatException;
        //  1303   1306   1306   1311   Ljava/lang/NumberFormatException;
        //  1308   1311   1311   1316   Ljava/lang/NumberFormatException;
        //  1313   1316   1316   1321   Ljava/lang/NumberFormatException;
        //  1318   1321   1321   1326   Ljava/lang/NumberFormatException;
        //  1323   1326   1326   1331   Ljava/lang/NumberFormatException;
        //  1328   1331   1331   1336   Ljava/lang/NumberFormatException;
        //  1333   1336   1336   1341   Ljava/lang/NumberFormatException;
        //  1338   1341   1341   1346   Ljava/lang/NumberFormatException;
        //  1343   1346   1346   1351   Ljava/lang/NumberFormatException;
        //  1348   1351   1351   1356   Ljava/lang/NumberFormatException;
        //  1353   1356   1356   1361   Ljava/lang/NumberFormatException;
        //  1386   1389   1389   1394   Ljava/lang/NumberFormatException;
        //  1391   1394   1394   1399   Ljava/lang/NumberFormatException;
        //  1424   1427   1427   1432   Ljava/lang/NumberFormatException;
        //  1429   1432   1432   1437   Ljava/lang/NumberFormatException;
        //  1462   1465   1465   1470   Ljava/lang/NumberFormatException;
        //  1467   1470   1470   1475   Ljava/lang/NumberFormatException;
        //  1477   1494   1854   1859   Ljava/lang/NumberFormatException;
        //  1498   1504   1854   1859   Ljava/lang/NumberFormatException;
        //  1511   1540   1859   1864   Ljava/lang/NumberFormatException;
        //  1544   1550   1864   1869   Ljava/lang/NumberFormatException;
        //  1557   1578   1869   1874   Ljava/lang/NumberFormatException;
        //  1600   1605   1874   1879   Ljava/lang/NumberFormatException;
        //  1660   1669   1879   1884   Ljava/lang/NumberFormatException;
        //  1673   1679   1879   1884   Ljava/lang/NumberFormatException;
        //  1686   1708   1884   1889   Ljava/lang/NumberFormatException;
        //  1713   1789   1790   1822   Ljava/lang/NumberFormatException;
        //  1792   1818   1849   1854   Ljava/lang/NumberFormatException;
        //  1822   1848   1849   1854   Ljava/lang/NumberFormatException;
        //  1856   1859   1859   1864   Ljava/lang/NumberFormatException;
        //  1861   1864   1864   1869   Ljava/lang/NumberFormatException;
        //  1866   1869   1869   1874   Ljava/lang/NumberFormatException;
        //  1881   1884   1884   1889   Ljava/lang/NumberFormatException;
        // 
        // The error that occurred was:
        // 
        // java.lang.IndexOutOfBoundsException: Index: 872, Size: 872
        //     at java.util.ArrayList.rangeCheck(ArrayList.java:653)
        //     at java.util.ArrayList.get(ArrayList.java:429)
        //     at com.strobel.decompiler.ast.AstBuilder.convertToAst(AstBuilder.java:3303)
        //     at com.strobel.decompiler.ast.AstBuilder.build(AstBuilder.java:113)
        //     at com.strobel.decompiler.languages.java.ast.AstMethodBodyBuilder.createMethodBody(AstMethodBodyBuilder.java:210)
        //     at com.strobel.decompiler.languages.java.ast.AstMethodBodyBuilder.createMethodBody(AstMethodBodyBuilder.java:99)
        //     at com.strobel.decompiler.languages.java.ast.AstBuilder.createMethodBody(AstBuilder.java:757)
        //     at com.strobel.decompiler.languages.java.ast.AstBuilder.createMethod(AstBuilder.java:655)
        //     at com.strobel.decompiler.languages.java.ast.AstBuilder.addTypeMembers(AstBuilder.java:532)
        //     at com.strobel.decompiler.languages.java.ast.AstBuilder.createTypeCore(AstBuilder.java:499)
        //     at com.strobel.decompiler.languages.java.ast.AstBuilder.createTypeNoCache(AstBuilder.java:141)
        //     at com.strobel.decompiler.languages.java.ast.AstBuilder.createType(AstBuilder.java:130)
        //     at com.strobel.decompiler.languages.java.ast.AstBuilder.addType(AstBuilder.java:105)
        //     at com.strobel.decompiler.languages.java.JavaLanguage.buildAst(JavaLanguage.java:71)
        //     at com.strobel.decompiler.languages.java.JavaLanguage.decompileType(JavaLanguage.java:59)
        //     at com.strobel.decompiler.DecompilerDriver.decompileType(DecompilerDriver.java:317)
        //     at com.strobel.decompiler.DecompilerDriver.decompileJar(DecompilerDriver.java:238)
        //     at com.strobel.decompiler.DecompilerDriver.main(DecompilerDriver.java:123)
        // 
        throw new IllegalStateException("An error occurred while decompiling this method.");
    }
    
    protected Object doInBackground(final Object[] array) {
        return this.a((byte[][])array);
    }
    
    protected void onPostExecute(final Object o) {
        this.a((Integer)o);
    }
    
    protected void onPreExecute() {
        this.c.showDialog(9);
    }
}
