// 
// Decompiled by Procyon v0.5.30
// 

package com.whatsapp;

import com.whatsapp.util.al;
import java.net.URL;
import android.os.ConditionVariable;
import com.whatsapp.util.h;
import android.content.pm.ActivityInfo;
import java.util.Iterator;
import java.util.List;
import com.whatsapp.util.Log;
import android.content.pm.ResolveInfo;
import android.os.Parcelable;
import android.net.Uri;
import android.content.Intent;
import java.io.File;
import java.util.ArrayList;
import android.app.Activity;
import android.net.NetworkInfo;
import android.text.TextUtils;
import android.net.ConnectivityManager;
import android.content.Context;

public class a8q
{
    private static final String[] z;
    
    static {
        final String[] z2 = new String[165];
        String s = "y1$+8x0";
        int n = -1;
        String[] array = z2;
        int n2 = 0;
        String intern = null;
    Label_4260:
        while (true) {
            final char[] charArray = s.toCharArray();
            for (int i = charArray.length, n3 = 0; i > n3; ++n3) {
                final char c = charArray[n3];
                char c2 = '\0';
                switch (n3 % 5) {
                    default: {
                        c2 = 'W';
                        break;
                    }
                    case 0: {
                        c2 = '\n';
                        break;
                    }
                    case 1: {
                        c2 = 'D';
                        break;
                    }
                    case 2: {
                        c2 = 'T';
                        break;
                    }
                    case 3: {
                        c2 = '[';
                        break;
                    }
                }
                charArray[n3] = (char)(c2 ^ c);
            }
            intern = new String(charArray).intern();
            switch (n) {
                default: {
                    array[n2] = intern;
                    n2 = 1;
                    array = z2;
                    s = "l6;6";
                    n = 0;
                    continue;
                }
                case 0: {
                    array[n2] = intern;
                    n2 = 2;
                    s = "~=$>";
                    n = 1;
                    array = z2;
                    continue;
                }
                case 1: {
                    array[n2] = intern;
                    n2 = 3;
                    s = "l+&82n";
                    n = 2;
                    array = z2;
                    continue;
                }
                case 2: {
                    array[n2] = intern;
                    n2 = 4;
                    s = "~6!>";
                    n = 3;
                    array = z2;
                    continue;
                }
                case 3: {
                    array[n2] = intern;
                    n2 = 5;
                    s = "o)52;'7153o6{.'f+5?zf+3(wd+t78m7t=8\u007f*0{#ed6>w\u007f4846n!0u";
                    n = 4;
                    array = z2;
                    continue;
                }
                case 4: {
                    array[n2] = intern;
                    n2 = 6;
                    s = "0d";
                    n = 5;
                    array = z2;
                    continue;
                }
                case 5: {
                    array[n2] = intern;
                    n2 = 7;
                    s = "o)52;y!:?2xk>(8dk1)%e6t";
                    n = 6;
                    array = z2;
                    continue;
                }
                case 6: {
                    array[n2] = intern;
                    n2 = 8;
                    s = "o)52;'7153o6{:'zd";
                    n = 7;
                    array = z2;
                    continue;
                }
                case 7: {
                    array[n2] = intern;
                    n2 = 9;
                    s = "*8t";
                    n = 8;
                    array = z2;
                    continue;
                }
                case 8: {
                    array[n2] = intern;
                    s = "o)52;";
                    n = 9;
                    n2 = 10;
                    array = z2;
                    continue;
                }
                case 9: {
                    array[n2] = intern;
                    n2 = 11;
                    array = z2;
                    s = "g%=73x+=?";
                    n = 10;
                    continue;
                }
                case 10: {
                    array[n2] = intern;
                    n2 = 12;
                    s = "s%:?2rj9:>f";
                    n = 11;
                    array = z2;
                    continue;
                }
                case 11: {
                    array[n2] = intern;
                    n2 = 13;
                    s = "m)";
                    n = 12;
                    array = z2;
                    continue;
                }
                case 12: {
                    array[n2] = intern;
                    n2 = 14;
                    s = "b+ 66c(";
                    n = 13;
                    array = z2;
                    continue;
                }
                case 13: {
                    array[n2] = intern;
                    n2 = 15;
                    s = "i+9u5k=029$&;4:o6550";
                    n = 14;
                    array = z2;
                    continue;
                }
                case 14: {
                    array[n2] = intern;
                    n2 = 16;
                    s = "k*0)8c z29~!:/yo< )6$\r\u001a\u0012\u0003C\u0005\u0018\u0004\u001eD\u0010\u0011\u0015\u0003Y";
                    n = 15;
                    array = z2;
                    continue;
                }
                case 15: {
                    array[n2] = intern;
                    n2 = 17;
                    s = "k*0)8c z66c(";
                    n = 16;
                    array = z2;
                    continue;
                }
                case 16: {
                    array[n2] = intern;
                    n2 = 18;
                    s = "l770ya}";
                    n = 17;
                    array = z2;
                    continue;
                }
                case 17: {
                    array[n2] = intern;
                    n2 = 19;
                    s = "D\u000b\u001a\u001e";
                    n = 18;
                    array = z2;
                    continue;
                }
                case 18: {
                    array[n2] = intern;
                    n2 = 20;
                    s = "*l";
                    n = 19;
                    array = z2;
                    continue;
                }
                case 19: {
                    array[n2] = intern;
                    n2 = 21;
                    s = "_\n\u001f\u0015\u0018]\n";
                    n = 20;
                    array = z2;
                    continue;
                }
                case 20: {
                    array[n2] = intern;
                    n2 = 22;
                    s = "M\u0017\u0019";
                    n = 21;
                    array = z2;
                    continue;
                }
                case 21: {
                    array[n2] = intern;
                    n2 = 23;
                    s = "I\u0000\u0019\u001a";
                    n = 22;
                    array = z2;
                    continue;
                }
                case 22: {
                    array[n2] = intern;
                    n2 = 24;
                    s = "Y\r\u0004";
                    n = 23;
                    array = z2;
                    continue;
                }
                case 23: {
                    array[n2] = intern;
                    n2 = 25;
                    s = "D\u000b\u001a\u001e";
                    n = 24;
                    array = z2;
                    continue;
                }
                case 24: {
                    array[n2] = intern;
                    n2 = 26;
                    s = "_\n\u001f\u0015\u0018]\nts9ed >;o4<49sd9:9k#1)~";
                    n = 25;
                    array = z2;
                    continue;
                }
                case 25: {
                    array[n2] = intern;
                    n2 = 27;
                    s = "_\n\u001f\u0015\u0018]\nts9ed >;o4<49sd9:9k#1)~";
                    n = 26;
                    array = z2;
                    continue;
                }
                case 26: {
                    array[n2] = intern;
                    n2 = 28;
                    s = "\u0000N^Q,q!9:>f\u001b1#4o4 28d9)Q";
                    n = 27;
                    array = z2;
                    continue;
                }
                case 27: {
                    array[n2] = intern;
                    n2 = 29;
                    s = "\u007f*&>0c7 >%o ";
                    n = 28;
                    array = z2;
                    continue;
                }
                case 28: {
                    array[n2] = intern;
                    n2 = 30;
                    s = "X%028*\t\u0017\u0018zG\n\u0017";
                    n = 29;
                    array = z2;
                    continue;
                }
                case 29: {
                    array[n2] = intern;
                    n2 = 31;
                    s = "E\u0017";
                    n = 30;
                    array = z2;
                    continue;
                }
                case 30: {
                    array[n2] = intern;
                    n2 = 32;
                    s = "8jeiy;sb";
                    n = 31;
                    array = z2;
                    continue;
                }
                case 31: {
                    array[n2] = intern;
                    n2 = 33;
                    s = "L61>wY4582*\u0016168|%672";
                    n = 32;
                    array = z2;
                    continue;
                }
                case 32: {
                    array[n2] = intern;
                    n2 = 34;
                    s = "|+=+wi%87wy! .'*!&)8x";
                    n = 33;
                    array = z2;
                    continue;
                }
                case 33: {
                    array[n2] = intern;
                    n2 = 35;
                    s = "8jeiy;sb";
                    n = 34;
                    array = z2;
                    continue;
                }
                case 34: {
                    array[n2] = intern;
                    n2 = 36;
                    s = "i,:.:*";
                    n = 35;
                    array = z2;
                    continue;
                }
                case 35: {
                    array[n2] = intern;
                    n2 = 37;
                    s = "I\u0007;?2";
                    n = 36;
                    array = z2;
                    continue;
                }
                case 36: {
                    array[n2] = intern;
                    n2 = 38;
                    s = "z(5\"";
                    n = 37;
                    array = z2;
                    continue;
                }
                case 37: {
                    array[n2] = intern;
                    n2 = 39;
                    s = "_\n\u001f\u0015\u0018]\nts9ed >;o4<49sd9:9k#1)~";
                    n = 38;
                    array = z2;
                    continue;
                }
                case 38: {
                    array[n2] = intern;
                    n2 = 40;
                    s = "^%&<2~";
                    n = 39;
                    array = z2;
                    continue;
                }
                case 39: {
                    array[n2] = intern;
                    n2 = 41;
                    s = "|+=+wi%87wy-0>";
                    n = 40;
                    array = z2;
                    continue;
                }
                case 40: {
                    array[n2] = intern;
                    n2 = 42;
                    s = "_\u0014";
                    n = 41;
                    array = z2;
                    continue;
                }
                case 41: {
                    array[n2] = intern;
                    n2 = 43;
                    s = "F\u0003";
                    n = 42;
                    array = z2;
                    continue;
                }
                case 42: {
                    array[n2] = intern;
                    n2 = 44;
                    s = "z,;52";
                    n = 43;
                    array = z2;
                    continue;
                }
                case 43: {
                    array[n2] = intern;
                    n2 = 45;
                    s = "D+";
                    n = 44;
                    array = z2;
                    continue;
                }
                case 44: {
                    array[n2] = intern;
                    n2 = 46;
                    s = "N!\"24od\u001d\b\u00182rdj";
                    n = 45;
                    array = z2;
                    continue;
                }
                case 45: {
                    array[n2] = intern;
                    n2 = 47;
                    s = "o)52;%*!65o6{/%c){>%x+&";
                    n = 46;
                    array = z2;
                    continue;
                }
                case 46: {
                    array[n2] = intern;
                    n2 = 48;
                    s = "G-'/.z!0";
                    n = 47;
                    array = z2;
                    continue;
                }
                case 47: {
                    array[n2] = intern;
                    n2 = 49;
                    s = "/7n~$";
                    n = 48;
                    array = z2;
                    continue;
                }
                case 48: {
                    array[n2] = intern;
                    n2 = 50;
                    s = "F\u0007";
                    n = 49;
                    array = z2;
                    continue;
                }
                case 49: {
                    array[n2] = intern;
                    n2 = 51;
                    s = "Dk\u0015";
                    n = 50;
                    array = z2;
                    continue;
                }
                case 50: {
                    array[n2] = intern;
                    n2 = 52;
                    s = "O<$";
                    n = 51;
                    array = z2;
                    continue;
                }
                case 51: {
                    array[n2] = intern;
                    n2 = 53;
                    s = "s=-\"zG\ty?3*\f\u001ca:g~'(yY\u0017\u0007\u0001";
                    n = 52;
                    array = z2;
                    continue;
                }
                case 52: {
                    array[n2] = intern;
                    n2 = 54;
                    s = "I%&)>o6";
                    n = 53;
                    array = z2;
                    continue;
                }
                case 53: {
                    array[n2] = intern;
                    n2 = 55;
                    s = "Dk\u0015{\u007fd+t/2f!$38d=t66d%3>%#";
                    n = 54;
                    array = z2;
                    continue;
                }
                case 54: {
                    array[n2] = intern;
                    n2 = 56;
                    s = "Y\r\u0019{\u001aI\u0007y\u0016\u0019I";
                    n = 55;
                    array = z2;
                    continue;
                }
                case 55: {
                    array[n2] = intern;
                    n2 = 57;
                    s = "x!2";
                    n = 56;
                    array = z2;
                    continue;
                }
                case 56: {
                    array[n2] = intern;
                    n2 = 58;
                    s = "N-'/%c&!/>e*";
                    n = 57;
                    array = z2;
                    continue;
                }
                case 57: {
                    array[n2] = intern;
                    n2 = 59;
                    s = "]!6{$o7'28d";
                    n = 58;
                    array = z2;
                    continue;
                }
                case 58: {
                    array[n2] = intern;
                    n2 = 60;
                    s = "i'";
                    n = 59;
                    array = z2;
                    continue;
                }
                case 59: {
                    array[n2] = intern;
                    n2 = 61;
                    s = "g+!5#o \u000b)8";
                    n = 60;
                    array = z2;
                    continue;
                }
                case 60: {
                    array[n2] = intern;
                    n2 = 62;
                    s = "z(5\"";
                    n = 61;
                    array = z2;
                    continue;
                }
                case 61: {
                    array[n2] = intern;
                    n2 = 63;
                    s = "Y!&-2x";
                    n = 62;
                    array = z2;
                    continue;
                }
                case 62: {
                    array[n2] = intern;
                    n2 = 64;
                    s = "D+ {'x!'>9~";
                    n = 63;
                    array = z2;
                    continue;
                }
                case 63: {
                    array[n2] = intern;
                    n2 = 65;
                    s = "k' 2!o";
                    n = 64;
                    array = z2;
                    continue;
                }
                case 64: {
                    array[n2] = intern;
                    n2 = 66;
                    s = "N% :wx+56>d#";
                    n = 65;
                    array = z2;
                    continue;
                }
                case 65: {
                    array[n2] = intern;
                    n2 = 67;
                    s = "\u007f*?58}*";
                    n = 66;
                    array = z2;
                    continue;
                }
                case 66: {
                    array[n2] = intern;
                    s = "N\n";
                    n = 67;
                    n2 = 68;
                    array = z2;
                    continue;
                }
                case 67: {
                    array[n2] = intern;
                    n2 = 69;
                    array = z2;
                    s = "*l&>6ni;5;sm";
                    n = 68;
                    continue;
                }
                case 68: {
                    array[n2] = intern;
                    n2 = 70;
                    s = "\\!&(>e*";
                    n = 69;
                    array = z2;
                    continue;
                }
                case 69: {
                    array[n2] = intern;
                    n2 = 71;
                    s = "x!8>6y!";
                    n = 70;
                    array = z2;
                    continue;
                }
                case 70: {
                    array[n2] = intern;
                    n2 = 72;
                    s = "D! ,8x/t)2y0&24~!0";
                    n = 71;
                    array = z2;
                    continue;
                }
                case 71: {
                    array[n2] = intern;
                    n2 = 73;
                    s = "S!'";
                    n = 72;
                    array = z2;
                    continue;
                }
                case 72: {
                    array[n2] = intern;
                    n2 = 74;
                    s = "i+9u b% (6z4\u000b+%o\"1)2d'1(";
                    n = 73;
                    array = z2;
                    continue;
                }
                case 73: {
                    array[n2] = intern;
                    n2 = 75;
                    s = "Y\u0007{\u0003\u0014";
                    n = 74;
                    array = z2;
                    continue;
                }
                case 74: {
                    array[n2] = intern;
                    n2 = 76;
                    s = "H1=73";
                    n = 75;
                    array = z2;
                    continue;
                }
                case 75: {
                    array[n2] = intern;
                    n2 = 77;
                    s = "x!8>6y!";
                    n = 76;
                    array = z2;
                    continue;
                }
                case 76: {
                    array[n2] = intern;
                    n2 = 78;
                    s = "*l";
                    n = 77;
                    array = z2;
                    continue;
                }
                case 77: {
                    array[n2] = intern;
                    n2 = 79;
                    s = "D! ,8x/t\u000f.z!";
                    n = 78;
                    array = z2;
                    continue;
                }
                case 78: {
                    array[n2] = intern;
                    n2 = 80;
                    s = "Y+702~d\u001749d";
                    n = 79;
                    array = z2;
                    continue;
                }
                case 79: {
                    array[n2] = intern;
                    n2 = 81;
                    s = "Z\u0013";
                    n = 80;
                    array = z2;
                    continue;
                }
                case 80: {
                    array[n2] = intern;
                    n2 = 82;
                    s = "'i\u0007.'z+&/wC*24z'N";
                    n = 81;
                    array = z2;
                    continue;
                }
                case 81: {
                    array[n2] = intern;
                    n2 = 83;
                    s = "p>";
                    n = 82;
                    array = z2;
                    continue;
                }
                case 82: {
                    array[n2] = intern;
                    s = "L61>wY4582*\u0006!2;~i\u001d5";
                    n = 83;
                    n2 = 84;
                    array = z2;
                    continue;
                }
                case 83: {
                    array[n2] = intern;
                    n2 = 85;
                    array = z2;
                    s = "Z6;?\"i0";
                    n = 84;
                    continue;
                }
                case 84: {
                    array[n2] = intern;
                    n2 = 86;
                    s = "L\u0005\u0005{\u0005o7!7#yd\u0006>#\u007f6:>3";
                    n = 85;
                    array = z2;
                    continue;
                }
                case 85: {
                    array[n2] = intern;
                    s = "\u007f*?58}*";
                    n = 86;
                    n2 = 87;
                    array = z2;
                    continue;
                }
                case 86: {
                    array[n2] = intern;
                    n2 = 88;
                    array = z2;
                    s = "|+=+wi%87w~!&6>d% >wx!5(8d";
                    n = 87;
                    continue;
                }
                case 87: {
                    array[n2] = intern;
                    n2 = 89;
                    s = "Dk\u0015{\u007fd+t/2f!$38d=t66d%3>%#";
                    n = 88;
                    array = z2;
                    continue;
                }
                case 88: {
                    array[n2] = intern;
                    n2 = 90;
                    s = "D+ {\u0014k(7.;k01?";
                    n = 89;
                    array = z2;
                    continue;
                }
                case 89: {
                    array[n2] = intern;
                    n2 = 91;
                    s = "i+:52i0=->~=";
                    n = 90;
                    array = z2;
                    continue;
                }
                case 90: {
                    array[n2] = intern;
                    n2 = 92;
                    s = "*l";
                    n = 91;
                    array = z2;
                    continue;
                }
                case 91: {
                    array[n2] = intern;
                    n2 = 93;
                    s = "D! ,8x/t62~!&>3";
                    n = 92;
                    array = z2;
                    continue;
                }
                case 92: {
                    array[n2] = intern;
                    n2 = 94;
                    s = "Y-9";
                    n = 93;
                    array = z2;
                    continue;
                }
                case 93: {
                    array[n2] = intern;
                    n2 = 95;
                    s = "p>";
                    n = 94;
                    array = z2;
                    continue;
                }
                case 94: {
                    array[n2] = intern;
                    n2 = 96;
                    s = "Z,;52*\u0010-+2";
                    n = 95;
                    array = z2;
                    continue;
                }
                case 95: {
                    array[n2] = intern;
                    n2 = 97;
                    s = "G+0>;";
                    n = 96;
                    array = z2;
                    continue;
                }
                case 96: {
                    array[n2] = intern;
                    n2 = 98;
                    s = "G%:.1k' .%o6";
                    n = 97;
                    array = z2;
                    continue;
                }
                case 97: {
                    array[n2] = intern;
                    n2 = 99;
                    s = "~+?>9*75-2n";
                    n = 98;
                    array = z2;
                    continue;
                }
                case 98: {
                    array[n2] = intern;
                    n2 = 100;
                    s = "\u007f*?58}*";
                    n = 99;
                    array = z2;
                    continue;
                }
                case 99: {
                    array[n2] = intern;
                    n2 = 101;
                    s = "\u0000N^Q";
                    n = 100;
                    array = z2;
                    continue;
                }
                case 100: {
                    array[n2] = intern;
                    n2 = 102;
                    s = "N!\"24o";
                    n = 101;
                    array = z2;
                    continue;
                }
                case 101: {
                    array[n2] = intern;
                    n2 = 103;
                    s = "A!&52f";
                    n = 102;
                    array = z2;
                    continue;
                }
                case 102: {
                    array[n2] = intern;
                    n2 = 104;
                    s = "*l";
                    n = 103;
                    array = z2;
                    continue;
                }
                case 103: {
                    array[n2] = intern;
                    n2 = 105;
                    s = "I+:52i0=49";
                    n = 104;
                    array = z2;
                    continue;
                }
                case 104: {
                    array[n2] = intern;
                    n2 = 106;
                    s = "o<7>'~-;5wn1&29md166c(t88g4;(>~-;5";
                    n = 105;
                    array = z2;
                    continue;
                }
                case 105: {
                    array[n2] = intern;
                    n2 = 107;
                    s = "|+=+wh-:?w~+t:9sd&>;k=";
                    n = 106;
                    array = z2;
                    continue;
                }
                case 106: {
                    array[n2] = intern;
                    n2 = 108;
                    s = "f-2>#c)1";
                    n = 107;
                    array = z2;
                    continue;
                }
                case 107: {
                    array[n2] = intern;
                    n2 = 109;
                    s = "z,";
                    n = 108;
                    array = z2;
                    continue;
                }
                case 108: {
                    array[n2] = intern;
                    n2 = 110;
                    s = "]!6{$o7'28d";
                    n = 109;
                    array = z2;
                    continue;
                }
                case 109: {
                    array[n2] = intern;
                    n2 = 111;
                    s = "N-5<9e7 24*\u0007;?2y";
                    n = 110;
                    array = z2;
                    continue;
                }
                case 110: {
                    array[n2] = intern;
                    n2 = 112;
                    s = "/7n~$";
                    n = 111;
                    array = z2;
                    continue;
                }
                case 111: {
                    array[n2] = intern;
                    n2 = 113;
                    s = "Dk\u0015";
                    n = 112;
                    array = z2;
                    continue;
                }
                case 112: {
                    array[n2] = intern;
                    n2 = 114;
                    s = "D+ {\u0014k(7.;k01?";
                    n = 113;
                    array = z2;
                    continue;
                }
                case 113: {
                    array[n2] = intern;
                    n2 = 115;
                    s = "o<$2%k0=49U 5/2";
                    n = 114;
                    array = z2;
                    continue;
                }
                case 114: {
                    array[n2] = intern;
                    n2 = 116;
                    s = "N!'8%c4 28d";
                    n = 115;
                    array = z2;
                    continue;
                }
                case 115: {
                    array[n2] = intern;
                    n2 = 117;
                    s = "|+=+wi%87wx!'.;~";
                    n = 116;
                    array = z2;
                    continue;
                }
                case 116: {
                    array[n2] = intern;
                    n2 = 118;
                    s = "^!8{%e%929m";
                    n = 117;
                    array = z2;
                    continue;
                }
                case 117: {
                    array[n2] = intern;
                    n2 = 119;
                    s = "L\u0005\u0005{\u0005o7!7#yd\u0006>6n";
                    n = 118;
                    array = z2;
                    continue;
                }
                case 118: {
                    array[n2] = intern;
                    n2 = 120;
                    s = "I+:/2r0";
                    n = 119;
                    array = z2;
                    continue;
                }
                case 119: {
                    array[n2] = intern;
                    n2 = 121;
                    s = "x!94!o ";
                    n = 120;
                    array = z2;
                    continue;
                }
                case 120: {
                    array[n2] = intern;
                    n2 = 122;
                    s = "N!6.0*-:=8";
                    n = 121;
                    array = z2;
                    continue;
                }
                case 121: {
                    array[n2] = intern;
                    n2 = 123;
                    s = "^\u000fy\u0015\u0007'";
                    n = 122;
                    array = z2;
                    continue;
                }
                case 122: {
                    array[n2] = intern;
                    n2 = 124;
                    s = "N\u0007y\t\u0003O\u0000t";
                    n = 123;
                    array = z2;
                    continue;
                }
                case 123: {
                    array[n2] = intern;
                    n2 = 125;
                    s = "e63u6i65u\u0016I\u0016\u0015";
                    n = 124;
                    array = z2;
                    continue;
                }
                case 124: {
                    array[n2] = intern;
                    n2 = 126;
                    s = "D\u0013y\f\u0016Zie{";
                    n = 125;
                    array = z2;
                    continue;
                }
                case 125: {
                    array[n2] = intern;
                    n2 = 127;
                    s = "N\u0007y\u0019\u0016I\u0016\u0019{";
                    n = 126;
                    array = z2;
                    continue;
                }
                case 126: {
                    array[n2] = intern;
                    n2 = 128;
                    s = "^\u000fy\u001d\u0010'tt";
                    n = 127;
                    array = z2;
                    continue;
                }
                case 127: {
                    array[n2] = intern;
                    n2 = 129;
                    s = "^\u000fy\u0015\u0004'";
                    n = 128;
                    array = z2;
                    continue;
                }
                case 128: {
                    array[n2] = intern;
                    n2 = 130;
                    s = "N\u0007y\u0015\u0011E\n\u0015{";
                    n = 129;
                    array = z2;
                    continue;
                }
                case 129: {
                    array[n2] = intern;
                    n2 = 131;
                    s = "D+t78md22;od 4wk0 :4bj^";
                    n = 130;
                    array = z2;
                    continue;
                }
                case 130: {
                    array[n2] = intern;
                    n2 = 132;
                    s = "k*0)8c z29~!:/yo< )6$\u0010\u0011\u0003\u0003";
                    n = 131;
                    array = z2;
                    continue;
                }
                case 131: {
                    array[n2] = intern;
                    n2 = 133;
                    s = "k*0)8c z29~!:/yo< )6$\u0017\u0001\u0019\u001dO\u0007\u0000";
                    n = 132;
                    array = z2;
                    continue;
                }
                case 132: {
                    array[n2] = intern;
                    n2 = 134;
                    s = "k*0)8c z29~!:/yk' 28dj\u0007\u001e\u0019N\u001b\u0019\u000e\u001b^\r\u0004\u0017\u0012";
                    n = 133;
                    array = z2;
                    continue;
                }
                case 133: {
                    array[n2] = intern;
                    n2 = 135;
                    s = "k*0)8c z29~!:/yo< )6$\u0017\u0000\t\u0012K\t";
                    n = 134;
                    array = z2;
                    continue;
                }
                case 134: {
                    array[n2] = intern;
                    n2 = 136;
                    s = "z(529%01##";
                    n = 135;
                    array = z2;
                    continue;
                }
                case 135: {
                    array[n2] = intern;
                    n2 = 137;
                    s = "z(529%01##";
                    n = 136;
                    array = z2;
                    continue;
                }
                case 136: {
                    array[n2] = intern;
                    n2 = 138;
                    s = "k*0)8c y(\"z4;)#J3<:#y%$+yi+9";
                    n = 137;
                    array = z2;
                    continue;
                }
                case 137: {
                    array[n2] = intern;
                    n2 = 139;
                    s = "k*0)8c z29~!:/yo< )6$\u0001\u0019\u001a\u001eF";
                    n = 138;
                    array = z2;
                    continue;
                }
                case 138: {
                    array[n2] = intern;
                    n2 = 140;
                    s = "k*0)8c z29~!:/yo< )6$\u0017\u0000\t\u0012K\t";
                    n = 139;
                    array = z2;
                    continue;
                }
                case 139: {
                    array[n2] = intern;
                    n2 = 141;
                    s = "k*0)8c z29~!:/yk' 28dj\u0007\u001e\u0019N";
                    n = 140;
                    array = z2;
                    continue;
                }
                case 140: {
                    array[n2] = intern;
                    n2 = 142;
                    s = "k4$7>i% 28dk.2'";
                    n = 141;
                    array = z2;
                    continue;
                }
                case 141: {
                    array[n2] = intern;
                    n2 = 143;
                    s = "*1:09e3:{!o6'28d";
                    n = 142;
                    array = z2;
                    continue;
                }
                case 142: {
                    array[n2] = intern;
                    n2 = 144;
                    s = "_*?58}*t)2f!5(2";
                    n = 143;
                    array = z2;
                    continue;
                }
                case 143: {
                    array[n2] = intern;
                    n2 = 145;
                    s = "%4&44%7-(xa!&52fk\">%y-;5";
                    n = 144;
                    array = z2;
                    continue;
                }
                case 144: {
                    array[n2] = intern;
                    n2 = 146;
                    s = "%4&44%7-(xa!&52fk;(%o(1:$o";
                    n = 145;
                    array = z2;
                    continue;
                }
                case 145: {
                    array[n2] = intern;
                    n2 = 147;
                    s = "%4&44%7-(xa!&52fk\">%y-;5";
                    n = 146;
                    array = z2;
                    continue;
                }
                case 146: {
                    array[n2] = intern;
                    n2 = 148;
                    s = "%4&44%7-(xa!&52fk;(%o(1:$o";
                    n = 147;
                    array = z2;
                    continue;
                }
                case 147: {
                    array[n2] = intern;
                    n2 = 149;
                    s = "I\u0000\u0019\u001aw'de#\u0005^\u0010";
                    n = 148;
                    array = z2;
                    continue;
                }
                case 148: {
                    array[n2] = intern;
                    n2 = 150;
                    s = "I\u0000\u0019\u001a";
                    n = 149;
                    array = z2;
                    continue;
                }
                case 149: {
                    array[n2] = intern;
                    n2 = 151;
                    s = "B\u0017\u0010\u000b\u0016";
                    n = 150;
                    array = z2;
                    continue;
                }
                case 150: {
                    array[n2] = intern;
                    n2 = 152;
                    s = "_\t\u0000\b";
                    n = 151;
                    array = z2;
                    continue;
                }
                case 151: {
                    array[n2] = intern;
                    n2 = 153;
                    s = "B\u0017\u0004\u001a";
                    n = 152;
                    array = z2;
                    continue;
                }
                case 152: {
                    array[n2] = intern;
                    n2 = 154;
                    s = "I\u0000\u0019\u001aw'd\u0011-\u0013ed&>!$dd";
                    n = 153;
                    array = z2;
                    continue;
                }
                case 153: {
                    array[n2] = intern;
                    n2 = 155;
                    s = "M\u0014\u0006\b";
                    n = 154;
                    array = z2;
                    continue;
                }
                case 154: {
                    array[n2] = intern;
                    n2 = 156;
                    s = "I\u0000\u0019\u001aw'd\u0011-\u0013ed&>!$d\u0016";
                    n = 155;
                    array = z2;
                    continue;
                }
                case 155: {
                    array[n2] = intern;
                    n2 = 157;
                    s = "B\u0017\u0001\u000b\u0016";
                    n = 156;
                    array = z2;
                    continue;
                }
                case 156: {
                    array[n2] = intern;
                    n2 = 158;
                    s = "B\u0017\u0004\u001a|";
                    n = 157;
                    array = z2;
                    continue;
                }
                case 157: {
                    array[n2] = intern;
                    n2 = 159;
                    s = "_\n\u001f\u0015\u0018]\n";
                    n = 158;
                    array = z2;
                    continue;
                }
                case 158: {
                    array[n2] = intern;
                    n2 = 160;
                    s = "F\u0010\u0011";
                    n = 159;
                    array = z2;
                    continue;
                }
                case 159: {
                    array[n2] = intern;
                    n2 = 161;
                    s = "I\u0000\u0019\u001aw'd1\u0013\u0005Z\u0000";
                    n = 160;
                    array = z2;
                    continue;
                }
                case 160: {
                    array[n2] = intern;
                    n2 = 162;
                    s = "c\u0000\u0011\u0015";
                    n = 161;
                    array = z2;
                    continue;
                }
                case 161: {
                    array[n2] = intern;
                    n2 = 163;
                    s = "O\u0000\u0013\u001e";
                    n = 162;
                    array = z2;
                    continue;
                }
                case 162: {
                    array[n2] = intern;
                    n2 = 164;
                    s = "I\u0000\u0019\u001aw'd\u0011-\u0013ed&>!$d\u0015";
                    n = 163;
                    array = z2;
                    continue;
                }
                case 163: {
                    break Label_4260;
                }
            }
        }
        array[n2] = intern;
        z = z2;
    }
    
    private static int a(final String s, final String s2, final int n) {
        int i = 0;
        final boolean j = App.I;
        int n2 = -1;
        if (s != null && s2 != null && s.length() >= n && s2.length() >= n) {
            final int n3 = s.length() - n;
            final int n4 = s2.length() - n;
            n2 = 0;
            while (i < n) {
                if (s.charAt(n3 + i) != s2.charAt(n4 + i)) {
                    ++n2;
                }
                ++i;
                if (j) {
                    break;
                }
            }
        }
        return n2;
    }
    
    public static String a() {
        // 
        // This method could not be decompiled.
        // 
        // Original Bytecode:
        // 
        //     0: getstatic       com/whatsapp/a8q.z:[Ljava/lang/String;
        //     3: sipush          146
        //     6: aaload         
        //     7: pop            
        //     8: getstatic       com/whatsapp/a8q.z:[Ljava/lang/String;
        //    11: sipush          145
        //    14: aaload         
        //    15: pop            
        //    16: new             Ljava/lang/StringBuilder;
        //    19: dup            
        //    20: invokespecial   java/lang/StringBuilder.<init>:()V
        //    23: astore_2       
        //    24: new             Ljava/io/BufferedReader;
        //    27: dup            
        //    28: new             Ljava/io/FileReader;
        //    31: dup            
        //    32: getstatic       com/whatsapp/a8q.z:[Ljava/lang/String;
        //    35: sipush          148
        //    38: aaload         
        //    39: invokespecial   java/io/FileReader.<init>:(Ljava/lang/String;)V
        //    42: invokespecial   java/io/BufferedReader.<init>:(Ljava/io/Reader;)V
        //    45: astore_3       
        //    46: aload_2        
        //    47: aload_3        
        //    48: invokevirtual   java/io/BufferedReader.readLine:()Ljava/lang/String;
        //    51: invokevirtual   java/lang/StringBuilder.append:(Ljava/lang/String;)Ljava/lang/StringBuilder;
        //    54: pop            
        //    55: aload_3        
        //    56: ifnull          63
        //    59: aload_3        
        //    60: invokevirtual   java/io/BufferedReader.close:()V
        //    63: aload_3        
        //    64: astore          7
        //    66: new             Ljava/io/BufferedReader;
        //    69: dup            
        //    70: new             Ljava/io/FileReader;
        //    73: dup            
        //    74: getstatic       com/whatsapp/a8q.z:[Ljava/lang/String;
        //    77: sipush          147
        //    80: aaload         
        //    81: invokespecial   java/io/FileReader.<init>:(Ljava/lang/String;)V
        //    84: invokespecial   java/io/BufferedReader.<init>:(Ljava/io/Reader;)V
        //    87: astore          8
        //    89: aload_2        
        //    90: bipush          32
        //    92: invokevirtual   java/lang/StringBuilder.append:(C)Ljava/lang/StringBuilder;
        //    95: aload           8
        //    97: invokevirtual   java/io/BufferedReader.readLine:()Ljava/lang/String;
        //   100: invokevirtual   java/lang/StringBuilder.append:(Ljava/lang/String;)Ljava/lang/StringBuilder;
        //   103: pop            
        //   104: aload           8
        //   106: ifnull          114
        //   109: aload           8
        //   111: invokevirtual   java/io/BufferedReader.close:()V
        //   114: aload_2        
        //   115: invokevirtual   java/lang/StringBuilder.toString:()Ljava/lang/String;
        //   118: areturn        
        //   119: astore          4
        //   121: aconst_null    
        //   122: astore_3       
        //   123: aload_3        
        //   124: ifnull          131
        //   127: aload_3        
        //   128: invokevirtual   java/io/BufferedReader.close:()V
        //   131: aload           4
        //   133: athrow         
        //   134: astore          5
        //   136: aload_2        
        //   137: getstatic       com/whatsapp/a8q.z:[Ljava/lang/String;
        //   140: sipush          144
        //   143: aaload         
        //   144: invokevirtual   java/lang/StringBuilder.append:(Ljava/lang/String;)Ljava/lang/StringBuilder;
        //   147: pop            
        //   148: aload           5
        //   150: invokestatic    com/whatsapp/util/Log.b:(Ljava/lang/Throwable;)V
        //   153: aload_3        
        //   154: astore          7
        //   156: goto            66
        //   159: astore          14
        //   161: aload           14
        //   163: athrow         
        //   164: astore          9
        //   166: aload           7
        //   168: astore          8
        //   170: aload           8
        //   172: ifnull          180
        //   175: aload           8
        //   177: invokevirtual   java/io/BufferedReader.close:()V
        //   180: aload           9
        //   182: athrow         
        //   183: astore          10
        //   185: aload_2        
        //   186: getstatic       com/whatsapp/a8q.z:[Ljava/lang/String;
        //   189: sipush          143
        //   192: aaload         
        //   193: invokevirtual   java/lang/StringBuilder.append:(Ljava/lang/String;)Ljava/lang/StringBuilder;
        //   196: pop            
        //   197: aload           10
        //   199: invokestatic    com/whatsapp/util/Log.b:(Ljava/lang/Throwable;)V
        //   202: goto            114
        //   205: astore          12
        //   207: aload           12
        //   209: athrow         
        //   210: astore          9
        //   212: goto            170
        //   215: astore          4
        //   217: goto            123
        //    Exceptions:
        //  Try           Handler
        //  Start  End    Start  End    Type                 
        //  -----  -----  -----  -----  ---------------------
        //  24     46     119    123    Any
        //  46     55     215    220    Any
        //  59     63     134    159    Ljava/io/IOException;
        //  66     89     164    170    Any
        //  89     104    210    215    Any
        //  109    114    183    205    Ljava/io/IOException;
        //  127    131    159    164    Ljava/io/IOException;
        //  131    134    134    159    Ljava/io/IOException;
        //  161    164    134    159    Ljava/io/IOException;
        //  175    180    205    210    Ljava/io/IOException;
        //  180    183    183    205    Ljava/io/IOException;
        //  207    210    183    205    Ljava/io/IOException;
        // 
        // The error that occurred was:
        // 
        // java.lang.IndexOutOfBoundsException: Index: 107, Size: 107
        //     at java.util.ArrayList.rangeCheck(ArrayList.java:653)
        //     at java.util.ArrayList.get(ArrayList.java:429)
        //     at com.strobel.decompiler.ast.AstBuilder.convertToAst(AstBuilder.java:3303)
        //     at com.strobel.decompiler.ast.AstBuilder.convertToAst(AstBuilder.java:3417)
        //     at com.strobel.decompiler.ast.AstBuilder.build(AstBuilder.java:113)
        //     at com.strobel.decompiler.languages.java.ast.AstMethodBodyBuilder.createMethodBody(AstMethodBodyBuilder.java:210)
        //     at com.strobel.decompiler.languages.java.ast.AstMethodBodyBuilder.createMethodBody(AstMethodBodyBuilder.java:99)
        //     at com.strobel.decompiler.languages.java.ast.AstBuilder.createMethodBody(AstBuilder.java:757)
        //     at com.strobel.decompiler.languages.java.ast.AstBuilder.createMethod(AstBuilder.java:655)
        //     at com.strobel.decompiler.languages.java.ast.AstBuilder.addTypeMembers(AstBuilder.java:532)
        //     at com.strobel.decompiler.languages.java.ast.AstBuilder.createTypeCore(AstBuilder.java:499)
        //     at com.strobel.decompiler.languages.java.ast.AstBuilder.createTypeNoCache(AstBuilder.java:141)
        //     at com.strobel.decompiler.languages.java.ast.AstBuilder.createType(AstBuilder.java:130)
        //     at com.strobel.decompiler.languages.java.ast.AstBuilder.addType(AstBuilder.java:105)
        //     at com.strobel.decompiler.languages.java.JavaLanguage.buildAst(JavaLanguage.java:71)
        //     at com.strobel.decompiler.languages.java.JavaLanguage.decompileType(JavaLanguage.java:59)
        //     at com.strobel.decompiler.DecompilerDriver.decompileType(DecompilerDriver.java:317)
        //     at com.strobel.decompiler.DecompilerDriver.decompileJar(DecompilerDriver.java:238)
        //     at com.strobel.decompiler.DecompilerDriver.main(DecompilerDriver.java:123)
        // 
        throw new IllegalStateException("An error occurred while decompiling this method.");
    }
    
    private static String a(final int n) {
        switch (n) {
            default: {
                return a8q.z[159];
            }
            case 1: {
                return a8q.z[155];
            }
            case 2: {
                return a8q.z[163];
            }
            case 3: {
                return a8q.z[152];
            }
            case 8: {
                return a8q.z[151];
            }
            case 9: {
                return a8q.z[157];
            }
            case 10: {
                return a8q.z[153];
            }
            case 4: {
                return a8q.z[150];
            }
            case 5: {
                return a8q.z[154];
            }
            case 6: {
                return a8q.z[164];
            }
            case 12: {
                return a8q.z[156];
            }
            case 7: {
                return a8q.z[149];
            }
            case 13: {
                return a8q.z[160];
            }
            case 14: {
                return a8q.z[161];
            }
            case 11: {
                return a8q.z[162];
            }
            case 15: {
                return a8q.z[158];
            }
        }
    }
    
    private static String a(final Context context, final String s, final String s2, final String s3, final String s4, final long n, final long n2, final String s5) {
        final StringBuilder sb = new StringBuilder();
        if (s2 != null) {
            sb.append(s2);
        }
        sb.append(a(context, s, s3, s4, false, n, n2, s5));
        return sb.toString();
    }
    
    public static String a(final Context p0, final String p1, final String p2, final String p3, final boolean p4, final long p5, final long p6, final String p7) {
        // 
        // This method could not be decompiled.
        // 
        // Original Bytecode:
        // 
        //     0: getstatic       com/whatsapp/App.I:Z
        //     3: istore          10
        //     5: new             Ljava/lang/StringBuilder;
        //     8: dup            
        //     9: invokespecial   java/lang/StringBuilder.<init>:()V
        //    12: astore          11
        //    14: new             Ljava/text/SimpleDateFormat;
        //    17: dup            
        //    18: getstatic       com/whatsapp/a8q.z:[Ljava/lang/String;
        //    21: bipush          53
        //    23: aaload         
        //    24: getstatic       java/util/Locale.US:Ljava/util/Locale;
        //    27: invokespecial   java/text/SimpleDateFormat.<init>:(Ljava/lang/String;Ljava/util/Locale;)V
        //    30: astore          12
        //    32: aload_0        
        //    33: invokevirtual   android/content/Context.getResources:()Landroid/content/res/Resources;
        //    36: invokevirtual   android/content/res/Resources.getConfiguration:()Landroid/content/res/Configuration;
        //    39: getfield        android/content/res/Configuration.locale:Ljava/util/Locale;
        //    42: astore          16
        //    44: aload_0        
        //    45: getstatic       com/whatsapp/a8q.z:[Ljava/lang/String;
        //    48: bipush          74
        //    50: aaload         
        //    51: iconst_0       
        //    52: invokevirtual   android/content/Context.getSharedPreferences:(Ljava/lang/String;I)Landroid/content/SharedPreferences;
        //    55: astore          17
        //    57: aload           17
        //    59: getstatic       com/whatsapp/a8q.z:[Ljava/lang/String;
        //    62: bipush          60
        //    64: aaload         
        //    65: ldc_w           ""
        //    68: invokeinterface android/content/SharedPreferences.getString:(Ljava/lang/String;Ljava/lang/String;)Ljava/lang/String;
        //    73: astore          18
        //    75: aload           17
        //    77: getstatic       com/whatsapp/a8q.z:[Ljava/lang/String;
        //    80: bipush          109
        //    82: aaload         
        //    83: ldc_w           ""
        //    86: invokeinterface android/content/SharedPreferences.getString:(Ljava/lang/String;Ljava/lang/String;)Ljava/lang/String;
        //    91: astore          19
        //    93: getstatic       com/whatsapp/App.aX:Lcom/whatsapp/App$Me;
        //    96: ifnull          2337
        //    99: getstatic       com/whatsapp/App.aX:Lcom/whatsapp/App$Me;
        //   102: getfield        com/whatsapp/App$Me.jabber_id:Ljava/lang/String;
        //   105: astore          156
        //   107: aload           156
        //   109: ifnull          2337
        //   112: new             Ljava/lang/StringBuilder;
        //   115: dup            
        //   116: invokespecial   java/lang/StringBuilder.<init>:()V
        //   119: ldc_w           "+"
        //   122: invokevirtual   java/lang/StringBuilder.append:(Ljava/lang/String;)Ljava/lang/StringBuilder;
        //   125: getstatic       com/whatsapp/App.aX:Lcom/whatsapp/App$Me;
        //   128: getfield        com/whatsapp/App$Me.jabber_id:Ljava/lang/String;
        //   131: invokevirtual   java/lang/StringBuilder.append:(Ljava/lang/String;)Ljava/lang/StringBuilder;
        //   134: invokevirtual   java/lang/StringBuilder.toString:()Ljava/lang/String;
        //   137: astore          157
        //   139: aload           157
        //   141: astore          22
        //   143: invokestatic    com/whatsapp/ChangeNumber.g:()Z
        //   146: ifeq            2657
        //   149: new             Ljava/lang/StringBuilder;
        //   152: dup            
        //   153: invokespecial   java/lang/StringBuilder.<init>:()V
        //   156: getstatic       com/whatsapp/a8q.z:[Ljava/lang/String;
        //   159: bipush          36
        //   161: aaload         
        //   162: invokevirtual   java/lang/StringBuilder.append:(Ljava/lang/String;)Ljava/lang/StringBuilder;
        //   165: aload           22
        //   167: invokevirtual   java/lang/StringBuilder.append:(Ljava/lang/String;)Ljava/lang/StringBuilder;
        //   170: invokevirtual   java/lang/StringBuilder.toString:()Ljava/lang/String;
        //   173: astore          22
        //   175: invokestatic    com/whatsapp/App.F:()Lcom/whatsapp/App$Me;
        //   178: astore          153
        //   180: aload           153
        //   182: ifnull          2657
        //   185: aload           153
        //   187: getfield        com/whatsapp/App$Me.jabber_id:Ljava/lang/String;
        //   190: astore          155
        //   192: aload           155
        //   194: ifnull          2657
        //   197: new             Ljava/lang/StringBuilder;
        //   200: dup            
        //   201: invokespecial   java/lang/StringBuilder.<init>:()V
        //   204: aload           22
        //   206: invokevirtual   java/lang/StringBuilder.append:(Ljava/lang/String;)Ljava/lang/StringBuilder;
        //   209: getstatic       com/whatsapp/a8q.z:[Ljava/lang/String;
        //   212: bipush          92
        //   214: aaload         
        //   215: invokevirtual   java/lang/StringBuilder.append:(Ljava/lang/String;)Ljava/lang/StringBuilder;
        //   218: aload           153
        //   220: getfield        com/whatsapp/App$Me.jabber_id:Ljava/lang/String;
        //   223: invokevirtual   java/lang/StringBuilder.append:(Ljava/lang/String;)Ljava/lang/StringBuilder;
        //   226: ldc_w           ")"
        //   229: invokevirtual   java/lang/StringBuilder.append:(Ljava/lang/String;)Ljava/lang/StringBuilder;
        //   232: invokevirtual   java/lang/StringBuilder.toString:()Ljava/lang/String;
        //   235: astore          23
        //   237: getstatic       com/whatsapp/a8q.z:[Ljava/lang/String;
        //   240: bipush          115
        //   242: aaload         
        //   243: invokestatic    com/whatsapp/ade.a:(Ljava/lang/String;)J
        //   246: lstore          24
        //   248: lload           24
        //   250: ldc2_w          4444444444000
        //   253: lcmp           
        //   254: iflt            270
        //   257: getstatic       com/whatsapp/a8q.z:[Ljava/lang/String;
        //   260: bipush          108
        //   262: aaload         
        //   263: astore          26
        //   265: iload           10
        //   267: ifeq            2650
        //   270: lload           24
        //   272: lconst_0       
        //   273: lcmp           
        //   274: ifle            298
        //   277: aload           12
        //   279: new             Ljava/util/Date;
        //   282: dup            
        //   283: lload           24
        //   285: invokespecial   java/util/Date.<init>:(J)V
        //   288: invokevirtual   java/text/SimpleDateFormat.format:(Ljava/util/Date;)Ljava/lang/String;
        //   291: astore          26
        //   293: iload           10
        //   295: ifeq            2650
        //   298: getstatic       com/whatsapp/a8q.z:[Ljava/lang/String;
        //   301: bipush          100
        //   303: aaload         
        //   304: astore          27
        //   306: getstatic       com/whatsapp/a8q.z:[Ljava/lang/String;
        //   309: bipush          71
        //   311: aaload         
        //   312: pop            
        //   313: getstatic       com/whatsapp/a8q.z:[Ljava/lang/String;
        //   316: bipush          38
        //   318: aaload         
        //   319: pop            
        //   320: aload_0        
        //   321: getstatic       com/whatsapp/a8q.z:[Ljava/lang/String;
        //   324: bipush          44
        //   326: aaload         
        //   327: invokevirtual   android/content/Context.getSystemService:(Ljava/lang/String;)Ljava/lang/Object;
        //   330: checkcast       Landroid/telephony/TelephonyManager;
        //   333: astore          30
        //   335: aload           30
        //   337: ifnull          404
        //   340: aload           30
        //   342: invokevirtual   android/telephony/TelephonyManager.getPhoneType:()I
        //   345: invokestatic    com/whatsapp/a8q.b:(I)Ljava/lang/String;
        //   348: astore          31
        //   350: aload           30
        //   352: invokevirtual   android/telephony/TelephonyManager.getNetworkType:()I
        //   355: invokestatic    com/whatsapp/a8q.a:(I)Ljava/lang/String;
        //   358: astore          32
        //   360: aload           30
        //   362: invokevirtual   android/telephony/TelephonyManager.getNetworkOperator:()Ljava/lang/String;
        //   365: getstatic       com/whatsapp/a8q.z:[Ljava/lang/String;
        //   368: bipush          51
        //   370: aaload         
        //   371: invokestatic    com/whatsapp/util/x.a:(Ljava/lang/String;Ljava/lang/String;)Ljava/lang/String;
        //   374: astore          33
        //   376: aload           30
        //   378: invokevirtual   android/telephony/TelephonyManager.getSimOperator:()Ljava/lang/String;
        //   381: getstatic       com/whatsapp/a8q.z:[Ljava/lang/String;
        //   384: bipush          113
        //   386: aaload         
        //   387: invokestatic    com/whatsapp/util/x.a:(Ljava/lang/String;Ljava/lang/String;)Ljava/lang/String;
        //   390: astore          34
        //   392: aload           30
        //   394: invokevirtual   android/telephony/TelephonyManager.getNetworkOperatorName:()Ljava/lang/String;
        //   397: astore          35
        //   399: iload           10
        //   401: ifeq            2627
        //   404: getstatic       com/whatsapp/a8q.z:[Ljava/lang/String;
        //   407: bipush          39
        //   409: aaload         
        //   410: astore          149
        //   412: getstatic       com/whatsapp/a8q.z:[Ljava/lang/String;
        //   415: bipush          26
        //   417: aaload         
        //   418: astore          150
        //   420: getstatic       com/whatsapp/a8q.z:[Ljava/lang/String;
        //   423: bipush          55
        //   425: aaload         
        //   426: astore          151
        //   428: getstatic       com/whatsapp/a8q.z:[Ljava/lang/String;
        //   431: bipush          89
        //   433: aaload         
        //   434: astore          152
        //   436: getstatic       com/whatsapp/a8q.z:[Ljava/lang/String;
        //   439: bipush          27
        //   441: aaload         
        //   442: astore          36
        //   444: aload           152
        //   446: astore          37
        //   448: aload           151
        //   450: astore          38
        //   452: aload           150
        //   454: astore          39
        //   456: aload           149
        //   458: astore          40
        //   460: getstatic       com/whatsapp/App.z:Z
        //   463: ifeq            479
        //   466: getstatic       com/whatsapp/a8q.z:[Ljava/lang/String;
        //   469: bipush          42
        //   471: aaload         
        //   472: astore          148
        //   474: iload           10
        //   476: ifeq            2620
        //   479: getstatic       com/whatsapp/App.y:Z
        //   482: istore          42
        //   484: iload           42
        //   486: ifeq            502
        //   489: getstatic       com/whatsapp/a8q.z:[Ljava/lang/String;
        //   492: bipush          75
        //   494: aaload         
        //   495: astore          148
        //   497: iload           10
        //   499: ifeq            2620
        //   502: invokestatic    com/whatsapp/App.aq:()Z
        //   505: istore          44
        //   507: iload           44
        //   509: ifeq            525
        //   512: getstatic       com/whatsapp/a8q.z:[Ljava/lang/String;
        //   515: bipush          81
        //   517: aaload         
        //   518: astore          148
        //   520: iload           10
        //   522: ifeq            2620
        //   525: getstatic       com/whatsapp/a8q.z:[Ljava/lang/String;
        //   528: bipush          68
        //   530: aaload         
        //   531: astore          45
        //   533: lload           7
        //   535: ldc2_w          -1
        //   538: lcmp           
        //   539: ifne            555
        //   542: getstatic       com/whatsapp/a8q.z:[Ljava/lang/String;
        //   545: bipush          90
        //   547: aaload         
        //   548: astore          46
        //   550: iload           10
        //   552: ifeq            2613
        //   555: lload           7
        //   557: invokestatic    java/lang/Long.toString:(J)Ljava/lang/String;
        //   560: astore          147
        //   562: new             Ljava/lang/StringBuilder;
        //   565: dup            
        //   566: invokespecial   java/lang/StringBuilder.<init>:()V
        //   569: aload           147
        //   571: invokevirtual   java/lang/StringBuilder.append:(Ljava/lang/String;)Ljava/lang/StringBuilder;
        //   574: getstatic       com/whatsapp/a8q.z:[Ljava/lang/String;
        //   577: bipush          104
        //   579: aaload         
        //   580: invokevirtual   java/lang/StringBuilder.append:(Ljava/lang/String;)Ljava/lang/StringBuilder;
        //   583: getstatic       com/whatsapp/App.aq:Lcom/whatsapp/App;
        //   586: lload           7
        //   588: invokestatic    android/text/format/Formatter.formatFileSize:(Landroid/content/Context;J)Ljava/lang/String;
        //   591: invokevirtual   java/lang/StringBuilder.append:(Ljava/lang/String;)Ljava/lang/StringBuilder;
        //   594: ldc_w           ")"
        //   597: invokevirtual   java/lang/StringBuilder.append:(Ljava/lang/String;)Ljava/lang/StringBuilder;
        //   600: invokevirtual   java/lang/StringBuilder.toString:()Ljava/lang/String;
        //   603: astore          47
        //   605: lload           5
        //   607: ldc2_w          -1
        //   610: lcmp           
        //   611: ifne            627
        //   614: getstatic       com/whatsapp/a8q.z:[Ljava/lang/String;
        //   617: bipush          114
        //   619: aaload         
        //   620: astore          48
        //   622: iload           10
        //   624: ifeq            2606
        //   627: lload           5
        //   629: ldc2_w          -2
        //   632: lcmp           
        //   633: ifne            670
        //   636: getstatic       com/whatsapp/a8q.z:[Ljava/lang/String;
        //   639: bipush          121
        //   641: aaload         
        //   642: aload           9
        //   644: invokevirtual   java/lang/String.equals:(Ljava/lang/Object;)Z
        //   647: istore          146
        //   649: iload           146
        //   651: ifeq            2664
        //   654: getstatic       com/whatsapp/a8q.z:[Ljava/lang/String;
        //   657: bipush          64
        //   659: aaload         
        //   660: astore          48
        //   662: iload           10
        //   664: ifeq            2606
        //   667: goto            2664
        //   670: lload           5
        //   672: invokestatic    java/lang/Long.toString:(J)Ljava/lang/String;
        //   675: astore          144
        //   677: new             Ljava/lang/StringBuilder;
        //   680: dup            
        //   681: invokespecial   java/lang/StringBuilder.<init>:()V
        //   684: aload           144
        //   686: invokevirtual   java/lang/StringBuilder.append:(Ljava/lang/String;)Ljava/lang/StringBuilder;
        //   689: getstatic       com/whatsapp/a8q.z:[Ljava/lang/String;
        //   692: bipush          78
        //   694: aaload         
        //   695: invokevirtual   java/lang/StringBuilder.append:(Ljava/lang/String;)Ljava/lang/StringBuilder;
        //   698: getstatic       com/whatsapp/App.aq:Lcom/whatsapp/App;
        //   701: lload           5
        //   703: invokestatic    android/text/format/Formatter.formatFileSize:(Landroid/content/Context;J)Ljava/lang/String;
        //   706: invokevirtual   java/lang/StringBuilder.append:(Ljava/lang/String;)Ljava/lang/StringBuilder;
        //   709: ldc_w           ")"
        //   712: invokevirtual   java/lang/StringBuilder.append:(Ljava/lang/String;)Ljava/lang/StringBuilder;
        //   715: invokevirtual   java/lang/StringBuilder.toString:()Ljava/lang/String;
        //   718: astore          48
        //   720: getstatic       com/whatsapp/a8q.z:[Ljava/lang/String;
        //   723: bipush          61
        //   725: aaload         
        //   726: aload           9
        //   728: invokevirtual   java/lang/String.equals:(Ljava/lang/Object;)Z
        //   731: ifeq            2606
        //   734: new             Ljava/lang/StringBuilder;
        //   737: dup            
        //   738: invokespecial   java/lang/StringBuilder.<init>:()V
        //   741: aload           48
        //   743: invokevirtual   java/lang/StringBuilder.append:(Ljava/lang/String;)Ljava/lang/StringBuilder;
        //   746: getstatic       com/whatsapp/a8q.z:[Ljava/lang/String;
        //   749: bipush          69
        //   751: aaload         
        //   752: invokevirtual   java/lang/StringBuilder.append:(Ljava/lang/String;)Ljava/lang/StringBuilder;
        //   755: invokevirtual   java/lang/StringBuilder.toString:()Ljava/lang/String;
        //   758: astore          9
        //   760: aload_0        
        //   761: instanceof      Lcom/whatsapp/SearchFAQ;
        //   764: ifeq            800
        //   767: aload_0        
        //   768: checkcast       Lcom/whatsapp/SearchFAQ;
        //   771: invokevirtual   com/whatsapp/SearchFAQ.b:()I
        //   774: invokestatic    java/lang/Integer.valueOf:(I)Ljava/lang/Integer;
        //   777: astore          141
        //   779: aload_0        
        //   780: checkcast       Lcom/whatsapp/SearchFAQ;
        //   783: invokevirtual   com/whatsapp/SearchFAQ.a:()I
        //   786: invokestatic    java/lang/Integer.valueOf:(I)Ljava/lang/Integer;
        //   789: astore          143
        //   791: aload           143
        //   793: astore          142
        //   795: iload           10
        //   797: ifeq            2595
        //   800: aload_0        
        //   801: instanceof      Lcom/whatsapp/DescribeProblemActivity;
        //   804: istore          50
        //   806: iload           50
        //   808: ifeq            828
        //   811: iconst_0       
        //   812: invokestatic    java/lang/Integer.valueOf:(I)Ljava/lang/Integer;
        //   815: astore          141
        //   817: iconst_0       
        //   818: invokestatic    java/lang/Integer.valueOf:(I)Ljava/lang/Integer;
        //   821: astore          142
        //   823: iload           10
        //   825: ifeq            2595
        //   828: iconst_m1      
        //   829: invokestatic    java/lang/Integer.valueOf:(I)Ljava/lang/Integer;
        //   832: astore          51
        //   834: iconst_m1      
        //   835: invokestatic    java/lang/Integer.valueOf:(I)Ljava/lang/Integer;
        //   838: astore          52
        //   840: aload           51
        //   842: astore          53
        //   844: aload           11
        //   846: getstatic       com/whatsapp/a8q.z:[Ljava/lang/String;
        //   849: bipush          101
        //   851: aaload         
        //   852: invokevirtual   java/lang/StringBuilder.append:(Ljava/lang/String;)Ljava/lang/StringBuilder;
        //   855: pop            
        //   856: aload           11
        //   858: getstatic       com/whatsapp/a8q.z:[Ljava/lang/String;
        //   861: bipush          82
        //   863: aaload         
        //   864: invokevirtual   java/lang/StringBuilder.append:(Ljava/lang/String;)Ljava/lang/StringBuilder;
        //   867: pop            
        //   868: new             Lorg/json/JSONObject;
        //   871: dup            
        //   872: invokespecial   org/json/JSONObject.<init>:()V
        //   875: astore          56
        //   877: iload           4
        //   879: ifeq            2672
        //   882: aload           56
        //   884: astore          57
        //   886: getstatic       com/whatsapp/a8q.z:[Ljava/lang/String;
        //   889: bipush          122
        //   891: aaload         
        //   892: aload           23
        //   894: aload           57
        //   896: invokestatic    com/whatsapp/a8q.a:(Ljava/lang/String;Ljava/lang/Object;Ljava/lang/Object;)V
        //   899: getstatic       com/whatsapp/a8q.z:[Ljava/lang/String;
        //   902: bipush          116
        //   904: aaload         
        //   905: getstatic       com/whatsapp/a8q.z:[Ljava/lang/String;
        //   908: bipush          35
        //   910: aaload         
        //   911: aload           57
        //   913: invokestatic    com/whatsapp/a8q.a:(Ljava/lang/String;Ljava/lang/Object;Ljava/lang/Object;)V
        //   916: getstatic       com/whatsapp/a8q.z:[Ljava/lang/String;
        //   919: bipush          70
        //   921: aaload         
        //   922: getstatic       com/whatsapp/a8q.z:[Ljava/lang/String;
        //   925: bipush          32
        //   927: aaload         
        //   928: aload           57
        //   930: invokestatic    com/whatsapp/a8q.a:(Ljava/lang/String;Ljava/lang/Object;Ljava/lang/Object;)V
        //   933: getstatic       com/whatsapp/a8q.z:[Ljava/lang/String;
        //   936: bipush          52
        //   938: aaload         
        //   939: aload           27
        //   941: aload           57
        //   943: invokestatic    com/whatsapp/a8q.a:(Ljava/lang/String;Ljava/lang/Object;Ljava/lang/Object;)V
        //   946: getstatic       com/whatsapp/a8q.z:[Ljava/lang/String;
        //   949: bipush          50
        //   951: aaload         
        //   952: astore          59
        //   954: aload           16
        //   956: ifnull          2378
        //   959: aload           16
        //   961: invokevirtual   java/util/Locale.getCountry:()Ljava/lang/String;
        //   964: astore          60
        //   966: aload           60
        //   968: astore          61
        //   970: aload           59
        //   972: aload           61
        //   974: aload           57
        //   976: invokestatic    com/whatsapp/a8q.a:(Ljava/lang/String;Ljava/lang/Object;Ljava/lang/Object;)V
        //   979: getstatic       com/whatsapp/a8q.z:[Ljava/lang/String;
        //   982: bipush          43
        //   984: aaload         
        //   985: astore          63
        //   987: aload           16
        //   989: ifnull          2394
        //   992: aload           16
        //   994: invokevirtual   java/util/Locale.getLanguage:()Ljava/lang/String;
        //   997: astore          64
        //   999: aload           64
        //  1001: astore          65
        //  1003: aload           63
        //  1005: aload           65
        //  1007: aload           57
        //  1009: invokestatic    com/whatsapp/a8q.a:(Ljava/lang/String;Ljava/lang/Object;Ljava/lang/Object;)V
        //  1012: getstatic       com/whatsapp/a8q.z:[Ljava/lang/String;
        //  1015: bipush          120
        //  1017: aaload         
        //  1018: aload_1        
        //  1019: aload           57
        //  1021: invokestatic    com/whatsapp/a8q.a:(Ljava/lang/String;Ljava/lang/Object;Ljava/lang/Object;)V
        //  1024: getstatic       com/whatsapp/a8q.z:[Ljava/lang/String;
        //  1027: bipush          54
        //  1029: aaload         
        //  1030: aload           36
        //  1032: aload           57
        //  1034: invokestatic    com/whatsapp/a8q.a:(Ljava/lang/String;Ljava/lang/Object;Ljava/lang/Object;)V
        //  1037: getstatic       com/whatsapp/a8q.z:[Ljava/lang/String;
        //  1040: bipush          98
        //  1042: aaload         
        //  1043: getstatic       android/os/Build.MANUFACTURER:Ljava/lang/String;
        //  1046: aload           57
        //  1048: invokestatic    com/whatsapp/a8q.a:(Ljava/lang/String;Ljava/lang/Object;Ljava/lang/Object;)V
        //  1051: getstatic       com/whatsapp/a8q.z:[Ljava/lang/String;
        //  1054: bipush          97
        //  1056: aaload         
        //  1057: getstatic       android/os/Build.MODEL:Ljava/lang/String;
        //  1060: aload           57
        //  1062: invokestatic    com/whatsapp/a8q.a:(Ljava/lang/String;Ljava/lang/Object;Ljava/lang/Object;)V
        //  1065: getstatic       com/whatsapp/a8q.z:[Ljava/lang/String;
        //  1068: bipush          31
        //  1070: aaload         
        //  1071: getstatic       android/os/Build$VERSION.RELEASE:Ljava/lang/String;
        //  1074: aload           57
        //  1076: invokestatic    com/whatsapp/a8q.a:(Ljava/lang/String;Ljava/lang/Object;Ljava/lang/Object;)V
        //  1079: getstatic       com/whatsapp/a8q.z:[Ljava/lang/String;
        //  1082: bipush          80
        //  1084: aaload         
        //  1085: aload           45
        //  1087: aload           57
        //  1089: invokestatic    com/whatsapp/a8q.a:(Ljava/lang/String;Ljava/lang/Object;Ljava/lang/Object;)V
        //  1092: getstatic       com/whatsapp/a8q.z:[Ljava/lang/String;
        //  1095: bipush          30
        //  1097: aaload         
        //  1098: aload           38
        //  1100: aload           57
        //  1102: invokestatic    com/whatsapp/a8q.a:(Ljava/lang/String;Ljava/lang/Object;Ljava/lang/Object;)V
        //  1105: getstatic       com/whatsapp/a8q.z:[Ljava/lang/String;
        //  1108: bipush          56
        //  1110: aaload         
        //  1111: aload           37
        //  1113: aload           57
        //  1115: invokestatic    com/whatsapp/a8q.a:(Ljava/lang/String;Ljava/lang/Object;Ljava/lang/Object;)V
        //  1118: getstatic       com/whatsapp/a8q.z:[Ljava/lang/String;
        //  1121: bipush          84
        //  1123: aaload         
        //  1124: aload           47
        //  1126: aload           57
        //  1128: invokestatic    com/whatsapp/a8q.a:(Ljava/lang/String;Ljava/lang/Object;Ljava/lang/Object;)V
        //  1131: getstatic       com/whatsapp/a8q.z:[Ljava/lang/String;
        //  1134: bipush          33
        //  1136: aaload         
        //  1137: aload           9
        //  1139: aload           57
        //  1141: invokestatic    com/whatsapp/a8q.a:(Ljava/lang/String;Ljava/lang/Object;Ljava/lang/Object;)V
        //  1144: aload           53
        //  1146: invokevirtual   java/lang/Integer.intValue:()I
        //  1149: iconst_m1      
        //  1150: if_icmpeq       1179
        //  1153: getstatic       com/whatsapp/a8q.z:[Ljava/lang/String;
        //  1156: bipush          86
        //  1158: aaload         
        //  1159: aload           53
        //  1161: aload           57
        //  1163: invokestatic    com/whatsapp/a8q.a:(Ljava/lang/String;Ljava/lang/Object;Ljava/lang/Object;)V
        //  1166: getstatic       com/whatsapp/a8q.z:[Ljava/lang/String;
        //  1169: bipush          119
        //  1171: aaload         
        //  1172: aload           52
        //  1174: aload           57
        //  1176: invokestatic    com/whatsapp/a8q.a:(Ljava/lang/String;Ljava/lang/Object;Ljava/lang/Object;)V
        //  1179: invokestatic    com/whatsapp/l7.d:()Z
        //  1182: ifeq            1207
        //  1185: getstatic       com/whatsapp/a8q.z:[Ljava/lang/String;
        //  1188: bipush          110
        //  1190: aaload         
        //  1191: getstatic       com/whatsapp/a8q.z:[Ljava/lang/String;
        //  1194: bipush          65
        //  1196: aaload         
        //  1197: aload           57
        //  1199: invokestatic    com/whatsapp/a8q.a:(Ljava/lang/String;Ljava/lang/Object;Ljava/lang/Object;)V
        //  1202: iload           10
        //  1204: ifeq            1234
        //  1207: invokestatic    com/whatsapp/l7.t:()Z
        //  1210: istore          70
        //  1212: iload           70
        //  1214: ifeq            1234
        //  1217: getstatic       com/whatsapp/a8q.z:[Ljava/lang/String;
        //  1220: bipush          59
        //  1222: aaload         
        //  1223: getstatic       com/whatsapp/a8q.z:[Ljava/lang/String;
        //  1226: bipush          99
        //  1228: aaload         
        //  1229: aload           57
        //  1231: invokestatic    com/whatsapp/a8q.a:(Ljava/lang/String;Ljava/lang/Object;Ljava/lang/Object;)V
        //  1234: getstatic       com/whatsapp/a8q.z:[Ljava/lang/String;
        //  1237: bipush          37
        //  1239: aaload         
        //  1240: new             Ljava/lang/StringBuilder;
        //  1243: dup            
        //  1244: invokespecial   java/lang/StringBuilder.<init>:()V
        //  1247: aload           18
        //  1249: invokevirtual   java/lang/StringBuilder.append:(Ljava/lang/String;)Ljava/lang/StringBuilder;
        //  1252: ldc_w           " "
        //  1255: invokevirtual   java/lang/StringBuilder.append:(Ljava/lang/String;)Ljava/lang/StringBuilder;
        //  1258: aload           19
        //  1260: invokevirtual   java/lang/StringBuilder.append:(Ljava/lang/String;)Ljava/lang/StringBuilder;
        //  1263: invokevirtual   java/lang/StringBuilder.toString:()Ljava/lang/String;
        //  1266: aload           57
        //  1268: invokestatic    com/whatsapp/a8q.a:(Ljava/lang/String;Ljava/lang/Object;Ljava/lang/Object;)V
        //  1271: getstatic       com/whatsapp/a8q.z:[Ljava/lang/String;
        //  1274: bipush          40
        //  1276: aaload         
        //  1277: getstatic       com/whatsapp/a8q.z:[Ljava/lang/String;
        //  1280: bipush          77
        //  1282: aaload         
        //  1283: aload           57
        //  1285: invokestatic    com/whatsapp/a8q.a:(Ljava/lang/String;Ljava/lang/Object;Ljava/lang/Object;)V
        //  1288: getstatic       com/whatsapp/a8q.z:[Ljava/lang/String;
        //  1291: bipush          58
        //  1293: aaload         
        //  1294: getstatic       com/whatsapp/a8q.z:[Ljava/lang/String;
        //  1297: bipush          62
        //  1299: aaload         
        //  1300: aload           57
        //  1302: invokestatic    com/whatsapp/a8q.a:(Ljava/lang/String;Ljava/lang/Object;Ljava/lang/Object;)V
        //  1305: getstatic       com/whatsapp/a8q.z:[Ljava/lang/String;
        //  1308: bipush          85
        //  1310: aaload         
        //  1311: getstatic       android/os/Build.PRODUCT:Ljava/lang/String;
        //  1314: aload           57
        //  1316: invokestatic    com/whatsapp/a8q.a:(Ljava/lang/String;Ljava/lang/Object;Ljava/lang/Object;)V
        //  1319: getstatic       com/whatsapp/a8q.z:[Ljava/lang/String;
        //  1322: bipush          102
        //  1324: aaload         
        //  1325: getstatic       android/os/Build.DEVICE:Ljava/lang/String;
        //  1328: aload           57
        //  1330: invokestatic    com/whatsapp/a8q.a:(Ljava/lang/String;Ljava/lang/Object;Ljava/lang/Object;)V
        //  1333: getstatic       com/whatsapp/a8q.z:[Ljava/lang/String;
        //  1336: bipush          76
        //  1338: aaload         
        //  1339: getstatic       android/os/Build.DISPLAY:Ljava/lang/String;
        //  1342: aload           57
        //  1344: invokestatic    com/whatsapp/a8q.a:(Ljava/lang/String;Ljava/lang/Object;Ljava/lang/Object;)V
        //  1347: getstatic       com/whatsapp/a8q.z:[Ljava/lang/String;
        //  1350: bipush          103
        //  1352: aaload         
        //  1353: invokestatic    com/whatsapp/a8q.a:()Ljava/lang/String;
        //  1356: aload           57
        //  1358: invokestatic    com/whatsapp/a8q.a:(Ljava/lang/String;Ljava/lang/Object;Ljava/lang/Object;)V
        //  1361: aload_0        
        //  1362: getstatic       com/whatsapp/a8q.z:[Ljava/lang/String;
        //  1365: bipush          91
        //  1367: aaload         
        //  1368: invokevirtual   android/content/Context.getSystemService:(Ljava/lang/String;)Ljava/lang/Object;
        //  1371: checkcast       Landroid/net/ConnectivityManager;
        //  1374: astore          71
        //  1376: getstatic       com/whatsapp/a8q.z:[Ljava/lang/String;
        //  1379: bipush          105
        //  1381: aaload         
        //  1382: aload           71
        //  1384: invokestatic    com/whatsapp/a8q.a:(Landroid/net/ConnectivityManager;)Ljava/lang/String;
        //  1387: aload           57
        //  1389: invokestatic    com/whatsapp/a8q.a:(Ljava/lang/String;Ljava/lang/Object;Ljava/lang/Object;)V
        //  1392: aload_2        
        //  1393: ifnull          1408
        //  1396: getstatic       com/whatsapp/a8q.z:[Ljava/lang/String;
        //  1399: bipush          63
        //  1401: aaload         
        //  1402: aload_2        
        //  1403: aload           57
        //  1405: invokestatic    com/whatsapp/a8q.a:(Ljava/lang/String;Ljava/lang/Object;Ljava/lang/Object;)V
        //  1408: getstatic       com/whatsapp/a8q.z:[Ljava/lang/String;
        //  1411: bipush          46
        //  1413: aaload         
        //  1414: aload           12
        //  1416: new             Ljava/util/Date;
        //  1419: dup            
        //  1420: invokespecial   java/util/Date.<init>:()V
        //  1423: invokevirtual   java/text/SimpleDateFormat.format:(Ljava/util/Date;)Ljava/lang/String;
        //  1426: aload           57
        //  1428: invokestatic    com/whatsapp/a8q.a:(Ljava/lang/String;Ljava/lang/Object;Ljava/lang/Object;)V
        //  1431: getstatic       com/whatsapp/a8q.z:[Ljava/lang/String;
        //  1434: bipush          96
        //  1436: aaload         
        //  1437: aload           40
        //  1439: invokestatic    com/whatsapp/a8q.a:(Ljava/lang/String;)Ljava/lang/String;
        //  1442: aload           57
        //  1444: invokestatic    com/whatsapp/a8q.a:(Ljava/lang/String;Ljava/lang/Object;Ljava/lang/Object;)V
        //  1447: getstatic       com/whatsapp/a8q.z:[Ljava/lang/String;
        //  1450: bipush          79
        //  1452: aaload         
        //  1453: aload           39
        //  1455: invokestatic    com/whatsapp/a8q.a:(Ljava/lang/String;)Ljava/lang/String;
        //  1458: aload           57
        //  1460: invokestatic    com/whatsapp/a8q.a:(Ljava/lang/String;Ljava/lang/Object;Ljava/lang/Object;)V
        //  1463: invokestatic    com/whatsapp/a8q.c:()Ljava/lang/String;
        //  1466: astore          73
        //  1468: aload           73
        //  1470: invokestatic    android/text/TextUtils.isEmpty:(Ljava/lang/CharSequence;)Z
        //  1473: ifne            1489
        //  1476: getstatic       com/whatsapp/a8q.z:[Ljava/lang/String;
        //  1479: bipush          111
        //  1481: aaload         
        //  1482: aload           73
        //  1484: aload           57
        //  1486: invokestatic    com/whatsapp/a8q.a:(Ljava/lang/String;Ljava/lang/Object;Ljava/lang/Object;)V
        //  1489: getstatic       com/whatsapp/App.aX:Lcom/whatsapp/App$Me;
        //  1492: ifnonnull       1730
        //  1495: getstatic       com/whatsapp/App.h:Landroid/telephony/TelephonyManager;
        //  1498: invokevirtual   android/telephony/TelephonyManager.getLine1Number:()Ljava/lang/String;
        //  1501: astore          122
        //  1503: getstatic       com/whatsapp/a8q.z:[Ljava/lang/String;
        //  1506: bipush          94
        //  1508: aaload         
        //  1509: new             Ljava/lang/StringBuilder;
        //  1512: dup            
        //  1513: invokespecial   java/lang/StringBuilder.<init>:()V
        //  1516: aload           122
        //  1518: invokevirtual   java/lang/StringBuilder.append:(Ljava/lang/String;)Ljava/lang/StringBuilder;
        //  1521: ldc_w           " "
        //  1524: invokevirtual   java/lang/StringBuilder.append:(Ljava/lang/String;)Ljava/lang/StringBuilder;
        //  1527: getstatic       com/whatsapp/App.h:Landroid/telephony/TelephonyManager;
        //  1530: invokevirtual   android/telephony/TelephonyManager.getSimState:()I
        //  1533: invokevirtual   java/lang/StringBuilder.append:(I)Ljava/lang/StringBuilder;
        //  1536: invokevirtual   java/lang/StringBuilder.toString:()Ljava/lang/String;
        //  1539: aload           57
        //  1541: invokestatic    com/whatsapp/a8q.a:(Ljava/lang/String;Ljava/lang/Object;Ljava/lang/Object;)V
        //  1544: aload           19
        //  1546: aload           122
        //  1548: bipush          6
        //  1550: invokestatic    com/whatsapp/a8q.a:(Ljava/lang/String;Ljava/lang/String;I)I
        //  1553: istore          123
        //  1555: iconst_1       
        //  1556: invokestatic    java/lang/Boolean.valueOf:(Z)Ljava/lang/Boolean;
        //  1559: astore          124
        //  1561: iload           123
        //  1563: ifeq            1572
        //  1566: iload           123
        //  1568: iconst_1       
        //  1569: if_icmpne       1730
        //  1572: iload           123
        //  1574: ifne            1700
        //  1577: aload           18
        //  1579: invokestatic    java/lang/Integer.parseInt:(Ljava/lang/String;)I
        //  1582: istore          125
        //  1584: iload           125
        //  1586: aload           122
        //  1588: invokestatic    com/whatsapp/vi.a:(ILjava/lang/String;)Ljava/lang/String;
        //  1591: astore          140
        //  1593: aload           140
        //  1595: astore          127
        //  1597: aload           122
        //  1599: aload           19
        //  1601: invokevirtual   java/lang/String.equals:(Ljava/lang/Object;)Z
        //  1604: ifne            1653
        //  1607: aload           122
        //  1609: new             Ljava/lang/StringBuilder;
        //  1612: dup            
        //  1613: invokespecial   java/lang/StringBuilder.<init>:()V
        //  1616: aload           18
        //  1618: invokevirtual   java/lang/StringBuilder.append:(Ljava/lang/String;)Ljava/lang/StringBuilder;
        //  1621: aload           19
        //  1623: invokevirtual   java/lang/StringBuilder.append:(Ljava/lang/String;)Ljava/lang/StringBuilder;
        //  1626: invokevirtual   java/lang/StringBuilder.toString:()Ljava/lang/String;
        //  1629: invokevirtual   java/lang/String.endsWith:(Ljava/lang/String;)Z
        //  1632: istore          138
        //  1634: iload           138
        //  1636: ifne            1653
        //  1639: aload           19
        //  1641: aload           127
        //  1643: invokevirtual   java/lang/String.equals:(Ljava/lang/Object;)Z
        //  1646: istore          139
        //  1648: iload           139
        //  1650: ifeq            1668
        //  1653: iconst_0       
        //  1654: invokestatic    java/lang/Boolean.valueOf:(Z)Ljava/lang/Boolean;
        //  1657: astore          130
        //  1659: aload           130
        //  1661: astore          124
        //  1663: iload           10
        //  1665: ifeq            1700
        //  1668: aload           19
        //  1670: aload           127
        //  1672: invokevirtual   java/lang/String.endsWith:(Ljava/lang/String;)Z
        //  1675: istore          136
        //  1677: iload           136
        //  1679: ifeq            1700
        //  1682: aload           18
        //  1684: aload           127
        //  1686: invokestatic    com/whatsapp/EnterPhoneNumber.a:(Ljava/lang/String;Ljava/lang/String;)I
        //  1689: istore          137
        //  1691: iload           137
        //  1693: iconst_5       
        //  1694: if_icmpne       1700
        //  1697: aconst_null    
        //  1698: astore          124
        //  1700: getstatic       com/whatsapp/a8q.z:[Ljava/lang/String;
        //  1703: bipush          48
        //  1705: aaload         
        //  1706: astore          132
        //  1708: aload           124
        //  1710: ifnonnull       2479
        //  1713: getstatic       com/whatsapp/a8q.z:[Ljava/lang/String;
        //  1716: bipush          87
        //  1718: aaload         
        //  1719: astore          133
        //  1721: aload           132
        //  1723: aload           133
        //  1725: aload           57
        //  1727: invokestatic    com/whatsapp/a8q.a:(Ljava/lang/String;Ljava/lang/Object;Ljava/lang/Object;)V
        //  1730: getstatic       android/os/Build$VERSION.SDK_INT:I
        //  1733: bipush          21
        //  1735: if_icmplt       1988
        //  1738: new             Ljava/lang/StringBuffer;
        //  1741: dup            
        //  1742: invokespecial   java/lang/StringBuffer.<init>:()V
        //  1745: astore          75
        //  1747: new             Ljava/lang/StringBuffer;
        //  1750: dup            
        //  1751: invokespecial   java/lang/StringBuffer.<init>:()V
        //  1754: astore          76
        //  1756: aload           71
        //  1758: invokevirtual   android/net/ConnectivityManager.getAllNetworks:()[Landroid/net/Network;
        //  1761: astore          77
        //  1763: aload           77
        //  1765: arraylength    
        //  1766: istore          78
        //  1768: iconst_0       
        //  1769: istore          79
        //  1771: iconst_0       
        //  1772: istore          80
        //  1774: iload           80
        //  1776: iload           78
        //  1778: if_icmpge       1956
        //  1781: aload           77
        //  1783: iload           80
        //  1785: aaload         
        //  1786: astore          81
        //  1788: aload           71
        //  1790: aload           81
        //  1792: invokevirtual   android/net/ConnectivityManager.getNetworkCapabilities:(Landroid/net/Network;)Landroid/net/NetworkCapabilities;
        //  1795: astore          82
        //  1797: getstatic       com/whatsapp/a8q.z:[Ljava/lang/String;
        //  1800: bipush          49
        //  1802: aaload         
        //  1803: astore          84
        //  1805: iconst_2       
        //  1806: anewarray       Ljava/lang/Object;
        //  1809: astore          85
        //  1811: aload           85
        //  1813: iconst_0       
        //  1814: aload           81
        //  1816: invokevirtual   android/net/Network.toString:()Ljava/lang/String;
        //  1819: aastore        
        //  1820: aload           82
        //  1822: bipush          11
        //  1824: invokevirtual   android/net/NetworkCapabilities.hasCapability:(I)Z
        //  1827: istore          86
        //  1829: iload           86
        //  1831: ifne            2679
        //  1834: iconst_1       
        //  1835: istore          87
        //  1837: aload           85
        //  1839: iconst_1       
        //  1840: iload           87
        //  1842: invokestatic    java/lang/String.valueOf:(Z)Ljava/lang/String;
        //  1845: aastore        
        //  1846: aload           75
        //  1848: aload           84
        //  1850: aload           85
        //  1852: invokestatic    java/lang/String.format:(Ljava/lang/String;[Ljava/lang/Object;)Ljava/lang/String;
        //  1855: invokevirtual   java/lang/StringBuffer.append:(Ljava/lang/String;)Ljava/lang/StringBuffer;
        //  1858: pop            
        //  1859: getstatic       com/whatsapp/a8q.z:[Ljava/lang/String;
        //  1862: bipush          112
        //  1864: aaload         
        //  1865: astore          90
        //  1867: iconst_2       
        //  1868: anewarray       Ljava/lang/Object;
        //  1871: astore          91
        //  1873: aload           91
        //  1875: iconst_0       
        //  1876: aload           81
        //  1878: invokevirtual   android/net/Network.toString:()Ljava/lang/String;
        //  1881: aastore        
        //  1882: aload           82
        //  1884: bipush          13
        //  1886: invokevirtual   android/net/NetworkCapabilities.hasCapability:(I)Z
        //  1889: istore          92
        //  1891: iload           92
        //  1893: ifne            2685
        //  1896: iconst_1       
        //  1897: istore          93
        //  1899: aload           91
        //  1901: iconst_1       
        //  1902: iload           93
        //  1904: invokestatic    java/lang/String.valueOf:(Z)Ljava/lang/String;
        //  1907: aastore        
        //  1908: aload           76
        //  1910: aload           90
        //  1912: aload           91
        //  1914: invokestatic    java/lang/String.format:(Ljava/lang/String;[Ljava/lang/Object;)Ljava/lang/String;
        //  1917: invokevirtual   java/lang/StringBuffer.append:(Ljava/lang/String;)Ljava/lang/StringBuffer;
        //  1920: pop            
        //  1921: iload           79
        //  1923: ifeq            1942
        //  1926: aload           75
        //  1928: bipush          59
        //  1930: invokevirtual   java/lang/StringBuffer.append:(C)Ljava/lang/StringBuffer;
        //  1933: pop            
        //  1934: aload           76
        //  1936: bipush          59
        //  1938: invokevirtual   java/lang/StringBuffer.append:(C)Ljava/lang/StringBuffer;
        //  1941: pop            
        //  1942: iinc            79, 1
        //  1945: iload           80
        //  1947: iconst_1       
        //  1948: iadd           
        //  1949: istore          98
        //  1951: iload           10
        //  1953: ifeq            2588
        //  1956: getstatic       com/whatsapp/a8q.z:[Ljava/lang/String;
        //  1959: bipush          93
        //  1961: aaload         
        //  1962: aload           75
        //  1964: invokevirtual   java/lang/StringBuffer.toString:()Ljava/lang/String;
        //  1967: aload           57
        //  1969: invokestatic    com/whatsapp/a8q.a:(Ljava/lang/String;Ljava/lang/Object;Ljava/lang/Object;)V
        //  1972: getstatic       com/whatsapp/a8q.z:[Ljava/lang/String;
        //  1975: bipush          72
        //  1977: aaload         
        //  1978: aload           76
        //  1980: invokevirtual   java/lang/StringBuffer.toString:()Ljava/lang/String;
        //  1983: aload           57
        //  1985: invokestatic    com/whatsapp/a8q.a:(Ljava/lang/String;Ljava/lang/Object;Ljava/lang/Object;)V
        //  1988: invokestatic    de/greenrobot/event/m.b:()Lde/greenrobot/event/m;
        //  1991: ldc_w           Lcom/whatsapp/vp;.class
        //  1994: invokevirtual   de/greenrobot/event/m.a:(Ljava/lang/Class;)Ljava/lang/Object;
        //  1997: checkcast       Lcom/whatsapp/vp;
        //  2000: astore          99
        //  2002: getstatic       com/whatsapp/a8q.z:[Ljava/lang/String;
        //  2005: bipush          66
        //  2007: aaload         
        //  2008: aload           99
        //  2010: invokevirtual   com/whatsapp/vp.a:()Z
        //  2013: invokestatic    java/lang/String.valueOf:(Z)Ljava/lang/String;
        //  2016: aload           57
        //  2018: invokestatic    com/whatsapp/a8q.a:(Ljava/lang/String;Ljava/lang/Object;Ljava/lang/Object;)V
        //  2021: getstatic       com/whatsapp/a8q.z:[Ljava/lang/String;
        //  2024: bipush          118
        //  2026: aaload         
        //  2027: astore          101
        //  2029: getstatic       com/whatsapp/App.h:Landroid/telephony/TelephonyManager;
        //  2032: ifnonnull       2509
        //  2035: getstatic       com/whatsapp/a8q.z:[Ljava/lang/String;
        //  2038: bipush          67
        //  2040: aaload         
        //  2041: astore          103
        //  2043: aload           101
        //  2045: aload           103
        //  2047: aload           57
        //  2049: invokestatic    com/whatsapp/a8q.a:(Ljava/lang/String;Ljava/lang/Object;Ljava/lang/Object;)V
        //  2052: getstatic       com/whatsapp/aam.a:Lcom/whatsapp/fieldstats/Events$Call;
        //  2055: astore          104
        //  2057: aload           104
        //  2059: ifnull          2252
        //  2062: aload           104
        //  2064: getfield        com/whatsapp/fieldstats/Events$Call.callSide:Ljava/lang/Double;
        //  2067: astore          110
        //  2069: aload           110
        //  2071: ifnull          2096
        //  2074: getstatic       com/whatsapp/a8q.z:[Ljava/lang/String;
        //  2077: bipush          41
        //  2079: aaload         
        //  2080: aload           104
        //  2082: getfield        com/whatsapp/fieldstats/Events$Call.callSide:Ljava/lang/Double;
        //  2085: invokevirtual   java/lang/Double.intValue:()I
        //  2088: invokestatic    com/whatsapp/Voip.c:(I)Ljava/lang/String;
        //  2091: aload           57
        //  2093: invokestatic    com/whatsapp/a8q.a:(Ljava/lang/String;Ljava/lang/Object;Ljava/lang/Object;)V
        //  2096: aload           104
        //  2098: getfield        com/whatsapp/fieldstats/Events$Call.callResult:Ljava/lang/Double;
        //  2101: ifnull          2126
        //  2104: getstatic       com/whatsapp/a8q.z:[Ljava/lang/String;
        //  2107: bipush          117
        //  2109: aaload         
        //  2110: aload           104
        //  2112: getfield        com/whatsapp/fieldstats/Events$Call.callResult:Ljava/lang/Double;
        //  2115: invokevirtual   java/lang/Double.intValue:()I
        //  2118: invokestatic    com/whatsapp/Voip.a:(I)Ljava/lang/String;
        //  2121: aload           57
        //  2123: invokestatic    com/whatsapp/a8q.a:(Ljava/lang/String;Ljava/lang/Object;Ljava/lang/Object;)V
        //  2126: aload           104
        //  2128: getfield        com/whatsapp/fieldstats/Events$Call.callSetupErrorType:Ljava/lang/Double;
        //  2131: ifnull          2156
        //  2134: getstatic       com/whatsapp/a8q.z:[Ljava/lang/String;
        //  2137: bipush          34
        //  2139: aaload         
        //  2140: aload           104
        //  2142: getfield        com/whatsapp/fieldstats/Events$Call.callSetupErrorType:Ljava/lang/Double;
        //  2145: invokevirtual   java/lang/Double.intValue:()I
        //  2148: invokestatic    com/whatsapp/Voip.b:(I)Ljava/lang/String;
        //  2151: aload           57
        //  2153: invokestatic    com/whatsapp/a8q.a:(Ljava/lang/String;Ljava/lang/Object;Ljava/lang/Object;)V
        //  2156: aload           104
        //  2158: getfield        com/whatsapp/fieldstats/Events$Call.callTermReason:Ljava/lang/Double;
        //  2161: ifnull          2186
        //  2164: getstatic       com/whatsapp/a8q.z:[Ljava/lang/String;
        //  2167: bipush          88
        //  2169: aaload         
        //  2170: aload           104
        //  2172: getfield        com/whatsapp/fieldstats/Events$Call.callTermReason:Ljava/lang/Double;
        //  2175: invokevirtual   java/lang/Double.intValue:()I
        //  2178: invokestatic    com/whatsapp/Voip.d:(I)Ljava/lang/String;
        //  2181: aload           57
        //  2183: invokestatic    com/whatsapp/a8q.a:(Ljava/lang/String;Ljava/lang/Object;Ljava/lang/Object;)V
        //  2186: aload           104
        //  2188: getfield        com/whatsapp/fieldstats/Events$Call.callRelayBindStatus:Ljava/lang/Double;
        //  2191: ifnull          2691
        //  2194: aload           104
        //  2196: getfield        com/whatsapp/fieldstats/Events$Call.callRelayBindStatus:Ljava/lang/Double;
        //  2199: invokevirtual   java/lang/Double.intValue:()I
        //  2202: istore          120
        //  2204: getstatic       com/whatsapp/fieldstats/x.BINDED:Lcom/whatsapp/fieldstats/x;
        //  2207: invokevirtual   com/whatsapp/fieldstats/x.getCode:()I
        //  2210: istore          121
        //  2212: iload           120
        //  2214: iload           121
        //  2216: if_icmpne       2691
        //  2219: iconst_1       
        //  2220: istore          116
        //  2222: getstatic       com/whatsapp/a8q.z:[Ljava/lang/String;
        //  2225: bipush          107
        //  2227: aaload         
        //  2228: astore          118
        //  2230: iload           116
        //  2232: ifeq            2567
        //  2235: getstatic       com/whatsapp/a8q.z:[Ljava/lang/String;
        //  2238: bipush          73
        //  2240: aaload         
        //  2241: astore          119
        //  2243: aload           118
        //  2245: aload           119
        //  2247: aload           57
        //  2249: invokestatic    com/whatsapp/a8q.a:(Ljava/lang/String;Ljava/lang/Object;Ljava/lang/Object;)V
        //  2252: aload_3        
        //  2253: ifnull          2268
        //  2256: getstatic       com/whatsapp/a8q.z:[Ljava/lang/String;
        //  2259: bipush          57
        //  2261: aaload         
        //  2262: aload_3        
        //  2263: aload           57
        //  2265: invokestatic    com/whatsapp/a8q.a:(Ljava/lang/String;Ljava/lang/Object;Ljava/lang/Object;)V
        //  2268: iload           4
        //  2270: ifeq            2285
        //  2273: aload           11
        //  2275: aload           56
        //  2277: iconst_1       
        //  2278: invokevirtual   org/json/JSONObject.toString:(I)Ljava/lang/String;
        //  2281: invokevirtual   java/lang/StringBuilder.append:(Ljava/lang/String;)Ljava/lang/StringBuilder;
        //  2284: pop            
        //  2285: aload           11
        //  2287: invokevirtual   java/lang/StringBuilder.toString:()Ljava/lang/String;
        //  2290: areturn        
        //  2291: astore          20
        //  2293: aload           20
        //  2295: athrow         
        //  2296: astore          21
        //  2298: aload           21
        //  2300: athrow         
        //  2301: astore          13
        //  2303: getstatic       com/whatsapp/a8q.z:[Ljava/lang/String;
        //  2306: bipush          106
        //  2308: aaload         
        //  2309: aload           13
        //  2311: invokestatic    com/whatsapp/util/Log.b:(Ljava/lang/String;Ljava/lang/Throwable;)V
        //  2314: aload           11
        //  2316: getstatic       com/whatsapp/a8q.z:[Ljava/lang/String;
        //  2319: bipush          28
        //  2321: aaload         
        //  2322: invokevirtual   java/lang/StringBuilder.append:(Ljava/lang/String;)Ljava/lang/StringBuilder;
        //  2325: pop            
        //  2326: aload           11
        //  2328: aload           13
        //  2330: invokevirtual   java/lang/StringBuilder.append:(Ljava/lang/Object;)Ljava/lang/StringBuilder;
        //  2333: pop            
        //  2334: goto            2285
        //  2337: getstatic       com/whatsapp/a8q.z:[Ljava/lang/String;
        //  2340: bipush          29
        //  2342: aaload         
        //  2343: astore          22
        //  2345: goto            143
        //  2348: astore          154
        //  2350: aload           154
        //  2352: athrow         
        //  2353: astore          41
        //  2355: aload           41
        //  2357: athrow         
        //  2358: astore          43
        //  2360: aload           43
        //  2362: athrow         
        //  2363: astore          145
        //  2365: aload           145
        //  2367: athrow         
        //  2368: astore          49
        //  2370: aload           49
        //  2372: athrow         
        //  2373: astore          58
        //  2375: aload           58
        //  2377: athrow         
        //  2378: getstatic       com/whatsapp/a8q.z:[Ljava/lang/String;
        //  2381: bipush          83
        //  2383: aaload         
        //  2384: astore          61
        //  2386: goto            970
        //  2389: astore          62
        //  2391: aload           62
        //  2393: athrow         
        //  2394: getstatic       com/whatsapp/a8q.z:[Ljava/lang/String;
        //  2397: bipush          95
        //  2399: aaload         
        //  2400: astore          65
        //  2402: goto            1003
        //  2405: astore          66
        //  2407: aload           66
        //  2409: athrow         
        //  2410: astore          67
        //  2412: aload           67
        //  2414: athrow         
        //  2415: astore          68
        //  2417: aload           68
        //  2419: athrow         
        //  2420: astore          69
        //  2422: aload           69
        //  2424: athrow         
        //  2425: astore          72
        //  2427: aload           72
        //  2429: athrow         
        //  2430: astore          74
        //  2432: aload           74
        //  2434: athrow         
        //  2435: astore          126
        //  2437: getstatic       com/whatsapp/a8q.z:[Ljava/lang/String;
        //  2440: bipush          47
        //  2442: aaload         
        //  2443: aload           126
        //  2445: invokestatic    com/whatsapp/util/Log.b:(Ljava/lang/String;Ljava/lang/Throwable;)V
        //  2448: aconst_null    
        //  2449: astore          127
        //  2451: goto            1597
        //  2454: astore          128
        //  2456: aload           128
        //  2458: athrow         
        //  2459: astore          129
        //  2461: aload           129
        //  2463: athrow         
        //  2464: astore          134
        //  2466: aload           134
        //  2468: athrow         
        //  2469: astore          135
        //  2471: aload           135
        //  2473: athrow         
        //  2474: astore          131
        //  2476: aload           131
        //  2478: athrow         
        //  2479: aload           124
        //  2481: invokestatic    java/lang/String.valueOf:(Ljava/lang/Object;)Ljava/lang/String;
        //  2484: astore          133
        //  2486: goto            1721
        //  2489: astore          83
        //  2491: aload           83
        //  2493: athrow         
        //  2494: astore          88
        //  2496: aload           88
        //  2498: athrow         
        //  2499: astore          94
        //  2501: aload           94
        //  2503: athrow         
        //  2504: astore          100
        //  2506: aload           100
        //  2508: athrow         
        //  2509: getstatic       com/whatsapp/App.h:Landroid/telephony/TelephonyManager;
        //  2512: invokevirtual   android/telephony/TelephonyManager.isNetworkRoaming:()Z
        //  2515: invokestatic    java/lang/String.valueOf:(Z)Ljava/lang/String;
        //  2518: astore          102
        //  2520: aload           102
        //  2522: astore          103
        //  2524: goto            2043
        //  2527: astore          108
        //  2529: aload           108
        //  2531: athrow         
        //  2532: astore          109
        //  2534: aload           109
        //  2536: athrow         
        //  2537: astore          111
        //  2539: aload           111
        //  2541: athrow         
        //  2542: astore          112
        //  2544: aload           112
        //  2546: athrow         
        //  2547: astore          113
        //  2549: aload           113
        //  2551: athrow         
        //  2552: astore          114
        //  2554: aload           114
        //  2556: athrow         
        //  2557: astore          115
        //  2559: aload           115
        //  2561: athrow         
        //  2562: astore          117
        //  2564: aload           117
        //  2566: athrow         
        //  2567: getstatic       com/whatsapp/a8q.z:[Ljava/lang/String;
        //  2570: bipush          45
        //  2572: aaload         
        //  2573: astore          119
        //  2575: goto            2243
        //  2578: astore          107
        //  2580: aload           107
        //  2582: athrow         
        //  2583: astore          105
        //  2585: aload           105
        //  2587: athrow         
        //  2588: iload           98
        //  2590: istore          80
        //  2592: goto            1774
        //  2595: aload           142
        //  2597: astore          52
        //  2599: aload           141
        //  2601: astore          53
        //  2603: goto            844
        //  2606: aload           48
        //  2608: astore          9
        //  2610: goto            760
        //  2613: aload           46
        //  2615: astore          47
        //  2617: goto            605
        //  2620: aload           148
        //  2622: astore          45
        //  2624: goto            533
        //  2627: aload           35
        //  2629: astore          36
        //  2631: aload           34
        //  2633: astore          37
        //  2635: aload           33
        //  2637: astore          38
        //  2639: aload           32
        //  2641: astore          39
        //  2643: aload           31
        //  2645: astore          40
        //  2647: goto            460
        //  2650: aload           26
        //  2652: astore          27
        //  2654: goto            306
        //  2657: aload           22
        //  2659: astore          23
        //  2661: goto            237
        //  2664: iload           10
        //  2666: ifeq            760
        //  2669: goto            670
        //  2672: aload           11
        //  2674: astore          57
        //  2676: goto            886
        //  2679: iconst_0       
        //  2680: istore          87
        //  2682: goto            1837
        //  2685: iconst_0       
        //  2686: istore          93
        //  2688: goto            1899
        //  2691: iconst_0       
        //  2692: istore          116
        //  2694: goto            2222
        //    Exceptions:
        //  Try           Handler
        //  Start  End    Start  End    Type                 
        //  -----  -----  -----  -----  ---------------------
        //  14     93     2301   2337   Ljava/lang/Exception;
        //  93     107    2291   2296   Ljava/io/IOException;
        //  93     107    2301   2337   Ljava/lang/Exception;
        //  112    139    2296   2301   Ljava/io/IOException;
        //  112    139    2301   2337   Ljava/lang/Exception;
        //  143    180    2301   2337   Ljava/lang/Exception;
        //  185    192    2348   2353   Ljava/io/IOException;
        //  185    192    2301   2337   Ljava/lang/Exception;
        //  197    237    2301   2337   Ljava/lang/Exception;
        //  237    248    2301   2337   Ljava/lang/Exception;
        //  257    265    2301   2337   Ljava/lang/Exception;
        //  277    293    2301   2337   Ljava/lang/Exception;
        //  298    306    2301   2337   Ljava/lang/Exception;
        //  306    335    2301   2337   Ljava/lang/Exception;
        //  340    399    2301   2337   Ljava/lang/Exception;
        //  404    444    2301   2337   Ljava/lang/Exception;
        //  460    474    2301   2337   Ljava/lang/Exception;
        //  479    484    2353   2358   Ljava/io/IOException;
        //  479    484    2301   2337   Ljava/lang/Exception;
        //  489    497    2301   2337   Ljava/lang/Exception;
        //  502    507    2358   2363   Ljava/io/IOException;
        //  502    507    2301   2337   Ljava/lang/Exception;
        //  512    520    2301   2337   Ljava/lang/Exception;
        //  525    533    2301   2337   Ljava/lang/Exception;
        //  542    550    2301   2337   Ljava/lang/Exception;
        //  555    605    2301   2337   Ljava/lang/Exception;
        //  614    622    2301   2337   Ljava/lang/Exception;
        //  636    649    2363   2368   Ljava/io/IOException;
        //  636    649    2301   2337   Ljava/lang/Exception;
        //  654    662    2301   2337   Ljava/lang/Exception;
        //  670    760    2301   2337   Ljava/lang/Exception;
        //  760    791    2301   2337   Ljava/lang/Exception;
        //  800    806    2368   2373   Ljava/io/IOException;
        //  800    806    2301   2337   Ljava/lang/Exception;
        //  811    823    2301   2337   Ljava/lang/Exception;
        //  828    840    2301   2337   Ljava/lang/Exception;
        //  844    877    2301   2337   Ljava/lang/Exception;
        //  886    954    2373   2378   Ljava/io/IOException;
        //  886    954    2301   2337   Ljava/lang/Exception;
        //  959    966    2373   2378   Ljava/io/IOException;
        //  959    966    2301   2337   Ljava/lang/Exception;
        //  970    987    2389   2394   Ljava/io/IOException;
        //  970    987    2301   2337   Ljava/lang/Exception;
        //  992    999    2389   2394   Ljava/io/IOException;
        //  992    999    2301   2337   Ljava/lang/Exception;
        //  1003   1179   2405   2410   Ljava/io/IOException;
        //  1003   1179   2301   2337   Ljava/lang/Exception;
        //  1179   1202   2410   2415   Ljava/io/IOException;
        //  1179   1202   2301   2337   Ljava/lang/Exception;
        //  1207   1212   2415   2420   Ljava/io/IOException;
        //  1207   1212   2301   2337   Ljava/lang/Exception;
        //  1217   1234   2420   2425   Ljava/io/IOException;
        //  1217   1234   2301   2337   Ljava/lang/Exception;
        //  1234   1376   2301   2337   Ljava/lang/Exception;
        //  1376   1392   2425   2430   Ljava/io/IOException;
        //  1376   1392   2301   2337   Ljava/lang/Exception;
        //  1396   1408   2425   2430   Ljava/io/IOException;
        //  1396   1408   2301   2337   Ljava/lang/Exception;
        //  1408   1468   2301   2337   Ljava/lang/Exception;
        //  1468   1489   2430   2435   Ljava/io/IOException;
        //  1468   1489   2301   2337   Ljava/lang/Exception;
        //  1489   1561   2301   2337   Ljava/lang/Exception;
        //  1577   1584   2301   2337   Ljava/lang/Exception;
        //  1584   1593   2435   2454   Ljava/io/IOException;
        //  1584   1593   2301   2337   Ljava/lang/Exception;
        //  1597   1634   2454   2459   Ljava/io/IOException;
        //  1597   1634   2301   2337   Ljava/lang/Exception;
        //  1639   1648   2459   2464   Ljava/io/IOException;
        //  1639   1648   2301   2337   Ljava/lang/Exception;
        //  1653   1659   2301   2337   Ljava/lang/Exception;
        //  1668   1677   2464   2469   Ljava/io/IOException;
        //  1668   1677   2301   2337   Ljava/lang/Exception;
        //  1682   1691   2469   2474   Ljava/io/IOException;
        //  1682   1691   2301   2337   Ljava/lang/Exception;
        //  1700   1708   2474   2479   Ljava/io/IOException;
        //  1700   1708   2301   2337   Ljava/lang/Exception;
        //  1713   1721   2474   2479   Ljava/io/IOException;
        //  1713   1721   2301   2337   Ljava/lang/Exception;
        //  1721   1730   2301   2337   Ljava/lang/Exception;
        //  1730   1768   2301   2337   Ljava/lang/Exception;
        //  1781   1797   2301   2337   Ljava/lang/Exception;
        //  1797   1829   2489   2494   Ljava/io/IOException;
        //  1797   1829   2301   2337   Ljava/lang/Exception;
        //  1837   1891   2494   2499   Ljava/io/IOException;
        //  1837   1891   2301   2337   Ljava/lang/Exception;
        //  1899   1921   2499   2504   Ljava/io/IOException;
        //  1899   1921   2301   2337   Ljava/lang/Exception;
        //  1926   1942   2499   2504   Ljava/io/IOException;
        //  1926   1942   2301   2337   Ljava/lang/Exception;
        //  1956   1988   2301   2337   Ljava/lang/Exception;
        //  1988   2002   2301   2337   Ljava/lang/Exception;
        //  2002   2043   2504   2509   Ljava/io/IOException;
        //  2002   2043   2301   2337   Ljava/lang/Exception;
        //  2043   2057   2301   2337   Ljava/lang/Exception;
        //  2062   2069   2527   2532   Ljava/io/IOException;
        //  2062   2069   2301   2337   Ljava/lang/Exception;
        //  2074   2096   2532   2537   Ljava/io/IOException;
        //  2074   2096   2301   2337   Ljava/lang/Exception;
        //  2096   2126   2537   2542   Ljava/io/IOException;
        //  2096   2126   2301   2337   Ljava/lang/Exception;
        //  2126   2156   2542   2547   Ljava/io/IOException;
        //  2126   2156   2301   2337   Ljava/lang/Exception;
        //  2156   2186   2547   2552   Ljava/io/IOException;
        //  2156   2186   2301   2337   Ljava/lang/Exception;
        //  2186   2212   2552   2562   Ljava/io/IOException;
        //  2186   2212   2301   2337   Ljava/lang/Exception;
        //  2222   2230   2562   2567   Ljava/io/IOException;
        //  2222   2230   2301   2337   Ljava/lang/Exception;
        //  2235   2243   2562   2567   Ljava/io/IOException;
        //  2235   2243   2301   2337   Ljava/lang/Exception;
        //  2243   2252   2301   2337   Ljava/lang/Exception;
        //  2256   2268   2578   2583   Ljava/io/IOException;
        //  2256   2268   2301   2337   Ljava/lang/Exception;
        //  2273   2285   2583   2588   Ljava/io/IOException;
        //  2273   2285   2301   2337   Ljava/lang/Exception;
        //  2293   2296   2296   2301   Ljava/io/IOException;
        //  2293   2296   2301   2337   Ljava/lang/Exception;
        //  2298   2301   2301   2337   Ljava/lang/Exception;
        //  2337   2345   2301   2337   Ljava/lang/Exception;
        //  2350   2353   2301   2337   Ljava/lang/Exception;
        //  2355   2358   2301   2337   Ljava/lang/Exception;
        //  2360   2363   2301   2337   Ljava/lang/Exception;
        //  2365   2368   2301   2337   Ljava/lang/Exception;
        //  2370   2373   2301   2337   Ljava/lang/Exception;
        //  2375   2378   2301   2337   Ljava/lang/Exception;
        //  2378   2386   2301   2337   Ljava/lang/Exception;
        //  2391   2394   2301   2337   Ljava/lang/Exception;
        //  2394   2402   2301   2337   Ljava/lang/Exception;
        //  2407   2410   2301   2337   Ljava/lang/Exception;
        //  2412   2415   2415   2420   Ljava/io/IOException;
        //  2412   2415   2301   2337   Ljava/lang/Exception;
        //  2417   2420   2420   2425   Ljava/io/IOException;
        //  2417   2420   2301   2337   Ljava/lang/Exception;
        //  2422   2425   2301   2337   Ljava/lang/Exception;
        //  2427   2430   2301   2337   Ljava/lang/Exception;
        //  2432   2435   2301   2337   Ljava/lang/Exception;
        //  2437   2448   2301   2337   Ljava/lang/Exception;
        //  2456   2459   2459   2464   Ljava/io/IOException;
        //  2456   2459   2301   2337   Ljava/lang/Exception;
        //  2461   2464   2301   2337   Ljava/lang/Exception;
        //  2466   2469   2469   2474   Ljava/io/IOException;
        //  2466   2469   2301   2337   Ljava/lang/Exception;
        //  2471   2474   2301   2337   Ljava/lang/Exception;
        //  2476   2479   2301   2337   Ljava/lang/Exception;
        //  2479   2486   2301   2337   Ljava/lang/Exception;
        //  2491   2494   2301   2337   Ljava/lang/Exception;
        //  2496   2499   2301   2337   Ljava/lang/Exception;
        //  2501   2504   2301   2337   Ljava/lang/Exception;
        //  2506   2509   2301   2337   Ljava/lang/Exception;
        //  2509   2520   2301   2337   Ljava/lang/Exception;
        //  2529   2532   2532   2537   Ljava/io/IOException;
        //  2529   2532   2301   2337   Ljava/lang/Exception;
        //  2534   2537   2301   2337   Ljava/lang/Exception;
        //  2539   2542   2301   2337   Ljava/lang/Exception;
        //  2544   2547   2301   2337   Ljava/lang/Exception;
        //  2549   2552   2301   2337   Ljava/lang/Exception;
        //  2554   2557   2557   2562   Ljava/io/IOException;
        //  2554   2557   2301   2337   Ljava/lang/Exception;
        //  2559   2562   2301   2337   Ljava/lang/Exception;
        //  2564   2567   2301   2337   Ljava/lang/Exception;
        //  2567   2575   2301   2337   Ljava/lang/Exception;
        //  2580   2583   2301   2337   Ljava/lang/Exception;
        //  2585   2588   2301   2337   Ljava/lang/Exception;
        // 
        // The error that occurred was:
        // 
        // java.lang.IndexOutOfBoundsException: Index: 1223, Size: 1223
        //     at java.util.ArrayList.rangeCheck(ArrayList.java:653)
        //     at java.util.ArrayList.get(ArrayList.java:429)
        //     at com.strobel.decompiler.ast.AstBuilder.convertToAst(AstBuilder.java:3303)
        //     at com.strobel.decompiler.ast.AstBuilder.convertToAst(AstBuilder.java:3551)
        //     at com.strobel.decompiler.ast.AstBuilder.convertToAst(AstBuilder.java:3417)
        //     at com.strobel.decompiler.ast.AstBuilder.convertToAst(AstBuilder.java:3417)
        //     at com.strobel.decompiler.ast.AstBuilder.convertToAst(AstBuilder.java:3417)
        //     at com.strobel.decompiler.ast.AstBuilder.convertToAst(AstBuilder.java:3417)
        //     at com.strobel.decompiler.ast.AstBuilder.convertToAst(AstBuilder.java:3417)
        //     at com.strobel.decompiler.ast.AstBuilder.convertToAst(AstBuilder.java:3417)
        //     at com.strobel.decompiler.ast.AstBuilder.convertToAst(AstBuilder.java:3417)
        //     at com.strobel.decompiler.ast.AstBuilder.convertToAst(AstBuilder.java:3417)
        //     at com.strobel.decompiler.ast.AstBuilder.convertToAst(AstBuilder.java:3417)
        //     at com.strobel.decompiler.ast.AstBuilder.convertToAst(AstBuilder.java:3417)
        //     at com.strobel.decompiler.ast.AstBuilder.convertToAst(AstBuilder.java:3417)
        //     at com.strobel.decompiler.ast.AstBuilder.convertToAst(AstBuilder.java:3417)
        //     at com.strobel.decompiler.ast.AstBuilder.convertToAst(AstBuilder.java:3417)
        //     at com.strobel.decompiler.ast.AstBuilder.convertToAst(AstBuilder.java:3417)
        //     at com.strobel.decompiler.ast.AstBuilder.convertToAst(AstBuilder.java:3417)
        //     at com.strobel.decompiler.ast.AstBuilder.convertToAst(AstBuilder.java:3417)
        //     at com.strobel.decompiler.ast.AstBuilder.convertToAst(AstBuilder.java:3417)
        //     at com.strobel.decompiler.ast.AstBuilder.convertToAst(AstBuilder.java:3417)
        //     at com.strobel.decompiler.ast.AstBuilder.convertToAst(AstBuilder.java:3417)
        //     at com.strobel.decompiler.ast.AstBuilder.convertToAst(AstBuilder.java:3417)
        //     at com.strobel.decompiler.ast.AstBuilder.convertToAst(AstBuilder.java:3417)
        //     at com.strobel.decompiler.ast.AstBuilder.convertToAst(AstBuilder.java:3417)
        //     at com.strobel.decompiler.ast.AstBuilder.convertToAst(AstBuilder.java:3417)
        //     at com.strobel.decompiler.ast.AstBuilder.convertToAst(AstBuilder.java:3551)
        //     at com.strobel.decompiler.ast.AstBuilder.convertToAst(AstBuilder.java:3417)
        //     at com.strobel.decompiler.ast.AstBuilder.build(AstBuilder.java:113)
        //     at com.strobel.decompiler.languages.java.ast.AstMethodBodyBuilder.createMethodBody(AstMethodBodyBuilder.java:210)
        //     at com.strobel.decompiler.languages.java.ast.AstMethodBodyBuilder.createMethodBody(AstMethodBodyBuilder.java:99)
        //     at com.strobel.decompiler.languages.java.ast.AstBuilder.createMethodBody(AstBuilder.java:757)
        //     at com.strobel.decompiler.languages.java.ast.AstBuilder.createMethod(AstBuilder.java:655)
        //     at com.strobel.decompiler.languages.java.ast.AstBuilder.addTypeMembers(AstBuilder.java:532)
        //     at com.strobel.decompiler.languages.java.ast.AstBuilder.createTypeCore(AstBuilder.java:499)
        //     at com.strobel.decompiler.languages.java.ast.AstBuilder.createTypeNoCache(AstBuilder.java:141)
        //     at com.strobel.decompiler.languages.java.ast.AstBuilder.createType(AstBuilder.java:130)
        //     at com.strobel.decompiler.languages.java.ast.AstBuilder.addType(AstBuilder.java:105)
        //     at com.strobel.decompiler.languages.java.JavaLanguage.buildAst(JavaLanguage.java:71)
        //     at com.strobel.decompiler.languages.java.JavaLanguage.decompileType(JavaLanguage.java:59)
        //     at com.strobel.decompiler.DecompilerDriver.decompileType(DecompilerDriver.java:317)
        //     at com.strobel.decompiler.DecompilerDriver.decompileJar(DecompilerDriver.java:238)
        //     at com.strobel.decompiler.DecompilerDriver.main(DecompilerDriver.java:123)
        // 
        throw new IllegalStateException("An error occurred while decompiling this method.");
    }
    
    private static String a(final ConnectivityManager connectivityManager) {
        final NetworkInfo activeNetworkInfo = connectivityManager.getActiveNetworkInfo();
        final StringBuilder sb = new StringBuilder();
        if (activeNetworkInfo != null) {
            a(sb, activeNetworkInfo.getTypeName());
            final String subtypeName = activeNetworkInfo.getSubtypeName();
            if (!TextUtils.isEmpty((CharSequence)subtypeName)) {
                sb.append(a8q.z[20]);
                a(sb, subtypeName);
                sb.append(')');
            }
            if (!App.I) {
                return sb.toString();
            }
        }
        sb.append(a8q.z[19]);
        return sb.toString();
    }
    
    private static String a(final String s) {
        if (s == null) {
            return null;
        }
        final StringBuilder sb = new StringBuilder(2 * s.length());
        a(sb, s);
        return sb.toString();
    }
    
    private static void a(final Activity activity, final gu gu, final String s, final String s2, final ArrayList list, final String s3, final String s4, final File file, final long n, final long n2, final String s5) {
        final boolean i = App.I;
        final String string = activity.getString(2131231059);
        final StringBuffer sb = new StringBuffer(a((Context)activity, s, s2, s3, s4, n, n2, s5));
        boolean b;
        if (list != null && !list.isEmpty()) {
            b = true;
        }
        else {
            b = false;
        }
        String s6;
        if (b) {
            s6 = a8q.z[134];
        }
        else {
            s6 = a8q.z[141];
        }
        final Intent intent = new Intent(s6);
        Label_0191: {
            if (s4 == null) {
                if (file == null) {
                    intent.setType(a8q.z[136]);
                    sb.append(a8q.z[131]);
                    if (!i) {
                        break Label_0191;
                    }
                }
                intent.setType(a8q.z[142]);
                if (b) {
                    list.add(Uri.fromFile(file));
                    if (!i) {
                        break Label_0191;
                    }
                }
                intent.putExtra(a8q.z[135], (Parcelable)Uri.fromFile(file));
                if (!i) {
                    break Label_0191;
                }
            }
            intent.setType(a8q.z[137]);
        }
        intent.putExtra(a8q.z[139], new String[] { a8q.z[138] });
        intent.putExtra(a8q.z[133], string);
        intent.putExtra(a8q.z[132], sb.toString());
        if (b) {
            intent.putParcelableArrayListExtra(a8q.z[140], list);
        }
        a(intent, activity, gu, activity.getString(2131230939));
    }
    
    public static void a(final Intent intent, final Activity activity, final gu gu, final String s) {
        final boolean i = App.I;
        final ArrayList<Object> list = new ArrayList<Object>();
        final List queryIntentActivities = activity.getPackageManager().queryIntentActivities(intent, 0);
        if (queryIntentActivities != null) {
            final Iterator<ResolveInfo> iterator = queryIntentActivities.iterator();
            while (iterator.hasNext()) {
                final ActivityInfo activityInfo = iterator.next().activityInfo;
                final String name = activityInfo.name;
                final String packageName = activityInfo.applicationInfo.packageName;
                Log.i(a8q.z[8] + packageName + a8q.z[9] + name);
                if (packageName.contains(a8q.z[13]) || packageName.contains(a8q.z[10]) || packageName.contains(a8q.z[18]) || packageName.contains(a8q.z[11]) || packageName.contains(a8q.z[14]) || packageName.contains(a8q.z[17]) || packageName.contains(a8q.z[15]) || packageName.contains(a8q.z[12])) {
                    final Intent intent2 = (Intent)intent.clone();
                    intent2.setClassName(packageName, name);
                    intent2.setPackage(packageName);
                    list.add(intent2);
                }
                if (i) {
                    break;
                }
            }
        }
        if (list.size() == 0) {
            if (gu != null) {
                gu.a(2131231079);
                if (!i) {
                    return;
                }
            }
            App.a((Context)activity, 2131231079, 0);
            if (!i) {
                return;
            }
        }
        final Intent chooser = Intent.createChooser((Intent)list.get(-1 + list.size()), (CharSequence)s);
        if (list.size() > 1) {
            list.remove(-1 + list.size());
            chooser.putExtra(a8q.z[16], (Parcelable[])list.toArray((Parcelable[])new Intent[list.size()]));
        }
        activity.startActivity(chooser);
    }
    
    public static void a(final DialogToastActivity dialogToastActivity, final String s, final String s2, final ArrayList list, final String s3, final String s4, final File file, final long n, final long n2, final String s5) {
        a(dialogToastActivity, dialogToastActivity, s, s2, list, s3, s4, file, n, n2, s5);
    }
    
    public static void a(final DialogToastListActivity dialogToastListActivity, final String s, final String s2, final ArrayList list, final String s3, final String s4, final File file, final long n, final long n2, final String s5) {
        a(dialogToastListActivity, dialogToastListActivity, s, s2, list, s3, s4, file, n, n2, s5);
    }
    
    private static void a(final String p0, final Object p1, final Object p2) {
        // 
        // This method could not be decompiled.
        // 
        // Original Bytecode:
        // 
        //     0: aload_2        
        //     1: instanceof      Lorg/json/JSONObject;
        //     4: ifeq            27
        //     7: aload_2        
        //     8: checkcast       Lorg/json/JSONObject;
        //    11: astore          6
        //    13: aload           6
        //    15: aload_0        
        //    16: aload_1        
        //    17: invokevirtual   org/json/JSONObject.put:(Ljava/lang/String;Ljava/lang/Object;)Lorg/json/JSONObject;
        //    20: pop            
        //    21: getstatic       com/whatsapp/App.I:Z
        //    24: ifeq            65
        //    27: aload_2        
        //    28: instanceof      Ljava/lang/StringBuilder;
        //    31: istore          4
        //    33: iload           4
        //    35: ifeq            65
        //    38: aload_2        
        //    39: checkcast       Ljava/lang/StringBuilder;
        //    42: aload_0        
        //    43: invokevirtual   java/lang/StringBuilder.append:(Ljava/lang/String;)Ljava/lang/StringBuilder;
        //    46: getstatic       com/whatsapp/a8q.z:[Ljava/lang/String;
        //    49: bipush          6
        //    51: aaload         
        //    52: invokevirtual   java/lang/StringBuilder.append:(Ljava/lang/String;)Ljava/lang/StringBuilder;
        //    55: aload_1        
        //    56: invokevirtual   java/lang/StringBuilder.append:(Ljava/lang/Object;)Ljava/lang/StringBuilder;
        //    59: bipush          10
        //    61: invokevirtual   java/lang/StringBuilder.append:(C)Ljava/lang/StringBuilder;
        //    64: pop            
        //    65: return         
        //    66: astore          7
        //    68: new             Ljava/lang/StringBuilder;
        //    71: dup            
        //    72: invokespecial   java/lang/StringBuilder.<init>:()V
        //    75: getstatic       com/whatsapp/a8q.z:[Ljava/lang/String;
        //    78: bipush          7
        //    80: aaload         
        //    81: invokevirtual   java/lang/StringBuilder.append:(Ljava/lang/String;)Ljava/lang/StringBuilder;
        //    84: aload           7
        //    86: invokevirtual   org/json/JSONException.toString:()Ljava/lang/String;
        //    89: invokevirtual   java/lang/StringBuilder.append:(Ljava/lang/String;)Ljava/lang/StringBuilder;
        //    92: invokevirtual   java/lang/StringBuilder.toString:()Ljava/lang/String;
        //    95: invokestatic    com/whatsapp/util/Log.e:(Ljava/lang/String;)V
        //    98: goto            21
        //   101: astore_3       
        //   102: aload_3        
        //   103: athrow         
        //    Exceptions:
        //  Try           Handler
        //  Start  End    Start  End    Type                    
        //  -----  -----  -----  -----  ------------------------
        //  13     21     66     101    Lorg/json/JSONException;
        //  21     27     101    104    Lorg/json/JSONException;
        //  27     33     101    104    Lorg/json/JSONException;
        // 
        // The error that occurred was:
        // 
        // java.lang.IllegalStateException: Expression is linked from several locations: Label_0021:
        //     at com.strobel.decompiler.ast.Error.expressionLinkedFromMultipleLocations(Error.java:27)
        //     at com.strobel.decompiler.ast.AstOptimizer.mergeDisparateObjectInitializations(AstOptimizer.java:2592)
        //     at com.strobel.decompiler.ast.AstOptimizer.optimize(AstOptimizer.java:235)
        //     at com.strobel.decompiler.ast.AstOptimizer.optimize(AstOptimizer.java:42)
        //     at com.strobel.decompiler.languages.java.ast.AstMethodBodyBuilder.createMethodBody(AstMethodBodyBuilder.java:214)
        //     at com.strobel.decompiler.languages.java.ast.AstMethodBodyBuilder.createMethodBody(AstMethodBodyBuilder.java:99)
        //     at com.strobel.decompiler.languages.java.ast.AstBuilder.createMethodBody(AstBuilder.java:757)
        //     at com.strobel.decompiler.languages.java.ast.AstBuilder.createMethod(AstBuilder.java:655)
        //     at com.strobel.decompiler.languages.java.ast.AstBuilder.addTypeMembers(AstBuilder.java:532)
        //     at com.strobel.decompiler.languages.java.ast.AstBuilder.createTypeCore(AstBuilder.java:499)
        //     at com.strobel.decompiler.languages.java.ast.AstBuilder.createTypeNoCache(AstBuilder.java:141)
        //     at com.strobel.decompiler.languages.java.ast.AstBuilder.createType(AstBuilder.java:130)
        //     at com.strobel.decompiler.languages.java.ast.AstBuilder.addType(AstBuilder.java:105)
        //     at com.strobel.decompiler.languages.java.JavaLanguage.buildAst(JavaLanguage.java:71)
        //     at com.strobel.decompiler.languages.java.JavaLanguage.decompileType(JavaLanguage.java:59)
        //     at com.strobel.decompiler.DecompilerDriver.decompileType(DecompilerDriver.java:317)
        //     at com.strobel.decompiler.DecompilerDriver.decompileJar(DecompilerDriver.java:238)
        //     at com.strobel.decompiler.DecompilerDriver.main(DecompilerDriver.java:123)
        // 
        throw new IllegalStateException("An error occurred while decompiling this method.");
    }
    
    private static void a(final StringBuilder sb, final String s) {
        final boolean i = App.I;
        if (s != null) {
            int j = 0;
            while (j < s.length()) {
                sb.append(s.charAt(j)).append('.');
                ++j;
                if (i) {
                    return;
                }
            }
        }
    }
    
    public static String b() {
        final ArrayList b = Log.b(1);
        try {
            if (b.size() < 1) {
                Log.e(a8q.z[5]);
                return null;
            }
        }
        catch (Exception ex) {
            throw ex;
        }
        final File file = b.get(0);
        File a;
        if (file.length() > 8388608L) {
            a = h.a(file, 8388608, 0);
            if (a == null) {
                return null;
            }
        }
        else {
            a = file;
        }
        final StringBuffer sb = new StringBuffer();
        final ConditionVariable conditionVariable = new ConditionVariable();
        final xu xu = new xu(sb, conditionVariable);
        Label_0212: {
            try {
                final alp alp = new alp(new URL(a6c.k), a, 16384, xu);
                alp.a(a8q.z[2], a8q.z[0]);
                alp.a(a8q.z[1], App.j((Context)App.aq));
                alp.a(a8q.z[3], a8q.z[4]);
                alp.a();
                final ConditionVariable conditionVariable2 = conditionVariable;
                final long n = 100000L;
                conditionVariable2.block(n);
                final StringBuffer sb2 = sb;
                final int length = sb2.length();
                final int length2 = length;
                if (length2 == 0) {
                    return null;
                }
                break Label_0212;
            }
            catch (Exception ex2) {
                Log.b(ex2);
                return null;
            }
            try {
                final ConditionVariable conditionVariable2 = conditionVariable;
                final long n = 100000L;
                conditionVariable2.block(n);
                final StringBuffer sb2 = sb;
                final int length2;
                final int length = length2 = sb2.length();
                if (length2 == 0) {
                    return null;
                }
            }
            catch (Exception ex3) {
                throw ex3;
            }
            try {
                if (!a.getAbsolutePath().equals(file.getAbsolutePath())) {
                    a.delete();
                }
                return sb.toString();
            }
            catch (Exception ex4) {
                throw ex4;
            }
        }
    }
    
    private static String b(final int n) {
        switch (n) {
            default: {
                return a8q.z[21];
            }
            case 0: {
                return a8q.z[25];
            }
            case 1: {
                return a8q.z[22];
            }
            case 2: {
                return a8q.z[23];
            }
            case 3: {
                return a8q.z[24];
            }
        }
    }
    
    private static String c() {
        // 
        // This method could not be decompiled.
        // 
        // Original Bytecode:
        // 
        //     0: new             Ljava/lang/StringBuilder;
        //     3: dup            
        //     4: invokespecial   java/lang/StringBuilder.<init>:()V
        //     7: astore_0       
        //     8: getstatic       com/whatsapp/App.aT:Lcom/whatsapp/util/a4;
        //    11: lconst_0       
        //    12: getstatic       java/util/concurrent/TimeUnit.MILLISECONDS:Ljava/util/concurrent/TimeUnit;
        //    15: invokevirtual   com/whatsapp/util/a4.a:(JLjava/util/concurrent/TimeUnit;)Lcom/whatsapp/util/bs;
        //    18: astore          17
        //    20: aload           17
        //    22: getfield        com/whatsapp/util/bs.b:Ljava/util/Set;
        //    25: ifnull          57
        //    28: aload_0        
        //    29: getstatic       com/whatsapp/a8q.z:[Ljava/lang/String;
        //    32: bipush          123
        //    34: aaload         
        //    35: invokevirtual   java/lang/StringBuilder.append:(Ljava/lang/String;)Ljava/lang/StringBuilder;
        //    38: aload           17
        //    40: getfield        com/whatsapp/util/bs.b:Ljava/util/Set;
        //    43: invokeinterface java/util/Set.size:()I
        //    48: invokevirtual   java/lang/StringBuilder.append:(I)Ljava/lang/StringBuilder;
        //    51: bipush          32
        //    53: invokevirtual   java/lang/StringBuilder.append:(C)Ljava/lang/StringBuilder;
        //    56: pop            
        //    57: aload           17
        //    59: getfield        com/whatsapp/util/bs.a:Ljava/util/Set;
        //    62: ifnull          95
        //    65: aload_0        
        //    66: getstatic       com/whatsapp/a8q.z:[Ljava/lang/String;
        //    69: sipush          129
        //    72: aaload         
        //    73: invokevirtual   java/lang/StringBuilder.append:(Ljava/lang/String;)Ljava/lang/StringBuilder;
        //    76: aload           17
        //    78: getfield        com/whatsapp/util/bs.a:Ljava/util/Set;
        //    81: invokeinterface java/util/Set.size:()I
        //    86: invokevirtual   java/lang/StringBuilder.append:(I)Ljava/lang/StringBuilder;
        //    89: bipush          32
        //    91: invokevirtual   java/lang/StringBuilder.append:(C)Ljava/lang/StringBuilder;
        //    94: pop            
        //    95: getstatic       com/whatsapp/a8q.z:[Ljava/lang/String;
        //    98: bipush          125
        //   100: aaload         
        //   101: invokestatic    java/lang/Class.forName:(Ljava/lang/String;)Ljava/lang/Class;
        //   104: pop            
        //   105: aload_0        
        //   106: getstatic       com/whatsapp/a8q.z:[Ljava/lang/String;
        //   109: bipush          126
        //   111: aaload         
        //   112: invokevirtual   java/lang/StringBuilder.append:(Ljava/lang/String;)Ljava/lang/StringBuilder;
        //   115: pop            
        //   116: invokestatic    com/whatsapp/al5.x:()Z
        //   119: istore          6
        //   121: iload           6
        //   123: ifeq            170
        //   126: invokestatic    com/whatsapp/al5.v:()Z
        //   129: ifeq            143
        //   132: aload_0        
        //   133: getstatic       com/whatsapp/a8q.z:[Ljava/lang/String;
        //   136: bipush          124
        //   138: aaload         
        //   139: invokevirtual   java/lang/StringBuilder.append:(Ljava/lang/String;)Ljava/lang/StringBuilder;
        //   142: pop            
        //   143: invokestatic    com/whatsapp/al5.N:()Ljava/lang/String;
        //   146: astore          12
        //   148: aload           12
        //   150: ifnull          182
        //   153: aload_0        
        //   154: getstatic       com/whatsapp/a8q.z:[Ljava/lang/String;
        //   157: bipush          127
        //   159: aaload         
        //   160: invokevirtual   java/lang/StringBuilder.append:(Ljava/lang/String;)Ljava/lang/StringBuilder;
        //   163: pop            
        //   164: getstatic       com/whatsapp/App.I:Z
        //   167: ifeq            182
        //   170: aload_0        
        //   171: getstatic       com/whatsapp/a8q.z:[Ljava/lang/String;
        //   174: sipush          130
        //   177: aaload         
        //   178: invokevirtual   java/lang/StringBuilder.append:(Ljava/lang/String;)Ljava/lang/StringBuilder;
        //   181: pop            
        //   182: aload_0        
        //   183: invokevirtual   java/lang/StringBuilder.length:()I
        //   186: istore          10
        //   188: iload           10
        //   190: ifne            246
        //   193: aconst_null    
        //   194: areturn        
        //   195: astore          18
        //   197: aload           18
        //   199: athrow         
        //   200: astore_1       
        //   201: aload_0        
        //   202: getstatic       com/whatsapp/a8q.z:[Ljava/lang/String;
        //   205: sipush          128
        //   208: aaload         
        //   209: invokevirtual   java/lang/StringBuilder.append:(Ljava/lang/String;)Ljava/lang/StringBuilder;
        //   212: pop            
        //   213: goto            95
        //   216: astore          19
        //   218: aload           19
        //   220: athrow         
        //   221: astore          4
        //   223: aload           4
        //   225: athrow         
        //   226: astore          5
        //   228: aload           5
        //   230: athrow         
        //   231: astore          11
        //   233: aload           11
        //   235: athrow         
        //   236: astore          7
        //   238: aload           7
        //   240: athrow         
        //   241: astore          9
        //   243: aload           9
        //   245: athrow         
        //   246: aload_0        
        //   247: invokevirtual   java/lang/StringBuilder.toString:()Ljava/lang/String;
        //   250: areturn        
        //   251: astore_3       
        //   252: goto            116
        //    Exceptions:
        //  Try           Handler
        //  Start  End    Start  End    Type                              
        //  -----  -----  -----  -----  ----------------------------------
        //  8      20     200    216    Ljava/lang/Exception;
        //  20     57     195    200    Ljava/lang/Exception;
        //  57     95     216    221    Ljava/lang/Exception;
        //  95     116    251    255    Ljava/lang/ClassNotFoundException;
        //  116    121    221    226    Ljava/lang/Exception;
        //  126    143    226    231    Ljava/lang/Exception;
        //  143    148    231    236    Ljava/lang/Exception;
        //  153    170    236    241    Ljava/lang/Exception;
        //  170    182    236    241    Ljava/lang/Exception;
        //  182    188    241    246    Ljava/lang/Exception;
        //  197    200    200    216    Ljava/lang/Exception;
        //  218    221    200    216    Ljava/lang/Exception;
        //  223    226    226    231    Ljava/lang/Exception;
        //  233    236    236    241    Ljava/lang/Exception;
        // 
        // The error that occurred was:
        // 
        // java.lang.IndexOutOfBoundsException: Index: 121, Size: 121
        //     at java.util.ArrayList.rangeCheck(ArrayList.java:653)
        //     at java.util.ArrayList.get(ArrayList.java:429)
        //     at com.strobel.decompiler.ast.AstBuilder.convertToAst(AstBuilder.java:3303)
        //     at com.strobel.decompiler.ast.AstBuilder.build(AstBuilder.java:113)
        //     at com.strobel.decompiler.languages.java.ast.AstMethodBodyBuilder.createMethodBody(AstMethodBodyBuilder.java:210)
        //     at com.strobel.decompiler.languages.java.ast.AstMethodBodyBuilder.createMethodBody(AstMethodBodyBuilder.java:99)
        //     at com.strobel.decompiler.languages.java.ast.AstBuilder.createMethodBody(AstBuilder.java:757)
        //     at com.strobel.decompiler.languages.java.ast.AstBuilder.createMethod(AstBuilder.java:655)
        //     at com.strobel.decompiler.languages.java.ast.AstBuilder.addTypeMembers(AstBuilder.java:532)
        //     at com.strobel.decompiler.languages.java.ast.AstBuilder.createTypeCore(AstBuilder.java:499)
        //     at com.strobel.decompiler.languages.java.ast.AstBuilder.createTypeNoCache(AstBuilder.java:141)
        //     at com.strobel.decompiler.languages.java.ast.AstBuilder.createType(AstBuilder.java:130)
        //     at com.strobel.decompiler.languages.java.ast.AstBuilder.addType(AstBuilder.java:105)
        //     at com.strobel.decompiler.languages.java.JavaLanguage.buildAst(JavaLanguage.java:71)
        //     at com.strobel.decompiler.languages.java.JavaLanguage.decompileType(JavaLanguage.java:59)
        //     at com.strobel.decompiler.DecompilerDriver.decompileType(DecompilerDriver.java:317)
        //     at com.strobel.decompiler.DecompilerDriver.decompileJar(DecompilerDriver.java:238)
        //     at com.strobel.decompiler.DecompilerDriver.main(DecompilerDriver.java:123)
        // 
        throw new IllegalStateException("An error occurred while decompiling this method.");
    }
    
    public static File d() {
        return al.a(Log.b(3), true);
    }
}
