// 
// Decompiled by Procyon v0.5.30
// 

package com.whatsapp;

import com.whatsapp.util.Log;
import java.util.List;
import org.apache.http.HttpResponse;

public class b0
{
    private static final String[] z;
    
    static {
        final String[] z2 = new String[19];
        String s = ",'\u0006D\r'<\u001cZF''\u001b[M";
        int n = -1;
        String[] array = z2;
        int n2 = 0;
        String intern = null;
    Label_0507:
        while (true) {
            final char[] charArray = s.toCharArray();
            for (int i = charArray.length, n3 = 0; i > n3; ++n3) {
                final char c = charArray[n3];
                char c2 = '\0';
                switch (n3 % 5) {
                    default: {
                        c2 = '#';
                        break;
                    }
                    case 0: {
                        c2 = 'D';
                        break;
                    }
                    case 1: {
                        c2 = 'S';
                        break;
                    }
                    case 2: {
                        c2 = 'r';
                        break;
                    }
                    case 3: {
                        c2 = '4';
                        break;
                    }
                }
                charArray[n3] = (char)(c2 ^ c);
            }
            intern = new String(charArray).intern();
            switch (n) {
                default: {
                    array[n2] = intern;
                    s = "d{";
                    n2 = 1;
                    array = z2;
                    n = 0;
                    continue;
                }
                case 0: {
                    array[n2] = intern;
                    s = ",'\u0006DP";
                    n2 = 2;
                    array = z2;
                    n = 1;
                    continue;
                }
                case 1: {
                    array[n2] = intern;
                    s = "ms";
                    n2 = 3;
                    array = z2;
                    n = 2;
                    continue;
                }
                case 2: {
                    array[n2] = intern;
                    s = "ms";
                    n2 = 4;
                    array = z2;
                    n = 3;
                    continue;
                }
                case 3: {
                    array[n2] = intern;
                    n2 = 5;
                    array = z2;
                    s = ",'\u0006DD!']\\W0#\u0017FQ+!R\u001c";
                    n = 4;
                    continue;
                }
                case 4: {
                    array[n2] = intern;
                    n2 = 6;
                    s = "\u0007<\u001cZF''\u001b[M";
                    n = 5;
                    array = z2;
                    continue;
                }
                case 5: {
                    array[n2] = intern;
                    n2 = 7;
                    s = ",'\u0006DD!']ZLi2\u0016PQ! \u0001QP";
                    n = 6;
                    array = z2;
                    continue;
                }
                case 6: {
                    array[n2] = intern;
                    n2 = 8;
                    s = "'?\u001dGF";
                    n = 7;
                    array = z2;
                    continue;
                }
                case 7: {
                    array[n2] = intern;
                    n2 = 9;
                    s = ",'\u0006DS+ \u0006\u001bA%7_GW%'\u0007G@+7\u0017\u0014";
                    n = 8;
                    array = z2;
                    continue;
                }
                case 8: {
                    array[n2] = intern;
                    n2 = 10;
                    s = ",'\u0006D\f&2\u0016\u0019S6<\u0006[@+?";
                    n = 9;
                    array = z2;
                    continue;
                }
                case 9: {
                    array[n2] = intern;
                    n2 = 11;
                    s = ",'\u0006D\f*<_@B64\u0017@";
                    n = 10;
                    array = z2;
                    continue;
                }
                case 10: {
                    array[n2] = intern;
                    n2 = 12;
                    s = "\u0003\u0016&";
                    n = 11;
                    array = z2;
                    continue;
                }
                case 11: {
                    array[n2] = intern;
                    n2 = 13;
                    s = "ms";
                    n = 12;
                    array = z2;
                    continue;
                }
                case 12: {
                    array[n2] = intern;
                    n2 = 14;
                    s = ",'\u0006D\f&2\u0016AQ(";
                    n = 13;
                    array = z2;
                    continue;
                }
                case 13: {
                    array[n2] = intern;
                    n2 = 15;
                    s = ",'\u0006DD!']]L!!\u0000[Qd{";
                    n = 14;
                    array = z2;
                    continue;
                }
                case 14: {
                    array[n2] = intern;
                    n2 = 16;
                    s = "\u0011\u00074\u0019\u001b";
                    n = 15;
                    array = z2;
                    continue;
                }
                case 15: {
                    array[n2] = intern;
                    n2 = 17;
                    s = ",'\u0006DD!']QQ6<\u0000\u0014\u000b";
                    n = 16;
                    array = z2;
                    continue;
                }
                case 16: {
                    array[n2] = intern;
                    n2 = 18;
                    s = ",'\u0006D\f%7\u0016F\f*<_\\L7'";
                    n = 17;
                    array = z2;
                    continue;
                }
                case 17: {
                    break Label_0507;
                }
            }
        }
        array[n2] = intern;
        z = z2;
    }
    
    public static HttpResponse a(final String p0) {
        // 
        // This method could not be decompiled.
        // 
        // Original Bytecode:
        // 
        //     0: getstatic       com/whatsapp/a_9.k:Z
        //     3: istore_1       
        //     4: aload_0        
        //     5: invokestatic    android/text/TextUtils.isEmpty:(Ljava/lang/CharSequence;)Z
        //     8: ifeq            29
        //    11: getstatic       com/whatsapp/b0.z:[Ljava/lang/String;
        //    14: bipush          11
        //    16: aaload         
        //    17: invokestatic    com/whatsapp/util/Log.e:(Ljava/lang/String;)V
        //    20: aconst_null    
        //    21: astore          34
        //    23: aload           34
        //    25: areturn        
        //    26: astore_2       
        //    27: aload_2        
        //    28: athrow         
        //    29: new             Ljava/net/URL;
        //    32: dup            
        //    33: aload_0        
        //    34: invokespecial   java/net/URL.<init>:(Ljava/lang/String;)V
        //    37: astore_3       
        //    38: aload_3        
        //    39: invokevirtual   java/net/URL.getProtocol:()Ljava/lang/String;
        //    42: getstatic       com/whatsapp/b0.z:[Ljava/lang/String;
        //    45: iconst_2       
        //    46: aaload         
        //    47: invokevirtual   java/lang/String.equals:(Ljava/lang/Object;)Z
        //    50: ifne            82
        //    53: getstatic       com/whatsapp/b0.z:[Ljava/lang/String;
        //    56: bipush          10
        //    58: aaload         
        //    59: invokestatic    com/whatsapp/util/Log.e:(Ljava/lang/String;)V
        //    62: aconst_null    
        //    63: areturn        
        //    64: astore          39
        //    66: getstatic       com/whatsapp/b0.z:[Ljava/lang/String;
        //    69: bipush          14
        //    71: aaload         
        //    72: invokestatic    com/whatsapp/util/Log.e:(Ljava/lang/String;)V
        //    75: aconst_null    
        //    76: areturn        
        //    77: astore          4
        //    79: aload           4
        //    81: athrow         
        //    82: aload_3        
        //    83: invokevirtual   java/net/URL.getHost:()Ljava/lang/String;
        //    86: invokestatic    com/whatsapp/b0.b:(Ljava/lang/String;)Ljava/util/List;
        //    89: astore          5
        //    91: aload           5
        //    93: ifnonnull       112
        //    96: getstatic       com/whatsapp/b0.z:[Ljava/lang/String;
        //    99: bipush          7
        //   101: aaload         
        //   102: invokestatic    com/whatsapp/util/Log.w:(Ljava/lang/String;)V
        //   105: aconst_null    
        //   106: areturn        
        //   107: astore          38
        //   109: aload           38
        //   111: athrow         
        //   112: aload_3        
        //   113: invokevirtual   java/net/URL.getPort:()I
        //   116: istore          6
        //   118: iload           6
        //   120: iconst_m1      
        //   121: if_icmpne       931
        //   124: aload_3        
        //   125: invokevirtual   java/net/URL.getDefaultPort:()I
        //   128: istore          7
        //   130: aload           5
        //   132: invokestatic    java/util/Collections.shuffle:(Ljava/util/List;)V
        //   135: aload           5
        //   137: invokeinterface java/util/List.size:()I
        //   142: istore          9
        //   144: iload           9
        //   146: iconst_4       
        //   147: if_icmple       650
        //   150: iconst_4       
        //   151: istore          10
        //   153: new             Lorg/apache/http/protocol/BasicHttpProcessor;
        //   156: dup            
        //   157: invokespecial   org/apache/http/protocol/BasicHttpProcessor.<init>:()V
        //   160: astore          11
        //   162: aload           11
        //   164: new             Lorg/apache/http/protocol/RequestContent;
        //   167: dup            
        //   168: invokespecial   org/apache/http/protocol/RequestContent.<init>:()V
        //   171: invokevirtual   org/apache/http/protocol/BasicHttpProcessor.addInterceptor:(Lorg/apache/http/HttpRequestInterceptor;)V
        //   174: aload           11
        //   176: new             Lorg/apache/http/protocol/RequestTargetHost;
        //   179: dup            
        //   180: invokespecial   org/apache/http/protocol/RequestTargetHost.<init>:()V
        //   183: invokevirtual   org/apache/http/protocol/BasicHttpProcessor.addInterceptor:(Lorg/apache/http/HttpRequestInterceptor;)V
        //   186: aload           11
        //   188: new             Lorg/apache/http/protocol/RequestUserAgent;
        //   191: dup            
        //   192: invokespecial   org/apache/http/protocol/RequestUserAgent.<init>:()V
        //   195: invokevirtual   org/apache/http/protocol/BasicHttpProcessor.addInterceptor:(Lorg/apache/http/HttpRequestInterceptor;)V
        //   198: aload           11
        //   200: ldc             Lorg/apache/http/protocol/RequestExpectContinue;.class
        //   202: invokevirtual   org/apache/http/protocol/BasicHttpProcessor.removeRequestInterceptorByClass:(Ljava/lang/Class;)V
        //   205: iconst_0       
        //   206: istore          12
        //   208: iload           12
        //   210: iload           10
        //   212: if_icmpge       643
        //   215: new             Lorg/apache/http/params/BasicHttpParams;
        //   218: dup            
        //   219: invokespecial   org/apache/http/params/BasicHttpParams.<init>:()V
        //   222: astore          13
        //   224: aload           13
        //   226: getstatic       org/apache/http/HttpVersion.HTTP_1_1:Lorg/apache/http/HttpVersion;
        //   229: invokestatic    org/apache/http/params/HttpProtocolParams.setVersion:(Lorg/apache/http/params/HttpParams;Lorg/apache/http/ProtocolVersion;)V
        //   232: aload           13
        //   234: getstatic       com/whatsapp/b0.z:[Ljava/lang/String;
        //   237: bipush          16
        //   239: aaload         
        //   240: invokestatic    org/apache/http/params/HttpProtocolParams.setContentCharset:(Lorg/apache/http/params/HttpParams;Ljava/lang/String;)V
        //   243: aload           13
        //   245: invokestatic    com/whatsapp/m3.a:()Ljava/lang/String;
        //   248: invokestatic    org/apache/http/params/HttpProtocolParams.setUserAgent:(Lorg/apache/http/params/HttpParams;Ljava/lang/String;)V
        //   251: new             Lorg/apache/http/protocol/HttpRequestExecutor;
        //   254: dup            
        //   255: invokespecial   org/apache/http/protocol/HttpRequestExecutor.<init>:()V
        //   258: astore          14
        //   260: new             Lorg/apache/http/protocol/BasicHttpContext;
        //   263: dup            
        //   264: aconst_null    
        //   265: invokespecial   org/apache/http/protocol/BasicHttpContext.<init>:(Lorg/apache/http/protocol/HttpContext;)V
        //   268: astore          15
        //   270: new             Lorg/apache/http/impl/DefaultHttpClientConnection;
        //   273: dup            
        //   274: invokespecial   org/apache/http/impl/DefaultHttpClientConnection.<init>:()V
        //   277: astore          16
        //   279: aload           5
        //   281: iload           12
        //   283: invokeinterface java/util/List.get:(I)Ljava/lang/Object;
        //   288: checkcast       Ljava/net/InetAddress;
        //   291: astore          17
        //   293: invokestatic    java/lang/Math.random:()D
        //   296: ldc2_w          4000.0
        //   299: ldc2_w          2.0
        //   302: iload           12
        //   304: i2d            
        //   305: invokestatic    java/lang/Math.pow:(DD)D
        //   308: dconst_1       
        //   309: dsub           
        //   310: dmul           
        //   311: dmul           
        //   312: d2i            
        //   313: i2l            
        //   314: invokestatic    java/lang/Thread.sleep:(J)V
        //   317: new             Ljava/net/Socket;
        //   320: dup            
        //   321: invokespecial   java/net/Socket.<init>:()V
        //   324: astore          28
        //   326: new             Ljava/net/InetSocketAddress;
        //   329: dup            
        //   330: aload           17
        //   332: iload           7
        //   334: invokespecial   java/net/InetSocketAddress.<init>:(Ljava/net/InetAddress;I)V
        //   337: astore          29
        //   339: aload           28
        //   341: aload           29
        //   343: ldc             60000
        //   345: invokevirtual   java/net/Socket.connect:(Ljava/net/SocketAddress;I)V
        //   348: aload           28
        //   350: ldc             60000
        //   352: invokevirtual   java/net/Socket.setSoTimeout:(I)V
        //   355: invokestatic    com/whatsapp/messaging/a6.b:()Lcom/whatsapp/messaging/a6;
        //   358: aload           28
        //   360: aload_3        
        //   361: invokevirtual   java/net/URL.getHost:()Ljava/lang/String;
        //   364: iload           7
        //   366: iconst_1       
        //   367: invokevirtual   javax/net/ssl/SSLSocketFactory.createSocket:(Ljava/net/Socket;Ljava/lang/String;IZ)Ljava/net/Socket;
        //   370: astore          30
        //   372: aload           15
        //   374: getstatic       com/whatsapp/b0.z:[Ljava/lang/String;
        //   377: iconst_0       
        //   378: aaload         
        //   379: aload           16
        //   381: invokeinterface org/apache/http/protocol/HttpContext.setAttribute:(Ljava/lang/String;Ljava/lang/Object;)V
        //   386: aload           16
        //   388: invokevirtual   org/apache/http/impl/DefaultHttpClientConnection.isOpen:()Z
        //   391: ifne            403
        //   394: aload           16
        //   396: aload           30
        //   398: aload           13
        //   400: invokevirtual   org/apache/http/impl/DefaultHttpClientConnection.bind:(Ljava/net/Socket;Lorg/apache/http/params/HttpParams;)V
        //   403: aload_3        
        //   404: invokevirtual   java/net/URL.getPath:()Ljava/lang/String;
        //   407: astore          32
        //   409: aload_3        
        //   410: invokevirtual   java/net/URL.getQuery:()Ljava/lang/String;
        //   413: ifnull          446
        //   416: new             Ljava/lang/StringBuilder;
        //   419: dup            
        //   420: invokespecial   java/lang/StringBuilder.<init>:()V
        //   423: aload           32
        //   425: invokevirtual   java/lang/StringBuilder.append:(Ljava/lang/String;)Ljava/lang/StringBuilder;
        //   428: ldc_w           "?"
        //   431: invokevirtual   java/lang/StringBuilder.append:(Ljava/lang/String;)Ljava/lang/StringBuilder;
        //   434: aload_3        
        //   435: invokevirtual   java/net/URL.getQuery:()Ljava/lang/String;
        //   438: invokevirtual   java/lang/StringBuilder.append:(Ljava/lang/String;)Ljava/lang/StringBuilder;
        //   441: invokevirtual   java/lang/StringBuilder.toString:()Ljava/lang/String;
        //   444: astore          32
        //   446: new             Lorg/apache/http/message/BasicHttpRequest;
        //   449: dup            
        //   450: getstatic       com/whatsapp/b0.z:[Ljava/lang/String;
        //   453: bipush          12
        //   455: aaload         
        //   456: aload           32
        //   458: invokespecial   org/apache/http/message/BasicHttpRequest.<init>:(Ljava/lang/String;Ljava/lang/String;)V
        //   461: astore          33
        //   463: aload           33
        //   465: getstatic       com/whatsapp/b0.z:[Ljava/lang/String;
        //   468: bipush          6
        //   470: aaload         
        //   471: getstatic       com/whatsapp/b0.z:[Ljava/lang/String;
        //   474: bipush          8
        //   476: aaload         
        //   477: invokevirtual   org/apache/http/message/BasicHttpRequest.addHeader:(Ljava/lang/String;Ljava/lang/String;)V
        //   480: aload           33
        //   482: aload           13
        //   484: invokevirtual   org/apache/http/message/BasicHttpRequest.setParams:(Lorg/apache/http/params/HttpParams;)V
        //   487: aload           14
        //   489: aload           33
        //   491: aload           11
        //   493: aload           15
        //   495: invokevirtual   org/apache/http/protocol/HttpRequestExecutor.preProcess:(Lorg/apache/http/HttpRequest;Lorg/apache/http/protocol/HttpProcessor;Lorg/apache/http/protocol/HttpContext;)V
        //   498: aload           14
        //   500: aload           33
        //   502: aload           16
        //   504: aload           15
        //   506: invokevirtual   org/apache/http/protocol/HttpRequestExecutor.execute:(Lorg/apache/http/HttpRequest;Lorg/apache/http/HttpClientConnection;Lorg/apache/http/protocol/HttpContext;)Lorg/apache/http/HttpResponse;
        //   509: astore          34
        //   511: aload           34
        //   513: aload           13
        //   515: invokeinterface org/apache/http/HttpResponse.setParams:(Lorg/apache/http/params/HttpParams;)V
        //   520: aload           14
        //   522: aload           34
        //   524: aload           11
        //   526: aload           15
        //   528: invokevirtual   org/apache/http/protocol/HttpRequestExecutor.postProcess:(Lorg/apache/http/HttpResponse;Lorg/apache/http/protocol/HttpProcessor;Lorg/apache/http/protocol/HttpContext;)V
        //   531: aload           34
        //   533: invokeinterface org/apache/http/HttpResponse.getStatusLine:()Lorg/apache/http/StatusLine;
        //   538: invokeinterface org/apache/http/StatusLine.getStatusCode:()I
        //   543: istore          35
        //   545: iload           35
        //   547: sipush          500
        //   550: if_icmplt       23
        //   553: iload           12
        //   555: iload           10
        //   557: iconst_1       
        //   558: isub           
        //   559: if_icmpeq       23
        //   562: invokestatic    com/whatsapp/App.O:()Z
        //   565: istore          37
        //   567: iload           37
        //   569: ifeq            23
        //   572: new             Ljava/lang/StringBuilder;
        //   575: dup            
        //   576: invokespecial   java/lang/StringBuilder.<init>:()V
        //   579: getstatic       com/whatsapp/b0.z:[Ljava/lang/String;
        //   582: bipush          9
        //   584: aaload         
        //   585: invokevirtual   java/lang/StringBuilder.append:(Ljava/lang/String;)Ljava/lang/StringBuilder;
        //   588: iload           35
        //   590: invokevirtual   java/lang/StringBuilder.append:(I)Ljava/lang/StringBuilder;
        //   593: getstatic       com/whatsapp/b0.z:[Ljava/lang/String;
        //   596: iconst_1       
        //   597: aaload         
        //   598: invokevirtual   java/lang/StringBuilder.append:(Ljava/lang/String;)Ljava/lang/StringBuilder;
        //   601: iload           12
        //   603: invokevirtual   java/lang/StringBuilder.append:(I)Ljava/lang/StringBuilder;
        //   606: ldc_w           "/"
        //   609: invokevirtual   java/lang/StringBuilder.append:(Ljava/lang/String;)Ljava/lang/StringBuilder;
        //   612: iload           10
        //   614: invokevirtual   java/lang/StringBuilder.append:(I)Ljava/lang/StringBuilder;
        //   617: ldc_w           ")"
        //   620: invokevirtual   java/lang/StringBuilder.append:(Ljava/lang/String;)Ljava/lang/StringBuilder;
        //   623: invokevirtual   java/lang/StringBuilder.toString:()Ljava/lang/String;
        //   626: invokestatic    com/whatsapp/util/Log.w:(Ljava/lang/String;)V
        //   629: iload_1        
        //   630: ifne            23
        //   633: iload           12
        //   635: iconst_1       
        //   636: iadd           
        //   637: istore          21
        //   639: iload_1        
        //   640: ifeq            924
        //   643: aconst_null    
        //   644: areturn        
        //   645: astore          8
        //   647: aload           8
        //   649: athrow         
        //   650: aload           5
        //   652: invokeinterface java/util/List.size:()I
        //   657: istore          10
        //   659: goto            153
        //   662: astore          31
        //   664: aload           31
        //   666: athrow         
        //   667: astore          25
        //   669: new             Ljava/lang/StringBuilder;
        //   672: dup            
        //   673: invokespecial   java/lang/StringBuilder.<init>:()V
        //   676: getstatic       com/whatsapp/b0.z:[Ljava/lang/String;
        //   679: bipush          15
        //   681: aaload         
        //   682: invokevirtual   java/lang/StringBuilder.append:(Ljava/lang/String;)Ljava/lang/StringBuilder;
        //   685: iload           12
        //   687: invokevirtual   java/lang/StringBuilder.append:(I)Ljava/lang/StringBuilder;
        //   690: ldc_w           "/"
        //   693: invokevirtual   java/lang/StringBuilder.append:(Ljava/lang/String;)Ljava/lang/StringBuilder;
        //   696: iload           10
        //   698: invokevirtual   java/lang/StringBuilder.append:(I)Ljava/lang/StringBuilder;
        //   701: getstatic       com/whatsapp/b0.z:[Ljava/lang/String;
        //   704: iconst_3       
        //   705: aaload         
        //   706: invokevirtual   java/lang/StringBuilder.append:(Ljava/lang/String;)Ljava/lang/StringBuilder;
        //   709: aload           25
        //   711: invokevirtual   java/io/IOException.toString:()Ljava/lang/String;
        //   714: invokevirtual   java/lang/StringBuilder.append:(Ljava/lang/String;)Ljava/lang/StringBuilder;
        //   717: invokevirtual   java/lang/StringBuilder.toString:()Ljava/lang/String;
        //   720: invokestatic    com/whatsapp/util/Log.w:(Ljava/lang/String;)V
        //   723: iload           12
        //   725: iload           10
        //   727: iconst_1       
        //   728: isub           
        //   729: if_icmpeq       738
        //   732: invokestatic    com/whatsapp/App.O:()Z
        //   735: ifne            633
        //   738: aload           25
        //   740: athrow         
        //   741: astore          27
        //   743: aload           27
        //   745: athrow         
        //   746: astore          36
        //   748: aload           36
        //   750: athrow         
        //   751: astore          22
        //   753: new             Ljava/lang/StringBuilder;
        //   756: dup            
        //   757: invokespecial   java/lang/StringBuilder.<init>:()V
        //   760: getstatic       com/whatsapp/b0.z:[Ljava/lang/String;
        //   763: iconst_5       
        //   764: aaload         
        //   765: invokevirtual   java/lang/StringBuilder.append:(Ljava/lang/String;)Ljava/lang/StringBuilder;
        //   768: iload           12
        //   770: invokevirtual   java/lang/StringBuilder.append:(I)Ljava/lang/StringBuilder;
        //   773: ldc_w           "/"
        //   776: invokevirtual   java/lang/StringBuilder.append:(Ljava/lang/String;)Ljava/lang/StringBuilder;
        //   779: iload           10
        //   781: invokevirtual   java/lang/StringBuilder.append:(I)Ljava/lang/StringBuilder;
        //   784: getstatic       com/whatsapp/b0.z:[Ljava/lang/String;
        //   787: iconst_4       
        //   788: aaload         
        //   789: invokevirtual   java/lang/StringBuilder.append:(Ljava/lang/String;)Ljava/lang/StringBuilder;
        //   792: aload           22
        //   794: invokevirtual   org/apache/http/HttpException.toString:()Ljava/lang/String;
        //   797: invokevirtual   java/lang/StringBuilder.append:(Ljava/lang/String;)Ljava/lang/StringBuilder;
        //   800: invokevirtual   java/lang/StringBuilder.toString:()Ljava/lang/String;
        //   803: invokestatic    com/whatsapp/util/Log.w:(Ljava/lang/String;)V
        //   806: iload           12
        //   808: iload           10
        //   810: iconst_1       
        //   811: isub           
        //   812: if_icmpeq       821
        //   815: invokestatic    com/whatsapp/App.O:()Z
        //   818: ifne            633
        //   821: aload           22
        //   823: athrow         
        //   824: astore          24
        //   826: aload           24
        //   828: athrow         
        //   829: astore          26
        //   831: aload           26
        //   833: athrow         
        //   834: astore          23
        //   836: aload           23
        //   838: athrow         
        //   839: astore          18
        //   841: new             Ljava/lang/StringBuilder;
        //   844: dup            
        //   845: invokespecial   java/lang/StringBuilder.<init>:()V
        //   848: getstatic       com/whatsapp/b0.z:[Ljava/lang/String;
        //   851: bipush          17
        //   853: aaload         
        //   854: invokevirtual   java/lang/StringBuilder.append:(Ljava/lang/String;)Ljava/lang/StringBuilder;
        //   857: iload           12
        //   859: invokevirtual   java/lang/StringBuilder.append:(I)Ljava/lang/StringBuilder;
        //   862: ldc_w           "/"
        //   865: invokevirtual   java/lang/StringBuilder.append:(Ljava/lang/String;)Ljava/lang/StringBuilder;
        //   868: iload           10
        //   870: invokevirtual   java/lang/StringBuilder.append:(I)Ljava/lang/StringBuilder;
        //   873: getstatic       com/whatsapp/b0.z:[Ljava/lang/String;
        //   876: bipush          13
        //   878: aaload         
        //   879: invokevirtual   java/lang/StringBuilder.append:(Ljava/lang/String;)Ljava/lang/StringBuilder;
        //   882: aload           18
        //   884: invokevirtual   java/lang/Exception.toString:()Ljava/lang/String;
        //   887: invokevirtual   java/lang/StringBuilder.append:(Ljava/lang/String;)Ljava/lang/StringBuilder;
        //   890: invokevirtual   java/lang/StringBuilder.toString:()Ljava/lang/String;
        //   893: invokestatic    com/whatsapp/util/Log.w:(Ljava/lang/String;)V
        //   896: iload           12
        //   898: iload           10
        //   900: iconst_1       
        //   901: isub           
        //   902: if_icmpeq       911
        //   905: invokestatic    com/whatsapp/App.O:()Z
        //   908: ifne            633
        //   911: aload           18
        //   913: athrow         
        //   914: astore          20
        //   916: aload           20
        //   918: athrow         
        //   919: astore          19
        //   921: aload           19
        //   923: athrow         
        //   924: iload           21
        //   926: istore          12
        //   928: goto            208
        //   931: iload           6
        //   933: istore          7
        //   935: goto            130
        //    Exceptions:
        //  Try           Handler
        //  Start  End    Start  End    Type                            
        //  -----  -----  -----  -----  --------------------------------
        //  4      20     26     29     Ljava/net/MalformedURLException;
        //  29     38     64     77     Ljava/net/MalformedURLException;
        //  38     62     77     82     Ljava/net/MalformedURLException;
        //  96     105    107    112    Ljava/net/MalformedURLException;
        //  130    144    645    650    Ljava/net/MalformedURLException;
        //  293    372    667    834    Ljava/io/IOException;
        //  293    372    751    839    Lorg/apache/http/HttpException;
        //  293    372    839    924    Ljava/lang/Exception;
        //  372    403    662    667    Ljava/net/MalformedURLException;
        //  372    403    667    834    Ljava/io/IOException;
        //  372    403    751    839    Lorg/apache/http/HttpException;
        //  372    403    839    924    Ljava/lang/Exception;
        //  403    446    667    834    Ljava/io/IOException;
        //  403    446    751    839    Lorg/apache/http/HttpException;
        //  403    446    839    924    Ljava/lang/Exception;
        //  446    545    667    834    Ljava/io/IOException;
        //  446    545    751    839    Lorg/apache/http/HttpException;
        //  446    545    839    924    Ljava/lang/Exception;
        //  562    567    746    751    Ljava/net/MalformedURLException;
        //  562    567    667    834    Ljava/io/IOException;
        //  562    567    751    839    Lorg/apache/http/HttpException;
        //  562    567    839    924    Ljava/lang/Exception;
        //  572    629    667    834    Ljava/io/IOException;
        //  572    629    751    839    Lorg/apache/http/HttpException;
        //  572    629    839    924    Ljava/lang/Exception;
        //  664    667    667    834    Ljava/io/IOException;
        //  664    667    751    839    Lorg/apache/http/HttpException;
        //  664    667    839    924    Ljava/lang/Exception;
        //  669    723    829    834    Ljava/net/MalformedURLException;
        //  732    738    741    746    Ljava/net/MalformedURLException;
        //  738    741    741    746    Ljava/net/MalformedURLException;
        //  748    751    667    834    Ljava/io/IOException;
        //  748    751    751    839    Lorg/apache/http/HttpException;
        //  748    751    839    924    Ljava/lang/Exception;
        //  753    806    834    839    Ljava/net/MalformedURLException;
        //  815    821    824    829    Ljava/net/MalformedURLException;
        //  821    824    824    829    Ljava/net/MalformedURLException;
        //  831    834    741    746    Ljava/net/MalformedURLException;
        //  836    839    824    829    Ljava/net/MalformedURLException;
        //  841    896    919    924    Ljava/net/MalformedURLException;
        //  905    911    914    919    Ljava/net/MalformedURLException;
        //  911    914    914    919    Ljava/net/MalformedURLException;
        //  921    924    914    919    Ljava/net/MalformedURLException;
        // 
        // The error that occurred was:
        // 
        // java.lang.IndexOutOfBoundsException: Index: 427, Size: 427
        //     at java.util.ArrayList.rangeCheck(ArrayList.java:653)
        //     at java.util.ArrayList.get(ArrayList.java:429)
        //     at com.strobel.decompiler.ast.AstBuilder.convertToAst(AstBuilder.java:3303)
        //     at com.strobel.decompiler.ast.AstBuilder.build(AstBuilder.java:113)
        //     at com.strobel.decompiler.languages.java.ast.AstMethodBodyBuilder.createMethodBody(AstMethodBodyBuilder.java:210)
        //     at com.strobel.decompiler.languages.java.ast.AstMethodBodyBuilder.createMethodBody(AstMethodBodyBuilder.java:99)
        //     at com.strobel.decompiler.languages.java.ast.AstBuilder.createMethodBody(AstBuilder.java:757)
        //     at com.strobel.decompiler.languages.java.ast.AstBuilder.createMethod(AstBuilder.java:655)
        //     at com.strobel.decompiler.languages.java.ast.AstBuilder.addTypeMembers(AstBuilder.java:532)
        //     at com.strobel.decompiler.languages.java.ast.AstBuilder.createTypeCore(AstBuilder.java:499)
        //     at com.strobel.decompiler.languages.java.ast.AstBuilder.createTypeNoCache(AstBuilder.java:141)
        //     at com.strobel.decompiler.languages.java.ast.AstBuilder.createType(AstBuilder.java:130)
        //     at com.strobel.decompiler.languages.java.ast.AstBuilder.addType(AstBuilder.java:105)
        //     at com.strobel.decompiler.languages.java.JavaLanguage.buildAst(JavaLanguage.java:71)
        //     at com.strobel.decompiler.languages.java.JavaLanguage.decompileType(JavaLanguage.java:59)
        //     at com.strobel.decompiler.DecompilerDriver.decompileType(DecompilerDriver.java:317)
        //     at com.strobel.decompiler.DecompilerDriver.decompileJar(DecompilerDriver.java:238)
        //     at com.strobel.decompiler.DecompilerDriver.main(DecompilerDriver.java:123)
        // 
        throw new IllegalStateException("An error occurred while decompiling this method.");
    }
    
    private static List b(final String s) {
        if (s == null) {
            Log.e(b0.z[18]);
            return null;
        }
        return App.g.d(s);
    }
}
