// 
// Decompiled by Procyon v0.5.30
// 

package com.whatsapp;

import android.os.AsyncTask;

public class hq extends AsyncTask
{
    private static final String[] z;
    final VerifySms a;
    String b;
    ct c;
    lq d;
    String e;
    
    static {
        final String[] z2 = new String[76];
        String s = "\u0014\u0011\u001f&\u0003\u001b\u0002\u0002&\u0006\u0007[\u001f*\u0014\u0017\u0011\u001e;J";
        int n = -1;
        String[] array = z2;
        int n2 = 0;
        String intern = null;
    Label_1932:
        while (true) {
            final char[] charArray = s.toCharArray();
            for (int i = charArray.length, n3 = 0; i > n3; ++n3) {
                final char c = charArray[n3];
                char c2 = '\0';
                switch (n3 % 5) {
                    default: {
                        c2 = 'e';
                        break;
                    }
                    case 0: {
                        c2 = 'b';
                        break;
                    }
                    case 1: {
                        c2 = 't';
                        break;
                    }
                    case 2: {
                        c2 = 'm';
                        break;
                    }
                    case 3: {
                        c2 = 'O';
                        break;
                    }
                }
                charArray[n3] = (char)(c2 ^ c);
            }
            intern = new String(charArray).intern();
            switch (n) {
                default: {
                    array[n2] = intern;
                    s = "\u0014\u0011\u001f&\u0003\u001b\u0002\u0002&\u0006\u0007[\u001f*\u0014\u0017\u0011\u001e;J";
                    n2 = 1;
                    array = z2;
                    n = 0;
                    continue;
                }
                case 0: {
                    array[n2] = intern;
                    s = "\u0014\u0011\u001f&\u0003\u001b\u0002\u0002&\u0006\u0007[\u001f*\u0014\u0017\u0011\u001e;J";
                    n2 = 2;
                    array = z2;
                    n = 1;
                    continue;
                }
                case 1: {
                    array[n2] = intern;
                    s = "M\u001d\u0002*\u0017\u0010\u001b\u001fo";
                    n2 = 3;
                    array = z2;
                    n = 2;
                    continue;
                }
                case 2: {
                    array[n2] = intern;
                    s = "M\u0011\u001f=\n\u0010T";
                    n2 = 4;
                    array = z2;
                    n = 3;
                    continue;
                }
                case 3: {
                    array[n2] = intern;
                    n2 = 5;
                    array = z2;
                    s = "M\u0007\u0019.\u0011\u0017\u0007B*\u0017\u0010\u001b\u001f`\u001c\u0007\u0007@8\f\u0016\u001c@,\n\u0006\u0011";
                    n = 4;
                    continue;
                }
                case 4: {
                    array[n2] = intern;
                    n2 = 6;
                    s = "\u0010\u0011\u000b:\u0016\u0007\u0010";
                    n = 5;
                    array = z2;
                    continue;
                }
                case 5: {
                    array[n2] = intern;
                    n2 = 7;
                    s = "\u0014\u001b\u0004,\u0000";
                    n = 6;
                    array = z2;
                    continue;
                }
                case 6: {
                    array[n2] = intern;
                    n2 = 8;
                    s = "\u0014\u0011\u001f&\u0003\u001b\u0002\u0002&\u0006\u0007[\u001f*\u0014\u0017\u0011\u001e;J";
                    n = 7;
                    array = z2;
                    continue;
                }
                case 7: {
                    array[n2] = intern;
                    n2 = 9;
                    s = "\u0014\u0011\u001f&\u0003\u001b\u0002\u0002&\u0006\u0007[\u001f*\u0014\u0017\u0011\u001e;J";
                    n = 8;
                    array = z2;
                    continue;
                }
                case 8: {
                    array[n2] = intern;
                    n2 = 10;
                    s = "\u0014\u001b\u0004,\u0000O\u0011\u001f=\n\u0010Y\u0019 \nO\u0019\f!\u001cO\u0000\u001f&\u0000\u0011Y\f#\tO\u0019\b;\r\r\u0010\u001e";
                    n = 9;
                    array = z2;
                    continue;
                }
                case 9: {
                    array[n2] = intern;
                    n2 = 11;
                    s = "\u0014\u001b\u0004,\u0000O\u0004\u001f \u0013\u000b\u0010\b=H\u0017\u001a\u001f \u0010\u0016\u0015\u000f#\u0000";
                    n = 10;
                    array = z2;
                    continue;
                }
                case 10: {
                    array[n2] = intern;
                    n2 = 12;
                    s = "\u0014\u0011\u001f&\u0003\u001b\u0002\u0002&\u0006\u0007[\u001f*\u0014\u0017\u0011\u001e;J";
                    n = 11;
                    array = z2;
                    continue;
                }
                case 11: {
                    array[n2] = intern;
                    n2 = 13;
                    s = "M\u0016\u0001 \u0006\t\u0011\t";
                    n = 12;
                    array = z2;
                    continue;
                }
                case 12: {
                    array[n2] = intern;
                    n2 = 14;
                    s = "M\u0000\u0002 H\u0010\u0011\u000e*\u000b\u0016[\u0019&\b\u0007Y\u0003 \u0011O\u001d\u0003;";
                    n = 13;
                    array = z2;
                    continue;
                }
                case 13: {
                    array[n2] = intern;
                    n2 = 15;
                    s = "\u0014\u001b\u0004,\u0000O\u0011\u001f=\n\u0010";
                    n = 14;
                    array = z2;
                    continue;
                }
                case 14: {
                    array[n2] = intern;
                    n2 = 16;
                    s = "B[\u001b*\u0017\u000b\u0012\u0004*\u0001M\u001b\u0006`\u0003\u0003\u001d\u0001*\u0001O\u0000\u0002b\u0010\u0012\u0010\f;\u0000O\u0011\u0015?\f\u0010\u0015\u0019&\n\f";
                    n = 15;
                    array = z2;
                    continue;
                }
                case 15: {
                    array[n2] = intern;
                    n2 = 17;
                    s = "\u000f\u001d\u001e<\f\f\u0013M?\u0004\u0010\u0015\u0000*\u0011\u0007\u0006";
                    n = 16;
                    array = z2;
                    continue;
                }
                case 16: {
                    array[n2] = intern;
                    n2 = 18;
                    s = "\u0014\u0011\u001f&\u0003\u001b\u0002\u0002&\u0006\u0007[\u001f*\u0014\u0017\u0011\u001e;J";
                    n = 17;
                    array = z2;
                    continue;
                }
                case 17: {
                    array[n2] = intern;
                    n2 = 19;
                    s = "\u0014\u0011\u001f&\u0003\u001b\u0002\u0002&\u0006\u0007[\u001f*\u0014\u0017\u0011\u001e;J";
                    n = 18;
                    array = z2;
                    continue;
                }
                case 18: {
                    array[n2] = intern;
                    n2 = 20;
                    s = "\u0014\u001b\u0004,\u0000O\u0000\u0002 H\u000f\u0015\u00036H\u0005\u0001\b<\u0016\u0007\u0007";
                    n = 19;
                    array = z2;
                    continue;
                }
                case 19: {
                    array[n2] = intern;
                    n2 = 21;
                    s = "\u0014\u0011\u001f&\u0003\u001b\u0002\u0002&\u0006\u0007[\u001f*\u0014\u0017\u0011\u001e;J";
                    n = 20;
                    array = z2;
                    continue;
                }
                case 20: {
                    array[n2] = intern;
                    n2 = 22;
                    s = "\u0014\u001b\u0004,\u0000O\u0016\u0001 \u0006\t\u0011\t";
                    n = 21;
                    array = z2;
                    continue;
                }
                case 21: {
                    array[n2] = intern;
                    n2 = 23;
                    s = "M\u0000\u0002 H\u000f\u0015\u00036H\u0016\u0006\u0004*\u0016O\u0015\u0001#H\u000f\u0011\u0019'\n\u0006\u0007";
                    n = 22;
                    array = z2;
                    continue;
                }
                case 22: {
                    array[n2] = intern;
                    n2 = 24;
                    s = "\u0014\u0011\u001f&\u0003\u001b\u0002\u0002&\u0006\u0007[\u001f*\u0014\u0017\u0011\u001e;J";
                    n = 23;
                    array = z2;
                    continue;
                }
                case 23: {
                    array[n2] = intern;
                    n2 = 25;
                    s = "\u0014\u0011\u001f&\u0003\u001b\u0002\u0002&\u0006\u0007[\u001f*\u0014\u0017\u0011\u001e;J";
                    n = 24;
                    array = z2;
                    continue;
                }
                case 24: {
                    array[n2] = intern;
                    n2 = 26;
                    s = "\n\u0000\u0019?\u0016X[B8\r\u0003\u0000\u001e.\u0015\u0012Z\u000e \bM\u0015\u0003+\u0017\r\u001d\t";
                    n = 25;
                    array = z2;
                    continue;
                }
                case 25: {
                    array[n2] = intern;
                    n2 = 27;
                    s = "\u0014\u0011\u001f&\u0003\u001b\u0002\u0002&\u0006\u0007[\u001f*\u0014\u0017\u0011\u001e;J";
                    n = 26;
                    array = z2;
                    continue;
                }
                case 26: {
                    array[n2] = intern;
                    n2 = 28;
                    s = "\u0014\u001b\u0004,\u0000O\u0004\u001f \u0013\u000b\u0010\b=H\u0016\u001d\u0000*\n\u0017\u0000";
                    n = 27;
                    array = z2;
                    continue;
                }
                case 27: {
                    array[n2] = intern;
                    n2 = 29;
                    s = "\u0014\u0011\u001f&\u0003\u001b\u0002\u0002&\u0006\u0007[\u001f*\u0014\u0017\u0011\u001e;J";
                    n = 28;
                    array = z2;
                    continue;
                }
                case 28: {
                    array[n2] = intern;
                    n2 = 30;
                    s = "\u0014\u0011\u001f&\u0003\u001b\u0002\u0002&\u0006\u0007[\u001f*\u0014\u0017\u0011\u001e;J";
                    n = 29;
                    array = z2;
                    continue;
                }
                case 29: {
                    array[n2] = intern;
                    n2 = 31;
                    s = "\u0014\u0011\u001f&\u0003\u001b\u0002\u0002&\u0006\u0007[\u001f*\u0014\u0017\u0011\u001e;J";
                    n = 30;
                    array = z2;
                    continue;
                }
                case 30: {
                    array[n2] = intern;
                    n2 = 32;
                    s = "\u0014\u0011\u001f&\u0003\u001b\u0002\u0002&\u0006\u0007[\u001f*\u0014\u0017\u0011\u001e;J";
                    n = 31;
                    array = z2;
                    continue;
                }
                case 31: {
                    array[n2] = intern;
                    n2 = 33;
                    s = "\u0014\u001b\u0004,\u0000O\u0000\b\"\u0015O\u0001\u0003.\u0013\u0003\u001d\u0001";
                    n = 32;
                    array = z2;
                    continue;
                }
                case 32: {
                    array[n2] = intern;
                    n2 = 34;
                    s = "M\u0016\f+H\u0016\u001b\u0006*\u000b";
                    n = 33;
                    array = z2;
                    continue;
                }
                case 33: {
                    array[n2] = intern;
                    n2 = 35;
                    s = "\u0014\u0011\u001f&\u0003\u001b\u0002\u0002&\u0006\u0007[\u001f*\u0014\u0017\u0011\u001e;J";
                    n = 34;
                    array = z2;
                    continue;
                }
                case 34: {
                    array[n2] = intern;
                    n2 = 36;
                    s = "\u0014\u0011\u001f&\u0003\u001b\u0002\u0002&\u0006\u0007[\u001f*\u0014\u0017\u0011\u001e;J";
                    n = 35;
                    array = z2;
                    continue;
                }
                case 35: {
                    array[n2] = intern;
                    n2 = 37;
                    s = "M\u0001\u0003<\u0015\u0007\u0017\u0004)\f\u0007\u0010";
                    n = 36;
                    array = z2;
                    continue;
                }
                case 36: {
                    array[n2] = intern;
                    n2 = 38;
                    s = "\u0014\u0011\u001f&\u0003\u001b\u0002\u0002&\u0006\u0007[\u001f*\u0014\u0017\u0011\u001e;J";
                    n = 37;
                    array = z2;
                    continue;
                }
                case 37: {
                    array[n2] = intern;
                    n2 = 39;
                    s = "\u0014\u001b\u0004,\u0000O\u0000\u0002 H\u0010\u0011\u000e*\u000b\u0016";
                    n = 38;
                    array = z2;
                    continue;
                }
                case 38: {
                    array[n2] = intern;
                    n2 = 40;
                    s = "M\u0000\b\"\u0015O\u0001\u0003.\u0013\u0003\u001d\u0001";
                    n = 39;
                    array = z2;
                    continue;
                }
                case 39: {
                    array[n2] = intern;
                    n2 = 41;
                    s = "\u0014\u0011\u001f&\u0003\u001b\u0002\u0002&\u0006\u0007[\u001f*\u0014\u0017\u0011\u001e;J";
                    n = 40;
                    array = z2;
                    continue;
                }
                case 40: {
                    array[n2] = intern;
                    n2 = 42;
                    s = "M\u0019\u0004<\u0016\u000b\u001a\nb\u0015\u0003\u0006\f\"\u0000\u0016\u0011\u001f";
                    n = 41;
                    array = z2;
                    continue;
                }
                case 41: {
                    array[n2] = intern;
                    n2 = 43;
                    s = "\u0014\u0011\u001f&\u0003\u001b\u0002\u0002&\u0006\u0007[\u001f*\u0014\u0017\u0011\u001e;J";
                    n = 42;
                    array = z2;
                    continue;
                }
                case 42: {
                    array[n2] = intern;
                    n2 = 44;
                    s = "M\u001a\b7\u0011O\u0019\b;\r\r\u0010";
                    n = 43;
                    array = z2;
                    continue;
                }
                case 43: {
                    array[n2] = intern;
                    n2 = 45;
                    s = "\u0014\u001b\u0004,\u0000O\u001a\b7\u0011O\u0019\b;\r\r\u0010";
                    n = 44;
                    array = z2;
                    continue;
                }
                case 44: {
                    array[n2] = intern;
                    n2 = 46;
                    s = "M\u0000\u0002 H\u000f\u0015\u00036H\u0005\u0001\b<\u0016\u0007\u0007";
                    n = 45;
                    array = z2;
                    continue;
                }
                case 45: {
                    array[n2] = intern;
                    n2 = 47;
                    s = "M\u0000\u0002 H\u0010\u0011\u000e*\u000b\u0016[\u0019&\b\u0007Y\u0003 \u0011O\u001d\u0003;";
                    n = 46;
                    array = z2;
                    continue;
                }
                case 46: {
                    array[n2] = intern;
                    n2 = 48;
                    s = "M\u0000\u001f&\u0000\u0006\u0000\u0002 \b\u0003\u001a\u0014;\f\u000f\u0011\u001e.\t\u000e\u0019\b;\r\r\u0010\u001e`\u0011\u000b\u0019\bb\u000b\r\u0000@&\u000b\u0016";
                    n = 47;
                    array = z2;
                    continue;
                }
                case 47: {
                    array[n2] = intern;
                    n2 = 49;
                    s = "M\u0000\u0002 H\u000f\u0015\u00036H\u0005\u0001\b<\u0016\u0007\u0007B;\f\u000f\u0011@!\n\u0016Y\u0004!\u0011";
                    n = 48;
                    array = z2;
                    continue;
                }
                case 48: {
                    array[n2] = intern;
                    n2 = 50;
                    s = "M\u0000\u001f&\u0000\u0006\u0000\u0002 \b\u0003\u001a\u0014;\f\u000f\u0011\u001e.\t\u000e\u0019\b;\r\r\u0010\u001e`\u0011\u000b\u0019\bb\u000b\r\u0000@&\u000b\u0016";
                    n = 49;
                    array = z2;
                    continue;
                }
                case 49: {
                    array[n2] = intern;
                    n2 = 51;
                    s = "\u0014\u0011\u001f&\u0003\u001b\u0002\u0002&\u0006\u0007[\u001f*\u0014\u0017\u0011\u001e;J";
                    n = 50;
                    array = z2;
                    continue;
                }
                case 50: {
                    array[n2] = intern;
                    n2 = 52;
                    s = "\u0014\u001b\u0004,\u0000O\u0016\f+H\u0016\u001b\u0006*\u000b";
                    n = 51;
                    array = z2;
                    continue;
                }
                case 51: {
                    array[n2] = intern;
                    n2 = 53;
                    s = "M\u001a\u0002b\u0017\r\u0001\u0019*\u0016";
                    n = 52;
                    array = z2;
                    continue;
                }
                case 52: {
                    array[n2] = intern;
                    n2 = 54;
                    s = "M\u0017\u0002+\u0000M\u001b\u0006";
                    n = 53;
                    array = z2;
                    continue;
                }
                case 53: {
                    array[n2] = intern;
                    n2 = 55;
                    s = "M\u0016\f+H\u0012\u0015\u001f.\b\u0007\u0000\b=";
                    n = 54;
                    array = z2;
                    continue;
                }
                case 54: {
                    array[n2] = intern;
                    n2 = 56;
                    s = "M\u0004\u001f \u0013\u000b\u0010\b=H\u0016\u001d\u0000*\n\u0017\u0000";
                    n = 55;
                    array = z2;
                    continue;
                }
                case 55: {
                    array[n2] = intern;
                    n2 = 57;
                    s = "\u0014\u0011\u001f&\u0003\u001b\u0002\u0002&\u0006\u0007[\u001f*\u0014\u0017\u0011\u001e;J";
                    n = 56;
                    array = z2;
                    continue;
                }
                case 56: {
                    array[n2] = intern;
                    n2 = 58;
                    s = "M\u0000\u0002 H\u0010\u0011\u000e*\u000b\u0016[\u0019&\b\u0007Y\u0003 \u0011O\u001d\u0003;";
                    n = 57;
                    array = z2;
                    continue;
                }
                case 57: {
                    array[n2] = intern;
                    n2 = 59;
                    s = "M\u0000\u0002 H\u000f\u0015\u00036H\u0016\u0006\u0004*\u0016";
                    n = 58;
                    array = z2;
                    continue;
                }
                case 58: {
                    array[n2] = intern;
                    n2 = 60;
                    s = "\u0014\u001b\u0004,\u0000O\u0019\u0004<\u0016\u000b\u001a\nb\u0015\u0003\u0006\f\"";
                    n = 59;
                    array = z2;
                    continue;
                }
                case 59: {
                    array[n2] = intern;
                    n2 = 61;
                    s = "\u0014\u0011\u001f&\u0003\u001b\u0002\u0002&\u0006\u0007[\u001f*\u0014\u0017\u0011\u001e;J";
                    n = 60;
                    array = z2;
                    continue;
                }
                case 60: {
                    array[n2] = intern;
                    n2 = 62;
                    s = "\u0000\u0015\to\u0015\u0003\u0006\f\"\u0000\u0016\u0011\u001f";
                    n = 61;
                    array = z2;
                    continue;
                }
                case 61: {
                    array[n2] = intern;
                    n2 = 63;
                    s = "\u0014\u0011\u001f&\u0003\u001b\u0002\u0002&\u0006\u0007[\u001f*\u0014\u0017\u0011\u001e;J";
                    n = 62;
                    array = z2;
                    continue;
                }
                case 62: {
                    array[n2] = intern;
                    n2 = 64;
                    s = "M\u0000\u0002 H\u0010\u0011\u000e*\u000b\u0016T";
                    n = 63;
                    array = z2;
                    continue;
                }
                case 63: {
                    array[n2] = intern;
                    n2 = 65;
                    s = "\u0014\u001b\u0004,\u0000O\u001a\u0002b\u0017\r\u0001\u0019*\u0016";
                    n = 64;
                    array = z2;
                    continue;
                }
                case 64: {
                    array[n2] = intern;
                    n2 = 66;
                    s = "\u0014\u001b\u0004,\u0000O\u0002\b=\u0016\u000b\u001b\u0003b\u0011\r\u001b@ \t\u0006";
                    n = 65;
                    array = z2;
                    continue;
                }
                case 65: {
                    array[n2] = intern;
                    n2 = 67;
                    s = "\u0014\u0011\u001f&\u0003\u001b\u0002\u0002&\u0006\u0007[\u001f*\u0014\u0017\u0011\u001e;J";
                    n = 66;
                    array = z2;
                    continue;
                }
                case 66: {
                    array[n2] = intern;
                    n2 = 68;
                    s = "M\u0000\u0002 H\u0010\u0011\u000e*\u000b\u0016[\u0019&\b\u0007Y\u0003 \u0011O\u001d\u0003;";
                    n = 67;
                    array = z2;
                    continue;
                }
                case 67: {
                    array[n2] = intern;
                    n2 = 69;
                    s = "M\u0004\u001f \u0013\u000b\u0010\b=H\u0017\u001a\u001f \u0010\u0016\u0015\u000f#\u0000";
                    n = 68;
                    array = z2;
                    continue;
                }
                case 68: {
                    array[n2] = intern;
                    n2 = 70;
                    s = "M\u0000\b\"\u0015\r\u0006\f=\f\u000e\r@:\u000b\u0003\u0002\f&\t\u0003\u0016\u0001*J\u0017\u001a\f-\t\u0007Y\u0019 H\u0012\u0015\u001f<\u0000O\u0006\b;\u0017\u001b5\u000b;\u0000\u0010";
                    n = 69;
                    array = z2;
                    continue;
                }
                case 69: {
                    array[n2] = intern;
                    n2 = 71;
                    s = "M\u0002\b=\u0016\u000b\u001b\u0003b\u0011\r\u001b@ \t\u0006";
                    n = 70;
                    array = z2;
                    continue;
                }
                case 70: {
                    array[n2] = intern;
                    n2 = 72;
                    s = "\u0014\u0011\u001f&\u0003\u001b\u0002\u0002&\u0006\u0007[\u001f*\u0014\u0017\u0011\u001e;J";
                    n = 71;
                    array = z2;
                    continue;
                }
                case 71: {
                    array[n2] = intern;
                    n2 = 73;
                    s = "\u0014\u0011\u001f&\u0003\u001b\u0002\u0002&\u0006\u0007[\u001f*\u0014\u0017\u0011\u001e;J";
                    n = 72;
                    array = z2;
                    continue;
                }
                case 72: {
                    array[n2] = intern;
                    n2 = 74;
                    s = "\u0014\u001b\u0004,\u0000O\u0011\u001f=\n\u0010Y\u0019 \nO\u0019\f!\u001cO\u0000\u001f&\u0000\u0011";
                    n = 73;
                    array = z2;
                    continue;
                }
                case 73: {
                    array[n2] = intern;
                    n2 = 75;
                    s = "\u0014\u001b\u0004,\u0000O\u0016\f+H\u0012\u0015\u001f.\b";
                    n = 74;
                    array = z2;
                    continue;
                }
                case 74: {
                    break Label_1932;
                }
            }
        }
        array[n2] = intern;
        z = z2;
    }
    
    protected hq(final VerifySms a) {
        this.a = a;
        this.e = hq.z[7];
        this.b = "v";
        this.d = new lq(wo.ERROR_UNSPECIFIED);
    }
    
    protected pf a(final String[] p0) {
        // 
        // This method could not be decompiled.
        // 
        // Original Bytecode:
        // 
        //     0: getstatic       com/whatsapp/App.I:Z
        //     3: istore_2       
        //     4: getstatic       com/whatsapp/pf.ERROR_UNSPECIFIED:Lcom/whatsapp/pf;
        //     7: astore_3       
        //     8: aload_0        
        //     9: aload_0        
        //    10: getfield        com/whatsapp/hq.a:Lcom/whatsapp/VerifySms;
        //    13: aload_0        
        //    14: getfield        com/whatsapp/hq.a:Lcom/whatsapp/VerifySms;
        //    17: invokestatic    com/whatsapp/VerifySms.e:(Lcom/whatsapp/VerifySms;)Ljava/lang/String;
        //    20: aload_0        
        //    21: getfield        com/whatsapp/hq.a:Lcom/whatsapp/VerifySms;
        //    24: invokestatic    com/whatsapp/VerifySms.y:(Lcom/whatsapp/VerifySms;)Ljava/lang/String;
        //    27: aload_0        
        //    28: getfield        com/whatsapp/hq.e:Ljava/lang/String;
        //    31: getstatic       com/whatsapp/VerifyNumber.m:Ljava/lang/String;
        //    34: invokestatic    com/whatsapp/VerifyNumber.a:(Landroid/content/Context;Ljava/lang/String;Ljava/lang/String;Ljava/lang/String;Ljava/lang/String;)Lcom/whatsapp/ct;
        //    37: putfield        com/whatsapp/hq.c:Lcom/whatsapp/ct;
        //    40: aload_0        
        //    41: getfield        com/whatsapp/hq.c:Lcom/whatsapp/ct;
        //    44: getfield        com/whatsapp/ct.b:Lcom/whatsapp/pf;
        //    47: astore          5
        //    49: aload           5
        //    51: getstatic       com/whatsapp/pf.YES_WITH_CODE:Lcom/whatsapp/pf;
        //    54: if_acmpne       97
        //    57: new             Ljava/lang/StringBuilder;
        //    60: dup            
        //    61: invokespecial   java/lang/StringBuilder.<init>:()V
        //    64: getstatic       com/whatsapp/hq.z:[Ljava/lang/String;
        //    67: iconst_2       
        //    68: aaload         
        //    69: invokevirtual   java/lang/StringBuilder.append:(Ljava/lang/String;)Ljava/lang/StringBuilder;
        //    72: aload_0        
        //    73: getfield        com/whatsapp/hq.b:Ljava/lang/String;
        //    76: invokevirtual   java/lang/StringBuilder.append:(Ljava/lang/String;)Ljava/lang/StringBuilder;
        //    79: getstatic       com/whatsapp/hq.z:[Ljava/lang/String;
        //    82: iconst_5       
        //    83: aaload         
        //    84: invokevirtual   java/lang/StringBuilder.append:(Ljava/lang/String;)Ljava/lang/StringBuilder;
        //    87: invokevirtual   java/lang/StringBuilder.toString:()Ljava/lang/String;
        //    90: invokestatic    com/whatsapp/util/Log.e:(Ljava/lang/String;)V
        //    93: iload_2        
        //    94: ifeq            134
        //    97: getstatic       com/whatsapp/pf.YES:Lcom/whatsapp/pf;
        //   100: astore          15
        //   102: aload           5
        //   104: aload           15
        //   106: if_acmpne       134
        //   109: aload_0        
        //   110: getfield        com/whatsapp/hq.c:Lcom/whatsapp/ct;
        //   113: getfield        com/whatsapp/ct.c:I
        //   116: istore          16
        //   118: iload           16
        //   120: ifeq            134
        //   123: aload_0        
        //   124: getfield        com/whatsapp/hq.c:Lcom/whatsapp/ct;
        //   127: getfield        com/whatsapp/ct.c:I
        //   130: invokestatic    com/whatsapp/VerifySms.i:(I)I
        //   133: pop            
        //   134: aload           5
        //   136: areturn        
        //   137: astore          11
        //   139: aload           11
        //   141: athrow         
        //   142: astore          12
        //   144: aload           12
        //   146: athrow         
        //   147: astore          13
        //   149: aload           13
        //   151: athrow         
        //   152: astore          14
        //   154: aload           14
        //   156: athrow         
        //   157: astore          7
        //   159: aload           7
        //   161: invokevirtual   java/io/IOException.toString:()Ljava/lang/String;
        //   164: astore          8
        //   166: new             Ljava/lang/StringBuilder;
        //   169: dup            
        //   170: invokespecial   java/lang/StringBuilder.<init>:()V
        //   173: getstatic       com/whatsapp/hq.z:[Ljava/lang/String;
        //   176: iconst_0       
        //   177: aaload         
        //   178: invokevirtual   java/lang/StringBuilder.append:(Ljava/lang/String;)Ljava/lang/StringBuilder;
        //   181: aload_0        
        //   182: getfield        com/whatsapp/hq.b:Ljava/lang/String;
        //   185: invokevirtual   java/lang/StringBuilder.append:(Ljava/lang/String;)Ljava/lang/StringBuilder;
        //   188: getstatic       com/whatsapp/hq.z:[Ljava/lang/String;
        //   191: iconst_3       
        //   192: aaload         
        //   193: invokevirtual   java/lang/StringBuilder.append:(Ljava/lang/String;)Ljava/lang/StringBuilder;
        //   196: aload           8
        //   198: invokevirtual   java/lang/StringBuilder.append:(Ljava/lang/String;)Ljava/lang/StringBuilder;
        //   201: invokevirtual   java/lang/StringBuilder.toString:()Ljava/lang/String;
        //   204: invokestatic    com/whatsapp/util/Log.e:(Ljava/lang/String;)V
        //   207: aload           8
        //   209: ifnull          239
        //   212: aload           8
        //   214: getstatic       com/whatsapp/hq.z:[Ljava/lang/String;
        //   217: bipush          6
        //   219: aaload         
        //   220: invokevirtual   java/lang/String.contains:(Ljava/lang/CharSequence;)Z
        //   223: istore          10
        //   225: iload           10
        //   227: ifeq            239
        //   230: getstatic       com/whatsapp/pf.ERROR_UNSPECIFIED:Lcom/whatsapp/pf;
        //   233: astore          5
        //   235: iload_2        
        //   236: ifeq            134
        //   239: getstatic       com/whatsapp/pf.ERROR_CONNECTIVITY:Lcom/whatsapp/pf;
        //   242: areturn        
        //   243: astore          9
        //   245: aload           9
        //   247: athrow         
        //   248: astore          4
        //   250: aload_3        
        //   251: astore          5
        //   253: aload           4
        //   255: astore          6
        //   257: new             Ljava/lang/StringBuilder;
        //   260: dup            
        //   261: invokespecial   java/lang/StringBuilder.<init>:()V
        //   264: getstatic       com/whatsapp/hq.z:[Ljava/lang/String;
        //   267: iconst_1       
        //   268: aaload         
        //   269: invokevirtual   java/lang/StringBuilder.append:(Ljava/lang/String;)Ljava/lang/StringBuilder;
        //   272: aload_0        
        //   273: getfield        com/whatsapp/hq.b:Ljava/lang/String;
        //   276: invokevirtual   java/lang/StringBuilder.append:(Ljava/lang/String;)Ljava/lang/StringBuilder;
        //   279: getstatic       com/whatsapp/hq.z:[Ljava/lang/String;
        //   282: iconst_4       
        //   283: aaload         
        //   284: invokevirtual   java/lang/StringBuilder.append:(Ljava/lang/String;)Ljava/lang/StringBuilder;
        //   287: invokevirtual   java/lang/StringBuilder.toString:()Ljava/lang/String;
        //   290: aload           6
        //   292: invokestatic    com/whatsapp/util/Log.b:(Ljava/lang/String;Ljava/lang/Throwable;)V
        //   295: aload           5
        //   297: areturn        
        //   298: astore          6
        //   300: goto            257
        //    Exceptions:
        //  Try           Handler
        //  Start  End    Start  End    Type                 
        //  -----  -----  -----  -----  ---------------------
        //  8      49     157    248    Ljava/io/IOException;
        //  8      49     248    257    Ljava/lang/Exception;
        //  49     93     137    142    Ljava/io/IOException;
        //  49     93     298    303    Ljava/lang/Exception;
        //  97     102    142    147    Ljava/io/IOException;
        //  97     102    298    303    Ljava/lang/Exception;
        //  109    118    147    152    Ljava/io/IOException;
        //  109    118    298    303    Ljava/lang/Exception;
        //  123    134    152    157    Ljava/io/IOException;
        //  123    134    298    303    Ljava/lang/Exception;
        //  139    142    142    147    Ljava/io/IOException;
        //  139    142    298    303    Ljava/lang/Exception;
        //  144    147    147    152    Ljava/io/IOException;
        //  144    147    298    303    Ljava/lang/Exception;
        //  149    152    152    157    Ljava/io/IOException;
        //  149    152    298    303    Ljava/lang/Exception;
        //  154    157    157    248    Ljava/io/IOException;
        //  154    157    298    303    Ljava/lang/Exception;
        //  166    207    243    248    Ljava/io/IOException;
        //  212    225    243    248    Ljava/io/IOException;
        // 
        // The error that occurred was:
        // 
        // java.lang.IndexOutOfBoundsException: Index: 0, Size: 0
        //     at java.util.ArrayList.rangeCheck(ArrayList.java:653)
        //     at java.util.ArrayList.get(ArrayList.java:429)
        //     at com.strobel.decompiler.ast.AstBuilder.convertLocalVariables(AstBuilder.java:3035)
        //     at com.strobel.decompiler.ast.AstBuilder.performStackAnalysis(AstBuilder.java:2445)
        //     at com.strobel.decompiler.ast.AstBuilder.build(AstBuilder.java:108)
        //     at com.strobel.decompiler.languages.java.ast.AstMethodBodyBuilder.createMethodBody(AstMethodBodyBuilder.java:210)
        //     at com.strobel.decompiler.languages.java.ast.AstMethodBodyBuilder.createMethodBody(AstMethodBodyBuilder.java:99)
        //     at com.strobel.decompiler.languages.java.ast.AstBuilder.createMethodBody(AstBuilder.java:757)
        //     at com.strobel.decompiler.languages.java.ast.AstBuilder.createMethod(AstBuilder.java:655)
        //     at com.strobel.decompiler.languages.java.ast.AstBuilder.addTypeMembers(AstBuilder.java:532)
        //     at com.strobel.decompiler.languages.java.ast.AstBuilder.createTypeCore(AstBuilder.java:499)
        //     at com.strobel.decompiler.languages.java.ast.AstBuilder.createTypeNoCache(AstBuilder.java:141)
        //     at com.strobel.decompiler.languages.java.ast.AstBuilder.createType(AstBuilder.java:130)
        //     at com.strobel.decompiler.languages.java.ast.AstBuilder.addType(AstBuilder.java:105)
        //     at com.strobel.decompiler.languages.java.JavaLanguage.buildAst(JavaLanguage.java:71)
        //     at com.strobel.decompiler.languages.java.JavaLanguage.decompileType(JavaLanguage.java:59)
        //     at com.strobel.decompiler.DecompilerDriver.decompileType(DecompilerDriver.java:317)
        //     at com.strobel.decompiler.DecompilerDriver.decompileJar(DecompilerDriver.java:238)
        //     at com.strobel.decompiler.DecompilerDriver.main(DecompilerDriver.java:123)
        // 
        throw new IllegalStateException("An error occurred while decompiling this method.");
    }
    
    protected void a(final pf p0) {
        // 
        // This method could not be decompiled.
        // 
        // Original Bytecode:
        // 
        //     0: getstatic       com/whatsapp/App.I:Z
        //     3: istore_2       
        //     4: ldc             ""
        //     6: putstatic       com/whatsapp/VerifyNumber.m:Ljava/lang/String;
        //     9: aload_0        
        //    10: getfield        com/whatsapp/hq.a:Lcom/whatsapp/VerifySms;
        //    13: bipush          25
        //    15: invokevirtual   com/whatsapp/VerifySms.removeDialog:(I)V
        //    18: aload_1        
        //    19: getstatic       com/whatsapp/pf.OK:Lcom/whatsapp/pf;
        //    22: if_acmpne       134
        //    25: new             Ljava/lang/StringBuilder;
        //    28: dup            
        //    29: invokespecial   java/lang/StringBuilder.<init>:()V
        //    32: getstatic       com/whatsapp/hq.z:[Ljava/lang/String;
        //    35: bipush          38
        //    37: aaload         
        //    38: invokevirtual   java/lang/StringBuilder.append:(Ljava/lang/String;)Ljava/lang/StringBuilder;
        //    41: aload_0        
        //    42: getfield        com/whatsapp/hq.b:Ljava/lang/String;
        //    45: invokevirtual   java/lang/StringBuilder.append:(Ljava/lang/String;)Ljava/lang/StringBuilder;
        //    48: getstatic       com/whatsapp/hq.z:[Ljava/lang/String;
        //    51: bipush          54
        //    53: aaload         
        //    54: invokevirtual   java/lang/StringBuilder.append:(Ljava/lang/String;)Ljava/lang/StringBuilder;
        //    57: invokevirtual   java/lang/StringBuilder.toString:()Ljava/lang/String;
        //    60: invokestatic    com/whatsapp/util/Log.i:(Ljava/lang/String;)V
        //    63: getstatic       com/whatsapp/App.aq:Lcom/whatsapp/App;
        //    66: aload_0        
        //    67: getfield        com/whatsapp/hq.c:Lcom/whatsapp/ct;
        //    70: getfield        com/whatsapp/ct.f:Ljava/lang/String;
        //    73: invokestatic    com/whatsapp/App.f:(Landroid/content/Context;Ljava/lang/String;)V
        //    76: aload_0        
        //    77: getfield        com/whatsapp/hq.c:Lcom/whatsapp/ct;
        //    80: getfield        com/whatsapp/ct.e:[B
        //    83: aload_0        
        //    84: getfield        com/whatsapp/hq.c:Lcom/whatsapp/ct;
        //    87: getfield        com/whatsapp/ct.f:Ljava/lang/String;
        //    90: invokestatic    com/whatsapp/al5.c:([BLjava/lang/String;)Z
        //    93: pop            
        //    94: aload_0        
        //    95: getfield        com/whatsapp/hq.c:Lcom/whatsapp/ct;
        //    98: getfield        com/whatsapp/ct.d:Z
        //   101: invokestatic    com/whatsapp/VerifyNumber.a:(Z)Z
        //   104: pop            
        //   105: getstatic       com/whatsapp/h6.WHATSAPP_INITIATED:Lcom/whatsapp/h6;
        //   108: ldc2_w          1000
        //   111: aload_0        
        //   112: getfield        com/whatsapp/hq.c:Lcom/whatsapp/ct;
        //   115: getfield        com/whatsapp/ct.a:J
        //   118: lmul           
        //   119: invokestatic    com/whatsapp/ade.a:(Lcom/whatsapp/h6;J)V
        //   122: aload_0        
        //   123: getfield        com/whatsapp/hq.a:Lcom/whatsapp/VerifySms;
        //   126: iconst_1       
        //   127: invokestatic    com/whatsapp/VerifySms.b:(Lcom/whatsapp/VerifySms;Z)V
        //   130: iload_2        
        //   131: ifeq            321
        //   134: getstatic       com/whatsapp/pf.YES:Lcom/whatsapp/pf;
        //   137: astore          7
        //   139: aload_1        
        //   140: aload           7
        //   142: if_acmpeq       2741
        //   145: getstatic       com/whatsapp/pf.ERROR_TEMPORARILY_UNAVAILABLE:Lcom/whatsapp/pf;
        //   148: astore          11
        //   150: aload_1        
        //   151: aload           11
        //   153: if_acmpne       451
        //   156: new             Ljava/lang/StringBuilder;
        //   159: dup            
        //   160: invokespecial   java/lang/StringBuilder.<init>:()V
        //   163: getstatic       com/whatsapp/hq.z:[Ljava/lang/String;
        //   166: bipush          73
        //   168: aaload         
        //   169: invokevirtual   java/lang/StringBuilder.append:(Ljava/lang/String;)Ljava/lang/StringBuilder;
        //   172: aload_0        
        //   173: getfield        com/whatsapp/hq.b:Ljava/lang/String;
        //   176: invokevirtual   java/lang/StringBuilder.append:(Ljava/lang/String;)Ljava/lang/StringBuilder;
        //   179: getstatic       com/whatsapp/hq.z:[Ljava/lang/String;
        //   182: bipush          40
        //   184: aaload         
        //   185: invokevirtual   java/lang/StringBuilder.append:(Ljava/lang/String;)Ljava/lang/StringBuilder;
        //   188: invokevirtual   java/lang/StringBuilder.toString:()Ljava/lang/String;
        //   191: invokestatic    com/whatsapp/util/Log.w:(Ljava/lang/String;)V
        //   194: aload_0        
        //   195: getfield        com/whatsapp/hq.a:Lcom/whatsapp/VerifySms;
        //   198: getstatic       com/whatsapp/hq.z:[Ljava/lang/String;
        //   201: bipush          33
        //   203: aaload         
        //   204: invokevirtual   com/whatsapp/VerifySms.c:(Ljava/lang/String;)V
        //   207: aload_0        
        //   208: getfield        com/whatsapp/hq.c:Lcom/whatsapp/ct;
        //   211: getfield        com/whatsapp/ct.g:Ljava/lang/String;
        //   214: astore          116
        //   216: aload           116
        //   218: ifnonnull       242
        //   221: aload_0        
        //   222: getfield        com/whatsapp/hq.a:Lcom/whatsapp/VerifySms;
        //   225: aload_0        
        //   226: getfield        com/whatsapp/hq.a:Lcom/whatsapp/VerifySms;
        //   229: ldc_w           2131231566
        //   232: invokevirtual   com/whatsapp/VerifySms.getString:(I)Ljava/lang/String;
        //   235: invokevirtual   com/whatsapp/VerifySms.d:(Ljava/lang/String;)V
        //   238: iload_2        
        //   239: ifeq            321
        //   242: ldc2_w          1000
        //   245: aload_0        
        //   246: getfield        com/whatsapp/hq.c:Lcom/whatsapp/ct;
        //   249: getfield        com/whatsapp/ct.g:Ljava/lang/String;
        //   252: invokestatic    java/lang/Long.parseLong:(Ljava/lang/String;)J
        //   255: lmul           
        //   256: lstore          118
        //   258: getstatic       com/whatsapp/App.aq:Lcom/whatsapp/App;
        //   261: lload           118
        //   263: invokevirtual   com/whatsapp/App.c:(J)V
        //   266: aload_0        
        //   267: getfield        com/whatsapp/hq.a:Lcom/whatsapp/VerifySms;
        //   270: astore          120
        //   272: aload_0        
        //   273: getfield        com/whatsapp/hq.a:Lcom/whatsapp/VerifySms;
        //   276: astore          121
        //   278: iconst_1       
        //   279: anewarray       Ljava/lang/Object;
        //   282: astore          122
        //   284: aload           122
        //   286: iconst_0       
        //   287: aload_0        
        //   288: getfield        com/whatsapp/hq.a:Lcom/whatsapp/VerifySms;
        //   291: lload           118
        //   293: invokestatic    com/whatsapp/util/b6.n:(Landroid/content/Context;J)Ljava/lang/String;
        //   296: aastore        
        //   297: aload           120
        //   299: aload           121
        //   301: ldc_w           2131231567
        //   304: aload           122
        //   306: invokevirtual   com/whatsapp/VerifySms.getString:(I[Ljava/lang/Object;)Ljava/lang/String;
        //   309: invokevirtual   com/whatsapp/VerifySms.d:(Ljava/lang/String;)V
        //   312: aload_0        
        //   313: getfield        com/whatsapp/hq.a:Lcom/whatsapp/VerifySms;
        //   316: lload           118
        //   318: invokestatic    com/whatsapp/VerifySms.c:(Lcom/whatsapp/VerifySms;J)V
        //   321: aload_0        
        //   322: getfield        com/whatsapp/hq.a:Lcom/whatsapp/VerifySms;
        //   325: invokestatic    com/whatsapp/VerifySms.A:(Lcom/whatsapp/VerifySms;)V
        //   328: return         
        //   329: astore          125
        //   331: new             Ljava/lang/StringBuilder;
        //   334: dup            
        //   335: invokespecial   java/lang/StringBuilder.<init>:()V
        //   338: getstatic       com/whatsapp/hq.z:[Ljava/lang/String;
        //   341: bipush          72
        //   343: aaload         
        //   344: invokevirtual   java/lang/StringBuilder.append:(Ljava/lang/String;)Ljava/lang/StringBuilder;
        //   347: aload_0        
        //   348: getfield        com/whatsapp/hq.b:Ljava/lang/String;
        //   351: invokevirtual   java/lang/StringBuilder.append:(Ljava/lang/String;)Ljava/lang/StringBuilder;
        //   354: getstatic       com/whatsapp/hq.z:[Ljava/lang/String;
        //   357: bipush          16
        //   359: aaload         
        //   360: invokevirtual   java/lang/StringBuilder.append:(Ljava/lang/String;)Ljava/lang/StringBuilder;
        //   363: invokevirtual   java/lang/StringBuilder.toString:()Ljava/lang/String;
        //   366: invokestatic    com/whatsapp/util/Log.e:(Ljava/lang/String;)V
        //   369: goto            122
        //   372: astore_3       
        //   373: aload_3        
        //   374: athrow         
        //   375: astore          4
        //   377: aload           4
        //   379: athrow         
        //   380: astore          5
        //   382: aload           5
        //   384: athrow         
        //   385: astore          6
        //   387: aload           6
        //   389: athrow         
        //   390: astore          117
        //   392: new             Ljava/lang/StringBuilder;
        //   395: dup            
        //   396: invokespecial   java/lang/StringBuilder.<init>:()V
        //   399: getstatic       com/whatsapp/hq.z:[Ljava/lang/String;
        //   402: bipush          21
        //   404: aaload         
        //   405: invokevirtual   java/lang/StringBuilder.append:(Ljava/lang/String;)Ljava/lang/StringBuilder;
        //   408: aload_0        
        //   409: getfield        com/whatsapp/hq.b:Ljava/lang/String;
        //   412: invokevirtual   java/lang/StringBuilder.append:(Ljava/lang/String;)Ljava/lang/StringBuilder;
        //   415: getstatic       com/whatsapp/hq.z:[Ljava/lang/String;
        //   418: bipush          70
        //   420: aaload         
        //   421: invokevirtual   java/lang/StringBuilder.append:(Ljava/lang/String;)Ljava/lang/StringBuilder;
        //   424: invokevirtual   java/lang/StringBuilder.toString:()Ljava/lang/String;
        //   427: invokestatic    com/whatsapp/util/Log.w:(Ljava/lang/String;)V
        //   430: aload_0        
        //   431: getfield        com/whatsapp/hq.a:Lcom/whatsapp/VerifySms;
        //   434: aload_0        
        //   435: getfield        com/whatsapp/hq.a:Lcom/whatsapp/VerifySms;
        //   438: ldc_w           2131231566
        //   441: invokevirtual   com/whatsapp/VerifySms.getString:(I)Ljava/lang/String;
        //   444: invokevirtual   com/whatsapp/VerifySms.d:(Ljava/lang/String;)V
        //   447: iload_2        
        //   448: ifeq            321
        //   451: getstatic       com/whatsapp/pf.ERROR_UNSPECIFIED:Lcom/whatsapp/pf;
        //   454: astore          17
        //   456: aload_1        
        //   457: aload           17
        //   459: if_acmpne       526
        //   462: new             Ljava/lang/StringBuilder;
        //   465: dup            
        //   466: invokespecial   java/lang/StringBuilder.<init>:()V
        //   469: getstatic       com/whatsapp/hq.z:[Ljava/lang/String;
        //   472: bipush          12
        //   474: aaload         
        //   475: invokevirtual   java/lang/StringBuilder.append:(Ljava/lang/String;)Ljava/lang/StringBuilder;
        //   478: aload_0        
        //   479: getfield        com/whatsapp/hq.b:Ljava/lang/String;
        //   482: invokevirtual   java/lang/StringBuilder.append:(Ljava/lang/String;)Ljava/lang/StringBuilder;
        //   485: getstatic       com/whatsapp/hq.z:[Ljava/lang/String;
        //   488: bipush          37
        //   490: aaload         
        //   491: invokevirtual   java/lang/StringBuilder.append:(Ljava/lang/String;)Ljava/lang/StringBuilder;
        //   494: invokevirtual   java/lang/StringBuilder.toString:()Ljava/lang/String;
        //   497: invokestatic    com/whatsapp/util/Log.w:(Ljava/lang/String;)V
        //   500: aload_0        
        //   501: getfield        com/whatsapp/hq.a:Lcom/whatsapp/VerifySms;
        //   504: getstatic       com/whatsapp/hq.z:[Ljava/lang/String;
        //   507: bipush          15
        //   509: aaload         
        //   510: invokevirtual   com/whatsapp/VerifySms.c:(Ljava/lang/String;)V
        //   513: aload_0        
        //   514: getfield        com/whatsapp/hq.a:Lcom/whatsapp/VerifySms;
        //   517: bipush          109
        //   519: invokevirtual   com/whatsapp/VerifySms.d:(I)V
        //   522: iload_2        
        //   523: ifeq            321
        //   526: getstatic       com/whatsapp/pf.ERROR_TOO_MANY:Lcom/whatsapp/pf;
        //   529: astore          18
        //   531: aload_1        
        //   532: aload           18
        //   534: if_acmpne       776
        //   537: new             Ljava/lang/StringBuilder;
        //   540: dup            
        //   541: invokespecial   java/lang/StringBuilder.<init>:()V
        //   544: getstatic       com/whatsapp/hq.z:[Ljava/lang/String;
        //   547: bipush          31
        //   549: aaload         
        //   550: invokevirtual   java/lang/StringBuilder.append:(Ljava/lang/String;)Ljava/lang/StringBuilder;
        //   553: aload_0        
        //   554: getfield        com/whatsapp/hq.b:Ljava/lang/String;
        //   557: invokevirtual   java/lang/StringBuilder.append:(Ljava/lang/String;)Ljava/lang/StringBuilder;
        //   560: getstatic       com/whatsapp/hq.z:[Ljava/lang/String;
        //   563: bipush          59
        //   565: aaload         
        //   566: invokevirtual   java/lang/StringBuilder.append:(Ljava/lang/String;)Ljava/lang/StringBuilder;
        //   569: invokevirtual   java/lang/StringBuilder.toString:()Ljava/lang/String;
        //   572: invokestatic    com/whatsapp/util/Log.w:(Ljava/lang/String;)V
        //   575: aload_0        
        //   576: getfield        com/whatsapp/hq.a:Lcom/whatsapp/VerifySms;
        //   579: getstatic       com/whatsapp/hq.z:[Ljava/lang/String;
        //   582: bipush          74
        //   584: aaload         
        //   585: invokevirtual   com/whatsapp/VerifySms.c:(Ljava/lang/String;)V
        //   588: iconst_1       
        //   589: invokestatic    com/whatsapp/VerifySms.b:(Z)Z
        //   592: pop            
        //   593: aload_0        
        //   594: getfield        com/whatsapp/hq.c:Lcom/whatsapp/ct;
        //   597: getfield        com/whatsapp/ct.g:Ljava/lang/String;
        //   600: astore          109
        //   602: aload           109
        //   604: ifnonnull       620
        //   607: aload_0        
        //   608: getfield        com/whatsapp/hq.a:Lcom/whatsapp/VerifySms;
        //   611: bipush          29
        //   613: invokevirtual   com/whatsapp/VerifySms.d:(I)V
        //   616: iload_2        
        //   617: ifeq            321
        //   620: aload_0        
        //   621: getfield        com/whatsapp/hq.a:Lcom/whatsapp/VerifySms;
        //   624: ldc2_w          1000
        //   627: aload_0        
        //   628: getfield        com/whatsapp/hq.c:Lcom/whatsapp/ct;
        //   631: getfield        com/whatsapp/ct.g:Ljava/lang/String;
        //   634: invokestatic    java/lang/Long.parseLong:(Ljava/lang/String;)J
        //   637: lmul           
        //   638: invokestatic    com/whatsapp/VerifySms.b:(Lcom/whatsapp/VerifySms;J)J
        //   641: pop2           
        //   642: getstatic       com/whatsapp/App.aq:Lcom/whatsapp/App;
        //   645: aload_0        
        //   646: getfield        com/whatsapp/hq.a:Lcom/whatsapp/VerifySms;
        //   649: invokestatic    com/whatsapp/VerifySms.p:(Lcom/whatsapp/VerifySms;)J
        //   652: invokevirtual   com/whatsapp/App.c:(J)V
        //   655: aload_0        
        //   656: getfield        com/whatsapp/hq.a:Lcom/whatsapp/VerifySms;
        //   659: astore          113
        //   661: aload_0        
        //   662: getfield        com/whatsapp/hq.a:Lcom/whatsapp/VerifySms;
        //   665: astore          114
        //   667: iconst_1       
        //   668: anewarray       Ljava/lang/Object;
        //   671: astore          115
        //   673: aload           115
        //   675: iconst_0       
        //   676: aload_0        
        //   677: getfield        com/whatsapp/hq.a:Lcom/whatsapp/VerifySms;
        //   680: aload_0        
        //   681: getfield        com/whatsapp/hq.a:Lcom/whatsapp/VerifySms;
        //   684: invokestatic    com/whatsapp/VerifySms.p:(Lcom/whatsapp/VerifySms;)J
        //   687: invokestatic    com/whatsapp/util/b6.n:(Landroid/content/Context;J)Ljava/lang/String;
        //   690: aastore        
        //   691: aload           113
        //   693: aload           114
        //   695: ldc_w           2131231579
        //   698: aload           115
        //   700: invokevirtual   com/whatsapp/VerifySms.getString:(I[Ljava/lang/Object;)Ljava/lang/String;
        //   703: invokevirtual   com/whatsapp/VerifySms.d:(Ljava/lang/String;)V
        //   706: aload_0        
        //   707: getfield        com/whatsapp/hq.a:Lcom/whatsapp/VerifySms;
        //   710: aload_0        
        //   711: getfield        com/whatsapp/hq.a:Lcom/whatsapp/VerifySms;
        //   714: invokestatic    com/whatsapp/VerifySms.p:(Lcom/whatsapp/VerifySms;)J
        //   717: invokestatic    com/whatsapp/VerifySms.c:(Lcom/whatsapp/VerifySms;J)V
        //   720: goto            321
        //   723: astore          110
        //   725: new             Ljava/lang/StringBuilder;
        //   728: dup            
        //   729: invokespecial   java/lang/StringBuilder.<init>:()V
        //   732: getstatic       com/whatsapp/hq.z:[Ljava/lang/String;
        //   735: bipush          61
        //   737: aaload         
        //   738: invokevirtual   java/lang/StringBuilder.append:(Ljava/lang/String;)Ljava/lang/StringBuilder;
        //   741: aload_0        
        //   742: getfield        com/whatsapp/hq.b:Ljava/lang/String;
        //   745: invokevirtual   java/lang/StringBuilder.append:(Ljava/lang/String;)Ljava/lang/StringBuilder;
        //   748: getstatic       com/whatsapp/hq.z:[Ljava/lang/String;
        //   751: bipush          48
        //   753: aaload         
        //   754: invokevirtual   java/lang/StringBuilder.append:(Ljava/lang/String;)Ljava/lang/StringBuilder;
        //   757: invokevirtual   java/lang/StringBuilder.toString:()Ljava/lang/String;
        //   760: invokestatic    com/whatsapp/util/Log.w:(Ljava/lang/String;)V
        //   763: aload_0        
        //   764: getfield        com/whatsapp/hq.a:Lcom/whatsapp/VerifySms;
        //   767: bipush          29
        //   769: invokevirtual   com/whatsapp/VerifySms.d:(I)V
        //   772: iload_2        
        //   773: ifeq            321
        //   776: getstatic       com/whatsapp/pf.ERROR_TOO_MANY_ALL_METHODS:Lcom/whatsapp/pf;
        //   779: astore          22
        //   781: aload_1        
        //   782: aload           22
        //   784: if_acmpne       984
        //   787: new             Ljava/lang/StringBuilder;
        //   790: dup            
        //   791: invokespecial   java/lang/StringBuilder.<init>:()V
        //   794: getstatic       com/whatsapp/hq.z:[Ljava/lang/String;
        //   797: bipush          41
        //   799: aaload         
        //   800: invokevirtual   java/lang/StringBuilder.append:(Ljava/lang/String;)Ljava/lang/StringBuilder;
        //   803: aload_0        
        //   804: getfield        com/whatsapp/hq.b:Ljava/lang/String;
        //   807: invokevirtual   java/lang/StringBuilder.append:(Ljava/lang/String;)Ljava/lang/StringBuilder;
        //   810: getstatic       com/whatsapp/hq.z:[Ljava/lang/String;
        //   813: bipush          23
        //   815: aaload         
        //   816: invokevirtual   java/lang/StringBuilder.append:(Ljava/lang/String;)Ljava/lang/StringBuilder;
        //   819: invokevirtual   java/lang/StringBuilder.toString:()Ljava/lang/String;
        //   822: invokestatic    com/whatsapp/util/Log.w:(Ljava/lang/String;)V
        //   825: aload_0        
        //   826: getfield        com/whatsapp/hq.a:Lcom/whatsapp/VerifySms;
        //   829: getstatic       com/whatsapp/hq.z:[Ljava/lang/String;
        //   832: bipush          10
        //   834: aaload         
        //   835: invokevirtual   com/whatsapp/VerifySms.c:(Ljava/lang/String;)V
        //   838: iconst_1       
        //   839: invokestatic    com/whatsapp/VerifySms.b:(Z)Z
        //   842: pop            
        //   843: aload_0        
        //   844: getfield        com/whatsapp/hq.c:Lcom/whatsapp/ct;
        //   847: getfield        com/whatsapp/ct.g:Ljava/lang/String;
        //   850: astore          104
        //   852: aload           104
        //   854: ifnonnull       870
        //   857: aload_0        
        //   858: getfield        com/whatsapp/hq.a:Lcom/whatsapp/VerifySms;
        //   861: bipush          30
        //   863: invokevirtual   com/whatsapp/VerifySms.d:(I)V
        //   866: iload_2        
        //   867: ifeq            321
        //   870: aload_0        
        //   871: getfield        com/whatsapp/hq.a:Lcom/whatsapp/VerifySms;
        //   874: ldc2_w          1000
        //   877: aload_0        
        //   878: getfield        com/whatsapp/hq.c:Lcom/whatsapp/ct;
        //   881: getfield        com/whatsapp/ct.g:Ljava/lang/String;
        //   884: invokestatic    java/lang/Long.parseLong:(Ljava/lang/String;)J
        //   887: lmul           
        //   888: invokestatic    com/whatsapp/VerifySms.b:(Lcom/whatsapp/VerifySms;J)J
        //   891: pop2           
        //   892: getstatic       com/whatsapp/App.aq:Lcom/whatsapp/App;
        //   895: aload_0        
        //   896: getfield        com/whatsapp/hq.a:Lcom/whatsapp/VerifySms;
        //   899: invokestatic    com/whatsapp/VerifySms.p:(Lcom/whatsapp/VerifySms;)J
        //   902: invokevirtual   com/whatsapp/App.c:(J)V
        //   905: aload_0        
        //   906: getfield        com/whatsapp/hq.a:Lcom/whatsapp/VerifySms;
        //   909: bipush          35
        //   911: invokevirtual   com/whatsapp/VerifySms.d:(I)V
        //   914: aload_0        
        //   915: getfield        com/whatsapp/hq.a:Lcom/whatsapp/VerifySms;
        //   918: aload_0        
        //   919: getfield        com/whatsapp/hq.a:Lcom/whatsapp/VerifySms;
        //   922: invokestatic    com/whatsapp/VerifySms.p:(Lcom/whatsapp/VerifySms;)J
        //   925: invokestatic    com/whatsapp/VerifySms.c:(Lcom/whatsapp/VerifySms;J)V
        //   928: goto            321
        //   931: astore          105
        //   933: new             Ljava/lang/StringBuilder;
        //   936: dup            
        //   937: invokespecial   java/lang/StringBuilder.<init>:()V
        //   940: getstatic       com/whatsapp/hq.z:[Ljava/lang/String;
        //   943: bipush          27
        //   945: aaload         
        //   946: invokevirtual   java/lang/StringBuilder.append:(Ljava/lang/String;)Ljava/lang/StringBuilder;
        //   949: aload_0        
        //   950: getfield        com/whatsapp/hq.b:Ljava/lang/String;
        //   953: invokevirtual   java/lang/StringBuilder.append:(Ljava/lang/String;)Ljava/lang/StringBuilder;
        //   956: getstatic       com/whatsapp/hq.z:[Ljava/lang/String;
        //   959: bipush          50
        //   961: aaload         
        //   962: invokevirtual   java/lang/StringBuilder.append:(Ljava/lang/String;)Ljava/lang/StringBuilder;
        //   965: invokevirtual   java/lang/StringBuilder.toString:()Ljava/lang/String;
        //   968: invokestatic    com/whatsapp/util/Log.w:(Ljava/lang/String;)V
        //   971: aload_0        
        //   972: getfield        com/whatsapp/hq.a:Lcom/whatsapp/VerifySms;
        //   975: bipush          30
        //   977: invokevirtual   com/whatsapp/VerifySms.d:(I)V
        //   980: iload_2        
        //   981: ifeq            321
        //   984: getstatic       com/whatsapp/pf.ERROR_CONNECTIVITY:Lcom/whatsapp/pf;
        //   987: astore          34
        //   989: aload_1        
        //   990: aload           34
        //   992: if_acmpne       1046
        //   995: aload_0        
        //   996: getfield        com/whatsapp/hq.a:Lcom/whatsapp/VerifySms;
        //   999: astore          100
        //  1001: aload_0        
        //  1002: getfield        com/whatsapp/hq.a:Lcom/whatsapp/VerifySms;
        //  1005: astore          101
        //  1007: iconst_1       
        //  1008: anewarray       Ljava/lang/Object;
        //  1011: astore          102
        //  1013: aload           102
        //  1015: iconst_0       
        //  1016: aload_0        
        //  1017: getfield        com/whatsapp/hq.a:Lcom/whatsapp/VerifySms;
        //  1020: ldc_w           2131230921
        //  1023: invokevirtual   com/whatsapp/VerifySms.getString:(I)Ljava/lang/String;
        //  1026: aastore        
        //  1027: aload           100
        //  1029: aload           101
        //  1031: ldc_w           2131231532
        //  1034: aload           102
        //  1036: invokevirtual   com/whatsapp/VerifySms.getString:(I[Ljava/lang/Object;)Ljava/lang/String;
        //  1039: invokevirtual   com/whatsapp/VerifySms.d:(Ljava/lang/String;)V
        //  1042: iload_2        
        //  1043: ifeq            321
        //  1046: getstatic       com/whatsapp/pf.ERROR_BAD_PARAMETER:Lcom/whatsapp/pf;
        //  1049: astore          35
        //  1051: aload_1        
        //  1052: aload           35
        //  1054: if_acmpne       1130
        //  1057: new             Ljava/lang/StringBuilder;
        //  1060: dup            
        //  1061: invokespecial   java/lang/StringBuilder.<init>:()V
        //  1064: getstatic       com/whatsapp/hq.z:[Ljava/lang/String;
        //  1067: bipush          35
        //  1069: aaload         
        //  1070: invokevirtual   java/lang/StringBuilder.append:(Ljava/lang/String;)Ljava/lang/StringBuilder;
        //  1073: aload_0        
        //  1074: getfield        com/whatsapp/hq.b:Ljava/lang/String;
        //  1077: invokevirtual   java/lang/StringBuilder.append:(Ljava/lang/String;)Ljava/lang/StringBuilder;
        //  1080: getstatic       com/whatsapp/hq.z:[Ljava/lang/String;
        //  1083: bipush          55
        //  1085: aaload         
        //  1086: invokevirtual   java/lang/StringBuilder.append:(Ljava/lang/String;)Ljava/lang/StringBuilder;
        //  1089: invokevirtual   java/lang/StringBuilder.toString:()Ljava/lang/String;
        //  1092: invokestatic    com/whatsapp/util/Log.e:(Ljava/lang/String;)V
        //  1095: getstatic       com/whatsapp/hq.z:[Ljava/lang/String;
        //  1098: bipush          62
        //  1100: aaload         
        //  1101: invokestatic    com/whatsapp/App.F:(Ljava/lang/String;)V
        //  1104: aload_0        
        //  1105: getfield        com/whatsapp/hq.a:Lcom/whatsapp/VerifySms;
        //  1108: getstatic       com/whatsapp/hq.z:[Ljava/lang/String;
        //  1111: bipush          75
        //  1113: aaload         
        //  1114: invokevirtual   com/whatsapp/VerifySms.c:(Ljava/lang/String;)V
        //  1117: aload_0        
        //  1118: getfield        com/whatsapp/hq.a:Lcom/whatsapp/VerifySms;
        //  1121: bipush          27
        //  1123: invokevirtual   com/whatsapp/VerifySms.d:(I)V
        //  1126: iload_2        
        //  1127: ifeq            321
        //  1130: getstatic       com/whatsapp/pf.ERROR_MISSING_PARAMETER:Lcom/whatsapp/pf;
        //  1133: astore          36
        //  1135: aload_1        
        //  1136: aload           36
        //  1138: if_acmpne       1214
        //  1141: new             Ljava/lang/StringBuilder;
        //  1144: dup            
        //  1145: invokespecial   java/lang/StringBuilder.<init>:()V
        //  1148: getstatic       com/whatsapp/hq.z:[Ljava/lang/String;
        //  1151: bipush          24
        //  1153: aaload         
        //  1154: invokevirtual   java/lang/StringBuilder.append:(Ljava/lang/String;)Ljava/lang/StringBuilder;
        //  1157: aload_0        
        //  1158: getfield        com/whatsapp/hq.b:Ljava/lang/String;
        //  1161: invokevirtual   java/lang/StringBuilder.append:(Ljava/lang/String;)Ljava/lang/StringBuilder;
        //  1164: getstatic       com/whatsapp/hq.z:[Ljava/lang/String;
        //  1167: bipush          42
        //  1169: aaload         
        //  1170: invokevirtual   java/lang/StringBuilder.append:(Ljava/lang/String;)Ljava/lang/StringBuilder;
        //  1173: invokevirtual   java/lang/StringBuilder.toString:()Ljava/lang/String;
        //  1176: invokestatic    com/whatsapp/util/Log.e:(Ljava/lang/String;)V
        //  1179: getstatic       com/whatsapp/hq.z:[Ljava/lang/String;
        //  1182: bipush          17
        //  1184: aaload         
        //  1185: invokestatic    com/whatsapp/App.F:(Ljava/lang/String;)V
        //  1188: aload_0        
        //  1189: getfield        com/whatsapp/hq.a:Lcom/whatsapp/VerifySms;
        //  1192: getstatic       com/whatsapp/hq.z:[Ljava/lang/String;
        //  1195: bipush          60
        //  1197: aaload         
        //  1198: invokevirtual   com/whatsapp/VerifySms.c:(Ljava/lang/String;)V
        //  1201: aload_0        
        //  1202: getfield        com/whatsapp/hq.a:Lcom/whatsapp/VerifySms;
        //  1205: bipush          28
        //  1207: invokevirtual   com/whatsapp/VerifySms.d:(I)V
        //  1210: iload_2        
        //  1211: ifeq            321
        //  1214: getstatic       com/whatsapp/pf.ERROR_OLD_VERSION:Lcom/whatsapp/pf;
        //  1217: astore          37
        //  1219: aload_1        
        //  1220: aload           37
        //  1222: if_acmpne       1289
        //  1225: new             Ljava/lang/StringBuilder;
        //  1228: dup            
        //  1229: invokespecial   java/lang/StringBuilder.<init>:()V
        //  1232: getstatic       com/whatsapp/hq.z:[Ljava/lang/String;
        //  1235: bipush          32
        //  1237: aaload         
        //  1238: invokevirtual   java/lang/StringBuilder.append:(Ljava/lang/String;)Ljava/lang/StringBuilder;
        //  1241: aload_0        
        //  1242: getfield        com/whatsapp/hq.b:Ljava/lang/String;
        //  1245: invokevirtual   java/lang/StringBuilder.append:(Ljava/lang/String;)Ljava/lang/StringBuilder;
        //  1248: getstatic       com/whatsapp/hq.z:[Ljava/lang/String;
        //  1251: bipush          71
        //  1253: aaload         
        //  1254: invokevirtual   java/lang/StringBuilder.append:(Ljava/lang/String;)Ljava/lang/StringBuilder;
        //  1257: invokevirtual   java/lang/StringBuilder.toString:()Ljava/lang/String;
        //  1260: invokestatic    com/whatsapp/util/Log.w:(Ljava/lang/String;)V
        //  1263: aload_0        
        //  1264: getfield        com/whatsapp/hq.a:Lcom/whatsapp/VerifySms;
        //  1267: getstatic       com/whatsapp/hq.z:[Ljava/lang/String;
        //  1270: bipush          66
        //  1272: aaload         
        //  1273: invokevirtual   com/whatsapp/VerifySms.c:(Ljava/lang/String;)V
        //  1276: aload_0        
        //  1277: getfield        com/whatsapp/hq.a:Lcom/whatsapp/VerifySms;
        //  1280: bipush          23
        //  1282: invokevirtual   com/whatsapp/VerifySms.e:(I)V
        //  1285: iload_2        
        //  1286: ifeq            321
        //  1289: getstatic       com/whatsapp/pf.ERROR_TOO_RECENT:Lcom/whatsapp/pf;
        //  1292: astore          38
        //  1294: aload_1        
        //  1295: aload           38
        //  1297: if_acmpne       1539
        //  1300: new             Ljava/lang/StringBuilder;
        //  1303: dup            
        //  1304: invokespecial   java/lang/StringBuilder.<init>:()V
        //  1307: getstatic       com/whatsapp/hq.z:[Ljava/lang/String;
        //  1310: bipush          57
        //  1312: aaload         
        //  1313: invokevirtual   java/lang/StringBuilder.append:(Ljava/lang/String;)Ljava/lang/StringBuilder;
        //  1316: aload_0        
        //  1317: getfield        com/whatsapp/hq.b:Ljava/lang/String;
        //  1320: invokevirtual   java/lang/StringBuilder.append:(Ljava/lang/String;)Ljava/lang/StringBuilder;
        //  1323: getstatic       com/whatsapp/hq.z:[Ljava/lang/String;
        //  1326: bipush          64
        //  1328: aaload         
        //  1329: invokevirtual   java/lang/StringBuilder.append:(Ljava/lang/String;)Ljava/lang/StringBuilder;
        //  1332: aload_0        
        //  1333: getfield        com/whatsapp/hq.c:Lcom/whatsapp/ct;
        //  1336: getfield        com/whatsapp/ct.g:Ljava/lang/String;
        //  1339: invokevirtual   java/lang/StringBuilder.append:(Ljava/lang/String;)Ljava/lang/StringBuilder;
        //  1342: invokevirtual   java/lang/StringBuilder.toString:()Ljava/lang/String;
        //  1345: invokestatic    com/whatsapp/util/Log.w:(Ljava/lang/String;)V
        //  1348: aload_0        
        //  1349: getfield        com/whatsapp/hq.a:Lcom/whatsapp/VerifySms;
        //  1352: getstatic       com/whatsapp/hq.z:[Ljava/lang/String;
        //  1355: bipush          39
        //  1357: aaload         
        //  1358: invokevirtual   com/whatsapp/VerifySms.c:(Ljava/lang/String;)V
        //  1361: aload_0        
        //  1362: getfield        com/whatsapp/hq.c:Lcom/whatsapp/ct;
        //  1365: getfield        com/whatsapp/ct.g:Ljava/lang/String;
        //  1368: astore          93
        //  1370: aload           93
        //  1372: ifnonnull       1396
        //  1375: aload_0        
        //  1376: getfield        com/whatsapp/hq.a:Lcom/whatsapp/VerifySms;
        //  1379: aload_0        
        //  1380: getfield        com/whatsapp/hq.a:Lcom/whatsapp/VerifySms;
        //  1383: ldc_w           2131231571
        //  1386: invokevirtual   com/whatsapp/VerifySms.getString:(I)Ljava/lang/String;
        //  1389: invokevirtual   com/whatsapp/VerifySms.d:(Ljava/lang/String;)V
        //  1392: iload_2        
        //  1393: ifeq            321
        //  1396: ldc2_w          1000
        //  1399: aload_0        
        //  1400: getfield        com/whatsapp/hq.c:Lcom/whatsapp/ct;
        //  1403: getfield        com/whatsapp/ct.g:Ljava/lang/String;
        //  1406: invokestatic    java/lang/Long.parseLong:(Ljava/lang/String;)J
        //  1409: lmul           
        //  1410: lstore          95
        //  1412: getstatic       com/whatsapp/App.aq:Lcom/whatsapp/App;
        //  1415: lload           95
        //  1417: invokevirtual   com/whatsapp/App.c:(J)V
        //  1420: aload_0        
        //  1421: getfield        com/whatsapp/hq.a:Lcom/whatsapp/VerifySms;
        //  1424: astore          97
        //  1426: aload_0        
        //  1427: getfield        com/whatsapp/hq.a:Lcom/whatsapp/VerifySms;
        //  1430: astore          98
        //  1432: iconst_1       
        //  1433: anewarray       Ljava/lang/Object;
        //  1436: astore          99
        //  1438: aload           99
        //  1440: iconst_0       
        //  1441: aload_0        
        //  1442: getfield        com/whatsapp/hq.a:Lcom/whatsapp/VerifySms;
        //  1445: lload           95
        //  1447: invokestatic    com/whatsapp/util/b6.n:(Landroid/content/Context;J)Ljava/lang/String;
        //  1450: aastore        
        //  1451: aload           97
        //  1453: aload           98
        //  1455: ldc_w           2131231570
        //  1458: aload           99
        //  1460: invokevirtual   com/whatsapp/VerifySms.getString:(I[Ljava/lang/Object;)Ljava/lang/String;
        //  1463: invokevirtual   com/whatsapp/VerifySms.d:(Ljava/lang/String;)V
        //  1466: aload_0        
        //  1467: getfield        com/whatsapp/hq.a:Lcom/whatsapp/VerifySms;
        //  1470: lload           95
        //  1472: invokestatic    com/whatsapp/VerifySms.c:(Lcom/whatsapp/VerifySms;J)V
        //  1475: goto            321
        //  1478: astore          94
        //  1480: new             Ljava/lang/StringBuilder;
        //  1483: dup            
        //  1484: invokespecial   java/lang/StringBuilder.<init>:()V
        //  1487: getstatic       com/whatsapp/hq.z:[Ljava/lang/String;
        //  1490: bipush          67
        //  1492: aaload         
        //  1493: invokevirtual   java/lang/StringBuilder.append:(Ljava/lang/String;)Ljava/lang/StringBuilder;
        //  1496: aload_0        
        //  1497: getfield        com/whatsapp/hq.b:Ljava/lang/String;
        //  1500: invokevirtual   java/lang/StringBuilder.append:(Ljava/lang/String;)Ljava/lang/StringBuilder;
        //  1503: getstatic       com/whatsapp/hq.z:[Ljava/lang/String;
        //  1506: bipush          47
        //  1508: aaload         
        //  1509: invokevirtual   java/lang/StringBuilder.append:(Ljava/lang/String;)Ljava/lang/StringBuilder;
        //  1512: invokevirtual   java/lang/StringBuilder.toString:()Ljava/lang/String;
        //  1515: invokestatic    com/whatsapp/util/Log.w:(Ljava/lang/String;)V
        //  1518: aload_0        
        //  1519: getfield        com/whatsapp/hq.a:Lcom/whatsapp/VerifySms;
        //  1522: aload_0        
        //  1523: getfield        com/whatsapp/hq.a:Lcom/whatsapp/VerifySms;
        //  1526: ldc_w           2131231571
        //  1529: invokevirtual   com/whatsapp/VerifySms.getString:(I)Ljava/lang/String;
        //  1532: invokevirtual   com/whatsapp/VerifySms.d:(Ljava/lang/String;)V
        //  1535: iload_2        
        //  1536: ifeq            321
        //  1539: getstatic       com/whatsapp/pf.ERROR_BLOCKED:Lcom/whatsapp/pf;
        //  1542: astore          46
        //  1544: aload_1        
        //  1545: aload           46
        //  1547: if_acmpne       1632
        //  1550: new             Ljava/lang/StringBuilder;
        //  1553: dup            
        //  1554: invokespecial   java/lang/StringBuilder.<init>:()V
        //  1557: getstatic       com/whatsapp/hq.z:[Ljava/lang/String;
        //  1560: bipush          36
        //  1562: aaload         
        //  1563: invokevirtual   java/lang/StringBuilder.append:(Ljava/lang/String;)Ljava/lang/StringBuilder;
        //  1566: aload_0        
        //  1567: getfield        com/whatsapp/hq.b:Ljava/lang/String;
        //  1570: invokevirtual   java/lang/StringBuilder.append:(Ljava/lang/String;)Ljava/lang/StringBuilder;
        //  1573: getstatic       com/whatsapp/hq.z:[Ljava/lang/String;
        //  1576: bipush          13
        //  1578: aaload         
        //  1579: invokevirtual   java/lang/StringBuilder.append:(Ljava/lang/String;)Ljava/lang/StringBuilder;
        //  1582: invokevirtual   java/lang/StringBuilder.toString:()Ljava/lang/String;
        //  1585: invokestatic    com/whatsapp/util/Log.e:(Ljava/lang/String;)V
        //  1588: bipush          12
        //  1590: invokestatic    com/whatsapp/VerifySms.j:(I)I
        //  1593: pop            
        //  1594: aload_0        
        //  1595: getfield        com/whatsapp/hq.a:Lcom/whatsapp/VerifySms;
        //  1598: invokestatic    com/whatsapp/VerifySms.k:(Lcom/whatsapp/VerifySms;)V
        //  1601: aload_0        
        //  1602: getfield        com/whatsapp/hq.a:Lcom/whatsapp/VerifySms;
        //  1605: getstatic       com/whatsapp/hq.z:[Ljava/lang/String;
        //  1608: bipush          22
        //  1610: aaload         
        //  1611: invokevirtual   com/whatsapp/VerifySms.c:(Ljava/lang/String;)V
        //  1614: aload_0        
        //  1615: getfield        com/whatsapp/hq.a:Lcom/whatsapp/VerifySms;
        //  1618: invokestatic    com/whatsapp/VerifySms.w:(Lcom/whatsapp/VerifySms;)V
        //  1621: aload_0        
        //  1622: getfield        com/whatsapp/hq.a:Lcom/whatsapp/VerifySms;
        //  1625: invokestatic    com/whatsapp/VerifySms.A:(Lcom/whatsapp/VerifySms;)V
        //  1628: iload_2        
        //  1629: ifeq            321
        //  1632: getstatic       com/whatsapp/pf.ERROR_NEXT_METHOD:Lcom/whatsapp/pf;
        //  1635: astore          47
        //  1637: aload_1        
        //  1638: aload           47
        //  1640: if_acmpne       1707
        //  1643: new             Ljava/lang/StringBuilder;
        //  1646: dup            
        //  1647: invokespecial   java/lang/StringBuilder.<init>:()V
        //  1650: getstatic       com/whatsapp/hq.z:[Ljava/lang/String;
        //  1653: bipush          43
        //  1655: aaload         
        //  1656: invokevirtual   java/lang/StringBuilder.append:(Ljava/lang/String;)Ljava/lang/StringBuilder;
        //  1659: aload_0        
        //  1660: getfield        com/whatsapp/hq.b:Ljava/lang/String;
        //  1663: invokevirtual   java/lang/StringBuilder.append:(Ljava/lang/String;)Ljava/lang/StringBuilder;
        //  1666: getstatic       com/whatsapp/hq.z:[Ljava/lang/String;
        //  1669: bipush          44
        //  1671: aaload         
        //  1672: invokevirtual   java/lang/StringBuilder.append:(Ljava/lang/String;)Ljava/lang/StringBuilder;
        //  1675: invokevirtual   java/lang/StringBuilder.toString:()Ljava/lang/String;
        //  1678: invokestatic    com/whatsapp/util/Log.w:(Ljava/lang/String;)V
        //  1681: aload_0        
        //  1682: getfield        com/whatsapp/hq.a:Lcom/whatsapp/VerifySms;
        //  1685: getstatic       com/whatsapp/hq.z:[Ljava/lang/String;
        //  1688: bipush          45
        //  1690: aaload         
        //  1691: invokevirtual   com/whatsapp/VerifySms.c:(Ljava/lang/String;)V
        //  1694: aload_0        
        //  1695: getfield        com/whatsapp/hq.a:Lcom/whatsapp/VerifySms;
        //  1698: bipush          109
        //  1700: invokevirtual   com/whatsapp/VerifySms.d:(I)V
        //  1703: iload_2        
        //  1704: ifeq            321
        //  1707: getstatic       com/whatsapp/pf.ERROR_TOO_MANY_GUESSES:Lcom/whatsapp/pf;
        //  1710: astore          48
        //  1712: aload_1        
        //  1713: aload           48
        //  1715: if_acmpne       1910
        //  1718: new             Ljava/lang/StringBuilder;
        //  1721: dup            
        //  1722: invokespecial   java/lang/StringBuilder.<init>:()V
        //  1725: getstatic       com/whatsapp/hq.z:[Ljava/lang/String;
        //  1728: bipush          8
        //  1730: aaload         
        //  1731: invokevirtual   java/lang/StringBuilder.append:(Ljava/lang/String;)Ljava/lang/StringBuilder;
        //  1734: aload_0        
        //  1735: getfield        com/whatsapp/hq.b:Ljava/lang/String;
        //  1738: invokevirtual   java/lang/StringBuilder.append:(Ljava/lang/String;)Ljava/lang/StringBuilder;
        //  1741: getstatic       com/whatsapp/hq.z:[Ljava/lang/String;
        //  1744: bipush          46
        //  1746: aaload         
        //  1747: invokevirtual   java/lang/StringBuilder.append:(Ljava/lang/String;)Ljava/lang/StringBuilder;
        //  1750: invokevirtual   java/lang/StringBuilder.toString:()Ljava/lang/String;
        //  1753: invokestatic    com/whatsapp/util/Log.w:(Ljava/lang/String;)V
        //  1756: aload_0        
        //  1757: getfield        com/whatsapp/hq.a:Lcom/whatsapp/VerifySms;
        //  1760: getstatic       com/whatsapp/hq.z:[Ljava/lang/String;
        //  1763: bipush          20
        //  1765: aaload         
        //  1766: invokevirtual   com/whatsapp/VerifySms.c:(Ljava/lang/String;)V
        //  1769: aload_0        
        //  1770: getfield        com/whatsapp/hq.c:Lcom/whatsapp/ct;
        //  1773: getfield        com/whatsapp/ct.g:Ljava/lang/String;
        //  1776: astore          88
        //  1778: aload           88
        //  1780: ifnonnull       1796
        //  1783: aload_0        
        //  1784: getfield        com/whatsapp/hq.a:Lcom/whatsapp/VerifySms;
        //  1787: bipush          31
        //  1789: invokevirtual   com/whatsapp/VerifySms.d:(I)V
        //  1792: iload_2        
        //  1793: ifeq            321
        //  1796: aload_0        
        //  1797: getfield        com/whatsapp/hq.a:Lcom/whatsapp/VerifySms;
        //  1800: ldc2_w          1000
        //  1803: aload_0        
        //  1804: getfield        com/whatsapp/hq.c:Lcom/whatsapp/ct;
        //  1807: getfield        com/whatsapp/ct.g:Ljava/lang/String;
        //  1810: invokestatic    java/lang/Long.parseLong:(Ljava/lang/String;)J
        //  1813: lmul           
        //  1814: invokestatic    com/whatsapp/VerifySms.b:(Lcom/whatsapp/VerifySms;J)J
        //  1817: pop2           
        //  1818: getstatic       com/whatsapp/App.aq:Lcom/whatsapp/App;
        //  1821: aload_0        
        //  1822: getfield        com/whatsapp/hq.a:Lcom/whatsapp/VerifySms;
        //  1825: invokestatic    com/whatsapp/VerifySms.p:(Lcom/whatsapp/VerifySms;)J
        //  1828: invokevirtual   com/whatsapp/App.c:(J)V
        //  1831: aload_0        
        //  1832: getfield        com/whatsapp/hq.a:Lcom/whatsapp/VerifySms;
        //  1835: bipush          36
        //  1837: invokevirtual   com/whatsapp/VerifySms.d:(I)V
        //  1840: aload_0        
        //  1841: getfield        com/whatsapp/hq.a:Lcom/whatsapp/VerifySms;
        //  1844: aload_0        
        //  1845: getfield        com/whatsapp/hq.a:Lcom/whatsapp/VerifySms;
        //  1848: invokestatic    com/whatsapp/VerifySms.p:(Lcom/whatsapp/VerifySms;)J
        //  1851: invokestatic    com/whatsapp/VerifySms.c:(Lcom/whatsapp/VerifySms;J)V
        //  1854: goto            321
        //  1857: astore          89
        //  1859: new             Ljava/lang/StringBuilder;
        //  1862: dup            
        //  1863: invokespecial   java/lang/StringBuilder.<init>:()V
        //  1866: getstatic       com/whatsapp/hq.z:[Ljava/lang/String;
        //  1869: bipush          63
        //  1871: aaload         
        //  1872: invokevirtual   java/lang/StringBuilder.append:(Ljava/lang/String;)Ljava/lang/StringBuilder;
        //  1875: aload_0        
        //  1876: getfield        com/whatsapp/hq.b:Ljava/lang/String;
        //  1879: invokevirtual   java/lang/StringBuilder.append:(Ljava/lang/String;)Ljava/lang/StringBuilder;
        //  1882: getstatic       com/whatsapp/hq.z:[Ljava/lang/String;
        //  1885: bipush          49
        //  1887: aaload         
        //  1888: invokevirtual   java/lang/StringBuilder.append:(Ljava/lang/String;)Ljava/lang/StringBuilder;
        //  1891: invokevirtual   java/lang/StringBuilder.toString:()Ljava/lang/String;
        //  1894: invokestatic    com/whatsapp/util/Log.w:(Ljava/lang/String;)V
        //  1897: aload_0        
        //  1898: getfield        com/whatsapp/hq.a:Lcom/whatsapp/VerifySms;
        //  1901: bipush          31
        //  1903: invokevirtual   com/whatsapp/VerifySms.d:(I)V
        //  1906: iload_2        
        //  1907: ifeq            321
        //  1910: getstatic       com/whatsapp/pf.ERROR_PROVIDER_TIMEOUT:Lcom/whatsapp/pf;
        //  1913: astore          52
        //  1915: aload_1        
        //  1916: aload           52
        //  1918: if_acmpne       2150
        //  1921: new             Ljava/lang/StringBuilder;
        //  1924: dup            
        //  1925: invokespecial   java/lang/StringBuilder.<init>:()V
        //  1928: getstatic       com/whatsapp/hq.z:[Ljava/lang/String;
        //  1931: bipush          19
        //  1933: aaload         
        //  1934: invokevirtual   java/lang/StringBuilder.append:(Ljava/lang/String;)Ljava/lang/StringBuilder;
        //  1937: aload_0        
        //  1938: getfield        com/whatsapp/hq.b:Ljava/lang/String;
        //  1941: invokevirtual   java/lang/StringBuilder.append:(Ljava/lang/String;)Ljava/lang/StringBuilder;
        //  1944: getstatic       com/whatsapp/hq.z:[Ljava/lang/String;
        //  1947: bipush          56
        //  1949: aaload         
        //  1950: invokevirtual   java/lang/StringBuilder.append:(Ljava/lang/String;)Ljava/lang/StringBuilder;
        //  1953: invokevirtual   java/lang/StringBuilder.toString:()Ljava/lang/String;
        //  1956: invokestatic    com/whatsapp/util/Log.e:(Ljava/lang/String;)V
        //  1959: aload_0        
        //  1960: getfield        com/whatsapp/hq.a:Lcom/whatsapp/VerifySms;
        //  1963: getstatic       com/whatsapp/hq.z:[Ljava/lang/String;
        //  1966: bipush          28
        //  1968: aaload         
        //  1969: invokevirtual   com/whatsapp/VerifySms.c:(Ljava/lang/String;)V
        //  1972: aload_0        
        //  1973: getfield        com/whatsapp/hq.c:Lcom/whatsapp/ct;
        //  1976: getfield        com/whatsapp/ct.g:Ljava/lang/String;
        //  1979: astore          81
        //  1981: aload           81
        //  1983: ifnonnull       2007
        //  1986: aload_0        
        //  1987: getfield        com/whatsapp/hq.a:Lcom/whatsapp/VerifySms;
        //  1990: aload_0        
        //  1991: getfield        com/whatsapp/hq.a:Lcom/whatsapp/VerifySms;
        //  1994: ldc_w           2131231585
        //  1997: invokevirtual   com/whatsapp/VerifySms.getString:(I)Ljava/lang/String;
        //  2000: invokevirtual   com/whatsapp/VerifySms.d:(Ljava/lang/String;)V
        //  2003: iload_2        
        //  2004: ifeq            321
        //  2007: ldc2_w          1000
        //  2010: aload_0        
        //  2011: getfield        com/whatsapp/hq.c:Lcom/whatsapp/ct;
        //  2014: getfield        com/whatsapp/ct.g:Ljava/lang/String;
        //  2017: invokestatic    java/lang/Long.parseLong:(Ljava/lang/String;)J
        //  2020: lmul           
        //  2021: lstore          83
        //  2023: getstatic       com/whatsapp/App.aq:Lcom/whatsapp/App;
        //  2026: lload           83
        //  2028: invokevirtual   com/whatsapp/App.c:(J)V
        //  2031: aload_0        
        //  2032: getfield        com/whatsapp/hq.a:Lcom/whatsapp/VerifySms;
        //  2035: astore          85
        //  2037: aload_0        
        //  2038: getfield        com/whatsapp/hq.a:Lcom/whatsapp/VerifySms;
        //  2041: astore          86
        //  2043: iconst_1       
        //  2044: anewarray       Ljava/lang/Object;
        //  2047: astore          87
        //  2049: aload           87
        //  2051: iconst_0       
        //  2052: aload_0        
        //  2053: getfield        com/whatsapp/hq.a:Lcom/whatsapp/VerifySms;
        //  2056: lload           83
        //  2058: invokestatic    com/whatsapp/util/b6.n:(Landroid/content/Context;J)Ljava/lang/String;
        //  2061: aastore        
        //  2062: aload           85
        //  2064: aload           86
        //  2066: ldc_w           2131231584
        //  2069: aload           87
        //  2071: invokevirtual   com/whatsapp/VerifySms.getString:(I[Ljava/lang/Object;)Ljava/lang/String;
        //  2074: invokevirtual   com/whatsapp/VerifySms.d:(Ljava/lang/String;)V
        //  2077: aload_0        
        //  2078: getfield        com/whatsapp/hq.a:Lcom/whatsapp/VerifySms;
        //  2081: lload           83
        //  2083: invokestatic    com/whatsapp/VerifySms.c:(Lcom/whatsapp/VerifySms;J)V
        //  2086: goto            321
        //  2089: astore          82
        //  2091: new             Ljava/lang/StringBuilder;
        //  2094: dup            
        //  2095: invokespecial   java/lang/StringBuilder.<init>:()V
        //  2098: getstatic       com/whatsapp/hq.z:[Ljava/lang/String;
        //  2101: bipush          29
        //  2103: aaload         
        //  2104: invokevirtual   java/lang/StringBuilder.append:(Ljava/lang/String;)Ljava/lang/StringBuilder;
        //  2107: aload_0        
        //  2108: getfield        com/whatsapp/hq.b:Ljava/lang/String;
        //  2111: invokevirtual   java/lang/StringBuilder.append:(Ljava/lang/String;)Ljava/lang/StringBuilder;
        //  2114: getstatic       com/whatsapp/hq.z:[Ljava/lang/String;
        //  2117: bipush          68
        //  2119: aaload         
        //  2120: invokevirtual   java/lang/StringBuilder.append:(Ljava/lang/String;)Ljava/lang/StringBuilder;
        //  2123: invokevirtual   java/lang/StringBuilder.toString:()Ljava/lang/String;
        //  2126: invokestatic    com/whatsapp/util/Log.w:(Ljava/lang/String;)V
        //  2129: aload_0        
        //  2130: getfield        com/whatsapp/hq.a:Lcom/whatsapp/VerifySms;
        //  2133: aload_0        
        //  2134: getfield        com/whatsapp/hq.a:Lcom/whatsapp/VerifySms;
        //  2137: ldc_w           2131231585
        //  2140: invokevirtual   com/whatsapp/VerifySms.getString:(I)Ljava/lang/String;
        //  2143: invokevirtual   com/whatsapp/VerifySms.d:(Ljava/lang/String;)V
        //  2146: iload_2        
        //  2147: ifeq            321
        //  2150: getstatic       com/whatsapp/pf.ERROR_PROVIDER_UNROUTABLE:Lcom/whatsapp/pf;
        //  2153: astore          56
        //  2155: aload_1        
        //  2156: aload           56
        //  2158: if_acmpne       2390
        //  2161: new             Ljava/lang/StringBuilder;
        //  2164: dup            
        //  2165: invokespecial   java/lang/StringBuilder.<init>:()V
        //  2168: getstatic       com/whatsapp/hq.z:[Ljava/lang/String;
        //  2171: bipush          51
        //  2173: aaload         
        //  2174: invokevirtual   java/lang/StringBuilder.append:(Ljava/lang/String;)Ljava/lang/StringBuilder;
        //  2177: aload_0        
        //  2178: getfield        com/whatsapp/hq.b:Ljava/lang/String;
        //  2181: invokevirtual   java/lang/StringBuilder.append:(Ljava/lang/String;)Ljava/lang/StringBuilder;
        //  2184: getstatic       com/whatsapp/hq.z:[Ljava/lang/String;
        //  2187: bipush          69
        //  2189: aaload         
        //  2190: invokevirtual   java/lang/StringBuilder.append:(Ljava/lang/String;)Ljava/lang/StringBuilder;
        //  2193: invokevirtual   java/lang/StringBuilder.toString:()Ljava/lang/String;
        //  2196: invokestatic    com/whatsapp/util/Log.e:(Ljava/lang/String;)V
        //  2199: aload_0        
        //  2200: getfield        com/whatsapp/hq.a:Lcom/whatsapp/VerifySms;
        //  2203: getstatic       com/whatsapp/hq.z:[Ljava/lang/String;
        //  2206: bipush          11
        //  2208: aaload         
        //  2209: invokevirtual   com/whatsapp/VerifySms.c:(Ljava/lang/String;)V
        //  2212: aload_0        
        //  2213: getfield        com/whatsapp/hq.c:Lcom/whatsapp/ct;
        //  2216: getfield        com/whatsapp/ct.g:Ljava/lang/String;
        //  2219: astore          74
        //  2221: aload           74
        //  2223: ifnonnull       2247
        //  2226: aload_0        
        //  2227: getfield        com/whatsapp/hq.a:Lcom/whatsapp/VerifySms;
        //  2230: aload_0        
        //  2231: getfield        com/whatsapp/hq.a:Lcom/whatsapp/VerifySms;
        //  2234: ldc_w           2131231587
        //  2237: invokevirtual   com/whatsapp/VerifySms.getString:(I)Ljava/lang/String;
        //  2240: invokevirtual   com/whatsapp/VerifySms.d:(Ljava/lang/String;)V
        //  2243: iload_2        
        //  2244: ifeq            321
        //  2247: ldc2_w          1000
        //  2250: aload_0        
        //  2251: getfield        com/whatsapp/hq.c:Lcom/whatsapp/ct;
        //  2254: getfield        com/whatsapp/ct.g:Ljava/lang/String;
        //  2257: invokestatic    java/lang/Long.parseLong:(Ljava/lang/String;)J
        //  2260: lmul           
        //  2261: lstore          76
        //  2263: getstatic       com/whatsapp/App.aq:Lcom/whatsapp/App;
        //  2266: lload           76
        //  2268: invokevirtual   com/whatsapp/App.c:(J)V
        //  2271: aload_0        
        //  2272: getfield        com/whatsapp/hq.a:Lcom/whatsapp/VerifySms;
        //  2275: astore          78
        //  2277: aload_0        
        //  2278: getfield        com/whatsapp/hq.a:Lcom/whatsapp/VerifySms;
        //  2281: astore          79
        //  2283: iconst_1       
        //  2284: anewarray       Ljava/lang/Object;
        //  2287: astore          80
        //  2289: aload           80
        //  2291: iconst_0       
        //  2292: aload_0        
        //  2293: getfield        com/whatsapp/hq.a:Lcom/whatsapp/VerifySms;
        //  2296: lload           76
        //  2298: invokestatic    com/whatsapp/util/b6.n:(Landroid/content/Context;J)Ljava/lang/String;
        //  2301: aastore        
        //  2302: aload           78
        //  2304: aload           79
        //  2306: ldc_w           2131231586
        //  2309: aload           80
        //  2311: invokevirtual   com/whatsapp/VerifySms.getString:(I[Ljava/lang/Object;)Ljava/lang/String;
        //  2314: invokevirtual   com/whatsapp/VerifySms.d:(Ljava/lang/String;)V
        //  2317: aload_0        
        //  2318: getfield        com/whatsapp/hq.a:Lcom/whatsapp/VerifySms;
        //  2321: lload           76
        //  2323: invokestatic    com/whatsapp/VerifySms.c:(Lcom/whatsapp/VerifySms;J)V
        //  2326: goto            321
        //  2329: astore          75
        //  2331: new             Ljava/lang/StringBuilder;
        //  2334: dup            
        //  2335: invokespecial   java/lang/StringBuilder.<init>:()V
        //  2338: getstatic       com/whatsapp/hq.z:[Ljava/lang/String;
        //  2341: bipush          25
        //  2343: aaload         
        //  2344: invokevirtual   java/lang/StringBuilder.append:(Ljava/lang/String;)Ljava/lang/StringBuilder;
        //  2347: aload_0        
        //  2348: getfield        com/whatsapp/hq.b:Ljava/lang/String;
        //  2351: invokevirtual   java/lang/StringBuilder.append:(Ljava/lang/String;)Ljava/lang/StringBuilder;
        //  2354: getstatic       com/whatsapp/hq.z:[Ljava/lang/String;
        //  2357: bipush          14
        //  2359: aaload         
        //  2360: invokevirtual   java/lang/StringBuilder.append:(Ljava/lang/String;)Ljava/lang/StringBuilder;
        //  2363: invokevirtual   java/lang/StringBuilder.toString:()Ljava/lang/String;
        //  2366: invokestatic    com/whatsapp/util/Log.w:(Ljava/lang/String;)V
        //  2369: aload_0        
        //  2370: getfield        com/whatsapp/hq.a:Lcom/whatsapp/VerifySms;
        //  2373: aload_0        
        //  2374: getfield        com/whatsapp/hq.a:Lcom/whatsapp/VerifySms;
        //  2377: ldc_w           2131231587
        //  2380: invokevirtual   com/whatsapp/VerifySms.getString:(I)Ljava/lang/String;
        //  2383: invokevirtual   com/whatsapp/VerifySms.d:(Ljava/lang/String;)V
        //  2386: iload_2        
        //  2387: ifeq            321
        //  2390: getstatic       com/whatsapp/pf.ERROR_NO_ROUTES:Lcom/whatsapp/pf;
        //  2393: astore          60
        //  2395: aload_1        
        //  2396: aload           60
        //  2398: if_acmpne       2630
        //  2401: new             Ljava/lang/StringBuilder;
        //  2404: dup            
        //  2405: invokespecial   java/lang/StringBuilder.<init>:()V
        //  2408: getstatic       com/whatsapp/hq.z:[Ljava/lang/String;
        //  2411: bipush          9
        //  2413: aaload         
        //  2414: invokevirtual   java/lang/StringBuilder.append:(Ljava/lang/String;)Ljava/lang/StringBuilder;
        //  2417: aload_0        
        //  2418: getfield        com/whatsapp/hq.b:Ljava/lang/String;
        //  2421: invokevirtual   java/lang/StringBuilder.append:(Ljava/lang/String;)Ljava/lang/StringBuilder;
        //  2424: getstatic       com/whatsapp/hq.z:[Ljava/lang/String;
        //  2427: bipush          53
        //  2429: aaload         
        //  2430: invokevirtual   java/lang/StringBuilder.append:(Ljava/lang/String;)Ljava/lang/StringBuilder;
        //  2433: invokevirtual   java/lang/StringBuilder.toString:()Ljava/lang/String;
        //  2436: invokestatic    com/whatsapp/util/Log.w:(Ljava/lang/String;)V
        //  2439: aload_0        
        //  2440: getfield        com/whatsapp/hq.a:Lcom/whatsapp/VerifySms;
        //  2443: getstatic       com/whatsapp/hq.z:[Ljava/lang/String;
        //  2446: bipush          65
        //  2448: aaload         
        //  2449: invokevirtual   com/whatsapp/VerifySms.c:(Ljava/lang/String;)V
        //  2452: aload_0        
        //  2453: getfield        com/whatsapp/hq.c:Lcom/whatsapp/ct;
        //  2456: getfield        com/whatsapp/ct.g:Ljava/lang/String;
        //  2459: astore          67
        //  2461: aload           67
        //  2463: ifnonnull       2487
        //  2466: aload_0        
        //  2467: getfield        com/whatsapp/hq.a:Lcom/whatsapp/VerifySms;
        //  2470: aload_0        
        //  2471: getfield        com/whatsapp/hq.a:Lcom/whatsapp/VerifySms;
        //  2474: ldc_w           2131231587
        //  2477: invokevirtual   com/whatsapp/VerifySms.getString:(I)Ljava/lang/String;
        //  2480: invokevirtual   com/whatsapp/VerifySms.d:(Ljava/lang/String;)V
        //  2483: iload_2        
        //  2484: ifeq            321
        //  2487: ldc2_w          1000
        //  2490: aload_0        
        //  2491: getfield        com/whatsapp/hq.c:Lcom/whatsapp/ct;
        //  2494: getfield        com/whatsapp/ct.g:Ljava/lang/String;
        //  2497: invokestatic    java/lang/Long.parseLong:(Ljava/lang/String;)J
        //  2500: lmul           
        //  2501: lstore          69
        //  2503: getstatic       com/whatsapp/App.aq:Lcom/whatsapp/App;
        //  2506: lload           69
        //  2508: invokevirtual   com/whatsapp/App.c:(J)V
        //  2511: aload_0        
        //  2512: getfield        com/whatsapp/hq.a:Lcom/whatsapp/VerifySms;
        //  2515: astore          71
        //  2517: aload_0        
        //  2518: getfield        com/whatsapp/hq.a:Lcom/whatsapp/VerifySms;
        //  2521: astore          72
        //  2523: iconst_1       
        //  2524: anewarray       Ljava/lang/Object;
        //  2527: astore          73
        //  2529: aload           73
        //  2531: iconst_0       
        //  2532: aload_0        
        //  2533: getfield        com/whatsapp/hq.a:Lcom/whatsapp/VerifySms;
        //  2536: lload           69
        //  2538: invokestatic    com/whatsapp/util/b6.n:(Landroid/content/Context;J)Ljava/lang/String;
        //  2541: aastore        
        //  2542: aload           71
        //  2544: aload           72
        //  2546: ldc_w           2131231586
        //  2549: aload           73
        //  2551: invokevirtual   com/whatsapp/VerifySms.getString:(I[Ljava/lang/Object;)Ljava/lang/String;
        //  2554: invokevirtual   com/whatsapp/VerifySms.d:(Ljava/lang/String;)V
        //  2557: aload_0        
        //  2558: getfield        com/whatsapp/hq.a:Lcom/whatsapp/VerifySms;
        //  2561: lload           69
        //  2563: invokestatic    com/whatsapp/VerifySms.c:(Lcom/whatsapp/VerifySms;J)V
        //  2566: goto            321
        //  2569: astore          68
        //  2571: new             Ljava/lang/StringBuilder;
        //  2574: dup            
        //  2575: invokespecial   java/lang/StringBuilder.<init>:()V
        //  2578: getstatic       com/whatsapp/hq.z:[Ljava/lang/String;
        //  2581: bipush          18
        //  2583: aaload         
        //  2584: invokevirtual   java/lang/StringBuilder.append:(Ljava/lang/String;)Ljava/lang/StringBuilder;
        //  2587: aload_0        
        //  2588: getfield        com/whatsapp/hq.b:Ljava/lang/String;
        //  2591: invokevirtual   java/lang/StringBuilder.append:(Ljava/lang/String;)Ljava/lang/StringBuilder;
        //  2594: getstatic       com/whatsapp/hq.z:[Ljava/lang/String;
        //  2597: bipush          58
        //  2599: aaload         
        //  2600: invokevirtual   java/lang/StringBuilder.append:(Ljava/lang/String;)Ljava/lang/StringBuilder;
        //  2603: invokevirtual   java/lang/StringBuilder.toString:()Ljava/lang/String;
        //  2606: invokestatic    com/whatsapp/util/Log.w:(Ljava/lang/String;)V
        //  2609: aload_0        
        //  2610: getfield        com/whatsapp/hq.a:Lcom/whatsapp/VerifySms;
        //  2613: aload_0        
        //  2614: getfield        com/whatsapp/hq.a:Lcom/whatsapp/VerifySms;
        //  2617: ldc_w           2131231587
        //  2620: invokevirtual   com/whatsapp/VerifySms.getString:(I)Ljava/lang/String;
        //  2623: invokevirtual   com/whatsapp/VerifySms.d:(Ljava/lang/String;)V
        //  2626: iload_2        
        //  2627: ifeq            321
        //  2630: getstatic       com/whatsapp/pf.ERROR_BAD_TOKEN:Lcom/whatsapp/pf;
        //  2633: astore          62
        //  2635: aload_1        
        //  2636: aload           62
        //  2638: if_acmpne       321
        //  2641: new             Ljava/lang/StringBuilder;
        //  2644: dup            
        //  2645: invokespecial   java/lang/StringBuilder.<init>:()V
        //  2648: getstatic       com/whatsapp/hq.z:[Ljava/lang/String;
        //  2651: bipush          30
        //  2653: aaload         
        //  2654: invokevirtual   java/lang/StringBuilder.append:(Ljava/lang/String;)Ljava/lang/StringBuilder;
        //  2657: aload_0        
        //  2658: getfield        com/whatsapp/hq.b:Ljava/lang/String;
        //  2661: invokevirtual   java/lang/StringBuilder.append:(Ljava/lang/String;)Ljava/lang/StringBuilder;
        //  2664: getstatic       com/whatsapp/hq.z:[Ljava/lang/String;
        //  2667: bipush          34
        //  2669: aaload         
        //  2670: invokevirtual   java/lang/StringBuilder.append:(Ljava/lang/String;)Ljava/lang/StringBuilder;
        //  2673: invokevirtual   java/lang/StringBuilder.toString:()Ljava/lang/String;
        //  2676: invokestatic    com/whatsapp/util/Log.e:(Ljava/lang/String;)V
        //  2679: aload_0        
        //  2680: getfield        com/whatsapp/hq.a:Lcom/whatsapp/VerifySms;
        //  2683: getstatic       com/whatsapp/hq.z:[Ljava/lang/String;
        //  2686: bipush          52
        //  2688: aaload         
        //  2689: invokevirtual   com/whatsapp/VerifySms.c:(Ljava/lang/String;)V
        //  2692: getstatic       com/whatsapp/App.aS:I
        //  2695: iconst_2       
        //  2696: if_icmpne       2971
        //  2699: aload_0        
        //  2700: getfield        com/whatsapp/hq.a:Lcom/whatsapp/VerifySms;
        //  2703: ldc_w           2131231555
        //  2706: invokevirtual   com/whatsapp/VerifySms.getString:(I)Ljava/lang/String;
        //  2709: astore          65
        //  2711: aload_0        
        //  2712: getfield        com/whatsapp/hq.a:Lcom/whatsapp/VerifySms;
        //  2715: aload_0        
        //  2716: getfield        com/whatsapp/hq.a:Lcom/whatsapp/VerifySms;
        //  2719: ldc_w           2131231531
        //  2722: iconst_1       
        //  2723: anewarray       Ljava/lang/Object;
        //  2726: dup            
        //  2727: iconst_0       
        //  2728: aload           65
        //  2730: aastore        
        //  2731: invokevirtual   com/whatsapp/VerifySms.getString:(I[Ljava/lang/Object;)Ljava/lang/String;
        //  2734: invokevirtual   com/whatsapp/VerifySms.d:(Ljava/lang/String;)V
        //  2737: iload_2        
        //  2738: ifeq            321
        //  2741: aload_0        
        //  2742: getfield        com/whatsapp/hq.c:Lcom/whatsapp/ct;
        //  2745: getfield        com/whatsapp/ct.c:I
        //  2748: ifeq            2775
        //  2751: aload_0        
        //  2752: getfield        com/whatsapp/hq.c:Lcom/whatsapp/ct;
        //  2755: getfield        com/whatsapp/ct.c:I
        //  2758: invokestatic    com/whatsapp/VerifySms.i:(I)I
        //  2761: pop            
        //  2762: getstatic       com/whatsapp/App.aq:Lcom/whatsapp/App;
        //  2765: aload_0        
        //  2766: getfield        com/whatsapp/hq.c:Lcom/whatsapp/ct;
        //  2769: getfield        com/whatsapp/ct.c:I
        //  2772: invokestatic    com/whatsapp/App.d:(Landroid/content/Context;I)V
        //  2775: bipush          10
        //  2777: invokestatic    com/whatsapp/VerifySms.j:(I)I
        //  2780: pop            
        //  2781: aload_0        
        //  2782: getfield        com/whatsapp/hq.a:Lcom/whatsapp/VerifySms;
        //  2785: invokestatic    com/whatsapp/VerifySms.k:(Lcom/whatsapp/VerifySms;)V
        //  2788: goto            321
        //  2791: astore          12
        //  2793: aload           12
        //  2795: athrow         
        //  2796: astore          13
        //  2798: aload           13
        //  2800: athrow         
        //  2801: astore          14
        //  2803: aload           14
        //  2805: athrow         
        //  2806: astore          15
        //  2808: aload           15
        //  2810: athrow         
        //  2811: astore          16
        //  2813: aload           16
        //  2815: athrow         
        //  2816: astore          19
        //  2818: aload           19
        //  2820: athrow         
        //  2821: astore          20
        //  2823: aload           20
        //  2825: athrow         
        //  2826: astore          21
        //  2828: aload           21
        //  2830: athrow         
        //  2831: astore          23
        //  2833: aload           23
        //  2835: athrow         
        //  2836: astore          24
        //  2838: aload           24
        //  2840: athrow         
        //  2841: astore          25
        //  2843: aload           25
        //  2845: athrow         
        //  2846: astore          26
        //  2848: aload           26
        //  2850: athrow         
        //  2851: astore          27
        //  2853: aload           27
        //  2855: athrow         
        //  2856: astore          28
        //  2858: aload           28
        //  2860: athrow         
        //  2861: astore          29
        //  2863: aload           29
        //  2865: athrow         
        //  2866: astore          30
        //  2868: aload           30
        //  2870: athrow         
        //  2871: astore          31
        //  2873: aload           31
        //  2875: athrow         
        //  2876: astore          32
        //  2878: aload           32
        //  2880: athrow         
        //  2881: astore          33
        //  2883: aload           33
        //  2885: athrow         
        //  2886: astore          39
        //  2888: aload           39
        //  2890: athrow         
        //  2891: astore          40
        //  2893: aload           40
        //  2895: athrow         
        //  2896: astore          41
        //  2898: aload           41
        //  2900: athrow         
        //  2901: astore          42
        //  2903: aload           42
        //  2905: athrow         
        //  2906: astore          43
        //  2908: aload           43
        //  2910: athrow         
        //  2911: astore          44
        //  2913: aload           44
        //  2915: athrow         
        //  2916: astore          45
        //  2918: aload           45
        //  2920: athrow         
        //  2921: astore          49
        //  2923: aload           49
        //  2925: athrow         
        //  2926: astore          50
        //  2928: aload           50
        //  2930: athrow         
        //  2931: astore          51
        //  2933: aload           51
        //  2935: athrow         
        //  2936: astore          53
        //  2938: aload           53
        //  2940: athrow         
        //  2941: astore          54
        //  2943: aload           54
        //  2945: athrow         
        //  2946: astore          55
        //  2948: aload           55
        //  2950: athrow         
        //  2951: astore          57
        //  2953: aload           57
        //  2955: athrow         
        //  2956: astore          58
        //  2958: aload           58
        //  2960: athrow         
        //  2961: astore          59
        //  2963: aload           59
        //  2965: athrow         
        //  2966: astore          61
        //  2968: aload           61
        //  2970: athrow         
        //  2971: getstatic       com/whatsapp/App.aS:I
        //  2974: ifne            2992
        //  2977: aload_0        
        //  2978: getfield        com/whatsapp/hq.a:Lcom/whatsapp/VerifySms;
        //  2981: ldc_w           2131231556
        //  2984: invokevirtual   com/whatsapp/VerifySms.getString:(I)Ljava/lang/String;
        //  2987: astore          65
        //  2989: goto            2711
        //  2992: aload_0        
        //  2993: getfield        com/whatsapp/hq.a:Lcom/whatsapp/VerifySms;
        //  2996: astore          63
        //  2998: iconst_1       
        //  2999: anewarray       Ljava/lang/Object;
        //  3002: astore          64
        //  3004: aload           64
        //  3006: iconst_0       
        //  3007: getstatic       com/whatsapp/hq.z:[Ljava/lang/String;
        //  3010: bipush          26
        //  3012: aaload         
        //  3013: aastore        
        //  3014: aload           63
        //  3016: ldc_w           2131231557
        //  3019: aload           64
        //  3021: invokevirtual   com/whatsapp/VerifySms.getString:(I[Ljava/lang/Object;)Ljava/lang/String;
        //  3024: astore          65
        //  3026: goto            2711
        //  3029: astore          66
        //  3031: aload           66
        //  3033: athrow         
        //  3034: astore          8
        //  3036: aload           8
        //  3038: athrow         
        //    Exceptions:
        //  Try           Handler
        //  Start  End    Start  End    Type                             
        //  -----  -----  -----  -----  ---------------------------------
        //  105    122    329    372    Ljava/lang/NumberFormatException;
        //  122    130    372    375    Ljava/lang/NumberFormatException;
        //  134    139    372    375    Ljava/lang/NumberFormatException;
        //  145    150    375    380    Ljava/lang/NumberFormatException;
        //  156    216    380    385    Ljava/lang/NumberFormatException;
        //  221    238    385    390    Ljava/lang/NumberFormatException;
        //  242    321    390    451    Ljava/lang/NumberFormatException;
        //  373    375    375    380    Ljava/lang/NumberFormatException;
        //  377    380    380    385    Ljava/lang/NumberFormatException;
        //  382    385    385    390    Ljava/lang/NumberFormatException;
        //  392    447    2791   2796   Ljava/lang/NumberFormatException;
        //  451    456    2791   2796   Ljava/lang/NumberFormatException;
        //  462    522    2796   2801   Ljava/lang/NumberFormatException;
        //  526    531    2801   2806   Ljava/lang/NumberFormatException;
        //  537    602    2806   2811   Ljava/lang/NumberFormatException;
        //  607    616    2811   2816   Ljava/lang/NumberFormatException;
        //  620    720    723    776    Ljava/lang/NumberFormatException;
        //  725    772    2816   2821   Ljava/lang/NumberFormatException;
        //  776    781    2816   2821   Ljava/lang/NumberFormatException;
        //  787    852    2821   2826   Ljava/lang/NumberFormatException;
        //  857    866    2826   2831   Ljava/lang/NumberFormatException;
        //  870    928    931    984    Ljava/lang/NumberFormatException;
        //  933    980    2831   2836   Ljava/lang/NumberFormatException;
        //  984    989    2831   2836   Ljava/lang/NumberFormatException;
        //  995    1042   2836   2841   Ljava/lang/NumberFormatException;
        //  1046   1051   2841   2846   Ljava/lang/NumberFormatException;
        //  1057   1126   2846   2851   Ljava/lang/NumberFormatException;
        //  1130   1135   2851   2856   Ljava/lang/NumberFormatException;
        //  1141   1210   2856   2861   Ljava/lang/NumberFormatException;
        //  1214   1219   2861   2866   Ljava/lang/NumberFormatException;
        //  1225   1285   2866   2871   Ljava/lang/NumberFormatException;
        //  1289   1294   2871   2876   Ljava/lang/NumberFormatException;
        //  1300   1370   2876   2881   Ljava/lang/NumberFormatException;
        //  1375   1392   2881   2886   Ljava/lang/NumberFormatException;
        //  1396   1475   1478   1539   Ljava/lang/NumberFormatException;
        //  1480   1535   2886   2891   Ljava/lang/NumberFormatException;
        //  1539   1544   2886   2891   Ljava/lang/NumberFormatException;
        //  1550   1628   2891   2896   Ljava/lang/NumberFormatException;
        //  1632   1637   2896   2901   Ljava/lang/NumberFormatException;
        //  1643   1703   2901   2906   Ljava/lang/NumberFormatException;
        //  1707   1712   2906   2911   Ljava/lang/NumberFormatException;
        //  1718   1778   2911   2916   Ljava/lang/NumberFormatException;
        //  1783   1792   2916   2921   Ljava/lang/NumberFormatException;
        //  1796   1854   1857   1910   Ljava/lang/NumberFormatException;
        //  1859   1906   2921   2926   Ljava/lang/NumberFormatException;
        //  1910   1915   2921   2926   Ljava/lang/NumberFormatException;
        //  1921   1981   2926   2931   Ljava/lang/NumberFormatException;
        //  1986   2003   2931   2936   Ljava/lang/NumberFormatException;
        //  2007   2086   2089   2150   Ljava/lang/NumberFormatException;
        //  2091   2146   2936   2941   Ljava/lang/NumberFormatException;
        //  2150   2155   2936   2941   Ljava/lang/NumberFormatException;
        //  2161   2221   2941   2946   Ljava/lang/NumberFormatException;
        //  2226   2243   2946   2951   Ljava/lang/NumberFormatException;
        //  2247   2326   2329   2390   Ljava/lang/NumberFormatException;
        //  2331   2386   2951   2956   Ljava/lang/NumberFormatException;
        //  2390   2395   2951   2956   Ljava/lang/NumberFormatException;
        //  2401   2461   2956   2961   Ljava/lang/NumberFormatException;
        //  2466   2483   2961   2966   Ljava/lang/NumberFormatException;
        //  2487   2566   2569   2630   Ljava/lang/NumberFormatException;
        //  2571   2626   2966   2971   Ljava/lang/NumberFormatException;
        //  2630   2635   2966   2971   Ljava/lang/NumberFormatException;
        //  2711   2737   3029   3034   Ljava/lang/NumberFormatException;
        //  2741   2775   3034   3039   Ljava/lang/NumberFormatException;
        //  2793   2796   2796   2801   Ljava/lang/NumberFormatException;
        //  2798   2801   2801   2806   Ljava/lang/NumberFormatException;
        //  2803   2806   2806   2811   Ljava/lang/NumberFormatException;
        //  2808   2811   2811   2816   Ljava/lang/NumberFormatException;
        //  2818   2821   2821   2826   Ljava/lang/NumberFormatException;
        //  2823   2826   2826   2831   Ljava/lang/NumberFormatException;
        //  2833   2836   2836   2841   Ljava/lang/NumberFormatException;
        //  2838   2841   2841   2846   Ljava/lang/NumberFormatException;
        //  2843   2846   2846   2851   Ljava/lang/NumberFormatException;
        //  2848   2851   2851   2856   Ljava/lang/NumberFormatException;
        //  2853   2856   2856   2861   Ljava/lang/NumberFormatException;
        //  2858   2861   2861   2866   Ljava/lang/NumberFormatException;
        //  2863   2866   2866   2871   Ljava/lang/NumberFormatException;
        //  2868   2871   2871   2876   Ljava/lang/NumberFormatException;
        //  2873   2876   2876   2881   Ljava/lang/NumberFormatException;
        //  2878   2881   2881   2886   Ljava/lang/NumberFormatException;
        //  2888   2891   2891   2896   Ljava/lang/NumberFormatException;
        //  2893   2896   2896   2901   Ljava/lang/NumberFormatException;
        //  2898   2901   2901   2906   Ljava/lang/NumberFormatException;
        //  2903   2906   2906   2911   Ljava/lang/NumberFormatException;
        //  2908   2911   2911   2916   Ljava/lang/NumberFormatException;
        //  2913   2916   2916   2921   Ljava/lang/NumberFormatException;
        //  2923   2926   2926   2931   Ljava/lang/NumberFormatException;
        //  2928   2931   2931   2936   Ljava/lang/NumberFormatException;
        //  2938   2941   2941   2946   Ljava/lang/NumberFormatException;
        //  2943   2946   2946   2951   Ljava/lang/NumberFormatException;
        //  2953   2956   2956   2961   Ljava/lang/NumberFormatException;
        //  2958   2961   2961   2966   Ljava/lang/NumberFormatException;
        //  3031   3034   3034   3039   Ljava/lang/NumberFormatException;
        // 
        // The error that occurred was:
        // 
        // java.lang.IndexOutOfBoundsException: Index: 1369, Size: 1369
        //     at java.util.ArrayList.rangeCheck(ArrayList.java:653)
        //     at java.util.ArrayList.get(ArrayList.java:429)
        //     at com.strobel.decompiler.ast.AstBuilder.convertToAst(AstBuilder.java:3303)
        //     at com.strobel.decompiler.ast.AstBuilder.build(AstBuilder.java:113)
        //     at com.strobel.decompiler.languages.java.ast.AstMethodBodyBuilder.createMethodBody(AstMethodBodyBuilder.java:210)
        //     at com.strobel.decompiler.languages.java.ast.AstMethodBodyBuilder.createMethodBody(AstMethodBodyBuilder.java:99)
        //     at com.strobel.decompiler.languages.java.ast.AstBuilder.createMethodBody(AstBuilder.java:757)
        //     at com.strobel.decompiler.languages.java.ast.AstBuilder.createMethod(AstBuilder.java:655)
        //     at com.strobel.decompiler.languages.java.ast.AstBuilder.addTypeMembers(AstBuilder.java:532)
        //     at com.strobel.decompiler.languages.java.ast.AstBuilder.createTypeCore(AstBuilder.java:499)
        //     at com.strobel.decompiler.languages.java.ast.AstBuilder.createTypeNoCache(AstBuilder.java:141)
        //     at com.strobel.decompiler.languages.java.ast.AstBuilder.createType(AstBuilder.java:130)
        //     at com.strobel.decompiler.languages.java.ast.AstBuilder.addType(AstBuilder.java:105)
        //     at com.strobel.decompiler.languages.java.JavaLanguage.buildAst(JavaLanguage.java:71)
        //     at com.strobel.decompiler.languages.java.JavaLanguage.decompileType(JavaLanguage.java:59)
        //     at com.strobel.decompiler.DecompilerDriver.decompileType(DecompilerDriver.java:317)
        //     at com.strobel.decompiler.DecompilerDriver.decompileJar(DecompilerDriver.java:238)
        //     at com.strobel.decompiler.DecompilerDriver.main(DecompilerDriver.java:123)
        // 
        throw new IllegalStateException("An error occurred while decompiling this method.");
    }
    
    protected Object doInBackground(final Object[] array) {
        return this.a((String[])array);
    }
    
    protected void onPostExecute(final Object o) {
        this.a((pf)o);
    }
    
    protected void onPreExecute() {
        try {
            if (!this.a.isFinishing()) {
                this.a.showDialog(25);
            }
        }
        catch (NumberFormatException ex) {
            throw ex;
        }
    }
}
