// 
// Decompiled by Procyon v0.5.30
// 

package com.whatsapp;

import android.text.TextUtils;
import android.net.NetworkInfo;
import java.util.Iterator;
import java.util.Locale;
import java.util.HashMap;
import java.util.Map;
import java.util.ArrayList;

public class vi
{
    private static String[][] a;
    private static boolean b;
    private static ArrayList c;
    private static final Map d;
    private static String[][] e;
    private static String[][] f;
    private static final String[] z;
    
    static {
        String[] array = new String[6];
        int n = 0;
        String s = "P\u001bd";
        int n2 = -1;
        final String[] z2 = array;
        String[] array2 = null;
        int n5 = 0;
        String intern2 = null;
        String[][] array3 = null;
        int n6 = 0;
        String[] array4 = null;
        String[][] a = null;
    Label_0016:
        while (true) {
            while (true) {
                final char[] charArray = s.toCharArray();
                final int length = charArray.length;
                int n3 = 0;
            Label_0267_Outer:
                while (true) {
                    while (true) {
                    Label_0365_Outer:
                        while (true) {
                            Locale[] availableLocales = null;
                            int n4 = 0;
                            while (true) {
                                final int length2;
                                Label_0273: {
                                    if (length > n3) {
                                        break Label_0273;
                                    }
                                    final String intern = new String(charArray).intern();
                                    switch (n2) {
                                        default: {
                                            array[n] = intern;
                                            n = 1;
                                            s = "\nM(.\u0004\u001bK83_\u0005M<$_\u000bC9m\u001e\u001cO?%\u0002S\u0002";
                                            array = z2;
                                            n2 = 0;
                                            continue Label_0016;
                                        }
                                        case 0: {
                                            array[n] = intern;
                                            n = 2;
                                            s = "\nM(.\u0004\u001bK83_\u0005M<$_\u001cL.5\u0000\u0019M/4\u0015\r\u000f8.\u0013\u0006F4.\u0017S\u0002\b\u00146D\u001a";
                                            n2 = 1;
                                            array = z2;
                                            continue Label_0016;
                                        }
                                        case 1: {
                                            array[n] = intern;
                                            n = 3;
                                            s = "<v\u001bmH";
                                            n2 = 2;
                                            array = z2;
                                            continue Label_0016;
                                        }
                                        case 2: {
                                            array[n] = intern;
                                            n = 4;
                                            s = "\nM(.\u0004\u001bK83_\u0006R8.";
                                            n2 = 3;
                                            array = z2;
                                            continue Label_0016;
                                        }
                                        case 3: {
                                            array[n] = intern;
                                            n = 5;
                                            s = "\nM(.\u0004\u001bK83_\u0005M<$_\u000bC9m\u001c\u0000L8zP";
                                            n2 = 4;
                                            array = z2;
                                            continue Label_0016;
                                        }
                                        case 4: {
                                            array[n] = intern;
                                            z = z2;
                                            vi.b = false;
                                            d = new HashMap();
                                            availableLocales = Locale.getAvailableLocales();
                                            length2 = availableLocales.length;
                                            n4 = 0;
                                            break Label_0273;
                                        }
                                    }
                                Label_0409_Outer:
                                    while (true) {
                                    Label_0409:
                                        while (true) {
                                            try {
                                                final String country;
                                                if (!vi.d.containsKey(country)) {
                                                    final Locale locale;
                                                    vi.d.put(country, locale);
                                                }
                                                ++n4;
                                                break;
                                                Label_1181: {
                                                    final char c = 'i';
                                                }
                                                while (true) {
                                                    break Label_1164;
                                                    Label_1068:
                                                    array2[n5] = intern2;
                                                    array3[n6] = array4;
                                                    array2 = new String[] { "1", null };
                                                    n5 = 1;
                                                    String s2 = "?G/)\n\u0006L";
                                                    n6 = 1;
                                                    array3 = a;
                                                    array4 = array2;
                                                    int n7 = 0;
                                                    break Label_0409;
                                                    char[] charArray2 = null;
                                                    int n8 = 0;
                                                    Label_1118:
                                                    final char c2 = charArray2[n8];
                                                    Label_0351:
                                                    char c3 = ']';
                                                Label_0424_Outer:
                                                    while (true) {
                                                        break Label_0320;
                                                        Label_0337:
                                                        c3 = 'i';
                                                        break Label_0320;
                                                        Label_1188:
                                                        char c = '\"';
                                                        break Label_1164;
                                                        while (true) {
                                                            Block_6: {
                                                                break Block_6;
                                                                final String[][] array5 = new String[18][];
                                                                array2 = new String[] { "1", null };
                                                                n5 = 1;
                                                                s2 = ":R/)\u001e\u001d";
                                                                n7 = -1;
                                                                array3 = array5;
                                                                a = array5;
                                                                n6 = 0;
                                                                array4 = array2;
                                                                break Label_0409;
                                                            }
                                                            intern2 = new String(charArray2).intern();
                                                            Label_1195:
                                                            c = ']';
                                                            charArray2[n8] = (char)(c ^ c2);
                                                            ++n8;
                                                            continue Label_0365_Outer;
                                                            Label_0316:
                                                            c3 = 'p';
                                                            final char c4;
                                                            charArray[n3] = (char)(c3 ^ c4);
                                                            ++n3;
                                                            continue Label_0267_Outer;
                                                            Label_0344:
                                                            c3 = '\"';
                                                            continue Label_0424_Outer;
                                                            charArray2 = s2.toCharArray();
                                                            final int length3 = charArray2.length;
                                                            n8 = 0;
                                                            continue Label_0365_Outer;
                                                        }
                                                        final char c4 = charArray[n3];
                                                        Label_1160:
                                                        c = 'p';
                                                        continue Label_0409_Outer;
                                                        Label_0358:
                                                        c3 = '@';
                                                        continue Label_0424_Outer;
                                                    }
                                                    Label_1202:
                                                    char c = '@';
                                                    continue Label_0409_Outer;
                                                }
                                            }
                                            // switch([Lcom.strobel.decompiler.ast.Label;@639421a, n8 % 5)
                                            // iftrue(Label_1118:, length3 > n8)
                                            // switch([Lcom.strobel.decompiler.ast.Label;@7b3278ab, n7)
                                            // switch([Lcom.strobel.decompiler.ast.Label;@1bcf945e, n3 % 5)
                                            catch (IllegalArgumentException ex) {
                                                throw ex;
                                            }
                                            Label_1214: {
                                                array2[n5] = intern2;
                                            }
                                            array3[n6] = array4;
                                            array2 = new String[] { "1", null };
                                            n5 = 1;
                                            String s2 = "$G)2\u001f9a\u000e";
                                            int n7 = 1;
                                            n6 = 2;
                                            array3 = a;
                                            array4 = array2;
                                            continue Label_0409;
                                            Label_1264:
                                            array2[n5] = intern2;
                                            array3[n6] = array4;
                                            array2 = new String[] { "1", null };
                                            n5 = 1;
                                            s2 = "?G/)\n\u0006L}\u0017\u0019\u001bG1%\u0003\u001a";
                                            n7 = 2;
                                            n6 = 3;
                                            array3 = a;
                                            array4 = array2;
                                            continue Label_0409;
                                            Label_1314:
                                            array2[n5] = intern2;
                                            array3[n6] = array4;
                                            array2 = new String[] { "1", null };
                                            n5 = 1;
                                            s2 = "*G1,\u0005\u0005C/`#\u0006W)(";
                                            n7 = 3;
                                            n6 = 4;
                                            array3 = a;
                                            array4 = array2;
                                            continue Label_0409;
                                            Label_1364:
                                            array2[n5] = intern2;
                                            array3[n6] = array4;
                                            array2 = new String[] { "1", null };
                                            n5 = 1;
                                            s2 = "<\f\u000en3\fN15\u001c\bP";
                                            n7 = 4;
                                            n6 = 5;
                                            array3 = a;
                                            array4 = array2;
                                            continue Label_0409;
                                            Label_1414:
                                            array2[n5] = intern2;
                                            array3[n6] = array4;
                                            array2 = new String[] { "1", null };
                                            n5 = 1;
                                            s2 = "<\f\u000enP*G1,\u0005\u0005C/";
                                            n7 = 5;
                                            n6 = 6;
                                            array3 = a;
                                            array4 = array2;
                                            continue Label_0409;
                                            Label_1465:
                                            array2[n5] = intern2;
                                            array3[n6] = array4;
                                            array2 = new String[] { "1", null };
                                            n5 = 1;
                                            s2 = ",Z)%\u001e\rG9`>\fV*/\u0002\u0002";
                                            n7 = 6;
                                            n6 = 7;
                                            array3 = a;
                                            array4 = array2;
                                            continue Label_0409;
                                            Label_1517:
                                            array2[n5] = intern2;
                                            array3[n6] = array4;
                                            array2 = new String[2];
                                            s2 = "Z\u001a";
                                            n7 = 7;
                                            n6 = 8;
                                            array3 = a;
                                            array4 = array2;
                                            n5 = 0;
                                            continue Label_0409;
                                            Label_1563:
                                            array2[n5] = intern2;
                                            n5 = 1;
                                            s2 = ":R/)\u001e\u001d";
                                            n7 = 8;
                                            array2 = array4;
                                            continue Label_0409;
                                            Label_1588:
                                            array2[n5] = intern2;
                                            array3[n6] = array4;
                                            array2 = new String[2];
                                            s2 = "Z\u001a";
                                            n7 = 9;
                                            n6 = 9;
                                            array3 = a;
                                            array4 = array2;
                                            n5 = 0;
                                            continue Label_0409;
                                            Label_1634:
                                            array2[n5] = intern2;
                                            n5 = 1;
                                            s2 = "?G/)\n\u0006L";
                                            n7 = 10;
                                            array2 = array4;
                                            continue Label_0409;
                                            Label_1659:
                                            array2[n5] = intern2;
                                            array3[n6] = array4;
                                            array2 = new String[2];
                                            s2 = "Z\u001a";
                                            n7 = 11;
                                            n6 = 10;
                                            array3 = a;
                                            array4 = array2;
                                            n5 = 0;
                                            continue Label_0409;
                                            Label_1705:
                                            array2[n5] = intern2;
                                            n5 = 1;
                                            s2 = "?G/)\n\u0006L}\u0017\u0019\u001bG1%\u0003\u001a";
                                            n7 = 12;
                                            array2 = array4;
                                            continue Label_0409;
                                            Label_1730:
                                            array2[n5] = intern2;
                                            array3[n6] = array4;
                                            array2 = new String[2];
                                            s2 = "\\\u0010";
                                            n7 = 13;
                                            n6 = 11;
                                            array3 = a;
                                            array4 = array2;
                                            n5 = 0;
                                            continue Label_0409;
                                            Label_1776:
                                            array2[n5] = intern2;
                                            n5 = 1;
                                            s2 = ":R/)\u001e\u001d";
                                            n7 = 14;
                                            array2 = array4;
                                            continue Label_0409;
                                            Label_1801:
                                            array2[n5] = intern2;
                                            array3[n6] = array4;
                                            array2 = new String[2];
                                            s2 = "Q\u0017m";
                                            n7 = 15;
                                            n6 = 12;
                                            array3 = a;
                                            array4 = array2;
                                            n5 = 0;
                                            continue Label_0409;
                                            Label_1847:
                                            array2[n5] = intern2;
                                            n5 = 1;
                                            s2 = "%e}\u0015[";
                                            n7 = 16;
                                            array2 = array4;
                                            continue Label_0409;
                                            Label_1872:
                                            array2[n5] = intern2;
                                            array3[n6] = array4;
                                            array2 = new String[2];
                                            s2 = "Q\u0017n";
                                            n7 = 17;
                                            n6 = 13;
                                            array3 = a;
                                            array4 = array2;
                                            n5 = 0;
                                            continue Label_0409;
                                            Label_1918:
                                            array2[n5] = intern2;
                                            n5 = 1;
                                            s2 = "*v\u001e";
                                            n7 = 18;
                                            array2 = array4;
                                            continue Label_0409;
                                            Label_1943:
                                            array2[n5] = intern2;
                                            array3[n6] = array4;
                                            array2 = new String[2];
                                            s2 = "_\u0014";
                                            n7 = 19;
                                            n6 = 14;
                                            array3 = a;
                                            array4 = array2;
                                            n5 = 0;
                                            continue Label_0409;
                                            Label_1989:
                                            array2[n5] = intern2;
                                            n5 = 1;
                                            s2 = "%e}\u0015[";
                                            n7 = 20;
                                            array2 = array4;
                                            continue Label_0409;
                                            Label_2014:
                                            array2[n5] = intern2;
                                            array3[n6] = array4;
                                            array2 = new String[2];
                                            s2 = "Q\u0014";
                                            n7 = 21;
                                            n6 = 15;
                                            array3 = a;
                                            array4 = array2;
                                            n5 = 0;
                                            continue Label_0409;
                                            Label_2060:
                                            array2[n5] = intern2;
                                            n5 = 1;
                                            s2 = "*v\u001e";
                                            n7 = 22;
                                            array2 = array4;
                                            continue Label_0409;
                                            Label_2085:
                                            array2[n5] = intern2;
                                            array3[n6] = array4;
                                            array2 = new String[2];
                                            s2 = "Q\u001ak";
                                            n7 = 23;
                                            n6 = 16;
                                            array3 = a;
                                            array4 = array2;
                                            n5 = 0;
                                            continue Label_0409;
                                            Label_2131:
                                            array2[n5] = intern2;
                                            n5 = 1;
                                            s2 = "(r\u001f\u0017";
                                            n7 = 24;
                                            array2 = array4;
                                            continue Label_0409;
                                            Label_2156:
                                            array2[n5] = intern2;
                                            array3[n6] = array4;
                                            array2 = new String[2];
                                            s2 = "Q\u001ak";
                                            n7 = 25;
                                            n6 = 17;
                                            array3 = a;
                                            array4 = array2;
                                            n5 = 0;
                                            continue Label_0409;
                                            Label_2202:
                                            array2[n5] = intern2;
                                            n5 = 1;
                                            s2 = "(r\t";
                                            n7 = 26;
                                            array2 = array4;
                                            continue Label_0409;
                                            Label_2227:
                                            array2[n5] = intern2;
                                            array3[n6] = array4;
                                            vi.e = a;
                                            final String[][] array6 = new String[30][];
                                            array2 = new String[] { "1", null };
                                            n5 = 1;
                                            s2 = ":R/)\u001e\u001d";
                                            n7 = 27;
                                            array3 = array6;
                                            a = array6;
                                            array4 = array2;
                                            n6 = 0;
                                            continue Label_0409;
                                            Label_2294:
                                            array2[n5] = intern2;
                                            array3[n6] = array4;
                                            array2 = new String[] { "1", null };
                                            n5 = 1;
                                            s2 = "?G/)\n\u0006L";
                                            n7 = 28;
                                            n6 = 1;
                                            array3 = a;
                                            array4 = array2;
                                            continue Label_0409;
                                            Label_2345:
                                            array2[n5] = intern2;
                                            array3[n6] = array4;
                                            array2 = new String[] { "1", null };
                                            n5 = 1;
                                            s2 = "?G/)\n\u0006L}\u0017\u0019\u001bG1%\u0003\u001a";
                                            n7 = 29;
                                            n6 = 2;
                                            array3 = a;
                                            array4 = array2;
                                            continue Label_0409;
                                            Label_2396:
                                            array2[n5] = intern2;
                                            array3[n6] = array4;
                                            array2 = new String[] { "1", null };
                                            n5 = 1;
                                            s2 = "<q\u001e\u0003";
                                            n7 = 30;
                                            n6 = 3;
                                            array3 = a;
                                            array4 = array2;
                                            continue Label_0409;
                                            Label_2447:
                                            array2[n5] = intern2;
                                            array3[n6] = array4;
                                            array2 = new String[] { "1", null };
                                            n5 = 1;
                                            s2 = "<\f\u000en3\fN15\u001c\bP";
                                            n7 = 31;
                                            n6 = 4;
                                            array3 = a;
                                            array4 = array2;
                                            continue Label_0409;
                                            Label_2498:
                                            array2[n5] = intern2;
                                            array3[n6] = array4;
                                            array2 = new String[] { "1", null };
                                            n5 = 1;
                                            s2 = ",Z)%\u001e\rG9`>\fV*/\u0002\u0002";
                                            n7 = 32;
                                            n6 = 5;
                                            array3 = a;
                                            array4 = array2;
                                            continue Label_0409;
                                            Label_2549:
                                            array2[n5] = intern2;
                                            array3[n6] = array4;
                                            array2 = new String[] { "1", null };
                                            n5 = 1;
                                            s2 = "$G)2\u001f9a\u000e";
                                            n7 = 33;
                                            n6 = 6;
                                            array3 = a;
                                            array4 = array2;
                                            continue Label_0409;
                                            Label_2601:
                                            array2[n5] = intern2;
                                            array3[n6] = array4;
                                            array2 = new String[2];
                                            s2 = "Z\u001a";
                                            n7 = 34;
                                            n6 = 7;
                                            array3 = a;
                                            array4 = array2;
                                            n5 = 0;
                                            continue Label_0409;
                                            Label_2647:
                                            array2[n5] = intern2;
                                            n5 = 1;
                                            s2 = ":R/)\u001e\u001d";
                                            n7 = 35;
                                            array2 = array4;
                                            continue Label_0409;
                                            Label_2672:
                                            array2[n5] = intern2;
                                            array3[n6] = array4;
                                            array2 = new String[2];
                                            s2 = "Z\u001a";
                                            n7 = 36;
                                            n6 = 8;
                                            array3 = a;
                                            array4 = array2;
                                            n5 = 0;
                                            continue Label_0409;
                                            Label_2718:
                                            array2[n5] = intern2;
                                            n5 = 1;
                                            s2 = "?G/)\n\u0006L";
                                            n7 = 37;
                                            array2 = array4;
                                            continue Label_0409;
                                            Label_2743:
                                            array2[n5] = intern2;
                                            array3[n6] = array4;
                                            array2 = new String[2];
                                            s2 = "Z\u001a";
                                            n7 = 38;
                                            n6 = 9;
                                            array3 = a;
                                            array4 = array2;
                                            n5 = 0;
                                            continue Label_0409;
                                            Label_2789:
                                            array2[n5] = intern2;
                                            n5 = 1;
                                            s2 = "?G/)\n\u0006L}\u0017\u0019\u001bG1%\u0003\u001a";
                                            n7 = 39;
                                            array2 = array4;
                                            continue Label_0409;
                                            Label_2814:
                                            array2[n5] = intern2;
                                            array3[n6] = array4;
                                            array2 = new String[2];
                                            s2 = "\\\u0010";
                                            n7 = 40;
                                            n6 = 10;
                                            array3 = a;
                                            array4 = array2;
                                            n5 = 0;
                                            continue Label_0409;
                                            Label_2860:
                                            array2[n5] = intern2;
                                            n5 = 1;
                                            s2 = ":R/)\u001e\u001d";
                                            n7 = 41;
                                            array2 = array4;
                                            continue Label_0409;
                                            Label_2885:
                                            array2[n5] = intern2;
                                            array3[n6] = array4;
                                            array2 = new String[2];
                                            s2 = "_\u0010";
                                            n7 = 42;
                                            n6 = 11;
                                            array3 = a;
                                            array4 = array2;
                                            n5 = 0;
                                            continue Label_0409;
                                            Label_2931:
                                            array2[n5] = intern2;
                                            n5 = 1;
                                            s2 = "\fQ4!^\nMs)\u0014";
                                            n7 = 43;
                                            array2 = array4;
                                            continue Label_0409;
                                            Label_2956:
                                            array2[n5] = intern2;
                                            array3[n6] = array4;
                                            array2 = new String[2];
                                            s2 = "_\u0010";
                                            n7 = 44;
                                            n6 = 12;
                                            array3 = a;
                                            array4 = array2;
                                            n5 = 0;
                                            continue Label_0409;
                                            Label_3002:
                                            array2[n5] = intern2;
                                            n5 = 1;
                                            s2 = "=G1+\u001f\u0004\u0002\u001b,\u0015\u0011K";
                                            n7 = 45;
                                            array2 = array4;
                                            continue Label_0409;
                                            Label_3027:
                                            array2[n5] = intern2;
                                            array3[n6] = array4;
                                            array2 = new String[2];
                                            s2 = "_\u0010";
                                            n7 = 46;
                                            n6 = 13;
                                            array3 = a;
                                            array4 = array2;
                                            n5 = 0;
                                            continue Label_0409;
                                            Label_3073:
                                            array2[n5] = intern2;
                                            n5 = 1;
                                            s2 = ":R/)\u001e\u001d";
                                            n7 = 47;
                                            array2 = array4;
                                            continue Label_0409;
                                            Label_3098:
                                            array2[n5] = intern2;
                                            array3[n6] = array4;
                                            array2 = new String[2];
                                            s2 = "_\u0010";
                                            n7 = 48;
                                            n6 = 14;
                                            array3 = a;
                                            array4 = array2;
                                            n5 = 0;
                                            continue Label_0409;
                                            Label_3144:
                                            array2[n5] = intern2;
                                            n5 = 1;
                                            s2 = "?G/)\n\u0006L";
                                            n7 = 49;
                                            array2 = array4;
                                            continue Label_0409;
                                            Label_3169:
                                            array2[n5] = intern2;
                                            array3[n6] = array4;
                                            array2 = new String[2];
                                            s2 = "_\u0010";
                                            n7 = 50;
                                            n6 = 15;
                                            array3 = a;
                                            array4 = array2;
                                            n5 = 0;
                                            continue Label_0409;
                                            Label_3215:
                                            array2[n5] = intern2;
                                            n5 = 1;
                                            s2 = "?G/)\n\u0006L}\u0017\u0019\u001bG1%\u0003\u001a";
                                            n7 = 51;
                                            array2 = array4;
                                            continue Label_0409;
                                            Label_3240:
                                            array2[n5] = intern2;
                                            array3[n6] = array4;
                                            array2 = new String[2];
                                            s2 = "_\u0014";
                                            n7 = 52;
                                            n6 = 16;
                                            array3 = a;
                                            array4 = array2;
                                            n5 = 0;
                                            continue Label_0409;
                                            Label_3286:
                                            array2[n5] = intern2;
                                            n5 = 1;
                                            s2 = "%e}\u0015[";
                                            n7 = 53;
                                            array2 = array4;
                                            continue Label_0409;
                                            Label_3311:
                                            array2[n5] = intern2;
                                            array3[n6] = array4;
                                            array2 = new String[2];
                                            s2 = "Q\u0013";
                                            n7 = 54;
                                            n6 = 17;
                                            array3 = a;
                                            array4 = array2;
                                            n5 = 0;
                                            continue Label_0409;
                                            Label_3357:
                                            array2[n5] = intern2;
                                            n5 = 1;
                                            s2 = "\"f\u0019\t";
                                            n7 = 55;
                                            array2 = array4;
                                            continue Label_0409;
                                            Label_3382:
                                            array2[n5] = intern2;
                                            array3[n6] = array4;
                                            array2 = new String[2];
                                            s2 = "Q\u0017m";
                                            n7 = 56;
                                            n6 = 18;
                                            array3 = a;
                                            array4 = array2;
                                            n5 = 0;
                                            continue Label_0409;
                                            Label_3428:
                                            array2[n5] = intern2;
                                            n5 = 1;
                                            s2 = "%e}\u0015[";
                                            n7 = 57;
                                            array2 = array4;
                                            continue Label_0409;
                                            Label_3453:
                                            array2[n5] = intern2;
                                            array3[n6] = array4;
                                            array2 = new String[2];
                                            s2 = "Q\u0017n";
                                            n7 = 58;
                                            n6 = 19;
                                            array3 = a;
                                            array4 = array2;
                                            n5 = 0;
                                            continue Label_0409;
                                            Label_3499:
                                            array2[n5] = intern2;
                                            n5 = 1;
                                            s2 = "*v\u001e";
                                            n7 = 59;
                                            array2 = array4;
                                            continue Label_0409;
                                            Label_3524:
                                            array2[n5] = intern2;
                                            array3[n6] = array4;
                                            array2 = new String[2];
                                            s2 = "Q\u0014";
                                            n7 = 60;
                                            n6 = 20;
                                            array3 = a;
                                            array4 = array2;
                                            n5 = 0;
                                            continue Label_0409;
                                            Label_3570:
                                            array2[n5] = intern2;
                                            n5 = 1;
                                            s2 = "*v\u001e";
                                            n7 = 61;
                                            array2 = array4;
                                            continue Label_0409;
                                            Label_3595:
                                            array2[n5] = intern2;
                                            array3[n6] = array4;
                                            array2 = new String[2];
                                            s2 = "Q\u001ak";
                                            n7 = 62;
                                            n6 = 21;
                                            array3 = a;
                                            array4 = array2;
                                            n5 = 0;
                                            continue Label_0409;
                                            Label_3641:
                                            array2[n5] = intern2;
                                            n5 = 1;
                                            s2 = "(r\u001f\u0017";
                                            n7 = 63;
                                            array2 = array4;
                                            continue Label_0409;
                                            Label_3666:
                                            array2[n5] = intern2;
                                            array3[n6] = array4;
                                            array2 = new String[2];
                                            s2 = "Q\u001ak";
                                            n7 = 64;
                                            n6 = 22;
                                            array3 = a;
                                            array4 = array2;
                                            n5 = 0;
                                            continue Label_0409;
                                            Label_3712:
                                            array2[n5] = intern2;
                                            n5 = 1;
                                            s2 = "(r\t";
                                            n7 = 65;
                                            array2 = array4;
                                            continue Label_0409;
                                            Label_3737:
                                            array2[n5] = intern2;
                                            array3[n6] = array4;
                                            array2 = new String[2];
                                            s2 = "P\u0013";
                                            n7 = 66;
                                            n6 = 23;
                                            array3 = a;
                                            array4 = array2;
                                            n5 = 0;
                                            continue Label_0409;
                                            Label_3783:
                                            array2[n5] = intern2;
                                            n5 = 1;
                                            s2 = ":R/)\u001e\u001d";
                                            n7 = 67;
                                            array2 = array4;
                                            continue Label_0409;
                                            Label_3808:
                                            array2[n5] = intern2;
                                            array3[n6] = array4;
                                            array2 = new String[2];
                                            s2 = "P\u0013";
                                            n7 = 68;
                                            n6 = 24;
                                            array3 = a;
                                            array4 = array2;
                                            n5 = 0;
                                            continue Label_0409;
                                            Label_3854:
                                            array2[n5] = intern2;
                                            n5 = 1;
                                            s2 = ":R/)\u001e\u001d\u0002}`PI\u0002";
                                            n7 = 69;
                                            array2 = array4;
                                            continue Label_0409;
                                            Label_3879:
                                            array2[n5] = intern2;
                                            array3[n6] = array4;
                                            array2 = new String[2];
                                            s2 = "P\u0013";
                                            n7 = 70;
                                            n6 = 25;
                                            array3 = a;
                                            array4 = array2;
                                            n5 = 0;
                                            continue Label_0409;
                                            Label_3925:
                                            array2[n5] = intern2;
                                            n5 = 1;
                                            s2 = "?G/)\n\u0006L";
                                            n7 = 71;
                                            array2 = array4;
                                            continue Label_0409;
                                            Label_3950:
                                            array2[n5] = intern2;
                                            array3[n6] = array4;
                                            array2 = new String[2];
                                            s2 = "P\u0013";
                                            n7 = 72;
                                            n6 = 26;
                                            array3 = a;
                                            array4 = array2;
                                            n5 = 0;
                                            continue Label_0409;
                                            Label_3996:
                                            array2[n5] = intern2;
                                            n5 = 1;
                                            s2 = "?G/)\n\u0006L}\u0017\u0019\u001bG1%\u0003\u001a";
                                            n7 = 73;
                                            array2 = array4;
                                            continue Label_0409;
                                            Label_4021:
                                            array2[n5] = intern2;
                                            array3[n6] = array4;
                                            array2 = new String[2];
                                            s2 = "P\u0013";
                                            n7 = 74;
                                            n6 = 27;
                                            array3 = a;
                                            array4 = array2;
                                            n5 = 0;
                                            continue Label_0409;
                                            Label_4067:
                                            array2[n5] = intern2;
                                            n5 = 1;
                                            s2 = ";G1)\u0011\u0007A8`PI\u0002";
                                            n7 = 75;
                                            array2 = array4;
                                            continue Label_0409;
                                            Label_4092:
                                            array2[n5] = intern2;
                                            array3[n6] = array4;
                                            array2 = new String[2];
                                            s2 = "P\u0013";
                                            n7 = 76;
                                            n6 = 28;
                                            array3 = a;
                                            array4 = array2;
                                            n5 = 0;
                                            continue Label_0409;
                                            Label_4138:
                                            array2[n5] = intern2;
                                            n5 = 1;
                                            s2 = ";g\u0011\t1'a\u0018`PI\u0002";
                                            n7 = 77;
                                            array2 = array4;
                                            continue Label_0409;
                                            Label_4163:
                                            array2[n5] = intern2;
                                            array3[n6] = array4;
                                            array2 = new String[2];
                                            s2 = "P\u0013";
                                            n7 = 78;
                                            n6 = 29;
                                            array3 = a;
                                            array4 = array2;
                                            n5 = 0;
                                            continue Label_0409;
                                            Label_4209:
                                            array2[n5] = intern2;
                                            n5 = 1;
                                            s2 = ";G1)\u0011\u0007A8";
                                            n7 = 79;
                                            array2 = array4;
                                            continue Label_0409;
                                            Label_4234:
                                            array2[n5] = intern2;
                                            array3[n6] = array4;
                                            vi.f = a;
                                            final String[][] array7 = new String[45][];
                                            array2 = new String[] { "1", null };
                                            n5 = 1;
                                            s2 = "Z\u0013mp";
                                            n7 = 80;
                                            array3 = array7;
                                            a = array7;
                                            array4 = array2;
                                            n6 = 0;
                                            continue Label_0409;
                                            Label_4301:
                                            array2[n5] = intern2;
                                            array3[n6] = array4;
                                            array2 = new String[] { "1", null };
                                            n5 = 1;
                                            s2 = "Z\u0013mt";
                                            n7 = 81;
                                            n6 = 1;
                                            array3 = a;
                                            array4 = array2;
                                            continue Label_0409;
                                            Label_4352:
                                            array2[n5] = intern2;
                                            array3[n6] = array4;
                                            array2 = new String[] { "1", null };
                                            n5 = 1;
                                            s2 = "Z\u0013mp@";
                                            n7 = 82;
                                            n6 = 2;
                                            array3 = a;
                                            array4 = array2;
                                            continue Label_0409;
                                            Label_4403:
                                            array2[n5] = intern2;
                                            array3[n6] = array4;
                                            array2 = new String[] { "1", null };
                                            n5 = 1;
                                            s2 = "Z\u0013mpD";
                                            n7 = 83;
                                            n6 = 3;
                                            array3 = a;
                                            array4 = array2;
                                            continue Label_0409;
                                            Label_4454:
                                            array2[n5] = intern2;
                                            array3[n6] = array4;
                                            array2 = new String[] { "1", null };
                                            n5 = 1;
                                            s2 = "Z\u0013mqB";
                                            n7 = 84;
                                            n6 = 4;
                                            array3 = a;
                                            array4 = array2;
                                            continue Label_0409;
                                            Label_4505:
                                            array2[n5] = intern2;
                                            array3[n6] = array4;
                                            array2 = new String[] { "1", null };
                                            n5 = 1;
                                            s2 = "Z\u0013mrH";
                                            n7 = 85;
                                            n6 = 5;
                                            array3 = a;
                                            array4 = array2;
                                            continue Label_0409;
                                            Label_4556:
                                            array2[n5] = intern2;
                                            array3[n6] = array4;
                                            array2 = new String[] { "1", null };
                                            n5 = 1;
                                            s2 = "Z\u0013lrC";
                                            n7 = 86;
                                            n6 = 6;
                                            array3 = a;
                                            array4 = array2;
                                            continue Label_0409;
                                            Label_4608:
                                            array2[n5] = intern2;
                                            array3[n6] = array4;
                                            array2 = new String[] { "1", null };
                                            n5 = 1;
                                            s2 = "Z\u0013lwB";
                                            n7 = 87;
                                            n6 = 7;
                                            array3 = a;
                                            array4 = array2;
                                            continue Label_0409;
                                            Label_4660:
                                            array2[n5] = intern2;
                                            array3[n6] = array4;
                                            array2 = new String[] { "1", null };
                                            n5 = 1;
                                            s2 = "Z\u0013mp@Y";
                                            n7 = 88;
                                            n6 = 8;
                                            array3 = a;
                                            array4 = array2;
                                            continue Label_0409;
                                            Label_4712:
                                            array2[n5] = intern2;
                                            array3[n6] = array4;
                                            array2 = new String[] { "1", null };
                                            n5 = 1;
                                            s2 = "Z\u0013mp@]";
                                            n7 = 89;
                                            n6 = 9;
                                            array3 = a;
                                            array4 = array2;
                                            continue Label_0409;
                                            Label_4764:
                                            array2[n5] = intern2;
                                            array3[n6] = array4;
                                            array2 = new String[] { "1", null };
                                            n5 = 1;
                                            s2 = "Z\u0013mpA[";
                                            n7 = 90;
                                            n6 = 10;
                                            array3 = a;
                                            array4 = array2;
                                            continue Label_0409;
                                            Label_4816:
                                            array2[n5] = intern2;
                                            array3[n6] = array4;
                                            array2 = new String[] { "1", null };
                                            n5 = 1;
                                            s2 = "Z\u0013mpBQ";
                                            n7 = 91;
                                            n6 = 11;
                                            array3 = a;
                                            array4 = array2;
                                            continue Label_0409;
                                            Label_4868:
                                            array2[n5] = intern2;
                                            array3[n6] = array4;
                                            array2 = new String[] { "1", null };
                                            n5 = 1;
                                            s2 = "Z\u0013mpCQ";
                                            n7 = 92;
                                            n6 = 12;
                                            array3 = a;
                                            array4 = array2;
                                            continue Label_0409;
                                            Label_4920:
                                            array2[n5] = intern2;
                                            array3[n6] = array4;
                                            array2 = new String[] { "1", null };
                                            n5 = 1;
                                            s2 = "Z\u0013mqBY";
                                            n7 = 93;
                                            n6 = 13;
                                            array3 = a;
                                            array4 = array2;
                                            continue Label_0409;
                                            Label_4972:
                                            array2[n5] = intern2;
                                            array3[n6] = array4;
                                            array2 = new String[] { "1", null };
                                            n5 = 1;
                                            s2 = "Z\u0013myI\\";
                                            n7 = 94;
                                            n6 = 14;
                                            array3 = a;
                                            array4 = array2;
                                            continue Label_0409;
                                            Label_5024:
                                            array2[n5] = intern2;
                                            array3[n6] = array4;
                                            array2 = new String[] { "1", null };
                                            n5 = 1;
                                            s2 = "Z\u0011ip";
                                            n7 = 95;
                                            n6 = 15;
                                            array3 = a;
                                            array4 = array2;
                                            continue Label_0409;
                                            Label_5076:
                                            array2[n5] = intern2;
                                            array3[n6] = array4;
                                            array2 = new String[] { "1", null };
                                            n5 = 1;
                                            s2 = "Z\u0011ip@";
                                            n7 = 96;
                                            n6 = 16;
                                            array3 = a;
                                            array4 = array2;
                                            continue Label_0409;
                                            Label_5128:
                                            array2[n5] = intern2;
                                            array3[n6] = array4;
                                            array2 = new String[] { "1", null };
                                            n5 = 1;
                                            s2 = "Z\u0011ip@Y";
                                            n7 = 97;
                                            n6 = 17;
                                            array3 = a;
                                            array4 = array2;
                                            continue Label_0409;
                                            Label_5180:
                                            array2[n5] = intern2;
                                            array3[n6] = array4;
                                            array2 = new String[2];
                                            s2 = "Z\u001a";
                                            n7 = 98;
                                            n6 = 18;
                                            array3 = a;
                                            array4 = array2;
                                            n5 = 0;
                                            continue Label_0409;
                                            Label_5226:
                                            array2[n5] = intern2;
                                            n5 = 1;
                                            s2 = "[\u0017hpD";
                                            n7 = 99;
                                            array2 = array4;
                                            continue Label_0409;
                                            Label_5251:
                                            array2[n5] = intern2;
                                            array3[n6] = array4;
                                            array2 = new String[2];
                                            s2 = "\\\u0010";
                                            n7 = 100;
                                            n6 = 19;
                                            array3 = a;
                                            array4 = array2;
                                            n5 = 0;
                                            continue Label_0409;
                                            Label_5297:
                                            array2[n5] = intern2;
                                            n5 = 1;
                                            s2 = "Z\u0013mp@";
                                            n7 = 101;
                                            array2 = array4;
                                            continue Label_0409;
                                            Label_5322:
                                            array2[n5] = intern2;
                                            array3[n6] = array4;
                                            array2 = new String[2];
                                            s2 = "\\\u0010";
                                            n7 = 102;
                                            n6 = 20;
                                            array3 = a;
                                            array4 = array2;
                                            n5 = 0;
                                            continue Label_0409;
                                            Label_5368:
                                            array2[n5] = intern2;
                                            n5 = 1;
                                            s2 = "Z\u0011ip";
                                            n7 = 103;
                                            array2 = array4;
                                            continue Label_0409;
                                            Label_5393:
                                            array2[n5] = intern2;
                                            array3[n6] = array4;
                                            array2 = new String[2];
                                            s2 = "\\\u0010";
                                            n7 = 104;
                                            n6 = 21;
                                            array3 = a;
                                            array4 = array2;
                                            n5 = 0;
                                            continue Label_0409;
                                            Label_5439:
                                            array2[n5] = intern2;
                                            n5 = 1;
                                            s2 = "Z\u0011ip@";
                                            n7 = 105;
                                            array2 = array4;
                                            continue Label_0409;
                                            Label_5464:
                                            array2[n5] = intern2;
                                            array3[n6] = array4;
                                            array2 = new String[2];
                                            s2 = "\\\u0010";
                                            n7 = 106;
                                            n6 = 22;
                                            array3 = a;
                                            array4 = array2;
                                            n5 = 0;
                                            continue Label_0409;
                                            Label_5510:
                                            array2[n5] = intern2;
                                            n5 = 1;
                                            s2 = "Z\u0011ip@Y";
                                            n7 = 107;
                                            array2 = array4;
                                            continue Label_0409;
                                            Label_5535:
                                            array2[n5] = intern2;
                                            array3[n6] = array4;
                                            array2 = new String[2];
                                            s2 = "_\u0010";
                                            n7 = 108;
                                            n6 = 23;
                                            array3 = a;
                                            array4 = array2;
                                            n5 = 0;
                                            continue Label_0409;
                                            Label_5581:
                                            array2[n5] = intern2;
                                            n5 = 1;
                                            s2 = "Z\u0013mqBY";
                                            n7 = 109;
                                            array2 = array4;
                                            continue Label_0409;
                                            Label_5606:
                                            array2[n5] = intern2;
                                            array3[n6] = array4;
                                            array2 = new String[2];
                                            s2 = "_\u0010";
                                            n7 = 110;
                                            n6 = 24;
                                            array3 = a;
                                            array4 = array2;
                                            n5 = 0;
                                            continue Label_0409;
                                            Label_5652:
                                            array2[n5] = intern2;
                                            n5 = 1;
                                            s2 = "\\\u0013mp@";
                                            n7 = 111;
                                            array2 = array4;
                                            continue Label_0409;
                                            Label_5677:
                                            array2[n5] = intern2;
                                            array3[n6] = array4;
                                            array2 = new String[2];
                                            s2 = "_\u0010";
                                            n7 = 112;
                                            n6 = 25;
                                            array3 = a;
                                            array4 = array2;
                                            n5 = 0;
                                            continue Label_0409;
                                            Label_5723:
                                            array2[n5] = intern2;
                                            n5 = 1;
                                            s2 = "\\\u0013mp@Y";
                                            n7 = 113;
                                            array2 = array4;
                                            continue Label_0409;
                                            Label_5748:
                                            array2[n5] = intern2;
                                            array3[n6] = array4;
                                            array2 = new String[2];
                                            s2 = "_\u0010";
                                            n7 = 114;
                                            n6 = 26;
                                            array3 = a;
                                            array4 = array2;
                                            n5 = 0;
                                            continue Label_0409;
                                            Label_5794:
                                            array2[n5] = intern2;
                                            n5 = 1;
                                            s2 = "\\\u0013myI";
                                            n7 = 115;
                                            array2 = array4;
                                            continue Label_0409;
                                            Label_5819:
                                            array2[n5] = intern2;
                                            array3[n6] = array4;
                                            array2 = new String[2];
                                            s2 = "_\u0010";
                                            n7 = 116;
                                            n6 = 27;
                                            array3 = a;
                                            array4 = array2;
                                            n5 = 0;
                                            continue Label_0409;
                                            Label_5865:
                                            array2[n5] = intern2;
                                            n5 = 1;
                                            s2 = "\\\u0013mpI";
                                            n7 = 117;
                                            array2 = array4;
                                            continue Label_0409;
                                            Label_5890:
                                            array2[n5] = intern2;
                                            array3[n6] = array4;
                                            array2 = new String[2];
                                            s2 = "_\u0014";
                                            n7 = 118;
                                            n6 = 28;
                                            array3 = a;
                                            array4 = array2;
                                            n5 = 0;
                                            continue Label_0409;
                                            Label_5936:
                                            array2[n5] = intern2;
                                            n5 = 1;
                                            s2 = "]\u0017mpF";
                                            n7 = 119;
                                            array2 = array4;
                                            continue Label_0409;
                                            Label_5961:
                                            array2[n5] = intern2;
                                            array3[n6] = array4;
                                            array2 = new String[2];
                                            s2 = "Q\u0013";
                                            n7 = 120;
                                            n6 = 29;
                                            array3 = a;
                                            array4 = array2;
                                            n5 = 0;
                                            continue Label_0409;
                                            Label_6007:
                                            array2[n5] = intern2;
                                            n5 = 1;
                                            s2 = "]\u0016mqB^";
                                            n7 = 121;
                                            array2 = array4;
                                            continue Label_0409;
                                            Label_6032:
                                            array2[n5] = intern2;
                                            array3[n6] = array4;
                                            array2 = new String[2];
                                            s2 = "Q\u0010";
                                            n7 = 122;
                                            n6 = 30;
                                            array3 = a;
                                            array4 = array2;
                                            n5 = 0;
                                            continue Label_0409;
                                            Label_6078:
                                            array2[n5] = intern2;
                                            n5 = 1;
                                            s2 = "]\u0017mp";
                                            n7 = 123;
                                            array2 = array4;
                                            continue Label_0409;
                                            Label_6103:
                                            array2[n5] = intern2;
                                            array3[n6] = array4;
                                            array2 = new String[2];
                                            s2 = "Q\u0010";
                                            n7 = 124;
                                            n6 = 31;
                                            array3 = a;
                                            array4 = array2;
                                            n5 = 0;
                                            continue Label_0409;
                                            Label_6149:
                                            array2[n5] = intern2;
                                            n5 = 1;
                                            s2 = "]\u0017mv";
                                            n7 = 125;
                                            array2 = array4;
                                            continue Label_0409;
                                            Label_6174:
                                            array2[n5] = intern2;
                                            array3[n6] = array4;
                                            array2 = new String[2];
                                            s2 = "Q\u0010";
                                            n7 = 126;
                                            n6 = 32;
                                            array3 = a;
                                            array4 = array2;
                                            n5 = 0;
                                            continue Label_0409;
                                            Label_6220:
                                            array2[n5] = intern2;
                                            n5 = 1;
                                            s2 = "]\u0017mp@";
                                            n7 = 127;
                                            array2 = array4;
                                            continue Label_0409;
                                            Label_6245:
                                            array2[n5] = intern2;
                                            array3[n6] = array4;
                                            array2 = new String[2];
                                            s2 = "Q\u0010";
                                            n7 = 128;
                                            n6 = 33;
                                            array3 = a;
                                            array4 = array2;
                                            n5 = 0;
                                            continue Label_0409;
                                            Label_6292:
                                            array2[n5] = intern2;
                                            n5 = 1;
                                            s2 = "]\u0017mpF";
                                            n7 = 129;
                                            array2 = array4;
                                            continue Label_0409;
                                            Label_6318:
                                            array2[n5] = intern2;
                                            array3[n6] = array4;
                                            array2 = new String[2];
                                            s2 = "Q\u0010";
                                            n7 = 130;
                                            n6 = 34;
                                            array3 = a;
                                            array4 = array2;
                                            n5 = 0;
                                            continue Label_0409;
                                            Label_6365:
                                            array2[n5] = intern2;
                                            n5 = 1;
                                            s2 = "]\u0017mp@Y";
                                            n7 = 131;
                                            array2 = array4;
                                            continue Label_0409;
                                            Label_6391:
                                            array2[n5] = intern2;
                                            array3[n6] = array4;
                                            array2 = new String[2];
                                            s2 = "Q\u0010";
                                            n7 = 132;
                                            n6 = 35;
                                            array3 = a;
                                            array4 = array2;
                                            n5 = 0;
                                            continue Label_0409;
                                            Label_6438:
                                            array2[n5] = intern2;
                                            n5 = 1;
                                            s2 = "]\u0017mp@_";
                                            n7 = 133;
                                            array2 = array4;
                                            continue Label_0409;
                                            Label_6464:
                                            array2[n5] = intern2;
                                            array3[n6] = array4;
                                            array2 = new String[2];
                                            s2 = "Q\u0017m";
                                            n7 = 134;
                                            n6 = 36;
                                            array3 = a;
                                            array4 = array2;
                                            n5 = 0;
                                            continue Label_0409;
                                            Label_6511:
                                            array2[n5] = intern2;
                                            n5 = 1;
                                            s2 = "]\u0017mp@";
                                            n7 = 135;
                                            array2 = array4;
                                            continue Label_0409;
                                            Label_6537:
                                            array2[n5] = intern2;
                                            array3[n6] = array4;
                                            array2 = new String[2];
                                            s2 = "Q\u0014";
                                            n7 = 136;
                                            n6 = 37;
                                            array3 = a;
                                            array4 = array2;
                                            n5 = 0;
                                            continue Label_0409;
                                            Label_6584:
                                            array2[n5] = intern2;
                                            n5 = 1;
                                            s2 = "]\u0014mp@Z";
                                            n7 = 137;
                                            array2 = array4;
                                            continue Label_0409;
                                            Label_6610:
                                            array2[n5] = intern2;
                                            array3[n6] = array4;
                                            array2 = new String[2];
                                            s2 = "Q\u0014";
                                            n7 = 138;
                                            n6 = 38;
                                            array3 = a;
                                            array4 = array2;
                                            n5 = 0;
                                            continue Label_0409;
                                            Label_6657:
                                            array2[n5] = intern2;
                                            n5 = 1;
                                            s2 = "]\u0014mpC";
                                            n7 = 139;
                                            array2 = array4;
                                            continue Label_0409;
                                            Label_6683:
                                            array2[n5] = intern2;
                                            array3[n6] = array4;
                                            array2 = new String[2];
                                            s2 = "Q\u001ak";
                                            n7 = 140;
                                            n6 = 39;
                                            array3 = a;
                                            array4 = array2;
                                            n5 = 0;
                                            continue Label_0409;
                                            Label_6730:
                                            array2[n5] = intern2;
                                            n5 = 1;
                                            s2 = "]\u0014kpE";
                                            n7 = 141;
                                            array2 = array4;
                                            continue Label_0409;
                                            Label_6756:
                                            array2[n5] = intern2;
                                            array3[n6] = array4;
                                            array2 = new String[2];
                                            s2 = "P\u0013";
                                            n7 = 142;
                                            n6 = 40;
                                            array3 = a;
                                            array4 = array2;
                                            n5 = 0;
                                            continue Label_0409;
                                            Label_6803:
                                            array2[n5] = intern2;
                                            n5 = 1;
                                            s2 = "]\u0012ip";
                                            n7 = 143;
                                            array2 = array4;
                                            continue Label_0409;
                                            Label_6829:
                                            array2[n5] = intern2;
                                            array3[n6] = array4;
                                            array2 = new String[2];
                                            s2 = "P\u0013";
                                            n7 = 144;
                                            n6 = 41;
                                            array3 = a;
                                            array4 = array2;
                                            n5 = 0;
                                            continue Label_0409;
                                            Label_6876:
                                            array2[n5] = intern2;
                                            n5 = 1;
                                            s2 = "]\u0012ip@";
                                            n7 = 145;
                                            array2 = array4;
                                            continue Label_0409;
                                            Label_6902:
                                            array2[n5] = intern2;
                                            array3[n6] = array4;
                                            array2 = new String[2];
                                            s2 = "P\u0013";
                                            n7 = 146;
                                            n6 = 42;
                                            array3 = a;
                                            array4 = array2;
                                            n5 = 0;
                                            continue Label_0409;
                                            Label_6949:
                                            array2[n5] = intern2;
                                            n5 = 1;
                                            s2 = "]\u0012ip@Y";
                                            n7 = 147;
                                            array2 = array4;
                                            continue Label_0409;
                                            Label_6975:
                                            array2[n5] = intern2;
                                            array3[n6] = array4;
                                            array2 = new String[2];
                                            s2 = "P\u0013";
                                            n7 = 148;
                                            n6 = 43;
                                            array3 = a;
                                            array4 = array2;
                                            n5 = 0;
                                            continue Label_0409;
                                            Label_7022:
                                            array2[n5] = intern2;
                                            n5 = 1;
                                            s2 = "Z\u0013mqBY";
                                            n7 = 149;
                                            array2 = array4;
                                            continue Label_0409;
                                            Label_7048:
                                            array2[n5] = intern2;
                                            array3[n6] = array4;
                                            array2 = new String[2];
                                            s2 = "P\u0013";
                                            n7 = 150;
                                            n6 = 44;
                                            array3 = a;
                                            array4 = array2;
                                            n5 = 0;
                                            continue Label_0409;
                                            Label_7095:
                                            array2[n5] = intern2;
                                            n5 = 1;
                                            s2 = "X\u0012osA[\u0015";
                                            n7 = 151;
                                            array2 = array4;
                                            continue Label_0409;
                                        }
                                    }
                                }
                                if (n4 >= length2) {
                                    continue;
                                }
                                break;
                            }
                            final Locale locale = availableLocales[n4];
                            final String country = locale.getCountry();
                            if (country != null) {
                                continue Label_0267_Outer;
                            }
                            break;
                        }
                        continue;
                    }
                }
            }
            break;
        }
        Label_7121: {
            array2[n5] = intern2;
        }
        array3[n6] = array4;
        vi.a = a;
    }
    
    public static int a(final int n, final int n2) {
        final boolean i = App.I;
        b();
        for (final a2d a2d : vi.c) {
            try {
                if (a2d.j == n) {
                    return a2d.a(n2);
                }
            }
            catch (IllegalArgumentException ex) {
                throw ex;
            }
            if (i) {
                break;
            }
        }
        return 0;
    }
    
    public static a2d a(final String s) {
        final boolean i = App.I;
        b();
        for (final a2d a2d : vi.c) {
            try {
                if (s.equals(a2d.l)) {
                    return a2d;
                }
            }
            catch (IllegalArgumentException ex) {
                throw ex;
            }
            if (i) {
                break;
            }
        }
        return null;
    }
    
    public static String a(final int n, String a) {
        final boolean i = App.I;
        b();
        final Iterator iterator = vi.c.iterator();
        do {
            if (!iterator.hasNext()) {
                return a;
            }
            final a2d a2d = iterator.next();
            try {
                if (a2d.j == n) {
                    a = a2d.a(a);
                    return a;
                }
                continue;
            }
            catch (IllegalArgumentException ex) {
                throw ex;
            }
        } while (!i);
        return a;
    }
    
    public static ArrayList a() {
        b();
        return vi.c;
    }
    
    public static boolean a(final String s, final NetworkInfo networkInfo) {
        final boolean i = App.I;
        if (s != null && networkInfo != null) {
            final String extraInfo = networkInfo.getExtraInfo();
            if (extraInfo != null) {
                int j = 0;
                while (j < vi.e.length) {
                    Label_0081: {
                        try {
                            if (!s.equals(vi.e[j][0])) {
                                break Label_0081;
                            }
                            final String s2 = extraInfo;
                            final String[][] array = vi.e;
                            final int n = j;
                            final String[] array2 = array[n];
                            final int n2 = 1;
                            final String s3 = array2[n2];
                            final boolean b = s2.equals(s3);
                            if (b) {
                                return true;
                            }
                            break Label_0081;
                        }
                        catch (IllegalArgumentException ex) {
                            throw ex;
                        }
                        try {
                            final String s2 = extraInfo;
                            final String[][] array = vi.e;
                            final int n = j;
                            final String[] array2 = array[n];
                            final int n2 = 1;
                            final String s3 = array2[n2];
                            final boolean b = s2.equals(s3);
                            if (b) {
                                return true;
                            }
                        }
                        catch (IllegalArgumentException ex2) {
                            throw ex2;
                        }
                    }
                    ++j;
                    if (i) {
                        return false;
                    }
                }
            }
        }
        return false;
    }
    
    public static boolean a(final String s, final String s2) {
        final boolean i = App.I;
        if (s != null && s2 != null) {
            int j = 0;
            while (j < vi.f.length) {
                Label_0068: {
                    try {
                        if (!s.equals(vi.f[j][0])) {
                            break Label_0068;
                        }
                        final String s3 = s2;
                        final String[][] array = vi.f;
                        final int n = j;
                        final String[] array2 = array[n];
                        final int n2 = 1;
                        final String s4 = array2[n2];
                        final boolean b = s3.equals(s4);
                        if (b) {
                            return true;
                        }
                        break Label_0068;
                    }
                    catch (IllegalArgumentException ex) {
                        throw ex;
                    }
                    try {
                        final String s3 = s2;
                        final String[][] array = vi.f;
                        final int n = j;
                        final String[] array2 = array[n];
                        final int n2 = 1;
                        final String s4 = array2[n2];
                        final boolean b = s3.equals(s4);
                        if (b) {
                            return true;
                        }
                    }
                    catch (IllegalArgumentException ex2) {
                        throw ex2;
                    }
                }
                ++j;
                if (i) {
                    return false;
                }
            }
        }
        return false;
    }
    
    private static void b() {
        // 
        // This method could not be decompiled.
        // 
        // Original Bytecode:
        // 
        //     0: getstatic       com/whatsapp/App.I:Z
        //     3: istore_0       
        //     4: getstatic       com/whatsapp/vi.b:Z
        //     7: istore_2       
        //     8: iload_2        
        //     9: ifeq            16
        //    12: return         
        //    13: astore_1       
        //    14: aload_1        
        //    15: athrow         
        //    16: new             Ljava/util/ArrayList;
        //    19: dup            
        //    20: invokespecial   java/util/ArrayList.<init>:()V
        //    23: putstatic       com/whatsapp/vi.c:Ljava/util/ArrayList;
        //    26: getstatic       com/whatsapp/App.aq:Lcom/whatsapp/App;
        //    29: invokevirtual   com/whatsapp/App.getResources:()Landroid/content/res/Resources;
        //    32: ldc_w           2131165184
        //    35: invokevirtual   android/content/res/Resources.openRawResource:(I)Ljava/io/InputStream;
        //    38: astore_3       
        //    39: aload_3        
        //    40: ifnonnull       61
        //    43: new             Ljava/io/IOException;
        //    46: dup            
        //    47: getstatic       com/whatsapp/vi.z:[Ljava/lang/String;
        //    50: iconst_4       
        //    51: aaload         
        //    52: invokespecial   java/io/IOException.<init>:(Ljava/lang/String;)V
        //    55: athrow         
        //    56: astore          14
        //    58: aload           14
        //    60: athrow         
        //    61: new             Ljava/io/BufferedReader;
        //    64: dup            
        //    65: new             Ljava/io/InputStreamReader;
        //    68: dup            
        //    69: aload_3        
        //    70: getstatic       com/whatsapp/vi.z:[Ljava/lang/String;
        //    73: iconst_3       
        //    74: aaload         
        //    75: invokespecial   java/io/InputStreamReader.<init>:(Ljava/io/InputStream;Ljava/lang/String;)V
        //    78: invokespecial   java/io/BufferedReader.<init>:(Ljava/io/Reader;)V
        //    81: astore          4
        //    83: aload           4
        //    85: invokevirtual   java/io/BufferedReader.readLine:()Ljava/lang/String;
        //    88: astore          5
        //    90: aload           5
        //    92: ifnull          233
        //    95: aload           5
        //    97: ldc_w           "\t"
        //   100: invokestatic    android/text/TextUtils.split:(Ljava/lang/String;Ljava/lang/String;)[Ljava/lang/String;
        //   103: astore          8
        //   105: aload           8
        //   107: ifnull          122
        //   110: aload           8
        //   112: arraylength    
        //   113: istore          11
        //   115: iload           11
        //   117: bipush          12
        //   119: if_icmpge       238
        //   122: new             Ljava/lang/IllegalArgumentException;
        //   125: dup            
        //   126: invokespecial   java/lang/IllegalArgumentException.<init>:()V
        //   129: athrow         
        //   130: astore          9
        //   132: aload           9
        //   134: athrow         
        //   135: astore          7
        //   137: new             Ljava/lang/StringBuilder;
        //   140: dup            
        //   141: invokespecial   java/lang/StringBuilder.<init>:()V
        //   144: getstatic       com/whatsapp/vi.z:[Ljava/lang/String;
        //   147: iconst_1       
        //   148: aaload         
        //   149: invokevirtual   java/lang/StringBuilder.append:(Ljava/lang/String;)Ljava/lang/StringBuilder;
        //   152: aload           5
        //   154: invokevirtual   java/lang/StringBuilder.append:(Ljava/lang/String;)Ljava/lang/StringBuilder;
        //   157: invokevirtual   java/lang/StringBuilder.toString:()Ljava/lang/String;
        //   160: invokestatic    com/whatsapp/util/Log.e:(Ljava/lang/String;)V
        //   163: goto            83
        //   166: astore          13
        //   168: getstatic       com/whatsapp/vi.z:[Ljava/lang/String;
        //   171: iconst_2       
        //   172: aaload         
        //   173: invokestatic    com/whatsapp/util/Log.i:(Ljava/lang/String;)V
        //   176: new             Ljava/io/BufferedReader;
        //   179: dup            
        //   180: new             Ljava/io/InputStreamReader;
        //   183: dup            
        //   184: aload_3        
        //   185: invokespecial   java/io/InputStreamReader.<init>:(Ljava/io/InputStream;)V
        //   188: invokespecial   java/io/BufferedReader.<init>:(Ljava/io/Reader;)V
        //   191: astore          4
        //   193: goto            83
        //   196: astore          10
        //   198: aload           10
        //   200: athrow         
        //   201: astore          6
        //   203: new             Ljava/lang/StringBuilder;
        //   206: dup            
        //   207: invokespecial   java/lang/StringBuilder.<init>:()V
        //   210: getstatic       com/whatsapp/vi.z:[Ljava/lang/String;
        //   213: iconst_5       
        //   214: aaload         
        //   215: invokevirtual   java/lang/StringBuilder.append:(Ljava/lang/String;)Ljava/lang/StringBuilder;
        //   218: aload           5
        //   220: invokevirtual   java/lang/StringBuilder.append:(Ljava/lang/String;)Ljava/lang/StringBuilder;
        //   223: invokevirtual   java/lang/StringBuilder.toString:()Ljava/lang/String;
        //   226: invokestatic    com/whatsapp/util/Log.e:(Ljava/lang/String;)V
        //   229: iload_0        
        //   230: ifeq            83
        //   233: iconst_1       
        //   234: putstatic       com/whatsapp/vi.b:Z
        //   237: return         
        //   238: getstatic       com/whatsapp/vi.c:Ljava/util/ArrayList;
        //   241: new             Lcom/whatsapp/a2d;
        //   244: dup            
        //   245: aload           8
        //   247: aconst_null    
        //   248: invokespecial   com/whatsapp/a2d.<init>:([Ljava/lang/String;Lcom/whatsapp/gn;)V
        //   251: invokevirtual   java/util/ArrayList.add:(Ljava/lang/Object;)Z
        //   254: pop            
        //   255: goto            83
        //    Exceptions:
        //  Try           Handler
        //  Start  End    Start  End    Type                                  
        //  -----  -----  -----  -----  --------------------------------------
        //  4      8      13     16     Ljava/io/UnsupportedEncodingException;
        //  43     56     56     61     Ljava/io/UnsupportedEncodingException;
        //  61     83     166    196    Ljava/io/UnsupportedEncodingException;
        //  95     105    135    166    Ljava/lang/NumberFormatException;
        //  95     105    201    233    Ljava/lang/IllegalArgumentException;
        //  110    115    196    201    Ljava/io/UnsupportedEncodingException;
        //  110    115    135    166    Ljava/lang/NumberFormatException;
        //  110    115    201    233    Ljava/lang/IllegalArgumentException;
        //  122    130    130    135    Ljava/io/UnsupportedEncodingException;
        //  122    130    135    166    Ljava/lang/NumberFormatException;
        //  122    130    201    233    Ljava/lang/IllegalArgumentException;
        //  132    135    135    166    Ljava/lang/NumberFormatException;
        //  132    135    201    233    Ljava/lang/IllegalArgumentException;
        //  198    201    130    135    Ljava/io/UnsupportedEncodingException;
        //  198    201    135    166    Ljava/lang/NumberFormatException;
        //  198    201    201    233    Ljava/lang/IllegalArgumentException;
        //  238    255    135    166    Ljava/lang/NumberFormatException;
        //  238    255    201    233    Ljava/lang/IllegalArgumentException;
        // 
        // The error that occurred was:
        // 
        // java.lang.IllegalStateException: Expression is linked from several locations: Label_0122:
        //     at com.strobel.decompiler.ast.Error.expressionLinkedFromMultipleLocations(Error.java:27)
        //     at com.strobel.decompiler.ast.AstOptimizer.mergeDisparateObjectInitializations(AstOptimizer.java:2592)
        //     at com.strobel.decompiler.ast.AstOptimizer.optimize(AstOptimizer.java:235)
        //     at com.strobel.decompiler.ast.AstOptimizer.optimize(AstOptimizer.java:42)
        //     at com.strobel.decompiler.languages.java.ast.AstMethodBodyBuilder.createMethodBody(AstMethodBodyBuilder.java:214)
        //     at com.strobel.decompiler.languages.java.ast.AstMethodBodyBuilder.createMethodBody(AstMethodBodyBuilder.java:99)
        //     at com.strobel.decompiler.languages.java.ast.AstBuilder.createMethodBody(AstBuilder.java:757)
        //     at com.strobel.decompiler.languages.java.ast.AstBuilder.createMethod(AstBuilder.java:655)
        //     at com.strobel.decompiler.languages.java.ast.AstBuilder.addTypeMembers(AstBuilder.java:532)
        //     at com.strobel.decompiler.languages.java.ast.AstBuilder.createTypeCore(AstBuilder.java:499)
        //     at com.strobel.decompiler.languages.java.ast.AstBuilder.createTypeNoCache(AstBuilder.java:141)
        //     at com.strobel.decompiler.languages.java.ast.AstBuilder.createType(AstBuilder.java:130)
        //     at com.strobel.decompiler.languages.java.ast.AstBuilder.addType(AstBuilder.java:105)
        //     at com.strobel.decompiler.languages.java.JavaLanguage.buildAst(JavaLanguage.java:71)
        //     at com.strobel.decompiler.languages.java.JavaLanguage.decompileType(JavaLanguage.java:59)
        //     at com.strobel.decompiler.DecompilerDriver.decompileType(DecompilerDriver.java:317)
        //     at com.strobel.decompiler.DecompilerDriver.decompileJar(DecompilerDriver.java:238)
        //     at com.strobel.decompiler.DecompilerDriver.main(DecompilerDriver.java:123)
        // 
        throw new IllegalStateException("An error occurred while decompiling this method.");
    }
    
    public static boolean b(final String s, final String s2) {
        final boolean i = App.I;
        if (s != null && s2 != null) {
            int j = 0;
            while (j < vi.a.length) {
                Label_0068: {
                    try {
                        if (!s.equals(vi.a[j][0])) {
                            break Label_0068;
                        }
                        final String s3 = s2;
                        final String[][] array = vi.a;
                        final int n = j;
                        final String[] array2 = array[n];
                        final int n2 = 1;
                        final String s4 = array2[n2];
                        final boolean b = s3.equals(s4);
                        if (b) {
                            return true;
                        }
                        break Label_0068;
                    }
                    catch (IllegalArgumentException ex) {
                        throw ex;
                    }
                    try {
                        final String s3 = s2;
                        final String[][] array = vi.a;
                        final int n = j;
                        final String[] array2 = array[n];
                        final int n2 = 1;
                        final String s4 = array2[n2];
                        final boolean b = s3.equals(s4);
                        if (b) {
                            return true;
                        }
                    }
                    catch (IllegalArgumentException ex2) {
                        throw ex2;
                    }
                }
                ++j;
                if (i) {
                    return false;
                }
            }
        }
        return false;
    }
    
    static int[] b(final String s) {
        return e(s);
    }
    
    public static String c(final String s) {
        final boolean i = App.I;
        try {
            b();
            if (s == null) {
                return null;
            }
        }
        catch (IllegalArgumentException ex) {
            throw ex;
        }
        Block_4: {
            switch (s.length()) {
                case 2: {
                    final String upperCase = s.toUpperCase(Locale.US);
                    for (final a2d a2d : vi.c) {
                        try {
                            if (a2d.l.equals(upperCase)) {
                                return Integer.toString(a2d.j);
                            }
                        }
                        catch (IllegalArgumentException ex2) {
                            throw ex2;
                        }
                        if (i) {
                            break;
                        }
                    }
                    if (i) {
                        break Block_4;
                    }
                    break;
                }
                case 3: {
                    try {
                        if (s.equals(vi.z[0])) {
                            return null;
                        }
                    }
                    catch (IllegalArgumentException ex3) {
                        throw ex3;
                    }
                    for (final a2d a2d2 : vi.c) {
                        int j = 0;
                        while (j < a2d2.g.length) {
                            try {
                                if (s.equals(a2d2.g[j] + "")) {
                                    return Integer.toString(a2d2.j);
                                }
                            }
                            catch (IllegalArgumentException ex4) {
                                throw ex4;
                            }
                            ++j;
                            if (i) {
                                break;
                            }
                        }
                        if (i) {
                            break;
                        }
                    }
                    break;
                }
            }
        }
        return null;
    }
    
    public static String d(final String s) {
        final boolean i = App.I;
        b();
        for (final a2d a2d : vi.c) {
            try {
                if (("" + a2d.j).equals(s)) {
                    return a2d.l;
                }
            }
            catch (IllegalArgumentException ex) {
                throw ex;
            }
            if (i) {
                break;
            }
        }
        return "";
    }
    
    private static int[] e(final String s) {
        final boolean i = App.I;
        final String[] split = TextUtils.split(s, ",");
        int[] array = null;
        if (split != null) {
            final int length = split.length;
            array = null;
            if (length != 0) {
                array = new int[length];
                int j = 0;
                while (j < length) {
                    array[j] = Integer.parseInt(split[j]);
                    ++j;
                    if (i) {
                        return array;
                    }
                }
            }
        }
        return array;
    }
    
    public static String f(final String s) {
        final boolean i = App.I;
        b();
        for (final a2d a2d : vi.c) {
            try {
                if (a2d.e.startsWith(s)) {
                    return a2d.l;
                }
            }
            catch (IllegalArgumentException ex) {
                throw ex;
            }
            if (i) {
                break;
            }
        }
        return "";
    }
    
    public static String g(final String s) {
        final boolean i = App.I;
        b();
        final Iterator<a2d> iterator = (Iterator<a2d>)vi.c.iterator();
        String e = null;
    Label_0102:
        while (iterator.hasNext()) {
            String e2;
            while (true) {
                final a2d a2d = iterator.next();
                while (true) {
                    try {
                        if (Integer.toString(a2d.j).equals(s)) {
                            if (a2d.b) {
                                e = a2d.e;
                                if (!i) {
                                    break Label_0102;
                                }
                            }
                            if (e == null) {
                                e2 = a2d.e;
                                if (i) {
                                    return e2;
                                }
                                break;
                            }
                        }
                    }
                    catch (IllegalArgumentException ex) {
                        throw ex;
                    }
                    e2 = e;
                    continue;
                }
            }
            e = e2;
        }
        return e;
    }
    
    public static String h(final String s) {
        final boolean i = App.I;
        b();
        for (final a2d a2d : vi.c) {
            try {
                if (a2d.e.equals(s)) {
                    return Integer.toString(a2d.j);
                }
            }
            catch (IllegalArgumentException ex) {
                throw ex;
            }
            if (i) {
                break;
            }
        }
        return null;
    }
}
