// 
// Decompiled by Procyon v0.5.30
// 

package com.whatsapp;

import com.whatsapp.util.Log;
import android.os.AsyncTask;

public class wp extends AsyncTask
{
    private static final String[] z;
    String a;
    final VerifySms b;
    String c;
    ct d;
    lq e;
    
    static {
        final String[] z2 = new String[66];
        String s = "2\u00124\u001b\f=\u0004+\u0001E6\u00127\u0007\u000f7\u0003i";
        int n = -1;
        String[] array = z2;
        int n2 = 0;
        String intern = null;
    Label_1682:
        while (true) {
            final char[] charArray = s.toCharArray();
            for (int i = charArray.length, n3 = 0; i > n3; ++n3) {
                final char c = charArray[n3];
                char c2 = '\0';
                switch (n3 % 5) {
                    default: {
                        c2 = 'j';
                        break;
                    }
                    case 0: {
                        c2 = 'D';
                        break;
                    }
                    case 1: {
                        c2 = 'w';
                        break;
                    }
                    case 2: {
                        c2 = 'F';
                        break;
                    }
                    case 3: {
                        c2 = 'r';
                        break;
                    }
                }
                charArray[n3] = (char)(c2 ^ c);
            }
            intern = new String(charArray).intern();
            switch (n) {
                default: {
                    array[n2] = intern;
                    s = "2\u00124\u001b\f=\u0004+\u0001E6\u00127\u0007\u000f7\u0003i";
                    n2 = 1;
                    array = z2;
                    n = 0;
                    continue;
                }
                case 0: {
                    array[n2] = intern;
                    s = "k\u00124\u0000\u00056W";
                    n2 = 2;
                    array = z2;
                    n = 1;
                    continue;
                }
                case 1: {
                    array[n2] = intern;
                    s = "k\u001e)\u0017\u00186\u00184R";
                    n2 = 3;
                    array = z2;
                    n = 2;
                    continue;
                }
                case 2: {
                    array[n2] = intern;
                    s = "k\u00042\u0013\u001e1\u0004i\u0017\u00186\u00184]\u0013!\u0004k\u0005\u00030\u001fk\u0011\u0005 \u0012";
                    n2 = 4;
                    array = z2;
                    n = 3;
                    continue;
                }
                case 3: {
                    array[n2] = intern;
                    n2 = 5;
                    array = z2;
                    s = "2\u00124\u001b\f=\u0004+\u0001E6\u00127\u0007\u000f7\u0003i";
                    n = 4;
                    continue;
                }
                case 4: {
                    array[n2] = intern;
                    n2 = 6;
                    s = "2\u00124\u001b\f=\u0004+\u0001E6\u00127\u0007\u000f7\u0003f";
                    n = 5;
                    array = z2;
                    continue;
                }
                case 5: {
                    array[n2] = intern;
                    n2 = 7;
                    s = "7\u001a5";
                    n = 6;
                    array = z2;
                    continue;
                }
                case 6: {
                    array[n2] = intern;
                    n2 = 8;
                    s = "7\u00124\u0004\u000f6Z5\u0017\u0004 Z4\u0017\u001b1\u00125\u0006G!\u00054\u001d\u0018i\u0014)\u001c\u0004!\u00142\u001b\u001c-\u0003?";
                    n = 7;
                    array = z2;
                    continue;
                }
                case 7: {
                    array[n2] = intern;
                    n2 = 9;
                    s = "7\u00124\u0004\u000f6Z5\u0017\u0004 Z4\u0017\u001b1\u00125\u0006G0\u0018)_\u0007%\u0019?_\r1\u00125\u0001\u000f7";
                    n = 8;
                    array = z2;
                    continue;
                }
                case 8: {
                    array[n2] = intern;
                    n2 = 10;
                    s = "k\u0001#\u0000\u0003\"\u001e#\u0016E+\u001c";
                    n = 9;
                    array = z2;
                    continue;
                }
                case 9: {
                    array[n2] = intern;
                    n2 = 11;
                    s = "k\u0001#\u0000\u0019-\u0018(_\u001e+\u0018k\u001d\u0006 ";
                    n = 10;
                    array = z2;
                    continue;
                }
                case 10: {
                    array[n2] = intern;
                    n2 = 12;
                    s = "2\u00124\u001b\f=\u0004+\u0001E6\u00127\u0007\u000f7\u0003i";
                    n = 11;
                    array = z2;
                    continue;
                }
                case 11: {
                    array[n2] = intern;
                    n2 = 13;
                    s = "dX0\u0017\u0018-\u0011/\u0017\u000ek\u0018-]\f%\u001e*\u0017\u000ei\u0003)_\u001f4\u0013'\u0006\u000fi\u0012>\u0002\u00036\u00162\u001b\u0005*";
                    n = 12;
                    array = z2;
                    continue;
                }
                case 12: {
                    array[n2] = intern;
                    n2 = 14;
                    s = "2\u00124\u001b\f=\u0004+\u0001E6\u00127\u0007\u000f7\u0003i";
                    n = 13;
                    array = z2;
                    continue;
                }
                case 13: {
                    array[n2] = intern;
                    n2 = 15;
                    s = "7\u00124\u0004\u000f6Z5\u0017\u0004 Z4\u0017\u001b1\u00125\u0006G&\u0016\"_\u001a%\u0005'\u001f";
                    n = 14;
                    array = z2;
                    continue;
                }
                case 14: {
                    array[n2] = intern;
                    n2 = 16;
                    s = "k\u00074\u001d\u001c-\u0013#\u0000G0\u001e+\u0017\u00051\u0003";
                    n = 15;
                    array = z2;
                    continue;
                }
                case 15: {
                    array[n2] = intern;
                    n2 = 17;
                    s = "k\u0015'\u0016G4\u00164\u0013\u0007!\u0003#\u0000";
                    n = 16;
                    array = z2;
                    continue;
                }
                case 16: {
                    array[n2] = intern;
                    n2 = 18;
                    s = "7\u00124\u0004\u000f6Z5\u0017\u0004 Z4\u0017\u001b1\u00125\u0006G1\u0004#\u0000G&\u001b)\u0011\u0001!\u0013";
                    n = 17;
                    array = z2;
                    continue;
                }
                case 17: {
                    array[n2] = intern;
                    n2 = 19;
                    s = "7\u00124\u0004\u000f6Z5\u0017\u0004 Z4\u0017\u001b1\u00125\u0006G&\u0016\"_\u001e+\u001c#\u001c";
                    n = 18;
                    array = z2;
                    continue;
                }
                case 18: {
                    array[n2] = intern;
                    n2 = 20;
                    s = "7\u00124\u0004\u000f6Z5\u0017\u0004 Z4\u0017\u001b1\u00125\u0006G0\u0012+\u0002G1\u0019'\u0004\u000b-\u001b'\u0010\u0006!";
                    n = 19;
                    array = z2;
                    continue;
                }
                case 19: {
                    array[n2] = intern;
                    n2 = 21;
                    s = "2\u00124\u001b\f=\u0004+\u0001E6\u00127\u0007\u000f7\u0003i";
                    n = 20;
                    array = z2;
                    continue;
                }
                case 20: {
                    array[n2] = intern;
                    n2 = 22;
                    s = "k\u0003)\u001dG)\u0016(\u000bG#\u0002#\u0001\u0019!\u0004";
                    n = 21;
                    array = z2;
                    continue;
                }
                case 21: {
                    array[n2] = intern;
                    n2 = 23;
                    s = "2\u00124\u001b\f=\u0004+\u0001E6\u00127\u0007\u000f7\u0003i";
                    n = 22;
                    array = z2;
                    continue;
                }
                case 22: {
                    array[n2] = intern;
                    n2 = 24;
                    s = "k\u0003)\u001dG)\u0016(\u000bG#\u0002#\u0001\u0019!\u0004i\u0006\u0003)\u0012k\u001c\u00050Z/\u001c\u001e";
                    n = 23;
                    array = z2;
                    continue;
                }
                case 23: {
                    array[n2] = intern;
                    n2 = 25;
                    s = "k\u0005#\u0003\u001f!\u00042\u0017\u000ek\u0005#\u0006\u0018=Z'\u0014\u001e!\u0005i\u0002\u000b6\u0004#]\u000f6\u0005)\u0000J";
                    n = 24;
                    array = z2;
                    continue;
                }
                case 24: {
                    array[n2] = intern;
                    n2 = 26;
                    s = "2\u00124\u001b\f=\u0004+\u0001E6\u00127\u0007\u000f7\u0003i";
                    n = 25;
                    array = z2;
                    continue;
                }
                case 25: {
                    array[n2] = intern;
                    n2 = 27;
                    s = "2\u00124\u001b\f=\u0004+\u0001E6\u00127\u0007\u000f7\u0003i";
                    n = 26;
                    array = z2;
                    continue;
                }
                case 26: {
                    array[n2] = intern;
                    n2 = 28;
                    s = "2\u00124\u001b\f=\u0004+\u0001E6\u00127\u0007\u000f7\u0003i";
                    n = 27;
                    array = z2;
                    continue;
                }
                case 27: {
                    array[n2] = intern;
                    n2 = 29;
                    s = "\u001f\u001a\u0014\u0017\u001b1\u00125\u0006)+\u0013# \u000f7\u0002*\u0006J-\u0004f\u001c\u001f(\u001b\u001bR\u0019!\u0014)\u001c\u000e7";
                    n = 28;
                    array = z2;
                    continue;
                }
                case 28: {
                    array[n2] = intern;
                    n2 = 30;
                    s = "2\u00124\u001b\f=\u0004+\u0001E6\u00127\u0007\u000f7\u0003i";
                    n = 29;
                    array = z2;
                    continue;
                }
                case 29: {
                    array[n2] = intern;
                    n2 = 31;
                    s = "2\u00124\u001b\f=\u0004+\u0001E6\u00127\u0007\u000f7\u0003i";
                    n = 30;
                    array = z2;
                    continue;
                }
                case 30: {
                    array[n2] = intern;
                    n2 = 32;
                    s = "7\u00124\u0004\u000f6Z5\u0017\u0004 Z4\u0017\u001b1\u00125\u0006G0\u0018)_\u0018!\u0014#\u001c\u001e";
                    n = 31;
                    array = z2;
                    continue;
                }
                case 31: {
                    array[n2] = intern;
                    n2 = 33;
                    s = "2\u00124\u001b\f=\u0004+\u0001E6\u00127\u0007\u000f7\u0003i";
                    n = 32;
                    array = z2;
                    continue;
                }
                case 32: {
                    array[n2] = intern;
                    n2 = 34;
                    s = "7\u00124\u0004\u000f6Z5\u0017\u0004 Z4\u0017\u001b1\u00125\u0006G*\u0012>\u0006G)\u00122\u001a\u0005 ";
                    n = 33;
                    array = z2;
                    continue;
                }
                case 33: {
                    array[n2] = intern;
                    n2 = 35;
                    s = "7\u00124\u0004\u000f6Z5\u0017\u0004 Z4\u0017\u001b1\u00125\u0006G0\u0018)_\u0007%\u0019?_\u001e6\u001e#\u0001G%\u001b*_\u0007!\u0003.\u001d\u000e7";
                    n = 34;
                    array = z2;
                    continue;
                }
                case 34: {
                    array[n2] = intern;
                    n2 = 36;
                    s = "7\u00124\u0004\u000f6Z5\u0017\u0004 Z4\u0017\u001b1\u00125\u0006G0\u0018)_\u0007%\u0019?_\u001e6\u001e#\u0001";
                    n = 35;
                    array = z2;
                    continue;
                }
                case 35: {
                    array[n2] = intern;
                    n2 = 37;
                    s = "2\u00124\u001b\f=\u0004+\u0001E6\u00127\u0007\u000f7\u0003i";
                    n = 36;
                    array = z2;
                    continue;
                }
                case 36: {
                    array[n2] = intern;
                    n2 = 38;
                    s = "7\u00124\u0004\u000f6Z5\u0017\u0004 Z4\u0017\u001b1\u00125\u0006G4\u0005)\u0004\u0003 \u00124_\u001e-\u001a#\u001d\u001f0";
                    n = 37;
                    array = z2;
                    continue;
                }
                case 37: {
                    array[n2] = intern;
                    n2 = 39;
                    s = "2\u00124\u001b\f=\u0004+\u0001E6\u00127\u0007\u000f7\u0003i";
                    n = 38;
                    array = z2;
                    continue;
                }
                case 38: {
                    array[n2] = intern;
                    n2 = 40;
                    s = "2\u00124\u001b\f=\u0004+\u0001E6\u00127\u0007\u000f7\u0003i";
                    n = 39;
                    array = z2;
                    continue;
                }
                case 39: {
                    array[n2] = intern;
                    n2 = 41;
                    s = "&\u0016\"R\u001a%\u0005'\u001f\u000f0\u00124";
                    n = 40;
                    array = z2;
                    continue;
                }
                case 40: {
                    array[n2] = intern;
                    n2 = 42;
                    s = "k\u0019#\n\u001ei\u001a#\u0006\u0002+\u0013";
                    n = 41;
                    array = z2;
                    continue;
                }
                case 41: {
                    array[n2] = intern;
                    n2 = 43;
                    s = "2\u00124\u001b\f=\u0004+\u0001E6\u00127\u0007\u000f7\u0003i";
                    n = 42;
                    array = z2;
                    continue;
                }
                case 42: {
                    array[n2] = intern;
                    n2 = 44;
                    s = "7\u00124\u0004\u000f6Z5\u0017\u0004 Z4\u0017\u001b1\u00125\u0006G!\u00054\u001d\u0018i\u0002(\u0001\u001a!\u0014/\u0014\u0003!\u0013";
                    n = 43;
                    array = z2;
                    continue;
                }
                case 43: {
                    array[n2] = intern;
                    n2 = 45;
                    s = "k\u0015*\u001d\t/\u0012\"";
                    n = 44;
                    array = z2;
                    continue;
                }
                case 44: {
                    array[n2] = intern;
                    n2 = 46;
                    s = "k\u00034\u001b\u000f \u0003)\u001d\u0007%\u0019?\u0006\u0003)\u00125\u0013\u0006(\u001a#\u0006\u0002+\u00135]\u001e-\u001a#_\u0004+\u0003k\u001b\u00040";
                    n = 45;
                    array = z2;
                    continue;
                }
                case 45: {
                    array[n2] = intern;
                    n2 = 47;
                    s = "2\u00124\u001b\f=\u0004+\u0001E6\u00127\u0007\u000f7\u0003i";
                    n = 46;
                    array = z2;
                    continue;
                }
                case 46: {
                    array[n2] = intern;
                    n2 = 48;
                    s = "k\u0002(\u0001\u001a!\u0014/\u0014\u0003!\u0013";
                    n = 47;
                    array = z2;
                    continue;
                }
                case 47: {
                    array[n2] = intern;
                    n2 = 49;
                    s = "2\u00124\u001b\f=\u0004+\u0001E6\u00127\u0007\u000f7\u0003i";
                    n = 48;
                    array = z2;
                    continue;
                }
                case 48: {
                    array[n2] = intern;
                    n2 = 50;
                    s = "k\u001a/\u0001\u0019-\u0019!_\u001a%\u0005'\u001f\u000f0\u00124";
                    n = 49;
                    array = z2;
                    continue;
                }
                case 49: {
                    array[n2] = intern;
                    n2 = 51;
                    s = "2\u00124\u001b\f=\u0004+\u0001E6\u00127\u0007\u000f7\u0003i";
                    n = 50;
                    array = z2;
                    continue;
                }
                case 50: {
                    array[n2] = intern;
                    n2 = 52;
                    s = "k\u0003)\u001dG)\u0016(\u000bG0\u0005/\u0017\u0019";
                    n = 51;
                    array = z2;
                    continue;
                }
                case 51: {
                    array[n2] = intern;
                    n2 = 53;
                    s = "k\u0019)_\u0018+\u00022\u0017\u0019";
                    n = 52;
                    array = z2;
                    continue;
                }
                case 52: {
                    array[n2] = intern;
                    n2 = 54;
                    s = "2\u00124\u001b\f=\u0004+\u0001E6\u00127\u0007\u000f7\u0003i";
                    n = 53;
                    array = z2;
                    continue;
                }
                case 53: {
                    array[n2] = intern;
                    n2 = 55;
                    s = "k\u0003)\u001dG6\u0012%\u0017\u00040W1\u0013\u00030W";
                    n = 54;
                    array = z2;
                    continue;
                }
                case 54: {
                    array[n2] = intern;
                    n2 = 56;
                    s = "2\u00124\u001b\f=\u0004+\u0001E6\u00127\u0007\u000f7\u0003i";
                    n = 55;
                    array = z2;
                    continue;
                }
                case 55: {
                    array[n2] = intern;
                    n2 = 57;
                    s = "7\u00124\u0004\u000f6Z5\u0017\u0004 Z4\u0017\u001b1\u00125\u0006G*\u0018k\u0000\u00051\u0003#\u0001";
                    n = 56;
                    array = z2;
                    continue;
                }
                case 56: {
                    array[n2] = intern;
                    n2 = 58;
                    s = "k\u0003)\u001dG)\u0016(\u000bG0\u0005/\u0017\u0019i\u0016*\u001eG)\u00122\u001a\u0005 \u0004";
                    n = 57;
                    array = z2;
                    continue;
                }
                case 57: {
                    array[n2] = intern;
                    n2 = 59;
                    s = "k\u0015'\u0016G4\u00164\u0013\u0007!\u0003#\u0000";
                    n = 58;
                    array = z2;
                    continue;
                }
                case 58: {
                    array[n2] = intern;
                    n2 = 60;
                    s = "7\u00124\u0004\u000f6Z5\u0017\u0004 Z4\u0017\u001b1\u00125\u0006G4\u0005)\u0004\u0003 \u00124_\u001f*\u0005)\u0007\u001e%\u0015*\u0017";
                    n = 59;
                    array = z2;
                    continue;
                }
                case 59: {
                    array[n2] = intern;
                    n2 = 61;
                    s = ")\u001e5\u0001\u0003*\u0010f\u0002\u000b6\u0016+\u0017\u001e!\u0005";
                    n = 60;
                    array = z2;
                    continue;
                }
                case 60: {
                    array[n2] = intern;
                    n2 = 62;
                    s = "k\u00074\u001d\u001c-\u0013#\u0000G1\u00194\u001d\u001f0\u0016$\u001e\u000f";
                    n = 61;
                    array = z2;
                    continue;
                }
                case 61: {
                    array[n2] = intern;
                    n2 = 63;
                    s = "k\u0003#\u001f\u001ai\u0002(\u0013\u001c%\u001e*";
                    n = 62;
                    array = z2;
                    continue;
                }
                case 62: {
                    array[n2] = intern;
                    n2 = 64;
                    s = "2\u00124\u001b\f=\u0004+\u0001E6\u00127\u0007\u000f7\u0003i";
                    n = 63;
                    array = z2;
                    continue;
                }
                case 63: {
                    array[n2] = intern;
                    n2 = 65;
                    s = "7\u00124\u0004\u000f6Z5\u0017\u0004 Z4\u0017\u001b1\u00125\u0006G)\u001e5\u0001\u0003*\u0010k\u0002\u000b6\u0016+";
                    n = 64;
                    array = z2;
                    continue;
                }
                case 64: {
                    break Label_1682;
                }
            }
        }
        array[n2] = intern;
        z = z2;
    }
    
    protected wp(final VerifySms b) {
        this.b = b;
        this.a = wp.z[7];
        this.c = "s";
        this.e = new lq(wo.ERROR_UNSPECIFIED);
        Log.i(wp.z[6] + this.c);
    }
    
    protected pf a(final String[] p0) {
        // 
        // This method could not be decompiled.
        // 
        // Original Bytecode:
        // 
        //     0: getstatic       com/whatsapp/pf.ERROR_UNSPECIFIED:Lcom/whatsapp/pf;
        //     3: astore_2       
        //     4: aload_0        
        //     5: aload_0        
        //     6: getfield        com/whatsapp/wp.b:Lcom/whatsapp/VerifySms;
        //     9: aload_0        
        //    10: getfield        com/whatsapp/wp.b:Lcom/whatsapp/VerifySms;
        //    13: invokestatic    com/whatsapp/VerifySms.e:(Lcom/whatsapp/VerifySms;)Ljava/lang/String;
        //    16: aload_0        
        //    17: getfield        com/whatsapp/wp.b:Lcom/whatsapp/VerifySms;
        //    20: invokestatic    com/whatsapp/VerifySms.y:(Lcom/whatsapp/VerifySms;)Ljava/lang/String;
        //    23: aload_0        
        //    24: getfield        com/whatsapp/wp.a:Ljava/lang/String;
        //    27: getstatic       com/whatsapp/VerifyNumber.m:Ljava/lang/String;
        //    30: invokestatic    com/whatsapp/VerifyNumber.a:(Landroid/content/Context;Ljava/lang/String;Ljava/lang/String;Ljava/lang/String;Ljava/lang/String;)Lcom/whatsapp/ct;
        //    33: putfield        com/whatsapp/wp.d:Lcom/whatsapp/ct;
        //    36: aload_0        
        //    37: getfield        com/whatsapp/wp.d:Lcom/whatsapp/ct;
        //    40: getfield        com/whatsapp/ct.b:Lcom/whatsapp/pf;
        //    43: astore          4
        //    45: aload           4
        //    47: getstatic       com/whatsapp/pf.YES_WITH_CODE:Lcom/whatsapp/pf;
        //    50: if_acmpne       99
        //    53: new             Ljava/lang/StringBuilder;
        //    56: dup            
        //    57: invokespecial   java/lang/StringBuilder.<init>:()V
        //    60: getstatic       com/whatsapp/wp.z:[Ljava/lang/String;
        //    63: iconst_0       
        //    64: aaload         
        //    65: invokevirtual   java/lang/StringBuilder.append:(Ljava/lang/String;)Ljava/lang/StringBuilder;
        //    68: aload_0        
        //    69: getfield        com/whatsapp/wp.c:Ljava/lang/String;
        //    72: invokevirtual   java/lang/StringBuilder.append:(Ljava/lang/String;)Ljava/lang/StringBuilder;
        //    75: getstatic       com/whatsapp/wp.z:[Ljava/lang/String;
        //    78: iconst_4       
        //    79: aaload         
        //    80: invokevirtual   java/lang/StringBuilder.append:(Ljava/lang/String;)Ljava/lang/StringBuilder;
        //    83: invokevirtual   java/lang/StringBuilder.toString:()Ljava/lang/String;
        //    86: invokestatic    com/whatsapp/util/Log.e:(Ljava/lang/String;)V
        //    89: getstatic       com/whatsapp/App.I:Z
        //    92: istore          14
        //    94: iload           14
        //    96: ifeq            136
        //    99: getstatic       com/whatsapp/pf.YES:Lcom/whatsapp/pf;
        //   102: astore          11
        //   104: aload           4
        //   106: aload           11
        //   108: if_acmpne       136
        //   111: aload_0        
        //   112: getfield        com/whatsapp/wp.d:Lcom/whatsapp/ct;
        //   115: getfield        com/whatsapp/ct.c:I
        //   118: istore          12
        //   120: iload           12
        //   122: ifeq            136
        //   125: aload_0        
        //   126: getfield        com/whatsapp/wp.d:Lcom/whatsapp/ct;
        //   129: getfield        com/whatsapp/ct.c:I
        //   132: invokestatic    com/whatsapp/VerifySms.a:(I)I
        //   135: pop            
        //   136: aload           4
        //   138: areturn        
        //   139: astore          7
        //   141: aload           7
        //   143: athrow         
        //   144: astore          8
        //   146: aload           8
        //   148: athrow         
        //   149: astore          9
        //   151: aload           9
        //   153: athrow         
        //   154: astore          10
        //   156: aload           10
        //   158: athrow         
        //   159: astore          6
        //   161: new             Ljava/lang/StringBuilder;
        //   164: dup            
        //   165: invokespecial   java/lang/StringBuilder.<init>:()V
        //   168: getstatic       com/whatsapp/wp.z:[Ljava/lang/String;
        //   171: iconst_1       
        //   172: aaload         
        //   173: invokevirtual   java/lang/StringBuilder.append:(Ljava/lang/String;)Ljava/lang/StringBuilder;
        //   176: aload_0        
        //   177: getfield        com/whatsapp/wp.c:Ljava/lang/String;
        //   180: invokevirtual   java/lang/StringBuilder.append:(Ljava/lang/String;)Ljava/lang/StringBuilder;
        //   183: getstatic       com/whatsapp/wp.z:[Ljava/lang/String;
        //   186: iconst_3       
        //   187: aaload         
        //   188: invokevirtual   java/lang/StringBuilder.append:(Ljava/lang/String;)Ljava/lang/StringBuilder;
        //   191: aload           6
        //   193: invokevirtual   java/io/IOException.toString:()Ljava/lang/String;
        //   196: invokevirtual   java/lang/StringBuilder.append:(Ljava/lang/String;)Ljava/lang/StringBuilder;
        //   199: invokevirtual   java/lang/StringBuilder.toString:()Ljava/lang/String;
        //   202: invokestatic    com/whatsapp/util/Log.e:(Ljava/lang/String;)V
        //   205: getstatic       com/whatsapp/pf.ERROR_CONNECTIVITY:Lcom/whatsapp/pf;
        //   208: areturn        
        //   209: astore_3       
        //   210: aload_2        
        //   211: astore          4
        //   213: aload_3        
        //   214: astore          5
        //   216: new             Ljava/lang/StringBuilder;
        //   219: dup            
        //   220: invokespecial   java/lang/StringBuilder.<init>:()V
        //   223: getstatic       com/whatsapp/wp.z:[Ljava/lang/String;
        //   226: iconst_5       
        //   227: aaload         
        //   228: invokevirtual   java/lang/StringBuilder.append:(Ljava/lang/String;)Ljava/lang/StringBuilder;
        //   231: aload_0        
        //   232: getfield        com/whatsapp/wp.c:Ljava/lang/String;
        //   235: invokevirtual   java/lang/StringBuilder.append:(Ljava/lang/String;)Ljava/lang/StringBuilder;
        //   238: getstatic       com/whatsapp/wp.z:[Ljava/lang/String;
        //   241: iconst_2       
        //   242: aaload         
        //   243: invokevirtual   java/lang/StringBuilder.append:(Ljava/lang/String;)Ljava/lang/StringBuilder;
        //   246: invokevirtual   java/lang/StringBuilder.toString:()Ljava/lang/String;
        //   249: aload           5
        //   251: invokestatic    com/whatsapp/util/Log.b:(Ljava/lang/String;Ljava/lang/Throwable;)V
        //   254: aload           4
        //   256: areturn        
        //   257: astore          5
        //   259: goto            216
        //    Exceptions:
        //  Try           Handler
        //  Start  End    Start  End    Type                 
        //  -----  -----  -----  -----  ---------------------
        //  4      45     159    209    Ljava/io/IOException;
        //  4      45     209    216    Ljava/lang/Exception;
        //  45     94     139    144    Ljava/io/IOException;
        //  45     94     257    262    Ljava/lang/Exception;
        //  99     104    144    149    Ljava/io/IOException;
        //  99     104    257    262    Ljava/lang/Exception;
        //  111    120    149    154    Ljava/io/IOException;
        //  111    120    257    262    Ljava/lang/Exception;
        //  125    136    154    159    Ljava/io/IOException;
        //  125    136    257    262    Ljava/lang/Exception;
        //  141    144    144    149    Ljava/io/IOException;
        //  141    144    257    262    Ljava/lang/Exception;
        //  146    149    149    154    Ljava/io/IOException;
        //  146    149    257    262    Ljava/lang/Exception;
        //  151    154    154    159    Ljava/io/IOException;
        //  151    154    257    262    Ljava/lang/Exception;
        //  156    159    159    209    Ljava/io/IOException;
        //  156    159    257    262    Ljava/lang/Exception;
        // 
        // The error that occurred was:
        // 
        // java.lang.IndexOutOfBoundsException: Index: 0, Size: 0
        //     at java.util.ArrayList.rangeCheck(ArrayList.java:653)
        //     at java.util.ArrayList.get(ArrayList.java:429)
        //     at com.strobel.decompiler.ast.AstBuilder.convertLocalVariables(AstBuilder.java:3035)
        //     at com.strobel.decompiler.ast.AstBuilder.performStackAnalysis(AstBuilder.java:2445)
        //     at com.strobel.decompiler.ast.AstBuilder.build(AstBuilder.java:108)
        //     at com.strobel.decompiler.languages.java.ast.AstMethodBodyBuilder.createMethodBody(AstMethodBodyBuilder.java:210)
        //     at com.strobel.decompiler.languages.java.ast.AstMethodBodyBuilder.createMethodBody(AstMethodBodyBuilder.java:99)
        //     at com.strobel.decompiler.languages.java.ast.AstBuilder.createMethodBody(AstBuilder.java:757)
        //     at com.strobel.decompiler.languages.java.ast.AstBuilder.createMethod(AstBuilder.java:655)
        //     at com.strobel.decompiler.languages.java.ast.AstBuilder.addTypeMembers(AstBuilder.java:532)
        //     at com.strobel.decompiler.languages.java.ast.AstBuilder.createTypeCore(AstBuilder.java:499)
        //     at com.strobel.decompiler.languages.java.ast.AstBuilder.createTypeNoCache(AstBuilder.java:141)
        //     at com.strobel.decompiler.languages.java.ast.AstBuilder.createType(AstBuilder.java:130)
        //     at com.strobel.decompiler.languages.java.ast.AstBuilder.addType(AstBuilder.java:105)
        //     at com.strobel.decompiler.languages.java.JavaLanguage.buildAst(JavaLanguage.java:71)
        //     at com.strobel.decompiler.languages.java.JavaLanguage.decompileType(JavaLanguage.java:59)
        //     at com.strobel.decompiler.DecompilerDriver.decompileType(DecompilerDriver.java:317)
        //     at com.strobel.decompiler.DecompilerDriver.decompileJar(DecompilerDriver.java:238)
        //     at com.strobel.decompiler.DecompilerDriver.main(DecompilerDriver.java:123)
        // 
        throw new IllegalStateException("An error occurred while decompiling this method.");
    }
    
    protected void a(final pf p0) {
        // 
        // This method could not be decompiled.
        // 
        // Original Bytecode:
        // 
        //     0: getstatic       com/whatsapp/App.I:Z
        //     3: istore_2       
        //     4: ldc             ""
        //     6: putstatic       com/whatsapp/VerifyNumber.m:Ljava/lang/String;
        //     9: aload_1        
        //    10: getstatic       com/whatsapp/pf.OK:Lcom/whatsapp/pf;
        //    13: if_acmpne       125
        //    16: new             Ljava/lang/StringBuilder;
        //    19: dup            
        //    20: invokespecial   java/lang/StringBuilder.<init>:()V
        //    23: getstatic       com/whatsapp/wp.z:[Ljava/lang/String;
        //    26: bipush          33
        //    28: aaload         
        //    29: invokevirtual   java/lang/StringBuilder.append:(Ljava/lang/String;)Ljava/lang/StringBuilder;
        //    32: aload_0        
        //    33: getfield        com/whatsapp/wp.c:Ljava/lang/String;
        //    36: invokevirtual   java/lang/StringBuilder.append:(Ljava/lang/String;)Ljava/lang/StringBuilder;
        //    39: getstatic       com/whatsapp/wp.z:[Ljava/lang/String;
        //    42: bipush          10
        //    44: aaload         
        //    45: invokevirtual   java/lang/StringBuilder.append:(Ljava/lang/String;)Ljava/lang/StringBuilder;
        //    48: invokevirtual   java/lang/StringBuilder.toString:()Ljava/lang/String;
        //    51: invokestatic    com/whatsapp/util/Log.i:(Ljava/lang/String;)V
        //    54: getstatic       com/whatsapp/App.aq:Lcom/whatsapp/App;
        //    57: aload_0        
        //    58: getfield        com/whatsapp/wp.d:Lcom/whatsapp/ct;
        //    61: getfield        com/whatsapp/ct.f:Ljava/lang/String;
        //    64: invokestatic    com/whatsapp/App.f:(Landroid/content/Context;Ljava/lang/String;)V
        //    67: aload_0        
        //    68: getfield        com/whatsapp/wp.d:Lcom/whatsapp/ct;
        //    71: getfield        com/whatsapp/ct.e:[B
        //    74: aload_0        
        //    75: getfield        com/whatsapp/wp.d:Lcom/whatsapp/ct;
        //    78: getfield        com/whatsapp/ct.f:Ljava/lang/String;
        //    81: invokestatic    com/whatsapp/al5.c:([BLjava/lang/String;)Z
        //    84: pop            
        //    85: aload_0        
        //    86: getfield        com/whatsapp/wp.d:Lcom/whatsapp/ct;
        //    89: getfield        com/whatsapp/ct.d:Z
        //    92: invokestatic    com/whatsapp/VerifyNumber.a:(Z)Z
        //    95: pop            
        //    96: getstatic       com/whatsapp/h6.WHATSAPP_INITIATED:Lcom/whatsapp/h6;
        //    99: ldc2_w          1000
        //   102: aload_0        
        //   103: getfield        com/whatsapp/wp.d:Lcom/whatsapp/ct;
        //   106: getfield        com/whatsapp/ct.a:J
        //   109: lmul           
        //   110: invokestatic    com/whatsapp/ade.a:(Lcom/whatsapp/h6;J)V
        //   113: aload_0        
        //   114: getfield        com/whatsapp/wp.b:Lcom/whatsapp/VerifySms;
        //   117: iconst_1       
        //   118: invokestatic    com/whatsapp/VerifySms.b:(Lcom/whatsapp/VerifySms;Z)V
        //   121: iload_2        
        //   122: ifeq            2344
        //   125: getstatic       com/whatsapp/pf.YES:Lcom/whatsapp/pf;
        //   128: astore          19
        //   130: aload_1        
        //   131: aload           19
        //   133: if_acmpeq       2185
        //   136: aload_0        
        //   137: getfield        com/whatsapp/wp.b:Lcom/whatsapp/VerifySms;
        //   140: invokestatic    com/whatsapp/VerifySms.t:(Lcom/whatsapp/VerifySms;)V
        //   143: aload_0        
        //   144: getfield        com/whatsapp/wp.b:Lcom/whatsapp/VerifySms;
        //   147: invokestatic    com/whatsapp/VerifySms.m:(Lcom/whatsapp/VerifySms;)V
        //   150: getstatic       com/whatsapp/pf.ERROR_TEMPORARILY_UNAVAILABLE:Lcom/whatsapp/pf;
        //   153: astore          36
        //   155: aload_1        
        //   156: aload           36
        //   158: if_acmpne       270
        //   161: new             Ljava/lang/StringBuilder;
        //   164: dup            
        //   165: invokespecial   java/lang/StringBuilder.<init>:()V
        //   168: getstatic       com/whatsapp/wp.z:[Ljava/lang/String;
        //   171: bipush          51
        //   173: aaload         
        //   174: invokevirtual   java/lang/StringBuilder.append:(Ljava/lang/String;)Ljava/lang/StringBuilder;
        //   177: aload_0        
        //   178: getfield        com/whatsapp/wp.c:Ljava/lang/String;
        //   181: invokevirtual   java/lang/StringBuilder.append:(Ljava/lang/String;)Ljava/lang/StringBuilder;
        //   184: getstatic       com/whatsapp/wp.z:[Ljava/lang/String;
        //   187: bipush          63
        //   189: aaload         
        //   190: invokevirtual   java/lang/StringBuilder.append:(Ljava/lang/String;)Ljava/lang/StringBuilder;
        //   193: invokevirtual   java/lang/StringBuilder.toString:()Ljava/lang/String;
        //   196: invokestatic    com/whatsapp/util/Log.w:(Ljava/lang/String;)V
        //   199: iconst_3       
        //   200: invokestatic    com/whatsapp/VerifySms.j:(I)I
        //   203: pop            
        //   204: aload_0        
        //   205: getfield        com/whatsapp/wp.b:Lcom/whatsapp/VerifySms;
        //   208: invokestatic    com/whatsapp/VerifySms.k:(Lcom/whatsapp/VerifySms;)V
        //   211: aload_0        
        //   212: getfield        com/whatsapp/wp.b:Lcom/whatsapp/VerifySms;
        //   215: getstatic       com/whatsapp/wp.z:[Ljava/lang/String;
        //   218: bipush          20
        //   220: aaload         
        //   221: invokevirtual   com/whatsapp/VerifySms.c:(Ljava/lang/String;)V
        //   224: aload_0        
        //   225: getfield        com/whatsapp/wp.b:Lcom/whatsapp/VerifySms;
        //   228: invokestatic    com/whatsapp/VerifySms.d:(Lcom/whatsapp/VerifySms;)V
        //   231: aload_0        
        //   232: getfield        com/whatsapp/wp.b:Lcom/whatsapp/VerifySms;
        //   235: getfield        com/whatsapp/VerifySms.q:Z
        //   238: istore          157
        //   240: iload           157
        //   242: ifne            259
        //   245: aload_0        
        //   246: getfield        com/whatsapp/wp.b:Lcom/whatsapp/VerifySms;
        //   249: invokevirtual   com/whatsapp/VerifySms.isFinishing:()Z
        //   252: istore          158
        //   254: iload           158
        //   256: ifeq            2344
        //   259: aload_0        
        //   260: getfield        com/whatsapp/wp.b:Lcom/whatsapp/VerifySms;
        //   263: invokevirtual   com/whatsapp/VerifySms.g:()V
        //   266: iload_2        
        //   267: ifeq            2344
        //   270: getstatic       com/whatsapp/pf.ERROR_UNSPECIFIED:Lcom/whatsapp/pf;
        //   273: astore          37
        //   275: aload_1        
        //   276: aload           37
        //   278: if_acmpne       390
        //   281: new             Ljava/lang/StringBuilder;
        //   284: dup            
        //   285: invokespecial   java/lang/StringBuilder.<init>:()V
        //   288: getstatic       com/whatsapp/wp.z:[Ljava/lang/String;
        //   291: bipush          21
        //   293: aaload         
        //   294: invokevirtual   java/lang/StringBuilder.append:(Ljava/lang/String;)Ljava/lang/StringBuilder;
        //   297: aload_0        
        //   298: getfield        com/whatsapp/wp.c:Ljava/lang/String;
        //   301: invokevirtual   java/lang/StringBuilder.append:(Ljava/lang/String;)Ljava/lang/StringBuilder;
        //   304: getstatic       com/whatsapp/wp.z:[Ljava/lang/String;
        //   307: bipush          48
        //   309: aaload         
        //   310: invokevirtual   java/lang/StringBuilder.append:(Ljava/lang/String;)Ljava/lang/StringBuilder;
        //   313: invokevirtual   java/lang/StringBuilder.toString:()Ljava/lang/String;
        //   316: invokestatic    com/whatsapp/util/Log.w:(Ljava/lang/String;)V
        //   319: iconst_3       
        //   320: invokestatic    com/whatsapp/VerifySms.j:(I)I
        //   323: pop            
        //   324: aload_0        
        //   325: getfield        com/whatsapp/wp.b:Lcom/whatsapp/VerifySms;
        //   328: invokestatic    com/whatsapp/VerifySms.k:(Lcom/whatsapp/VerifySms;)V
        //   331: aload_0        
        //   332: getfield        com/whatsapp/wp.b:Lcom/whatsapp/VerifySms;
        //   335: getstatic       com/whatsapp/wp.z:[Ljava/lang/String;
        //   338: bipush          44
        //   340: aaload         
        //   341: invokevirtual   com/whatsapp/VerifySms.c:(Ljava/lang/String;)V
        //   344: aload_0        
        //   345: getfield        com/whatsapp/wp.b:Lcom/whatsapp/VerifySms;
        //   348: invokestatic    com/whatsapp/VerifySms.d:(Lcom/whatsapp/VerifySms;)V
        //   351: aload_0        
        //   352: getfield        com/whatsapp/wp.b:Lcom/whatsapp/VerifySms;
        //   355: getfield        com/whatsapp/VerifySms.q:Z
        //   358: istore          154
        //   360: iload           154
        //   362: ifne            379
        //   365: aload_0        
        //   366: getfield        com/whatsapp/wp.b:Lcom/whatsapp/VerifySms;
        //   369: invokevirtual   com/whatsapp/VerifySms.isFinishing:()Z
        //   372: istore          155
        //   374: iload           155
        //   376: ifeq            2344
        //   379: aload_0        
        //   380: getfield        com/whatsapp/wp.b:Lcom/whatsapp/VerifySms;
        //   383: invokevirtual   com/whatsapp/VerifySms.g:()V
        //   386: iload_2        
        //   387: ifeq            2344
        //   390: getstatic       com/whatsapp/pf.ERROR_TOO_MANY:Lcom/whatsapp/pf;
        //   393: astore          38
        //   395: aload_1        
        //   396: aload           38
        //   398: if_acmpne       510
        //   401: new             Ljava/lang/StringBuilder;
        //   404: dup            
        //   405: invokespecial   java/lang/StringBuilder.<init>:()V
        //   408: getstatic       com/whatsapp/wp.z:[Ljava/lang/String;
        //   411: bipush          40
        //   413: aaload         
        //   414: invokevirtual   java/lang/StringBuilder.append:(Ljava/lang/String;)Ljava/lang/StringBuilder;
        //   417: aload_0        
        //   418: getfield        com/whatsapp/wp.c:Ljava/lang/String;
        //   421: invokevirtual   java/lang/StringBuilder.append:(Ljava/lang/String;)Ljava/lang/StringBuilder;
        //   424: getstatic       com/whatsapp/wp.z:[Ljava/lang/String;
        //   427: bipush          52
        //   429: aaload         
        //   430: invokevirtual   java/lang/StringBuilder.append:(Ljava/lang/String;)Ljava/lang/StringBuilder;
        //   433: invokevirtual   java/lang/StringBuilder.toString:()Ljava/lang/String;
        //   436: invokestatic    com/whatsapp/util/Log.w:(Ljava/lang/String;)V
        //   439: iconst_3       
        //   440: invokestatic    com/whatsapp/VerifySms.j:(I)I
        //   443: pop            
        //   444: aload_0        
        //   445: getfield        com/whatsapp/wp.b:Lcom/whatsapp/VerifySms;
        //   448: invokestatic    com/whatsapp/VerifySms.k:(Lcom/whatsapp/VerifySms;)V
        //   451: aload_0        
        //   452: getfield        com/whatsapp/wp.b:Lcom/whatsapp/VerifySms;
        //   455: getstatic       com/whatsapp/wp.z:[Ljava/lang/String;
        //   458: bipush          36
        //   460: aaload         
        //   461: invokevirtual   com/whatsapp/VerifySms.c:(Ljava/lang/String;)V
        //   464: aload_0        
        //   465: getfield        com/whatsapp/wp.b:Lcom/whatsapp/VerifySms;
        //   468: invokestatic    com/whatsapp/VerifySms.d:(Lcom/whatsapp/VerifySms;)V
        //   471: aload_0        
        //   472: getfield        com/whatsapp/wp.b:Lcom/whatsapp/VerifySms;
        //   475: getfield        com/whatsapp/VerifySms.q:Z
        //   478: istore          151
        //   480: iload           151
        //   482: ifne            499
        //   485: aload_0        
        //   486: getfield        com/whatsapp/wp.b:Lcom/whatsapp/VerifySms;
        //   489: invokevirtual   com/whatsapp/VerifySms.isFinishing:()Z
        //   492: istore          152
        //   494: iload           152
        //   496: ifeq            2344
        //   499: aload_0        
        //   500: getfield        com/whatsapp/wp.b:Lcom/whatsapp/VerifySms;
        //   503: invokevirtual   com/whatsapp/VerifySms.g:()V
        //   506: iload_2        
        //   507: ifeq            2344
        //   510: getstatic       com/whatsapp/pf.ERROR_TOO_MANY_ALL_METHODS:Lcom/whatsapp/pf;
        //   513: astore          39
        //   515: aload_1        
        //   516: aload           39
        //   518: if_acmpne       704
        //   521: new             Ljava/lang/StringBuilder;
        //   524: dup            
        //   525: invokespecial   java/lang/StringBuilder.<init>:()V
        //   528: getstatic       com/whatsapp/wp.z:[Ljava/lang/String;
        //   531: bipush          14
        //   533: aaload         
        //   534: invokevirtual   java/lang/StringBuilder.append:(Ljava/lang/String;)Ljava/lang/StringBuilder;
        //   537: aload_0        
        //   538: getfield        com/whatsapp/wp.c:Ljava/lang/String;
        //   541: invokevirtual   java/lang/StringBuilder.append:(Ljava/lang/String;)Ljava/lang/StringBuilder;
        //   544: getstatic       com/whatsapp/wp.z:[Ljava/lang/String;
        //   547: bipush          58
        //   549: aaload         
        //   550: invokevirtual   java/lang/StringBuilder.append:(Ljava/lang/String;)Ljava/lang/StringBuilder;
        //   553: invokevirtual   java/lang/StringBuilder.toString:()Ljava/lang/String;
        //   556: invokestatic    com/whatsapp/util/Log.w:(Ljava/lang/String;)V
        //   559: iconst_3       
        //   560: invokestatic    com/whatsapp/VerifySms.j:(I)I
        //   563: pop            
        //   564: aload_0        
        //   565: getfield        com/whatsapp/wp.b:Lcom/whatsapp/VerifySms;
        //   568: invokestatic    com/whatsapp/VerifySms.k:(Lcom/whatsapp/VerifySms;)V
        //   571: aload_0        
        //   572: getfield        com/whatsapp/wp.b:Lcom/whatsapp/VerifySms;
        //   575: getstatic       com/whatsapp/wp.z:[Ljava/lang/String;
        //   578: bipush          35
        //   580: aaload         
        //   581: invokevirtual   com/whatsapp/VerifySms.c:(Ljava/lang/String;)V
        //   584: iconst_1       
        //   585: invokestatic    com/whatsapp/VerifySms.b:(Z)Z
        //   588: pop            
        //   589: aload_0        
        //   590: getfield        com/whatsapp/wp.d:Lcom/whatsapp/ct;
        //   593: getfield        com/whatsapp/ct.g:Ljava/lang/String;
        //   596: astore          142
        //   598: aload           142
        //   600: ifnonnull       616
        //   603: aload_0        
        //   604: getfield        com/whatsapp/wp.b:Lcom/whatsapp/VerifySms;
        //   607: bipush          30
        //   609: invokevirtual   com/whatsapp/VerifySms.d:(I)V
        //   612: iload_2        
        //   613: ifeq            669
        //   616: aload_0        
        //   617: getfield        com/whatsapp/wp.b:Lcom/whatsapp/VerifySms;
        //   620: ldc2_w          1000
        //   623: aload_0        
        //   624: getfield        com/whatsapp/wp.d:Lcom/whatsapp/ct;
        //   627: getfield        com/whatsapp/ct.g:Ljava/lang/String;
        //   630: invokestatic    java/lang/Long.parseLong:(Ljava/lang/String;)J
        //   633: lmul           
        //   634: invokestatic    com/whatsapp/VerifySms.b:(Lcom/whatsapp/VerifySms;J)J
        //   637: pop2           
        //   638: getstatic       com/whatsapp/App.aq:Lcom/whatsapp/App;
        //   641: aload_0        
        //   642: getfield        com/whatsapp/wp.b:Lcom/whatsapp/VerifySms;
        //   645: invokestatic    com/whatsapp/VerifySms.p:(Lcom/whatsapp/VerifySms;)J
        //   648: invokevirtual   com/whatsapp/App.c:(J)V
        //   651: aload_0        
        //   652: getfield        com/whatsapp/wp.b:Lcom/whatsapp/VerifySms;
        //   655: iconst_1       
        //   656: invokestatic    com/whatsapp/VerifySms.a:(Lcom/whatsapp/VerifySms;Z)Z
        //   659: pop            
        //   660: aload_0        
        //   661: getfield        com/whatsapp/wp.b:Lcom/whatsapp/VerifySms;
        //   664: bipush          35
        //   666: invokevirtual   com/whatsapp/VerifySms.d:(I)V
        //   669: aload_0        
        //   670: getfield        com/whatsapp/wp.b:Lcom/whatsapp/VerifySms;
        //   673: getfield        com/whatsapp/VerifySms.q:Z
        //   676: ifne            693
        //   679: aload_0        
        //   680: getfield        com/whatsapp/wp.b:Lcom/whatsapp/VerifySms;
        //   683: invokevirtual   com/whatsapp/VerifySms.isFinishing:()Z
        //   686: istore          146
        //   688: iload           146
        //   690: ifeq            2344
        //   693: aload_0        
        //   694: getfield        com/whatsapp/wp.b:Lcom/whatsapp/VerifySms;
        //   697: invokevirtual   com/whatsapp/VerifySms.g:()V
        //   700: iload_2        
        //   701: ifeq            2344
        //   704: getstatic       com/whatsapp/pf.ERROR_CONNECTIVITY:Lcom/whatsapp/pf;
        //   707: astore          57
        //   709: aload_1        
        //   710: aload           57
        //   712: if_acmpne       786
        //   715: iconst_3       
        //   716: invokestatic    com/whatsapp/VerifySms.j:(I)I
        //   719: pop            
        //   720: aload_0        
        //   721: getfield        com/whatsapp/wp.b:Lcom/whatsapp/VerifySms;
        //   724: invokestatic    com/whatsapp/VerifySms.k:(Lcom/whatsapp/VerifySms;)V
        //   727: aload_0        
        //   728: getfield        com/whatsapp/wp.b:Lcom/whatsapp/VerifySms;
        //   731: getstatic       com/whatsapp/wp.z:[Ljava/lang/String;
        //   734: bipush          8
        //   736: aaload         
        //   737: invokevirtual   com/whatsapp/VerifySms.c:(Ljava/lang/String;)V
        //   740: aload_0        
        //   741: getfield        com/whatsapp/wp.b:Lcom/whatsapp/VerifySms;
        //   744: invokestatic    com/whatsapp/VerifySms.d:(Lcom/whatsapp/VerifySms;)V
        //   747: aload_0        
        //   748: getfield        com/whatsapp/wp.b:Lcom/whatsapp/VerifySms;
        //   751: getfield        com/whatsapp/VerifySms.q:Z
        //   754: istore          138
        //   756: iload           138
        //   758: ifne            775
        //   761: aload_0        
        //   762: getfield        com/whatsapp/wp.b:Lcom/whatsapp/VerifySms;
        //   765: invokevirtual   com/whatsapp/VerifySms.isFinishing:()Z
        //   768: istore          139
        //   770: iload           139
        //   772: ifeq            2344
        //   775: aload_0        
        //   776: getfield        com/whatsapp/wp.b:Lcom/whatsapp/VerifySms;
        //   779: invokevirtual   com/whatsapp/VerifySms.g:()V
        //   782: iload_2        
        //   783: ifeq            2344
        //   786: getstatic       com/whatsapp/pf.ERROR_BAD_PARAMETER:Lcom/whatsapp/pf;
        //   789: astore          58
        //   791: aload_1        
        //   792: aload           58
        //   794: if_acmpne       915
        //   797: new             Ljava/lang/StringBuilder;
        //   800: dup            
        //   801: invokespecial   java/lang/StringBuilder.<init>:()V
        //   804: getstatic       com/whatsapp/wp.z:[Ljava/lang/String;
        //   807: bipush          28
        //   809: aaload         
        //   810: invokevirtual   java/lang/StringBuilder.append:(Ljava/lang/String;)Ljava/lang/StringBuilder;
        //   813: aload_0        
        //   814: getfield        com/whatsapp/wp.c:Ljava/lang/String;
        //   817: invokevirtual   java/lang/StringBuilder.append:(Ljava/lang/String;)Ljava/lang/StringBuilder;
        //   820: getstatic       com/whatsapp/wp.z:[Ljava/lang/String;
        //   823: bipush          59
        //   825: aaload         
        //   826: invokevirtual   java/lang/StringBuilder.append:(Ljava/lang/String;)Ljava/lang/StringBuilder;
        //   829: invokevirtual   java/lang/StringBuilder.toString:()Ljava/lang/String;
        //   832: invokestatic    com/whatsapp/util/Log.e:(Ljava/lang/String;)V
        //   835: getstatic       com/whatsapp/wp.z:[Ljava/lang/String;
        //   838: bipush          41
        //   840: aaload         
        //   841: invokestatic    com/whatsapp/App.F:(Ljava/lang/String;)V
        //   844: iconst_3       
        //   845: invokestatic    com/whatsapp/VerifySms.j:(I)I
        //   848: pop            
        //   849: aload_0        
        //   850: getfield        com/whatsapp/wp.b:Lcom/whatsapp/VerifySms;
        //   853: invokestatic    com/whatsapp/VerifySms.k:(Lcom/whatsapp/VerifySms;)V
        //   856: aload_0        
        //   857: getfield        com/whatsapp/wp.b:Lcom/whatsapp/VerifySms;
        //   860: getstatic       com/whatsapp/wp.z:[Ljava/lang/String;
        //   863: bipush          15
        //   865: aaload         
        //   866: invokevirtual   com/whatsapp/VerifySms.c:(Ljava/lang/String;)V
        //   869: aload_0        
        //   870: getfield        com/whatsapp/wp.b:Lcom/whatsapp/VerifySms;
        //   873: invokestatic    com/whatsapp/VerifySms.d:(Lcom/whatsapp/VerifySms;)V
        //   876: aload_0        
        //   877: getfield        com/whatsapp/wp.b:Lcom/whatsapp/VerifySms;
        //   880: getfield        com/whatsapp/VerifySms.q:Z
        //   883: istore          135
        //   885: iload           135
        //   887: ifne            904
        //   890: aload_0        
        //   891: getfield        com/whatsapp/wp.b:Lcom/whatsapp/VerifySms;
        //   894: invokevirtual   com/whatsapp/VerifySms.isFinishing:()Z
        //   897: istore          136
        //   899: iload           136
        //   901: ifeq            2344
        //   904: aload_0        
        //   905: getfield        com/whatsapp/wp.b:Lcom/whatsapp/VerifySms;
        //   908: invokevirtual   com/whatsapp/VerifySms.g:()V
        //   911: iload_2        
        //   912: ifeq            2344
        //   915: getstatic       com/whatsapp/pf.ERROR_MISSING_PARAMETER:Lcom/whatsapp/pf;
        //   918: astore          59
        //   920: aload_1        
        //   921: aload           59
        //   923: if_acmpne       1044
        //   926: new             Ljava/lang/StringBuilder;
        //   929: dup            
        //   930: invokespecial   java/lang/StringBuilder.<init>:()V
        //   933: getstatic       com/whatsapp/wp.z:[Ljava/lang/String;
        //   936: bipush          49
        //   938: aaload         
        //   939: invokevirtual   java/lang/StringBuilder.append:(Ljava/lang/String;)Ljava/lang/StringBuilder;
        //   942: aload_0        
        //   943: getfield        com/whatsapp/wp.c:Ljava/lang/String;
        //   946: invokevirtual   java/lang/StringBuilder.append:(Ljava/lang/String;)Ljava/lang/StringBuilder;
        //   949: getstatic       com/whatsapp/wp.z:[Ljava/lang/String;
        //   952: bipush          50
        //   954: aaload         
        //   955: invokevirtual   java/lang/StringBuilder.append:(Ljava/lang/String;)Ljava/lang/StringBuilder;
        //   958: invokevirtual   java/lang/StringBuilder.toString:()Ljava/lang/String;
        //   961: invokestatic    com/whatsapp/util/Log.e:(Ljava/lang/String;)V
        //   964: getstatic       com/whatsapp/wp.z:[Ljava/lang/String;
        //   967: bipush          61
        //   969: aaload         
        //   970: invokestatic    com/whatsapp/App.F:(Ljava/lang/String;)V
        //   973: iconst_3       
        //   974: invokestatic    com/whatsapp/VerifySms.j:(I)I
        //   977: pop            
        //   978: aload_0        
        //   979: getfield        com/whatsapp/wp.b:Lcom/whatsapp/VerifySms;
        //   982: invokestatic    com/whatsapp/VerifySms.k:(Lcom/whatsapp/VerifySms;)V
        //   985: aload_0        
        //   986: getfield        com/whatsapp/wp.b:Lcom/whatsapp/VerifySms;
        //   989: getstatic       com/whatsapp/wp.z:[Ljava/lang/String;
        //   992: bipush          65
        //   994: aaload         
        //   995: invokevirtual   com/whatsapp/VerifySms.c:(Ljava/lang/String;)V
        //   998: aload_0        
        //   999: getfield        com/whatsapp/wp.b:Lcom/whatsapp/VerifySms;
        //  1002: invokestatic    com/whatsapp/VerifySms.d:(Lcom/whatsapp/VerifySms;)V
        //  1005: aload_0        
        //  1006: getfield        com/whatsapp/wp.b:Lcom/whatsapp/VerifySms;
        //  1009: getfield        com/whatsapp/VerifySms.q:Z
        //  1012: istore          132
        //  1014: iload           132
        //  1016: ifne            1033
        //  1019: aload_0        
        //  1020: getfield        com/whatsapp/wp.b:Lcom/whatsapp/VerifySms;
        //  1023: invokevirtual   com/whatsapp/VerifySms.isFinishing:()Z
        //  1026: istore          133
        //  1028: iload           133
        //  1030: ifeq            2344
        //  1033: aload_0        
        //  1034: getfield        com/whatsapp/wp.b:Lcom/whatsapp/VerifySms;
        //  1037: invokevirtual   com/whatsapp/VerifySms.g:()V
        //  1040: iload_2        
        //  1041: ifeq            2344
        //  1044: getstatic       com/whatsapp/pf.ERROR_OLD_VERSION:Lcom/whatsapp/pf;
        //  1047: astore          60
        //  1049: aload_1        
        //  1050: aload           60
        //  1052: if_acmpne       1123
        //  1055: new             Ljava/lang/StringBuilder;
        //  1058: dup            
        //  1059: invokespecial   java/lang/StringBuilder.<init>:()V
        //  1062: getstatic       com/whatsapp/wp.z:[Ljava/lang/String;
        //  1065: bipush          47
        //  1067: aaload         
        //  1068: invokevirtual   java/lang/StringBuilder.append:(Ljava/lang/String;)Ljava/lang/StringBuilder;
        //  1071: aload_0        
        //  1072: getfield        com/whatsapp/wp.c:Ljava/lang/String;
        //  1075: invokevirtual   java/lang/StringBuilder.append:(Ljava/lang/String;)Ljava/lang/StringBuilder;
        //  1078: getstatic       com/whatsapp/wp.z:[Ljava/lang/String;
        //  1081: bipush          11
        //  1083: aaload         
        //  1084: invokevirtual   java/lang/StringBuilder.append:(Ljava/lang/String;)Ljava/lang/StringBuilder;
        //  1087: invokevirtual   java/lang/StringBuilder.toString:()Ljava/lang/String;
        //  1090: invokestatic    com/whatsapp/util/Log.w:(Ljava/lang/String;)V
        //  1093: iconst_1       
        //  1094: putstatic       com/whatsapp/App.aA:Z
        //  1097: bipush          8
        //  1099: invokestatic    com/whatsapp/VerifySms.j:(I)I
        //  1102: pop            
        //  1103: aload_0        
        //  1104: getfield        com/whatsapp/wp.b:Lcom/whatsapp/VerifySms;
        //  1107: invokestatic    com/whatsapp/VerifySms.k:(Lcom/whatsapp/VerifySms;)V
        //  1110: aload_0        
        //  1111: getfield        com/whatsapp/wp.b:Lcom/whatsapp/VerifySms;
        //  1114: bipush          23
        //  1116: invokevirtual   com/whatsapp/VerifySms.e:(I)V
        //  1119: iload_2        
        //  1120: ifeq            2344
        //  1123: getstatic       com/whatsapp/pf.ERROR_TOO_RECENT:Lcom/whatsapp/pf;
        //  1126: astore          61
        //  1128: aload_1        
        //  1129: aload           61
        //  1131: if_acmpne       1268
        //  1134: new             Ljava/lang/StringBuilder;
        //  1137: dup            
        //  1138: invokespecial   java/lang/StringBuilder.<init>:()V
        //  1141: getstatic       com/whatsapp/wp.z:[Ljava/lang/String;
        //  1144: bipush          26
        //  1146: aaload         
        //  1147: invokevirtual   java/lang/StringBuilder.append:(Ljava/lang/String;)Ljava/lang/StringBuilder;
        //  1150: aload_0        
        //  1151: getfield        com/whatsapp/wp.c:Ljava/lang/String;
        //  1154: invokevirtual   java/lang/StringBuilder.append:(Ljava/lang/String;)Ljava/lang/StringBuilder;
        //  1157: getstatic       com/whatsapp/wp.z:[Ljava/lang/String;
        //  1160: bipush          55
        //  1162: aaload         
        //  1163: invokevirtual   java/lang/StringBuilder.append:(Ljava/lang/String;)Ljava/lang/StringBuilder;
        //  1166: astore          123
        //  1168: aload_0        
        //  1169: getfield        com/whatsapp/wp.d:Lcom/whatsapp/ct;
        //  1172: astore          124
        //  1174: aload           124
        //  1176: ifnull          2613
        //  1179: aload_0        
        //  1180: getfield        com/whatsapp/wp.d:Lcom/whatsapp/ct;
        //  1183: getfield        com/whatsapp/ct.g:Ljava/lang/String;
        //  1186: astore          125
        //  1188: aload           123
        //  1190: aload           125
        //  1192: invokevirtual   java/lang/StringBuilder.append:(Ljava/lang/String;)Ljava/lang/StringBuilder;
        //  1195: invokevirtual   java/lang/StringBuilder.toString:()Ljava/lang/String;
        //  1198: invokestatic    com/whatsapp/util/Log.w:(Ljava/lang/String;)V
        //  1201: iconst_3       
        //  1202: invokestatic    com/whatsapp/VerifySms.j:(I)I
        //  1205: pop            
        //  1206: aload_0        
        //  1207: getfield        com/whatsapp/wp.b:Lcom/whatsapp/VerifySms;
        //  1210: invokestatic    com/whatsapp/VerifySms.k:(Lcom/whatsapp/VerifySms;)V
        //  1213: aload_0        
        //  1214: getfield        com/whatsapp/wp.b:Lcom/whatsapp/VerifySms;
        //  1217: getstatic       com/whatsapp/wp.z:[Ljava/lang/String;
        //  1220: bipush          32
        //  1222: aaload         
        //  1223: invokevirtual   com/whatsapp/VerifySms.c:(Ljava/lang/String;)V
        //  1226: aload_0        
        //  1227: getfield        com/whatsapp/wp.b:Lcom/whatsapp/VerifySms;
        //  1230: invokestatic    com/whatsapp/VerifySms.d:(Lcom/whatsapp/VerifySms;)V
        //  1233: aload_0        
        //  1234: getfield        com/whatsapp/wp.b:Lcom/whatsapp/VerifySms;
        //  1237: getfield        com/whatsapp/VerifySms.q:Z
        //  1240: ifne            1257
        //  1243: aload_0        
        //  1244: getfield        com/whatsapp/wp.b:Lcom/whatsapp/VerifySms;
        //  1247: invokevirtual   com/whatsapp/VerifySms.isFinishing:()Z
        //  1250: istore          129
        //  1252: iload           129
        //  1254: ifeq            2344
        //  1257: aload_0        
        //  1258: getfield        com/whatsapp/wp.b:Lcom/whatsapp/VerifySms;
        //  1261: invokevirtual   com/whatsapp/VerifySms.g:()V
        //  1264: iload_2        
        //  1265: ifeq            2344
        //  1268: getstatic       com/whatsapp/pf.ERROR_BLOCKED:Lcom/whatsapp/pf;
        //  1271: astore          77
        //  1273: aload_1        
        //  1274: aload           77
        //  1276: if_acmpne       1389
        //  1279: new             Ljava/lang/StringBuilder;
        //  1282: dup            
        //  1283: invokespecial   java/lang/StringBuilder.<init>:()V
        //  1286: getstatic       com/whatsapp/wp.z:[Ljava/lang/String;
        //  1289: bipush          27
        //  1291: aaload         
        //  1292: invokevirtual   java/lang/StringBuilder.append:(Ljava/lang/String;)Ljava/lang/StringBuilder;
        //  1295: aload_0        
        //  1296: getfield        com/whatsapp/wp.c:Ljava/lang/String;
        //  1299: invokevirtual   java/lang/StringBuilder.append:(Ljava/lang/String;)Ljava/lang/StringBuilder;
        //  1302: getstatic       com/whatsapp/wp.z:[Ljava/lang/String;
        //  1305: bipush          45
        //  1307: aaload         
        //  1308: invokevirtual   java/lang/StringBuilder.append:(Ljava/lang/String;)Ljava/lang/StringBuilder;
        //  1311: invokevirtual   java/lang/StringBuilder.toString:()Ljava/lang/String;
        //  1314: invokestatic    com/whatsapp/util/Log.e:(Ljava/lang/String;)V
        //  1317: bipush          12
        //  1319: invokestatic    com/whatsapp/VerifySms.j:(I)I
        //  1322: pop            
        //  1323: aload_0        
        //  1324: getfield        com/whatsapp/wp.b:Lcom/whatsapp/VerifySms;
        //  1327: invokestatic    com/whatsapp/VerifySms.k:(Lcom/whatsapp/VerifySms;)V
        //  1330: aload_0        
        //  1331: getfield        com/whatsapp/wp.b:Lcom/whatsapp/VerifySms;
        //  1334: getstatic       com/whatsapp/wp.z:[Ljava/lang/String;
        //  1337: bipush          18
        //  1339: aaload         
        //  1340: invokevirtual   com/whatsapp/VerifySms.c:(Ljava/lang/String;)V
        //  1343: aload_0        
        //  1344: getfield        com/whatsapp/wp.b:Lcom/whatsapp/VerifySms;
        //  1347: invokestatic    com/whatsapp/VerifySms.w:(Lcom/whatsapp/VerifySms;)V
        //  1350: aload_0        
        //  1351: getfield        com/whatsapp/wp.b:Lcom/whatsapp/VerifySms;
        //  1354: getfield        com/whatsapp/VerifySms.q:Z
        //  1357: istore          121
        //  1359: iload           121
        //  1361: ifne            1378
        //  1364: aload_0        
        //  1365: getfield        com/whatsapp/wp.b:Lcom/whatsapp/VerifySms;
        //  1368: invokevirtual   com/whatsapp/VerifySms.isFinishing:()Z
        //  1371: istore          122
        //  1373: iload           122
        //  1375: ifeq            2344
        //  1378: aload_0        
        //  1379: getfield        com/whatsapp/wp.b:Lcom/whatsapp/VerifySms;
        //  1382: invokevirtual   com/whatsapp/VerifySms.g:()V
        //  1385: iload_2        
        //  1386: ifeq            2344
        //  1389: getstatic       com/whatsapp/pf.ERROR_NEXT_METHOD:Lcom/whatsapp/pf;
        //  1392: astore          78
        //  1394: aload_1        
        //  1395: aload           78
        //  1397: if_acmpne       1509
        //  1400: new             Ljava/lang/StringBuilder;
        //  1403: dup            
        //  1404: invokespecial   java/lang/StringBuilder.<init>:()V
        //  1407: getstatic       com/whatsapp/wp.z:[Ljava/lang/String;
        //  1410: bipush          31
        //  1412: aaload         
        //  1413: invokevirtual   java/lang/StringBuilder.append:(Ljava/lang/String;)Ljava/lang/StringBuilder;
        //  1416: aload_0        
        //  1417: getfield        com/whatsapp/wp.c:Ljava/lang/String;
        //  1420: invokevirtual   java/lang/StringBuilder.append:(Ljava/lang/String;)Ljava/lang/StringBuilder;
        //  1423: getstatic       com/whatsapp/wp.z:[Ljava/lang/String;
        //  1426: bipush          42
        //  1428: aaload         
        //  1429: invokevirtual   java/lang/StringBuilder.append:(Ljava/lang/String;)Ljava/lang/StringBuilder;
        //  1432: invokevirtual   java/lang/StringBuilder.toString:()Ljava/lang/String;
        //  1435: invokestatic    com/whatsapp/util/Log.w:(Ljava/lang/String;)V
        //  1438: iconst_3       
        //  1439: invokestatic    com/whatsapp/VerifySms.j:(I)I
        //  1442: pop            
        //  1443: aload_0        
        //  1444: getfield        com/whatsapp/wp.b:Lcom/whatsapp/VerifySms;
        //  1447: invokestatic    com/whatsapp/VerifySms.k:(Lcom/whatsapp/VerifySms;)V
        //  1450: aload_0        
        //  1451: getfield        com/whatsapp/wp.b:Lcom/whatsapp/VerifySms;
        //  1454: getstatic       com/whatsapp/wp.z:[Ljava/lang/String;
        //  1457: bipush          34
        //  1459: aaload         
        //  1460: invokevirtual   com/whatsapp/VerifySms.c:(Ljava/lang/String;)V
        //  1463: aload_0        
        //  1464: getfield        com/whatsapp/wp.b:Lcom/whatsapp/VerifySms;
        //  1467: invokestatic    com/whatsapp/VerifySms.d:(Lcom/whatsapp/VerifySms;)V
        //  1470: aload_0        
        //  1471: getfield        com/whatsapp/wp.b:Lcom/whatsapp/VerifySms;
        //  1474: getfield        com/whatsapp/VerifySms.q:Z
        //  1477: istore          118
        //  1479: iload           118
        //  1481: ifne            1498
        //  1484: aload_0        
        //  1485: getfield        com/whatsapp/wp.b:Lcom/whatsapp/VerifySms;
        //  1488: invokevirtual   com/whatsapp/VerifySms.isFinishing:()Z
        //  1491: istore          119
        //  1493: iload           119
        //  1495: ifeq            2344
        //  1498: aload_0        
        //  1499: getfield        com/whatsapp/wp.b:Lcom/whatsapp/VerifySms;
        //  1502: invokevirtual   com/whatsapp/VerifySms.g:()V
        //  1505: iload_2        
        //  1506: ifeq            2344
        //  1509: getstatic       com/whatsapp/pf.ERROR_NO_ROUTES:Lcom/whatsapp/pf;
        //  1512: astore          79
        //  1514: aload_1        
        //  1515: aload           79
        //  1517: if_acmpne       1629
        //  1520: new             Ljava/lang/StringBuilder;
        //  1523: dup            
        //  1524: invokespecial   java/lang/StringBuilder.<init>:()V
        //  1527: getstatic       com/whatsapp/wp.z:[Ljava/lang/String;
        //  1530: bipush          37
        //  1532: aaload         
        //  1533: invokevirtual   java/lang/StringBuilder.append:(Ljava/lang/String;)Ljava/lang/StringBuilder;
        //  1536: aload_0        
        //  1537: getfield        com/whatsapp/wp.c:Ljava/lang/String;
        //  1540: invokevirtual   java/lang/StringBuilder.append:(Ljava/lang/String;)Ljava/lang/StringBuilder;
        //  1543: getstatic       com/whatsapp/wp.z:[Ljava/lang/String;
        //  1546: bipush          53
        //  1548: aaload         
        //  1549: invokevirtual   java/lang/StringBuilder.append:(Ljava/lang/String;)Ljava/lang/StringBuilder;
        //  1552: invokevirtual   java/lang/StringBuilder.toString:()Ljava/lang/String;
        //  1555: invokestatic    com/whatsapp/util/Log.w:(Ljava/lang/String;)V
        //  1558: iconst_3       
        //  1559: invokestatic    com/whatsapp/VerifySms.j:(I)I
        //  1562: pop            
        //  1563: aload_0        
        //  1564: getfield        com/whatsapp/wp.b:Lcom/whatsapp/VerifySms;
        //  1567: invokestatic    com/whatsapp/VerifySms.k:(Lcom/whatsapp/VerifySms;)V
        //  1570: aload_0        
        //  1571: getfield        com/whatsapp/wp.b:Lcom/whatsapp/VerifySms;
        //  1574: getstatic       com/whatsapp/wp.z:[Ljava/lang/String;
        //  1577: bipush          57
        //  1579: aaload         
        //  1580: invokevirtual   com/whatsapp/VerifySms.c:(Ljava/lang/String;)V
        //  1583: aload_0        
        //  1584: getfield        com/whatsapp/wp.b:Lcom/whatsapp/VerifySms;
        //  1587: invokestatic    com/whatsapp/VerifySms.d:(Lcom/whatsapp/VerifySms;)V
        //  1590: aload_0        
        //  1591: getfield        com/whatsapp/wp.b:Lcom/whatsapp/VerifySms;
        //  1594: getfield        com/whatsapp/VerifySms.q:Z
        //  1597: istore          115
        //  1599: iload           115
        //  1601: ifne            1618
        //  1604: aload_0        
        //  1605: getfield        com/whatsapp/wp.b:Lcom/whatsapp/VerifySms;
        //  1608: invokevirtual   com/whatsapp/VerifySms.isFinishing:()Z
        //  1611: istore          116
        //  1613: iload           116
        //  1615: ifeq            2344
        //  1618: aload_0        
        //  1619: getfield        com/whatsapp/wp.b:Lcom/whatsapp/VerifySms;
        //  1622: invokevirtual   com/whatsapp/VerifySms.g:()V
        //  1625: iload_2        
        //  1626: ifeq            2344
        //  1629: getstatic       com/whatsapp/pf.ERROR_TOO_MANY_GUESSES:Lcom/whatsapp/pf;
        //  1632: astore          80
        //  1634: aload_1        
        //  1635: aload           80
        //  1637: if_acmpne       1825
        //  1640: new             Ljava/lang/StringBuilder;
        //  1643: dup            
        //  1644: invokespecial   java/lang/StringBuilder.<init>:()V
        //  1647: getstatic       com/whatsapp/wp.z:[Ljava/lang/String;
        //  1650: bipush          30
        //  1652: aaload         
        //  1653: invokevirtual   java/lang/StringBuilder.append:(Ljava/lang/String;)Ljava/lang/StringBuilder;
        //  1656: aload_0        
        //  1657: getfield        com/whatsapp/wp.c:Ljava/lang/String;
        //  1660: invokevirtual   java/lang/StringBuilder.append:(Ljava/lang/String;)Ljava/lang/StringBuilder;
        //  1663: getstatic       com/whatsapp/wp.z:[Ljava/lang/String;
        //  1666: bipush          22
        //  1668: aaload         
        //  1669: invokevirtual   java/lang/StringBuilder.append:(Ljava/lang/String;)Ljava/lang/StringBuilder;
        //  1672: invokevirtual   java/lang/StringBuilder.toString:()Ljava/lang/String;
        //  1675: invokestatic    com/whatsapp/util/Log.w:(Ljava/lang/String;)V
        //  1678: iconst_3       
        //  1679: invokestatic    com/whatsapp/VerifySms.j:(I)I
        //  1682: pop            
        //  1683: aload_0        
        //  1684: getfield        com/whatsapp/wp.b:Lcom/whatsapp/VerifySms;
        //  1687: invokestatic    com/whatsapp/VerifySms.k:(Lcom/whatsapp/VerifySms;)V
        //  1690: aload_0        
        //  1691: getfield        com/whatsapp/wp.b:Lcom/whatsapp/VerifySms;
        //  1694: getstatic       com/whatsapp/wp.z:[Ljava/lang/String;
        //  1697: bipush          9
        //  1699: aaload         
        //  1700: invokevirtual   com/whatsapp/VerifySms.c:(Ljava/lang/String;)V
        //  1703: aload_0        
        //  1704: getfield        com/whatsapp/wp.b:Lcom/whatsapp/VerifySms;
        //  1707: invokestatic    com/whatsapp/VerifySms.d:(Lcom/whatsapp/VerifySms;)V
        //  1710: aload_0        
        //  1711: getfield        com/whatsapp/wp.d:Lcom/whatsapp/ct;
        //  1714: getfield        com/whatsapp/ct.g:Ljava/lang/String;
        //  1717: astore          106
        //  1719: aload           106
        //  1721: ifnonnull       1737
        //  1724: aload_0        
        //  1725: getfield        com/whatsapp/wp.b:Lcom/whatsapp/VerifySms;
        //  1728: bipush          31
        //  1730: invokevirtual   com/whatsapp/VerifySms.d:(I)V
        //  1733: iload_2        
        //  1734: ifeq            1790
        //  1737: aload_0        
        //  1738: getfield        com/whatsapp/wp.b:Lcom/whatsapp/VerifySms;
        //  1741: ldc2_w          1000
        //  1744: aload_0        
        //  1745: getfield        com/whatsapp/wp.d:Lcom/whatsapp/ct;
        //  1748: getfield        com/whatsapp/ct.g:Ljava/lang/String;
        //  1751: invokestatic    java/lang/Long.parseLong:(Ljava/lang/String;)J
        //  1754: lmul           
        //  1755: invokestatic    com/whatsapp/VerifySms.b:(Lcom/whatsapp/VerifySms;J)J
        //  1758: pop2           
        //  1759: getstatic       com/whatsapp/App.aq:Lcom/whatsapp/App;
        //  1762: aload_0        
        //  1763: getfield        com/whatsapp/wp.b:Lcom/whatsapp/VerifySms;
        //  1766: invokestatic    com/whatsapp/VerifySms.p:(Lcom/whatsapp/VerifySms;)J
        //  1769: invokevirtual   com/whatsapp/App.c:(J)V
        //  1772: aload_0        
        //  1773: getfield        com/whatsapp/wp.b:Lcom/whatsapp/VerifySms;
        //  1776: iconst_1       
        //  1777: invokestatic    com/whatsapp/VerifySms.a:(Lcom/whatsapp/VerifySms;Z)Z
        //  1780: pop            
        //  1781: aload_0        
        //  1782: getfield        com/whatsapp/wp.b:Lcom/whatsapp/VerifySms;
        //  1785: bipush          36
        //  1787: invokevirtual   com/whatsapp/VerifySms.d:(I)V
        //  1790: aload_0        
        //  1791: getfield        com/whatsapp/wp.b:Lcom/whatsapp/VerifySms;
        //  1794: getfield        com/whatsapp/VerifySms.q:Z
        //  1797: ifne            1814
        //  1800: aload_0        
        //  1801: getfield        com/whatsapp/wp.b:Lcom/whatsapp/VerifySms;
        //  1804: invokevirtual   com/whatsapp/VerifySms.isFinishing:()Z
        //  1807: istore          110
        //  1809: iload           110
        //  1811: ifeq            2344
        //  1814: aload_0        
        //  1815: getfield        com/whatsapp/wp.b:Lcom/whatsapp/VerifySms;
        //  1818: invokevirtual   com/whatsapp/VerifySms.g:()V
        //  1821: iload_2        
        //  1822: ifeq            2344
        //  1825: getstatic       com/whatsapp/pf.ERROR_PROVIDER_TIMEOUT:Lcom/whatsapp/pf;
        //  1828: astore          93
        //  1830: aload_1        
        //  1831: aload           93
        //  1833: if_acmpne       1945
        //  1836: new             Ljava/lang/StringBuilder;
        //  1839: dup            
        //  1840: invokespecial   java/lang/StringBuilder.<init>:()V
        //  1843: getstatic       com/whatsapp/wp.z:[Ljava/lang/String;
        //  1846: bipush          43
        //  1848: aaload         
        //  1849: invokevirtual   java/lang/StringBuilder.append:(Ljava/lang/String;)Ljava/lang/StringBuilder;
        //  1852: aload_0        
        //  1853: getfield        com/whatsapp/wp.c:Ljava/lang/String;
        //  1856: invokevirtual   java/lang/StringBuilder.append:(Ljava/lang/String;)Ljava/lang/StringBuilder;
        //  1859: getstatic       com/whatsapp/wp.z:[Ljava/lang/String;
        //  1862: bipush          16
        //  1864: aaload         
        //  1865: invokevirtual   java/lang/StringBuilder.append:(Ljava/lang/String;)Ljava/lang/StringBuilder;
        //  1868: invokevirtual   java/lang/StringBuilder.toString:()Ljava/lang/String;
        //  1871: invokestatic    com/whatsapp/util/Log.e:(Ljava/lang/String;)V
        //  1874: iconst_3       
        //  1875: invokestatic    com/whatsapp/VerifySms.j:(I)I
        //  1878: pop            
        //  1879: aload_0        
        //  1880: getfield        com/whatsapp/wp.b:Lcom/whatsapp/VerifySms;
        //  1883: invokestatic    com/whatsapp/VerifySms.k:(Lcom/whatsapp/VerifySms;)V
        //  1886: aload_0        
        //  1887: getfield        com/whatsapp/wp.b:Lcom/whatsapp/VerifySms;
        //  1890: getstatic       com/whatsapp/wp.z:[Ljava/lang/String;
        //  1893: bipush          38
        //  1895: aaload         
        //  1896: invokevirtual   com/whatsapp/VerifySms.c:(Ljava/lang/String;)V
        //  1899: aload_0        
        //  1900: getfield        com/whatsapp/wp.b:Lcom/whatsapp/VerifySms;
        //  1903: invokestatic    com/whatsapp/VerifySms.d:(Lcom/whatsapp/VerifySms;)V
        //  1906: aload_0        
        //  1907: getfield        com/whatsapp/wp.b:Lcom/whatsapp/VerifySms;
        //  1910: getfield        com/whatsapp/VerifySms.q:Z
        //  1913: istore          103
        //  1915: iload           103
        //  1917: ifne            1934
        //  1920: aload_0        
        //  1921: getfield        com/whatsapp/wp.b:Lcom/whatsapp/VerifySms;
        //  1924: invokevirtual   com/whatsapp/VerifySms.isFinishing:()Z
        //  1927: istore          104
        //  1929: iload           104
        //  1931: ifeq            2344
        //  1934: aload_0        
        //  1935: getfield        com/whatsapp/wp.b:Lcom/whatsapp/VerifySms;
        //  1938: invokevirtual   com/whatsapp/VerifySms.g:()V
        //  1941: iload_2        
        //  1942: ifeq            2344
        //  1945: getstatic       com/whatsapp/pf.ERROR_PROVIDER_UNROUTABLE:Lcom/whatsapp/pf;
        //  1948: astore          94
        //  1950: aload_1        
        //  1951: aload           94
        //  1953: if_acmpne       2065
        //  1956: new             Ljava/lang/StringBuilder;
        //  1959: dup            
        //  1960: invokespecial   java/lang/StringBuilder.<init>:()V
        //  1963: getstatic       com/whatsapp/wp.z:[Ljava/lang/String;
        //  1966: bipush          39
        //  1968: aaload         
        //  1969: invokevirtual   java/lang/StringBuilder.append:(Ljava/lang/String;)Ljava/lang/StringBuilder;
        //  1972: aload_0        
        //  1973: getfield        com/whatsapp/wp.c:Ljava/lang/String;
        //  1976: invokevirtual   java/lang/StringBuilder.append:(Ljava/lang/String;)Ljava/lang/StringBuilder;
        //  1979: getstatic       com/whatsapp/wp.z:[Ljava/lang/String;
        //  1982: bipush          62
        //  1984: aaload         
        //  1985: invokevirtual   java/lang/StringBuilder.append:(Ljava/lang/String;)Ljava/lang/StringBuilder;
        //  1988: invokevirtual   java/lang/StringBuilder.toString:()Ljava/lang/String;
        //  1991: invokestatic    com/whatsapp/util/Log.e:(Ljava/lang/String;)V
        //  1994: iconst_3       
        //  1995: invokestatic    com/whatsapp/VerifySms.j:(I)I
        //  1998: pop            
        //  1999: aload_0        
        //  2000: getfield        com/whatsapp/wp.b:Lcom/whatsapp/VerifySms;
        //  2003: invokestatic    com/whatsapp/VerifySms.k:(Lcom/whatsapp/VerifySms;)V
        //  2006: aload_0        
        //  2007: getfield        com/whatsapp/wp.b:Lcom/whatsapp/VerifySms;
        //  2010: getstatic       com/whatsapp/wp.z:[Ljava/lang/String;
        //  2013: bipush          60
        //  2015: aaload         
        //  2016: invokevirtual   com/whatsapp/VerifySms.c:(Ljava/lang/String;)V
        //  2019: aload_0        
        //  2020: getfield        com/whatsapp/wp.b:Lcom/whatsapp/VerifySms;
        //  2023: invokestatic    com/whatsapp/VerifySms.d:(Lcom/whatsapp/VerifySms;)V
        //  2026: aload_0        
        //  2027: getfield        com/whatsapp/wp.b:Lcom/whatsapp/VerifySms;
        //  2030: getfield        com/whatsapp/VerifySms.q:Z
        //  2033: istore          100
        //  2035: iload           100
        //  2037: ifne            2054
        //  2040: aload_0        
        //  2041: getfield        com/whatsapp/wp.b:Lcom/whatsapp/VerifySms;
        //  2044: invokevirtual   com/whatsapp/VerifySms.isFinishing:()Z
        //  2047: istore          101
        //  2049: iload           101
        //  2051: ifeq            2344
        //  2054: aload_0        
        //  2055: getfield        com/whatsapp/wp.b:Lcom/whatsapp/VerifySms;
        //  2058: invokevirtual   com/whatsapp/VerifySms.g:()V
        //  2061: iload_2        
        //  2062: ifeq            2344
        //  2065: getstatic       com/whatsapp/pf.ERROR_BAD_TOKEN:Lcom/whatsapp/pf;
        //  2068: astore          95
        //  2070: aload_1        
        //  2071: aload           95
        //  2073: if_acmpne       2344
        //  2076: new             Ljava/lang/StringBuilder;
        //  2079: dup            
        //  2080: invokespecial   java/lang/StringBuilder.<init>:()V
        //  2083: getstatic       com/whatsapp/wp.z:[Ljava/lang/String;
        //  2086: bipush          23
        //  2088: aaload         
        //  2089: invokevirtual   java/lang/StringBuilder.append:(Ljava/lang/String;)Ljava/lang/StringBuilder;
        //  2092: aload_0        
        //  2093: getfield        com/whatsapp/wp.c:Ljava/lang/String;
        //  2096: invokevirtual   java/lang/StringBuilder.append:(Ljava/lang/String;)Ljava/lang/StringBuilder;
        //  2099: getstatic       com/whatsapp/wp.z:[Ljava/lang/String;
        //  2102: bipush          17
        //  2104: aaload         
        //  2105: invokevirtual   java/lang/StringBuilder.append:(Ljava/lang/String;)Ljava/lang/StringBuilder;
        //  2108: invokevirtual   java/lang/StringBuilder.toString:()Ljava/lang/String;
        //  2111: invokestatic    com/whatsapp/util/Log.e:(Ljava/lang/String;)V
        //  2114: iconst_3       
        //  2115: invokestatic    com/whatsapp/VerifySms.j:(I)I
        //  2118: pop            
        //  2119: aload_0        
        //  2120: getfield        com/whatsapp/wp.b:Lcom/whatsapp/VerifySms;
        //  2123: invokestatic    com/whatsapp/VerifySms.k:(Lcom/whatsapp/VerifySms;)V
        //  2126: aload_0        
        //  2127: getfield        com/whatsapp/wp.b:Lcom/whatsapp/VerifySms;
        //  2130: getstatic       com/whatsapp/wp.z:[Ljava/lang/String;
        //  2133: bipush          19
        //  2135: aaload         
        //  2136: invokevirtual   com/whatsapp/VerifySms.c:(Ljava/lang/String;)V
        //  2139: aload_0        
        //  2140: getfield        com/whatsapp/wp.b:Lcom/whatsapp/VerifySms;
        //  2143: invokestatic    com/whatsapp/VerifySms.d:(Lcom/whatsapp/VerifySms;)V
        //  2146: aload_0        
        //  2147: getfield        com/whatsapp/wp.b:Lcom/whatsapp/VerifySms;
        //  2150: getfield        com/whatsapp/VerifySms.q:Z
        //  2153: istore          97
        //  2155: iload           97
        //  2157: ifne            2174
        //  2160: aload_0        
        //  2161: getfield        com/whatsapp/wp.b:Lcom/whatsapp/VerifySms;
        //  2164: invokevirtual   com/whatsapp/VerifySms.isFinishing:()Z
        //  2167: istore          98
        //  2169: iload           98
        //  2171: ifeq            2344
        //  2174: aload_0        
        //  2175: getfield        com/whatsapp/wp.b:Lcom/whatsapp/VerifySms;
        //  2178: invokevirtual   com/whatsapp/VerifySms.g:()V
        //  2181: iload_2        
        //  2182: ifeq            2344
        //  2185: aload_0        
        //  2186: getfield        com/whatsapp/wp.d:Lcom/whatsapp/ct;
        //  2189: getfield        com/whatsapp/ct.c:I
        //  2192: istore          22
        //  2194: iload           22
        //  2196: ifeq            2344
        //  2199: aload_0        
        //  2200: getfield        com/whatsapp/wp.d:Lcom/whatsapp/ct;
        //  2203: getfield        com/whatsapp/ct.c:I
        //  2206: invokestatic    com/whatsapp/VerifySms.a:(I)I
        //  2209: pop            
        //  2210: getstatic       com/whatsapp/App.aq:Lcom/whatsapp/App;
        //  2213: aload_0        
        //  2214: getfield        com/whatsapp/wp.d:Lcom/whatsapp/ct;
        //  2217: getfield        com/whatsapp/ct.c:I
        //  2220: invokestatic    com/whatsapp/App.e:(Landroid/content/Context;I)V
        //  2223: aload_0        
        //  2224: getfield        com/whatsapp/wp.d:Lcom/whatsapp/ct;
        //  2227: getfield        com/whatsapp/ct.g:Ljava/lang/String;
        //  2230: astore          24
        //  2232: aload           24
        //  2234: ifnull          2337
        //  2237: aload_0        
        //  2238: getfield        com/whatsapp/wp.d:Lcom/whatsapp/ct;
        //  2241: getfield        com/whatsapp/ct.g:Ljava/lang/String;
        //  2244: invokestatic    java/lang/Integer.parseInt:(Ljava/lang/String;)I
        //  2247: istore          27
        //  2249: iload           27
        //  2251: ifle            2326
        //  2254: aload_0        
        //  2255: getfield        com/whatsapp/wp.b:Lcom/whatsapp/VerifySms;
        //  2258: iload           27
        //  2260: invokestatic    com/whatsapp/VerifySms.a:(Lcom/whatsapp/VerifySms;I)V
        //  2263: invokestatic    com/whatsapp/VerifySms.b:()J
        //  2266: ldc2_w          1000
        //  2269: iload           27
        //  2271: i2l            
        //  2272: lmul           
        //  2273: invokestatic    java/lang/Math.min:(JJ)J
        //  2276: lstore          28
        //  2278: lload           28
        //  2280: invokestatic    com/whatsapp/VerifySms.b:()J
        //  2283: lcmp           
        //  2284: ifge            2322
        //  2287: aload_0        
        //  2288: getfield        com/whatsapp/wp.b:Lcom/whatsapp/VerifySms;
        //  2291: invokestatic    com/whatsapp/VerifySms.t:(Lcom/whatsapp/VerifySms;)V
        //  2294: aload_0        
        //  2295: getfield        com/whatsapp/wp.b:Lcom/whatsapp/VerifySms;
        //  2298: lload           28
        //  2300: invokestatic    com/whatsapp/VerifySms.e:(Lcom/whatsapp/VerifySms;J)J
        //  2303: pop2           
        //  2304: aload_0        
        //  2305: getfield        com/whatsapp/wp.b:Lcom/whatsapp/VerifySms;
        //  2308: invokestatic    com/whatsapp/VerifySms.c:(Lcom/whatsapp/VerifySms;)J
        //  2311: invokestatic    com/whatsapp/VerifySms.a:(J)J
        //  2314: pop2           
        //  2315: aload_0        
        //  2316: getfield        com/whatsapp/wp.b:Lcom/whatsapp/VerifySms;
        //  2319: invokestatic    com/whatsapp/VerifySms.x:(Lcom/whatsapp/VerifySms;)V
        //  2322: iload_2        
        //  2323: ifeq            2333
        //  2326: aload_0        
        //  2327: getfield        com/whatsapp/wp.b:Lcom/whatsapp/VerifySms;
        //  2330: invokestatic    com/whatsapp/VerifySms.v:(Lcom/whatsapp/VerifySms;)V
        //  2333: iload_2        
        //  2334: ifeq            2344
        //  2337: aload_0        
        //  2338: getfield        com/whatsapp/wp.b:Lcom/whatsapp/VerifySms;
        //  2341: invokestatic    com/whatsapp/VerifySms.v:(Lcom/whatsapp/VerifySms;)V
        //  2344: return         
        //  2345: astore          161
        //  2347: new             Ljava/lang/StringBuilder;
        //  2350: dup            
        //  2351: invokespecial   java/lang/StringBuilder.<init>:()V
        //  2354: getstatic       com/whatsapp/wp.z:[Ljava/lang/String;
        //  2357: bipush          64
        //  2359: aaload         
        //  2360: invokevirtual   java/lang/StringBuilder.append:(Ljava/lang/String;)Ljava/lang/StringBuilder;
        //  2363: aload_0        
        //  2364: getfield        com/whatsapp/wp.c:Ljava/lang/String;
        //  2367: invokevirtual   java/lang/StringBuilder.append:(Ljava/lang/String;)Ljava/lang/StringBuilder;
        //  2370: getstatic       com/whatsapp/wp.z:[Ljava/lang/String;
        //  2373: bipush          13
        //  2375: aaload         
        //  2376: invokevirtual   java/lang/StringBuilder.append:(Ljava/lang/String;)Ljava/lang/StringBuilder;
        //  2379: invokevirtual   java/lang/StringBuilder.toString:()Ljava/lang/String;
        //  2382: invokestatic    com/whatsapp/util/Log.e:(Ljava/lang/String;)V
        //  2385: goto            113
        //  2388: astore_3       
        //  2389: aload_3        
        //  2390: athrow         
        //  2391: astore          4
        //  2393: aload           4
        //  2395: athrow         
        //  2396: astore          5
        //  2398: aload           5
        //  2400: athrow         
        //  2401: astore          6
        //  2403: aload           6
        //  2405: athrow         
        //  2406: astore          7
        //  2408: aload           7
        //  2410: athrow         
        //  2411: astore          8
        //  2413: aload           8
        //  2415: athrow         
        //  2416: astore          9
        //  2418: aload           9
        //  2420: athrow         
        //  2421: astore          10
        //  2423: aload           10
        //  2425: athrow         
        //  2426: astore          11
        //  2428: aload           11
        //  2430: athrow         
        //  2431: astore          12
        //  2433: aload           12
        //  2435: athrow         
        //  2436: astore          13
        //  2438: aload           13
        //  2440: athrow         
        //  2441: astore          14
        //  2443: aload           14
        //  2445: athrow         
        //  2446: astore          15
        //  2448: aload           15
        //  2450: athrow         
        //  2451: astore          16
        //  2453: aload           16
        //  2455: athrow         
        //  2456: astore          17
        //  2458: aload           17
        //  2460: athrow         
        //  2461: astore          18
        //  2463: aload           18
        //  2465: athrow         
        //  2466: astore          143
        //  2468: new             Ljava/lang/StringBuilder;
        //  2471: dup            
        //  2472: invokespecial   java/lang/StringBuilder.<init>:()V
        //  2475: getstatic       com/whatsapp/wp.z:[Ljava/lang/String;
        //  2478: bipush          56
        //  2480: aaload         
        //  2481: invokevirtual   java/lang/StringBuilder.append:(Ljava/lang/String;)Ljava/lang/StringBuilder;
        //  2484: aload_0        
        //  2485: getfield        com/whatsapp/wp.c:Ljava/lang/String;
        //  2488: invokevirtual   java/lang/StringBuilder.append:(Ljava/lang/String;)Ljava/lang/StringBuilder;
        //  2491: getstatic       com/whatsapp/wp.z:[Ljava/lang/String;
        //  2494: bipush          46
        //  2496: aaload         
        //  2497: invokevirtual   java/lang/StringBuilder.append:(Ljava/lang/String;)Ljava/lang/StringBuilder;
        //  2500: invokevirtual   java/lang/StringBuilder.toString:()Ljava/lang/String;
        //  2503: invokestatic    com/whatsapp/util/Log.w:(Ljava/lang/String;)V
        //  2506: aload_0        
        //  2507: getfield        com/whatsapp/wp.b:Lcom/whatsapp/VerifySms;
        //  2510: bipush          30
        //  2512: invokevirtual   com/whatsapp/VerifySms.d:(I)V
        //  2515: goto            669
        //  2518: astore          144
        //  2520: aload           144
        //  2522: athrow         
        //  2523: astore          145
        //  2525: aload           145
        //  2527: athrow         
        //  2528: astore          40
        //  2530: aload           40
        //  2532: athrow         
        //  2533: astore          41
        //  2535: aload           41
        //  2537: athrow         
        //  2538: astore          42
        //  2540: aload           42
        //  2542: athrow         
        //  2543: astore          43
        //  2545: aload           43
        //  2547: athrow         
        //  2548: astore          44
        //  2550: aload           44
        //  2552: athrow         
        //  2553: astore          45
        //  2555: aload           45
        //  2557: athrow         
        //  2558: astore          46
        //  2560: aload           46
        //  2562: athrow         
        //  2563: astore          47
        //  2565: aload           47
        //  2567: athrow         
        //  2568: astore          48
        //  2570: aload           48
        //  2572: athrow         
        //  2573: astore          49
        //  2575: aload           49
        //  2577: athrow         
        //  2578: astore          50
        //  2580: aload           50
        //  2582: athrow         
        //  2583: astore          51
        //  2585: aload           51
        //  2587: athrow         
        //  2588: astore          52
        //  2590: aload           52
        //  2592: athrow         
        //  2593: astore          53
        //  2595: aload           53
        //  2597: athrow         
        //  2598: astore          54
        //  2600: aload           54
        //  2602: athrow         
        //  2603: astore          55
        //  2605: aload           55
        //  2607: athrow         
        //  2608: astore          56
        //  2610: aload           56
        //  2612: athrow         
        //  2613: getstatic       com/whatsapp/wp.z:[Ljava/lang/String;
        //  2616: bipush          29
        //  2618: aaload         
        //  2619: astore          125
        //  2621: goto            1188
        //  2624: astore          126
        //  2626: aload           126
        //  2628: athrow         
        //  2629: astore          127
        //  2631: aload           127
        //  2633: athrow         
        //  2634: astore          62
        //  2636: aload           62
        //  2638: athrow         
        //  2639: astore          63
        //  2641: aload           63
        //  2643: athrow         
        //  2644: astore          64
        //  2646: aload           64
        //  2648: athrow         
        //  2649: astore          65
        //  2651: aload           65
        //  2653: athrow         
        //  2654: astore          66
        //  2656: aload           66
        //  2658: athrow         
        //  2659: astore          67
        //  2661: aload           67
        //  2663: athrow         
        //  2664: astore          68
        //  2666: aload           68
        //  2668: athrow         
        //  2669: astore          69
        //  2671: aload           69
        //  2673: athrow         
        //  2674: astore          70
        //  2676: aload           70
        //  2678: athrow         
        //  2679: astore          71
        //  2681: aload           71
        //  2683: athrow         
        //  2684: astore          72
        //  2686: aload           72
        //  2688: athrow         
        //  2689: astore          73
        //  2691: aload           73
        //  2693: athrow         
        //  2694: astore          74
        //  2696: aload           74
        //  2698: athrow         
        //  2699: astore          75
        //  2701: aload           75
        //  2703: athrow         
        //  2704: astore          76
        //  2706: aload           76
        //  2708: athrow         
        //  2709: astore          107
        //  2711: new             Ljava/lang/StringBuilder;
        //  2714: dup            
        //  2715: invokespecial   java/lang/StringBuilder.<init>:()V
        //  2718: getstatic       com/whatsapp/wp.z:[Ljava/lang/String;
        //  2721: bipush          12
        //  2723: aaload         
        //  2724: invokevirtual   java/lang/StringBuilder.append:(Ljava/lang/String;)Ljava/lang/StringBuilder;
        //  2727: aload_0        
        //  2728: getfield        com/whatsapp/wp.c:Ljava/lang/String;
        //  2731: invokevirtual   java/lang/StringBuilder.append:(Ljava/lang/String;)Ljava/lang/StringBuilder;
        //  2734: getstatic       com/whatsapp/wp.z:[Ljava/lang/String;
        //  2737: bipush          24
        //  2739: aaload         
        //  2740: invokevirtual   java/lang/StringBuilder.append:(Ljava/lang/String;)Ljava/lang/StringBuilder;
        //  2743: invokevirtual   java/lang/StringBuilder.toString:()Ljava/lang/String;
        //  2746: invokestatic    com/whatsapp/util/Log.w:(Ljava/lang/String;)V
        //  2749: aload_0        
        //  2750: getfield        com/whatsapp/wp.b:Lcom/whatsapp/VerifySms;
        //  2753: bipush          31
        //  2755: invokevirtual   com/whatsapp/VerifySms.d:(I)V
        //  2758: goto            1790
        //  2761: astore          108
        //  2763: aload           108
        //  2765: athrow         
        //  2766: astore          109
        //  2768: aload           109
        //  2770: athrow         
        //  2771: astore          81
        //  2773: aload           81
        //  2775: athrow         
        //  2776: astore          82
        //  2778: aload           82
        //  2780: athrow         
        //  2781: astore          83
        //  2783: aload           83
        //  2785: athrow         
        //  2786: astore          84
        //  2788: aload           84
        //  2790: athrow         
        //  2791: astore          85
        //  2793: aload           85
        //  2795: athrow         
        //  2796: astore          86
        //  2798: aload           86
        //  2800: athrow         
        //  2801: astore          87
        //  2803: aload           87
        //  2805: athrow         
        //  2806: astore          88
        //  2808: aload           88
        //  2810: athrow         
        //  2811: astore          89
        //  2813: aload           89
        //  2815: athrow         
        //  2816: astore          90
        //  2818: aload           90
        //  2820: athrow         
        //  2821: astore          91
        //  2823: aload           91
        //  2825: athrow         
        //  2826: astore          92
        //  2828: aload           92
        //  2830: athrow         
        //  2831: astore          20
        //  2833: aload           20
        //  2835: athrow         
        //  2836: astore          21
        //  2838: aload           21
        //  2840: athrow         
        //  2841: astore          30
        //  2843: aload           30
        //  2845: athrow         
        //  2846: astore          26
        //  2848: new             Ljava/lang/StringBuilder;
        //  2851: dup            
        //  2852: invokespecial   java/lang/StringBuilder.<init>:()V
        //  2855: getstatic       com/whatsapp/wp.z:[Ljava/lang/String;
        //  2858: bipush          54
        //  2860: aaload         
        //  2861: invokevirtual   java/lang/StringBuilder.append:(Ljava/lang/String;)Ljava/lang/StringBuilder;
        //  2864: aload_0        
        //  2865: getfield        com/whatsapp/wp.c:Ljava/lang/String;
        //  2868: invokevirtual   java/lang/StringBuilder.append:(Ljava/lang/String;)Ljava/lang/StringBuilder;
        //  2871: getstatic       com/whatsapp/wp.z:[Ljava/lang/String;
        //  2874: bipush          25
        //  2876: aaload         
        //  2877: invokevirtual   java/lang/StringBuilder.append:(Ljava/lang/String;)Ljava/lang/StringBuilder;
        //  2880: aload_0        
        //  2881: getfield        com/whatsapp/wp.d:Lcom/whatsapp/ct;
        //  2884: getfield        com/whatsapp/ct.g:Ljava/lang/String;
        //  2887: invokevirtual   java/lang/StringBuilder.append:(Ljava/lang/String;)Ljava/lang/StringBuilder;
        //  2890: invokevirtual   java/lang/StringBuilder.toString:()Ljava/lang/String;
        //  2893: invokestatic    com/whatsapp/util/Log.e:(Ljava/lang/String;)V
        //  2896: aload_0        
        //  2897: getfield        com/whatsapp/wp.b:Lcom/whatsapp/VerifySms;
        //  2900: invokestatic    com/whatsapp/VerifySms.v:(Lcom/whatsapp/VerifySms;)V
        //  2903: goto            2333
        //  2906: astore          31
        //  2908: aload           31
        //  2910: athrow         
        //  2911: astore          25
        //  2913: aload           25
        //  2915: athrow         
        //    Exceptions:
        //  Try           Handler
        //  Start  End    Start  End    Type                             
        //  -----  -----  -----  -----  ---------------------------------
        //  96     113    2345   2388   Ljava/lang/NumberFormatException;
        //  113    121    2388   2391   Ljava/lang/NumberFormatException;
        //  125    130    2388   2391   Ljava/lang/NumberFormatException;
        //  136    155    2391   2396   Ljava/lang/NumberFormatException;
        //  161    240    2396   2401   Ljava/lang/NumberFormatException;
        //  245    254    2401   2406   Ljava/lang/NumberFormatException;
        //  259    266    2406   2411   Ljava/lang/NumberFormatException;
        //  270    275    2411   2416   Ljava/lang/NumberFormatException;
        //  281    360    2416   2421   Ljava/lang/NumberFormatException;
        //  365    374    2421   2426   Ljava/lang/NumberFormatException;
        //  379    386    2426   2431   Ljava/lang/NumberFormatException;
        //  390    395    2431   2436   Ljava/lang/NumberFormatException;
        //  401    480    2436   2441   Ljava/lang/NumberFormatException;
        //  485    494    2441   2446   Ljava/lang/NumberFormatException;
        //  499    506    2446   2451   Ljava/lang/NumberFormatException;
        //  510    515    2451   2456   Ljava/lang/NumberFormatException;
        //  521    598    2456   2461   Ljava/lang/NumberFormatException;
        //  603    612    2461   2466   Ljava/lang/NumberFormatException;
        //  616    669    2466   2518   Ljava/lang/NumberFormatException;
        //  669    688    2518   2523   Ljava/lang/NumberFormatException;
        //  693    700    2523   2528   Ljava/lang/NumberFormatException;
        //  704    709    2528   2533   Ljava/lang/NumberFormatException;
        //  715    756    2533   2538   Ljava/lang/NumberFormatException;
        //  761    770    2538   2543   Ljava/lang/NumberFormatException;
        //  775    782    2543   2548   Ljava/lang/NumberFormatException;
        //  786    791    2548   2553   Ljava/lang/NumberFormatException;
        //  797    885    2553   2558   Ljava/lang/NumberFormatException;
        //  890    899    2558   2563   Ljava/lang/NumberFormatException;
        //  904    911    2563   2568   Ljava/lang/NumberFormatException;
        //  915    920    2568   2573   Ljava/lang/NumberFormatException;
        //  926    1014   2573   2578   Ljava/lang/NumberFormatException;
        //  1019   1028   2578   2583   Ljava/lang/NumberFormatException;
        //  1033   1040   2583   2588   Ljava/lang/NumberFormatException;
        //  1044   1049   2588   2593   Ljava/lang/NumberFormatException;
        //  1055   1119   2593   2598   Ljava/lang/NumberFormatException;
        //  1123   1128   2598   2603   Ljava/lang/NumberFormatException;
        //  1134   1174   2603   2608   Ljava/lang/NumberFormatException;
        //  1179   1188   2608   2613   Ljava/lang/NumberFormatException;
        //  1188   1252   2624   2629   Ljava/lang/NumberFormatException;
        //  1257   1264   2629   2634   Ljava/lang/NumberFormatException;
        //  1268   1273   2634   2639   Ljava/lang/NumberFormatException;
        //  1279   1359   2639   2644   Ljava/lang/NumberFormatException;
        //  1364   1373   2644   2649   Ljava/lang/NumberFormatException;
        //  1378   1385   2649   2654   Ljava/lang/NumberFormatException;
        //  1389   1394   2654   2659   Ljava/lang/NumberFormatException;
        //  1400   1479   2659   2664   Ljava/lang/NumberFormatException;
        //  1484   1493   2664   2669   Ljava/lang/NumberFormatException;
        //  1498   1505   2669   2674   Ljava/lang/NumberFormatException;
        //  1509   1514   2674   2679   Ljava/lang/NumberFormatException;
        //  1520   1599   2679   2684   Ljava/lang/NumberFormatException;
        //  1604   1613   2684   2689   Ljava/lang/NumberFormatException;
        //  1618   1625   2689   2694   Ljava/lang/NumberFormatException;
        //  1629   1634   2694   2699   Ljava/lang/NumberFormatException;
        //  1640   1719   2699   2704   Ljava/lang/NumberFormatException;
        //  1724   1733   2704   2709   Ljava/lang/NumberFormatException;
        //  1737   1790   2709   2761   Ljava/lang/NumberFormatException;
        //  1790   1809   2761   2766   Ljava/lang/NumberFormatException;
        //  1814   1821   2766   2771   Ljava/lang/NumberFormatException;
        //  1825   1830   2771   2776   Ljava/lang/NumberFormatException;
        //  1836   1915   2776   2781   Ljava/lang/NumberFormatException;
        //  1920   1929   2781   2786   Ljava/lang/NumberFormatException;
        //  1934   1941   2786   2791   Ljava/lang/NumberFormatException;
        //  1945   1950   2791   2796   Ljava/lang/NumberFormatException;
        //  1956   2035   2796   2801   Ljava/lang/NumberFormatException;
        //  2040   2049   2801   2806   Ljava/lang/NumberFormatException;
        //  2054   2061   2806   2811   Ljava/lang/NumberFormatException;
        //  2065   2070   2811   2816   Ljava/lang/NumberFormatException;
        //  2076   2155   2816   2821   Ljava/lang/NumberFormatException;
        //  2160   2169   2821   2826   Ljava/lang/NumberFormatException;
        //  2174   2181   2826   2831   Ljava/lang/NumberFormatException;
        //  2185   2194   2831   2836   Ljava/lang/NumberFormatException;
        //  2199   2232   2836   2841   Ljava/lang/NumberFormatException;
        //  2237   2249   2846   2906   Ljava/lang/NumberFormatException;
        //  2254   2278   2846   2906   Ljava/lang/NumberFormatException;
        //  2278   2322   2841   2846   Ljava/lang/NumberFormatException;
        //  2326   2333   2906   2911   Ljava/lang/NumberFormatException;
        //  2337   2344   2911   2916   Ljava/lang/NumberFormatException;
        //  2389   2391   2391   2396   Ljava/lang/NumberFormatException;
        //  2393   2396   2396   2401   Ljava/lang/NumberFormatException;
        //  2398   2401   2401   2406   Ljava/lang/NumberFormatException;
        //  2403   2406   2406   2411   Ljava/lang/NumberFormatException;
        //  2408   2411   2411   2416   Ljava/lang/NumberFormatException;
        //  2413   2416   2416   2421   Ljava/lang/NumberFormatException;
        //  2418   2421   2421   2426   Ljava/lang/NumberFormatException;
        //  2423   2426   2426   2431   Ljava/lang/NumberFormatException;
        //  2428   2431   2431   2436   Ljava/lang/NumberFormatException;
        //  2433   2436   2436   2441   Ljava/lang/NumberFormatException;
        //  2438   2441   2441   2446   Ljava/lang/NumberFormatException;
        //  2443   2446   2446   2451   Ljava/lang/NumberFormatException;
        //  2448   2451   2451   2456   Ljava/lang/NumberFormatException;
        //  2453   2456   2456   2461   Ljava/lang/NumberFormatException;
        //  2458   2461   2461   2466   Ljava/lang/NumberFormatException;
        //  2520   2523   2523   2528   Ljava/lang/NumberFormatException;
        //  2525   2528   2528   2533   Ljava/lang/NumberFormatException;
        //  2530   2533   2533   2538   Ljava/lang/NumberFormatException;
        //  2535   2538   2538   2543   Ljava/lang/NumberFormatException;
        //  2540   2543   2543   2548   Ljava/lang/NumberFormatException;
        //  2545   2548   2548   2553   Ljava/lang/NumberFormatException;
        //  2550   2553   2553   2558   Ljava/lang/NumberFormatException;
        //  2555   2558   2558   2563   Ljava/lang/NumberFormatException;
        //  2560   2563   2563   2568   Ljava/lang/NumberFormatException;
        //  2565   2568   2568   2573   Ljava/lang/NumberFormatException;
        //  2570   2573   2573   2578   Ljava/lang/NumberFormatException;
        //  2575   2578   2578   2583   Ljava/lang/NumberFormatException;
        //  2580   2583   2583   2588   Ljava/lang/NumberFormatException;
        //  2585   2588   2588   2593   Ljava/lang/NumberFormatException;
        //  2590   2593   2593   2598   Ljava/lang/NumberFormatException;
        //  2595   2598   2598   2603   Ljava/lang/NumberFormatException;
        //  2600   2603   2603   2608   Ljava/lang/NumberFormatException;
        //  2605   2608   2608   2613   Ljava/lang/NumberFormatException;
        //  2626   2629   2629   2634   Ljava/lang/NumberFormatException;
        //  2631   2634   2634   2639   Ljava/lang/NumberFormatException;
        //  2636   2639   2639   2644   Ljava/lang/NumberFormatException;
        //  2641   2644   2644   2649   Ljava/lang/NumberFormatException;
        //  2646   2649   2649   2654   Ljava/lang/NumberFormatException;
        //  2651   2654   2654   2659   Ljava/lang/NumberFormatException;
        //  2656   2659   2659   2664   Ljava/lang/NumberFormatException;
        //  2661   2664   2664   2669   Ljava/lang/NumberFormatException;
        //  2666   2669   2669   2674   Ljava/lang/NumberFormatException;
        //  2671   2674   2674   2679   Ljava/lang/NumberFormatException;
        //  2676   2679   2679   2684   Ljava/lang/NumberFormatException;
        //  2681   2684   2684   2689   Ljava/lang/NumberFormatException;
        //  2686   2689   2689   2694   Ljava/lang/NumberFormatException;
        //  2691   2694   2694   2699   Ljava/lang/NumberFormatException;
        //  2696   2699   2699   2704   Ljava/lang/NumberFormatException;
        //  2701   2704   2704   2709   Ljava/lang/NumberFormatException;
        //  2763   2766   2766   2771   Ljava/lang/NumberFormatException;
        //  2768   2771   2771   2776   Ljava/lang/NumberFormatException;
        //  2773   2776   2776   2781   Ljava/lang/NumberFormatException;
        //  2778   2781   2781   2786   Ljava/lang/NumberFormatException;
        //  2783   2786   2786   2791   Ljava/lang/NumberFormatException;
        //  2788   2791   2791   2796   Ljava/lang/NumberFormatException;
        //  2793   2796   2796   2801   Ljava/lang/NumberFormatException;
        //  2798   2801   2801   2806   Ljava/lang/NumberFormatException;
        //  2803   2806   2806   2811   Ljava/lang/NumberFormatException;
        //  2808   2811   2811   2816   Ljava/lang/NumberFormatException;
        //  2813   2816   2816   2821   Ljava/lang/NumberFormatException;
        //  2818   2821   2821   2826   Ljava/lang/NumberFormatException;
        //  2823   2826   2826   2831   Ljava/lang/NumberFormatException;
        //  2828   2831   2831   2836   Ljava/lang/NumberFormatException;
        //  2833   2836   2836   2841   Ljava/lang/NumberFormatException;
        //  2843   2846   2846   2906   Ljava/lang/NumberFormatException;
        //  2908   2911   2846   2906   Ljava/lang/NumberFormatException;
        // 
        // The error that occurred was:
        // 
        // java.lang.IndexOutOfBoundsException: Index: 1342, Size: 1342
        //     at java.util.ArrayList.rangeCheck(ArrayList.java:653)
        //     at java.util.ArrayList.get(ArrayList.java:429)
        //     at com.strobel.decompiler.ast.AstBuilder.convertToAst(AstBuilder.java:3303)
        //     at com.strobel.decompiler.ast.AstBuilder.build(AstBuilder.java:113)
        //     at com.strobel.decompiler.languages.java.ast.AstMethodBodyBuilder.createMethodBody(AstMethodBodyBuilder.java:210)
        //     at com.strobel.decompiler.languages.java.ast.AstMethodBodyBuilder.createMethodBody(AstMethodBodyBuilder.java:99)
        //     at com.strobel.decompiler.languages.java.ast.AstBuilder.createMethodBody(AstBuilder.java:757)
        //     at com.strobel.decompiler.languages.java.ast.AstBuilder.createMethod(AstBuilder.java:655)
        //     at com.strobel.decompiler.languages.java.ast.AstBuilder.addTypeMembers(AstBuilder.java:532)
        //     at com.strobel.decompiler.languages.java.ast.AstBuilder.createTypeCore(AstBuilder.java:499)
        //     at com.strobel.decompiler.languages.java.ast.AstBuilder.createTypeNoCache(AstBuilder.java:141)
        //     at com.strobel.decompiler.languages.java.ast.AstBuilder.createType(AstBuilder.java:130)
        //     at com.strobel.decompiler.languages.java.ast.AstBuilder.addType(AstBuilder.java:105)
        //     at com.strobel.decompiler.languages.java.JavaLanguage.buildAst(JavaLanguage.java:71)
        //     at com.strobel.decompiler.languages.java.JavaLanguage.decompileType(JavaLanguage.java:59)
        //     at com.strobel.decompiler.DecompilerDriver.decompileType(DecompilerDriver.java:317)
        //     at com.strobel.decompiler.DecompilerDriver.decompileJar(DecompilerDriver.java:238)
        //     at com.strobel.decompiler.DecompilerDriver.main(DecompilerDriver.java:123)
        // 
        throw new IllegalStateException("An error occurred while decompiling this method.");
    }
    
    protected Object doInBackground(final Object[] array) {
        return this.a((String[])array);
    }
    
    protected void onPostExecute(final Object o) {
        this.a((pf)o);
    }
    
    protected void onPreExecute() {
        VerifySms.j(2);
        VerifySms.k(this.b);
        VerifySms.x(this.b);
        VerifySms.a(this.b);
        App.aq.aO();
    }
}
